{
  "type": "Feature",
  "properties": {
    "gn:admin1_code":"8.0",
    "gn:asciiname":"Moulaydi",
    "gn:country_code":"TD",
    "gn:dem":409,
    "gn:feature_class":"P",
    "gn:feature_code":"PPL",
    "gn:name":"Moulaydi",
    "gn:population":0,
    "gn:timezone":"Africa/Ndjamena",
    "iso:country":"TD",
    "name:und_x_variant":[
        "Moula\u00efdi",
        "Moulaydi"
    ],
    "wof:name":"Moulaydi",
    "wof:placetype":"locality"
},
  "geometry": {"coordinates":[15.67006,8.70143],"type":"Point"}
}