{
  "type": "Feature",
  "properties": {
    "gn:admin1_code":"17.0",
    "gn:asciiname":"Djindjibo",
    "gn:country_code":"TD",
    "gn:dem":401,
    "gn:feature_class":"P",
    "gn:feature_code":"PPL",
    "gn:name":"Djindjibo",
    "gn:population":0,
    "gn:timezone":"Africa/Ndjamena",
    "iso:country":"TD",
    "wof:name":"Djindjibo",
    "wof:placetype":"locality"
},
  "geometry": {"coordinates":[18.71681,9.62859],"type":"Point"}
}