{
  "type": "Feature",
  "properties": {
    "gn:admin1_code":"12.0",
    "gn:asciiname":"Tirti",
    "gn:country_code":"TD",
    "gn:dem":813,
    "gn:feature_class":"P",
    "gn:feature_code":"PPL",
    "gn:name":"Tirti",
    "gn:population":0,
    "gn:timezone":"Africa/Ndjamena",
    "iso:country":"TD",
    "wof:name":"Tirti",
    "wof:placetype":"locality"
},
  "geometry": {"coordinates":[21.83131,13.58948],"type":"Point"}
}