{
  "type": "Feature",
  "properties": {
    "gn:admin1_code":"8.0",
    "gn:asciiname":"Bilibeni",
    "gn:country_code":"TD",
    "gn:dem":470,
    "gn:feature_class":"P",
    "gn:feature_code":"PPL",
    "gn:name":"Bilib\u00e9ni",
    "gn:population":0,
    "gn:timezone":"Africa/Ndjamena",
    "iso:country":"TD",
    "wof:name":"Bilibeni",
    "wof:placetype":"locality"
},
  "geometry": {"coordinates":[15.489,8.5409],"type":"Point"}
}