{
  "type": "Feature",
  "properties": {
    "gn:admin1_code":"1.0",
    "gn:asciiname":"Am Habile",
    "gn:country_code":"TD",
    "gn:dem":425,
    "gn:feature_class":"P",
    "gn:feature_code":"PPL",
    "gn:name":"Am Habil\u00e9",
    "gn:population":0,
    "gn:timezone":"Africa/Ndjamena",
    "iso:country":"TD",
    "wof:name":"Am Habile",
    "wof:placetype":"locality"
},
  "geometry": {"coordinates":[19.4396,12.9043],"type":"Point"}
}