{
  "type": "Feature",
  "properties": {
    "gn:admin1_code":"6.0",
    "gn:asciiname":"Ngoudegilbou",
    "gn:country_code":"TD",
    "gn:dem":323,
    "gn:feature_class":"P",
    "gn:feature_code":"PPL",
    "gn:name":"Ngoud\u00e9gilbou",
    "gn:population":0,
    "gn:timezone":"Africa/Ndjamena",
    "iso:country":"TD",
    "wof:name":"Ngoudegilbou",
    "wof:placetype":"locality"
},
  "geometry": {"coordinates":[15.4793,14.01949],"type":"Point"}
}