{
  "type": "Feature",
  "properties": {
    "gn:admin1_code":"5.0",
    "gn:asciiname":"Mataya",
    "gn:country_code":"TD",
    "gn:dem":409,
    "gn:feature_class":"P",
    "gn:feature_code":"PPL",
    "gn:name":"Mataya",
    "gn:population":0,
    "gn:timezone":"Africa/Ndjamena",
    "iso:country":"TD",
    "wof:name":"Mataya",
    "wof:placetype":"locality"
},
  "geometry": {"coordinates":[18.04647000000001,11.99443],"type":"Point"}
}