{
  "type": "Feature",
  "properties": {
    "gn:admin1_code":"12.0",
    "gn:asciiname":"Kaingam",
    "gn:country_code":"TD",
    "gn:dem":481,
    "gn:feature_class":"P",
    "gn:feature_code":"PPL",
    "gn:name":"Kaingam",
    "gn:population":0,
    "gn:timezone":"Africa/Ndjamena",
    "iso:country":"TD",
    "name:fra_x_preferred":[
        "Kaingam"
    ],
    "wof:name":"Kaingam",
    "wof:placetype":"locality"
},
  "geometry": {"coordinates":[20.54967000000001,13.97862],"type":"Point"}
}