{
  "type": "Feature",
  "properties": {
    "gn:admin1_code":"9.0",
    "gn:asciiname":"Betabar",
    "gn:country_code":"TD",
    "gn:dem":481,
    "gn:feature_class":"P",
    "gn:feature_code":"PPL",
    "gn:name":"B\u00e9tabar",
    "gn:population":0,
    "gn:timezone":"Africa/Ndjamena",
    "iso:country":"TD",
    "name:und_x_variant":[
        "Betaba",
        "B\u00e9tabar"
    ],
    "wof:name":"Betabar",
    "wof:placetype":"locality"
},
  "geometry": {"coordinates":[15.7444,8.1318],"type":"Point"}
}