{
  "type": "Feature",
  "properties": {
    "gn:admin1_code":"15.0",
    "gn:asciiname":"Mossio",
    "gn:country_code":"TD",
    "gn:dem":328,
    "gn:feature_class":"P",
    "gn:feature_code":"PPL",
    "gn:name":"Mossio",
    "gn:population":0,
    "gn:timezone":"Africa/Ndjamena",
    "iso:country":"TD",
    "name:und_x_variant":[
        "Mossia",
        "Mossio"
    ],
    "wof:name":"Mossio",
    "wof:placetype":"locality"
},
  "geometry": {"coordinates":[15.87484,10.81853],"type":"Point"}
}