{
  "type": "Feature",
  "properties": {
    "gn:admin1_code":"12.0",
    "gn:asciiname":"Fardjia",
    "gn:country_code":"TD",
    "gn:dem":705,
    "gn:feature_class":"P",
    "gn:feature_code":"PPL",
    "gn:name":"Fardjia",
    "gn:population":0,
    "gn:timezone":"Africa/Ndjamena",
    "iso:country":"TD",
    "wof:name":"Fardjia",
    "wof:placetype":"locality"
},
  "geometry": {"coordinates":[21.57381,13.33445],"type":"Point"}
}