{
  "type": "Feature",
  "properties": {
    "gn:admin1_code":"12.0",
    "gn:asciiname":"Guerdout",
    "gn:country_code":"TD",
    "gn:dem":602,
    "gn:feature_class":"P",
    "gn:feature_code":"PPL",
    "gn:name":"Guerdout",
    "gn:population":0,
    "gn:timezone":"Africa/Ndjamena",
    "iso:country":"TD",
    "name:und_x_variant":[
        "Gerdout"
    ],
    "wof:name":"Guerdout",
    "wof:placetype":"locality"
},
  "geometry": {"coordinates":[21.64248,13.01477],"type":"Point"}
}