{
  "type": "Feature",
  "properties": {
    "gn:admin1_code":"12.0",
    "gn:asciiname":"Zouma Asab Momo",
    "gn:country_code":"TD",
    "gn:dem":431,
    "gn:feature_class":"P",
    "gn:feature_code":"PPL",
    "gn:name":"Zouma Asab Momo",
    "gn:population":0,
    "gn:timezone":"Africa/Ndjamena",
    "iso:country":"TD",
    "wof:name":"Zouma Asab Momo",
    "wof:placetype":"locality"
},
  "geometry": {"coordinates":[20.2305,14.02788],"type":"Point"}
}