{
  "type": "Feature",
  "properties": {
    "gn:admin1_code":"1.0",
    "gn:asciiname":"Seheba",
    "gn:country_code":"TD",
    "gn:dem":369,
    "gn:feature_class":"P",
    "gn:feature_code":"PPL",
    "gn:name":"S\u00e9h\u00e9ba",
    "gn:population":0,
    "gn:timezone":"Africa/Ndjamena",
    "iso:country":"TD",
    "wof:name":"Seheba",
    "wof:placetype":"locality"
},
  "geometry": {"coordinates":[19.3009,13.2768],"type":"Point"}
}