{
  "type": "Feature",
  "properties": {
    "gn:admin1_code":"1.0",
    "gn:asciiname":"Am Goulma Techer",
    "gn:country_code":"TD",
    "gn:dem":418,
    "gn:feature_class":"P",
    "gn:feature_code":"PPL",
    "gn:name":"Am Goulma T\u00e9cher",
    "gn:population":0,
    "gn:timezone":"Africa/Ndjamena",
    "iso:country":"TD",
    "name:und_x_variant":[
        "Am Goulma",
        "Am Goulma T\u00e9cher"
    ],
    "wof:name":"Am Goulma Techer",
    "wof:placetype":"locality"
},
  "geometry": {"coordinates":[20.02162,13.54824],"type":"Point"}
}