{
  "type": "Feature",
  "properties": {
    "gn:admin1_code":"9.0",
    "gn:asciiname":"Mitinge",
    "gn:country_code":"TD",
    "gn:dem":487,
    "gn:feature_class":"P",
    "gn:feature_code":"PPL",
    "gn:name":"Miting\u00e9",
    "gn:population":0,
    "gn:timezone":"Africa/Ndjamena",
    "iso:country":"TD",
    "wof:name":"Mitinge",
    "wof:placetype":"locality"
},
  "geometry": {"coordinates":[15.75,8.25],"type":"Point"}
}