{
  "type": "Feature",
  "properties": {
    "gn:admin1_code":"19.0",
    "gn:asciiname":"Bendanga",
    "gn:country_code":"TD",
    "gn:dem":380,
    "gn:feature_class":"P",
    "gn:feature_code":"PPL",
    "gn:name":"Bendanga",
    "gn:population":0,
    "gn:timezone":"Africa/Ndjamena",
    "iso:country":"TD",
    "name:und_x_variant":[
        "Bendaga",
        "Bendanga"
    ],
    "wof:name":"Bendanga",
    "wof:placetype":"locality"
},
  "geometry": {"coordinates":[17.7611,8.6279],"type":"Point"}
}