{
  "type": "Feature",
  "properties": {
    "gn:admin1_code":"18.0",
    "gn:asciiname":"Mouk",
    "gn:country_code":"TD",
    "gn:dem":295,
    "gn:feature_class":"P",
    "gn:feature_code":"PPL",
    "gn:name":"Mouk",
    "gn:population":0,
    "gn:timezone":"Africa/Ndjamena",
    "iso:country":"TD",
    "name:deu_x_preferred":[
        "Mouk"
    ],
    "name:fin_x_preferred":[
        "Mouk"
    ],
    "name:fra_x_preferred":[
        "Mouk"
    ],
    "name:jpn_x_preferred":[
        "\u30e0\u30fc\u30af\u306e\u305b\u304b\u3044\u308a\u3087\u3053\u3046"
    ],
    "name:nld_x_preferred":[
        "Mouk"
    ],
    "name:pol_x_preferred":[
        "Mi\u015b Mouki"
    ],
    "name:swe_x_preferred":[
        "Mouk"
    ],
    "wof:name":"Mouk",
    "wof:placetype":"locality"
},
  "geometry": {"coordinates":[15.87814,12.37291],"type":"Point"}
}