{
  "type": "Feature",
  "properties": {
    "gn:admin1_code":"2.0",
    "gn:asciiname":"Kapka Geni",
    "gn:country_code":"TD",
    "gn:dem":655,
    "gn:feature_class":"P",
    "gn:feature_code":"PPL",
    "gn:name":"Kapka G\u00e9ni",
    "gn:population":0,
    "gn:timezone":"Africa/Ndjamena",
    "iso:country":"TD",
    "wof:name":"Kapka Geni",
    "wof:placetype":"locality"
},
  "geometry": {"coordinates":[21.61667000000001,15.05],"type":"Point"}
}