{
  "type": "Feature",
  "properties": {
    "gn:admin1_code":"12.0",
    "gn:asciiname":"Dougi",
    "gn:country_code":"TD",
    "gn:dem":585,
    "gn:feature_class":"P",
    "gn:feature_code":"PPL",
    "gn:name":"Dougi",
    "gn:population":0,
    "gn:timezone":"Africa/Ndjamena",
    "iso:country":"TD",
    "wof:name":"Dougi",
    "wof:placetype":"locality"
},
  "geometry": {"coordinates":[21.38226,13.2611],"type":"Point"}
}