{
  "type": "Feature",
  "properties": {
    "gn:country":"TD",
    "gn:fcode":"PPLA",
    "gn:population":36263,
    "iso:country":"TD",
    "name:ara_x_preferred":[
        "\u0642\u0645\u0631\u0629"
    ],
    "name:arz_x_preferred":[
        "\u0642\u0645\u0631\u0647"
    ],
    "name:ast_x_preferred":[
        "Koumra"
    ],
    "name:azb_x_preferred":[
        "\u06a9\u0648\u0645\u0631\u0627"
    ],
    "name:cat_x_preferred":[
        "Koumra"
    ],
    "name:ceb_x_preferred":[
        "Koumra"
    ],
    "name:dan_x_preferred":[
        "Koumra"
    ],
    "name:deu_x_preferred":[
        "Koumra"
    ],
    "name:eng_x_preferred":[
        "Koumra"
    ],
    "name:eus_x_preferred":[
        "Koumra"
    ],
    "name:fas_x_preferred":[
        "\u06a9\u0648\u0645\u0631\u0627"
    ],
    "name:fra_x_preferred":[
        "Koumra"
    ],
    "name:hin_x_preferred":[
        "\u0915\u0941\u092e\u0930\u093e"
    ],
    "name:hrv_x_preferred":[
        "Koumra"
    ],
    "name:ind_x_preferred":[
        "Koumra"
    ],
    "name:ita_x_preferred":[
        "Koumra"
    ],
    "name:jpn_x_preferred":[
        "\u30af\u30e0\u30e9"
    ],
    "name:kor_x_preferred":[
        "\ucff0\ub77c"
    ],
    "name:lit_x_preferred":[
        "Kumra"
    ],
    "name:mrj_x_preferred":[
        "\u041a\u0443\u043c\u0440\u0430"
    ],
    "name:nld_x_preferred":[
        "Koumra"
    ],
    "name:nob_x_preferred":[
        "Koumra"
    ],
    "name:pol_x_preferred":[
        "Koumra"
    ],
    "name:ron_x_preferred":[
        "Koumra"
    ],
    "name:rus_x_preferred":[
        "\u041a\u0443\u043c\u0440\u0430"
    ],
    "name:spa_x_preferred":[
        "Koumra"
    ],
    "name:swa_x_preferred":[
        "Koumra"
    ],
    "name:tgl_x_preferred":[
        "Koumra"
    ],
    "name:tur_x_preferred":[
        "Koumra"
    ],
    "name:ukr_x_preferred":[
        "\u041a\u0443\u043c\u0440\u0430"
    ],
    "name:und_x_variant":[
        "Koumbra"
    ],
    "name:urd_x_preferred":[
        "\u06a9\u0624\u0645\u0631\u0627"
    ],
    "name:vie_x_preferred":[
        "Koumra"
    ],
    "name:zho_x_preferred":[
        "\u5eab\u59c6\u62c9"
    ],
    "qs:name":"Koumra",
    "qs:photos_9r":0,
    "qs:photos_sr":0,
    "qs:pop_sr":"7",
    "wd:wordcount":34,
    "wof:name":"Koumra",
    "wof:placetype":"locality",
    "wof:population":36263
},
  "geometry": {"coordinates":[17.55392,8.91256],"type":"Point"}
}