{
  "type": "Feature",
  "properties": {
    "gn:admin1_code":"12.0",
    "gn:asciiname":"Bidin",
    "gn:country_code":"TD",
    "gn:dem":669,
    "gn:feature_class":"P",
    "gn:feature_code":"PPL",
    "gn:name":"Bidin",
    "gn:population":0,
    "gn:timezone":"Africa/Ndjamena",
    "iso:country":"TD",
    "wof:name":"Bidin",
    "wof:placetype":"locality"
},
  "geometry": {"coordinates":[21.53406,13.43801],"type":"Point"}
}