{
  "type": "Feature",
  "properties": {
    "gn:admin1_code":"25.0",
    "gn:asciiname":"Feride",
    "gn:country_code":"TD",
    "gn:dem":576,
    "gn:feature_class":"P",
    "gn:feature_code":"PPL",
    "gn:name":"F\u00e9rid\u00e9",
    "gn:population":0,
    "gn:timezone":"Africa/Ndjamena",
    "iso:country":"TD",
    "name:und_x_variant":[
        "Foride",
        "Florid\u00e9",
        "F\u00e9rid\u00e9"
    ],
    "wof:name":"Feride",
    "wof:placetype":"locality"
},
  "geometry": {"coordinates":[21.88333,12.25],"type":"Point"}
}