{
  "type": "Feature",
  "properties": {
    "gn:admin1_code":"25.0",
    "gn:asciiname":"Soumagoum",
    "gn:country_code":"TD",
    "gn:dem":514,
    "gn:feature_class":"P",
    "gn:feature_code":"PPL",
    "gn:name":"Soumagoum",
    "gn:population":0,
    "gn:timezone":"Africa/Ndjamena",
    "iso:country":"TD",
    "wof:name":"Soumagoum",
    "wof:placetype":"locality"
},
  "geometry": {"coordinates":[21.1131,11.9898],"type":"Point"}
}