{
  "type": "Feature",
  "properties": {
    "gn:admin1_code":"9.0",
    "gn:asciiname":"Kourangati",
    "gn:country_code":"TD",
    "gn:dem":413,
    "gn:feature_class":"P",
    "gn:feature_code":"PPL",
    "gn:name":"Kourangati",
    "gn:population":0,
    "gn:timezone":"Africa/Ndjamena",
    "iso:country":"TD",
    "name:fra_x_preferred":[
        "Kourangati"
    ],
    "name:fra_x_variant":[
        "B\u00e9boto"
    ],
    "name:und_x_variant":[
        "B\u00e9boto"
    ],
    "wof:name":"Kourangati",
    "wof:placetype":"locality"
},
  "geometry": {"coordinates":[16.6695,8.3878],"type":"Point"}
}