{
  "type": "Feature",
  "properties": {
    "gn:admin1_code":"25.0",
    "gn:asciiname":"Am Hido",
    "gn:country_code":"TD",
    "gn:dem":589,
    "gn:feature_class":"P",
    "gn:feature_code":"PPL",
    "gn:name":"Am Hido",
    "gn:population":0,
    "gn:timezone":"Africa/Ndjamena",
    "iso:country":"TD",
    "wof:name":"Am Hido",
    "wof:placetype":"locality"
},
  "geometry": {"coordinates":[22.15,12.18333],"type":"Point"}
}