{
  "type": "Feature",
  "properties": {
    "gn:admin1_code":"14.0",
    "gn:asciiname":"Narga",
    "gn:country_code":"TD",
    "gn:dem":350,
    "gn:feature_class":"P",
    "gn:feature_code":"PPL",
    "gn:name":"Narga",
    "gn:population":0,
    "gn:timezone":"Africa/Ndjamena",
    "iso:country":"TD",
    "wof:name":"Narga",
    "wof:placetype":"locality"
},
  "geometry": {"coordinates":[16.2842,9.6603],"type":"Point"}
}