{
  "type": "Feature",
  "properties": {
    "gn:admin1_code":"20.0",
    "gn:asciiname":"Dang",
    "gn:country_code":"TD",
    "gn:dem":420,
    "gn:feature_class":"P",
    "gn:feature_code":"PPL",
    "gn:name":"Dang",
    "gn:population":0,
    "gn:timezone":"Africa/Ndjamena",
    "iso:country":"TD",
    "name:und_x_variant":[
        "Dan",
        "Dang"
    ],
    "wof:name":"Dang",
    "wof:placetype":"locality"
},
  "geometry": {"coordinates":[15.3485,8.8222],"type":"Point"}
}