{
  "type": "Feature",
  "properties": {
    "gn:admin1_code":"20.0",
    "gn:asciiname":"Dang",
    "gn:country_code":"TD",
    "gn:dem":420,
    "gn:feature_class":"P",
    "gn:feature_code":"PPL",
    "gn:name":"Dang",
    "gn:population":0,
    "gn:timezone":"Africa/Ndjamena",
    "iso:country":"TD",
    "name:ceb_x_preferred":[
        "Dang"
    ],
    "name:deu_x_preferred":[
        "Dang"
    ],
    "name:fra_x_preferred":[
        "Dang"
    ],
    "name:nld_x_preferred":[
        "Dang"
    ],
    "name:swe_x_preferred":[
        "Dang"
    ],
    "name:tam_x_preferred":[
        "\u0b9f\u0bbe\u0b99\u0bcd \u0bae\u0bbe\u0bb5\u0b9f\u0bcd\u0b9f\u0bae\u0bcd"
    ],
    "name:und_x_variant":[
        "Dan"
    ],
    "wof:name":"Dang",
    "wof:placetype":"locality"
},
  "geometry": {"coordinates":[15.3485,8.8222],"type":"Point"}
}