{
  "type": "Feature",
  "properties": {
    "gn:admin1_code":"9.0",
    "gn:asciiname":"Bakouadenedje",
    "gn:country_code":"TD",
    "gn:dem":472,
    "gn:feature_class":"P",
    "gn:feature_code":"PPL",
    "gn:name":"Bakouad\u00e9n\u00e9dje",
    "gn:population":0,
    "gn:timezone":"Africa/Ndjamena",
    "iso:country":"TD",
    "wof:name":"Bakouadenedje",
    "wof:placetype":"locality"
},
  "geometry": {"coordinates":[16.2692,8.3029],"type":"Point"}
}