{
  "type": "Feature",
  "properties": {
    "gn:admin1_code":"15.0",
    "gn:asciiname":"Gadang",
    "gn:country_code":"TD",
    "gn:dem":338,
    "gn:feature_class":"P",
    "gn:feature_code":"PPL",
    "gn:name":"Gadang",
    "gn:population":0,
    "gn:timezone":"Africa/Ndjamena",
    "iso:country":"TD",
    "wof:name":"Gadang",
    "wof:placetype":"locality"
},
  "geometry": {"coordinates":[16.8184,10.4436],"type":"Point"}
}