{
  "type": "Feature",
  "properties": {
    "gn:admin1_code":"7.0",
    "gn:asciiname":"Iga",
    "gn:country_code":"TD",
    "gn:dem":295,
    "gn:feature_class":"P",
    "gn:feature_code":"PPL",
    "gn:name":"Iga",
    "gn:population":0,
    "gn:timezone":"Africa/Ndjamena",
    "iso:country":"TD",
    "wof:name":"Iga",
    "wof:placetype":"locality"
},
  "geometry": {"coordinates":[14.96667,13.35],"type":"Point"}
}