{
  "type": "Feature",
  "properties": {
    "gn:admin1_code":"5.0",
    "gn:asciiname":"Domboti",
    "gn:country_code":"TD",
    "gn:dem":554,
    "gn:feature_class":"P",
    "gn:feature_code":"PPL",
    "gn:name":"Domboti",
    "gn:population":0,
    "gn:timezone":"Africa/Ndjamena",
    "iso:country":"TD",
    "name:und_x_variant":[
        "Demboti",
        "Domboti"
    ],
    "wof:name":"Domboti",
    "wof:placetype":"locality"
},
  "geometry": {"coordinates":[19.0032,11.9938],"type":"Point"}
}