{
  "type": "Feature",
  "properties": {
    "gn:admin1_code":"15.0",
    "gn:asciiname":"Tomat",
    "gn:country_code":"TD",
    "gn:dem":306,
    "gn:feature_class":"P",
    "gn:feature_code":"PPL",
    "gn:name":"Tomat",
    "gn:population":0,
    "gn:timezone":"Africa/Ndjamena",
    "iso:country":"TD",
    "wof:name":"Tomat",
    "wof:placetype":"locality"
},
  "geometry": {"coordinates":[15.51867,11.72549],"type":"Point"}
}