{
  "type": "Feature",
  "properties": {
    "gn:admin1_code":"12.0",
    "gn:asciiname":"Igueme",
    "gn:country_code":"TD",
    "gn:dem":605,
    "gn:feature_class":"P",
    "gn:feature_code":"PPL",
    "gn:name":"Igu\u00e9m\u00e9",
    "gn:population":0,
    "gn:timezone":"Africa/Ndjamena",
    "iso:country":"TD",
    "name:und_x_variant":[
        "Igu\u00e9m\u00e9",
        "Ig\u00e9m\u00e9"
    ],
    "wof:name":"Igueme",
    "wof:placetype":"locality"
},
  "geometry": {"coordinates":[21.2265,13.25684],"type":"Point"}
}