{
  "type": "Feature",
  "properties": {
    "gn:admin1_code":"9.0",
    "gn:asciiname":"Nankesse",
    "gn:country_code":"TD",
    "gn:dem":390,
    "gn:feature_class":"P",
    "gn:feature_code":"PPL",
    "gn:name":"Nank\u00e9ss\u00e9",
    "gn:population":0,
    "gn:timezone":"Africa/Ndjamena",
    "iso:country":"TD",
    "name:fra_x_preferred":[
        "Nankasi"
    ],
    "name:fra_x_variant":[
        "Nakasse"
    ],
    "name:und_x_variant":[
        "Nankasi",
        "Nakasse",
        "Nank\u00e9ss\u00e9"
    ],
    "wof:name":"Nankesse",
    "wof:placetype":"locality"
},
  "geometry": {"coordinates":[16.80692,8.73161],"type":"Point"}
}