{
  "type": "Feature",
  "properties": {
    "gn:admin1_code":"25.0",
    "gn:asciiname":"Sangara",
    "gn:country_code":"TD",
    "gn:dem":538,
    "gn:feature_class":"P",
    "gn:feature_code":"PPL",
    "gn:name":"Sangara",
    "gn:population":0,
    "gn:timezone":"Africa/Ndjamena",
    "iso:country":"TD",
    "wof:name":"Sangara",
    "wof:placetype":"locality"
},
  "geometry": {"coordinates":[22.04176,11.92907],"type":"Point"}
}