{
  "type": "Feature",
  "properties": {
    "gn:admin1_code":"14.0",
    "gn:asciiname":"Ninde",
    "gn:country_code":"TD",
    "gn:dem":351,
    "gn:feature_class":"P",
    "gn:feature_code":"PPL",
    "gn:name":"Nind\u00e9",
    "gn:population":0,
    "gn:timezone":"Africa/Ndjamena",
    "iso:country":"TD",
    "name:ara_x_preferred":[
        "\u0646\u064a\u0646\u062f\u064a"
    ],
    "name:ceb_x_preferred":[
        "Ninde"
    ],
    "name:ell_x_preferred":[
        "\u039d\u03af\u03bd\u03c4\u03b5"
    ],
    "name:fas_x_preferred":[
        "\u0646\u06cc\u0646\u062f\u0647"
    ],
    "name:heb_x_preferred":[
        "\u05e0\u05d9\u05e0\u05d3\u05d4"
    ],
    "name:hin_x_preferred":[
        "\u0928\u093f\u0902\u0921\u0947"
    ],
    "name:hun_x_preferred":[
        "Ninde"
    ],
    "name:ind_x_preferred":[
        "Ninde"
    ],
    "name:pol_x_preferred":[
        "Ninde"
    ],
    "name:por_x_preferred":[
        "Ninde"
    ],
    "name:swe_x_preferred":[
        "Ninde"
    ],
    "name:tur_x_preferred":[
        "Ninde"
    ],
    "name:ukr_x_preferred":[
        "\u041d\u0456\u043d\u0434\u0435"
    ],
    "name:urd_x_preferred":[
        "\u0646\u0646\u062f\u06d2"
    ],
    "wof:name":"Ninde",
    "wof:placetype":"locality"
},
  "geometry": {"coordinates":[16.31122,9.6744],"type":"Point"}
}