{
  "type": "Feature",
  "properties": {
    "gn:admin1_code":"14.0",
    "gn:asciiname":"Ninde",
    "gn:country_code":"TD",
    "gn:dem":351,
    "gn:feature_class":"P",
    "gn:feature_code":"PPL",
    "gn:name":"Nind\u00e9",
    "gn:population":0,
    "gn:timezone":"Africa/Ndjamena",
    "iso:country":"TD",
    "name:ceb_x_preferred":[
        "Ninde"
    ],
    "name:swe_x_preferred":[
        "Ninde"
    ],
    "wof:name":"Ninde",
    "wof:placetype":"locality"
},
  "geometry": {"coordinates":[16.31122,9.6744],"type":"Point"}
}