{
  "type": "Feature",
  "properties": {
    "gn:admin1_code":"9.0",
    "gn:asciiname":"Timberi",
    "gn:country_code":"TD",
    "gn:dem":441,
    "gn:feature_class":"P",
    "gn:feature_code":"PPL",
    "gn:name":"Timb\u00e9ri",
    "gn:population":0,
    "gn:timezone":"Africa/Ndjamena",
    "iso:country":"TD",
    "name:fra_x_preferred":[
        "Timb\u00e9ri"
    ],
    "wof:name":"Timberi",
    "wof:placetype":"locality"
},
  "geometry": {"coordinates":[16.52218,8.15018],"type":"Point"}
}