{
  "type": "Feature",
  "properties": {
    "gn:admin1_code":"7.0",
    "gn:asciiname":"Naza",
    "gn:country_code":"TD",
    "gn:dem":297,
    "gn:feature_class":"P",
    "gn:feature_code":"PPL",
    "gn:name":"Naza",
    "gn:population":0,
    "gn:timezone":"Africa/Ndjamena",
    "iso:country":"TD",
    "name:deu_x_preferred":[
        "Naza"
    ],
    "name:fra_x_preferred":[
        "Naza"
    ],
    "name:kur_x_preferred":[
        "Naza"
    ],
    "name:msa_x_preferred":[
        "Naza"
    ],
    "name:nld_x_preferred":[
        "Naza"
    ],
    "name:por_x_preferred":[
        "Naza"
    ],
    "wof:name":"Naza",
    "wof:placetype":"locality"
},
  "geometry": {"coordinates":[15.66747,13.22757],"type":"Point"}
}