{
  "type": "Feature",
  "properties": {
    "gn:admin1_code":"8.0",
    "gn:asciiname":"Bemrang",
    "gn:country_code":"TD",
    "gn:dem":454,
    "gn:feature_class":"P",
    "gn:feature_code":"PPL",
    "gn:name":"B\u00e8mrang",
    "gn:population":0,
    "gn:timezone":"Africa/Ndjamena",
    "iso:country":"TD",
    "wof:name":"Bemrang",
    "wof:placetype":"locality"
},
  "geometry": {"coordinates":[15.90292,8.83791],"type":"Point"}
}