{
  "type": "Feature",
  "properties": {
    "gn:admin1_code":"7.0",
    "gn:asciiname":"Sowala",
    "gn:country_code":"TD",
    "gn:dem":291,
    "gn:feature_class":"P",
    "gn:feature_code":"PPL",
    "gn:name":"Sowala",
    "gn:population":0,
    "gn:timezone":"Africa/Ndjamena",
    "iso:country":"TD",
    "wof:name":"Sowala",
    "wof:placetype":"locality"
},
  "geometry": {"coordinates":[15.55394,13.38019],"type":"Point"}
}