{
  "type": "Feature",
  "properties": {
    "gn:admin1_code":"1.0",
    "gn:asciiname":"Chiguek",
    "gn:country_code":"TD",
    "gn:dem":385,
    "gn:feature_class":"P",
    "gn:feature_code":"PPL",
    "gn:name":"Chiguek",
    "gn:population":0,
    "gn:timezone":"Africa/Ndjamena",
    "iso:country":"TD",
    "name:und_x_variant":[
        "Chigek",
        "Chiguek"
    ],
    "wof:name":"Chiguek",
    "wof:placetype":"locality"
},
  "geometry": {"coordinates":[19.5898,13.5462],"type":"Point"}
}