{
  "type": "Feature",
  "properties": {
    "gn:admin1_code":"19.0",
    "gn:asciiname":"Morom I",
    "gn:country_code":"TD",
    "gn:dem":376,
    "gn:feature_class":"P",
    "gn:feature_code":"PPL",
    "gn:name":"Morom I",
    "gn:population":0,
    "gn:timezone":"Africa/Ndjamena",
    "iso:country":"TD",
    "wof:name":"Morom I",
    "wof:placetype":"locality"
},
  "geometry": {"coordinates":[17.46368,9.42999],"type":"Point"}
}