{
  "type": "Feature",
  "properties": {
    "gn:admin1_code":"15.0",
    "gn:asciiname":"Abougarga",
    "gn:country_code":"TD",
    "gn:dem":309,
    "gn:feature_class":"P",
    "gn:feature_code":"PPL",
    "gn:name":"Abougarga",
    "gn:population":0,
    "gn:timezone":"Africa/Ndjamena",
    "iso:country":"TD",
    "wof:name":"Abougarga",
    "wof:placetype":"locality"
},
  "geometry": {"coordinates":[16.4074,11.9549],"type":"Point"}
}