{
  "type": "Feature",
  "properties": {
    "gn:admin1_code":"12.0",
    "gn:asciiname":"Magaren",
    "gn:country_code":"TD",
    "gn:dem":478,
    "gn:feature_class":"P",
    "gn:feature_code":"PPL",
    "gn:name":"Magaren",
    "gn:population":0,
    "gn:timezone":"Africa/Ndjamena",
    "iso:country":"TD",
    "name:fra_x_preferred":[
        "Magaren"
    ],
    "wof:name":"Magaren",
    "wof:placetype":"locality"
},
  "geometry": {"coordinates":[20.61625,13.58554],"type":"Point"}
}