{
  "type": "Feature",
  "properties": {
    "gn:admin1_code":"12.0",
    "gn:asciiname":"Misterede",
    "gn:country_code":"TD",
    "gn:dem":512,
    "gn:feature_class":"P",
    "gn:feature_code":"PPL",
    "gn:name":"Mist\u00e9r\u00e9d\u00e9",
    "gn:population":0,
    "gn:timezone":"Africa/Ndjamena",
    "iso:country":"TD",
    "name:fra_x_preferred":[
        "Mist\u00e9r\u00e9d\u00e9"
    ],
    "wof:name":"Misterede",
    "wof:placetype":"locality"
},
  "geometry": {"coordinates":[20.566,13.87033],"type":"Point"}
}