{
  "type": "Feature",
  "properties": {
    "gn:admin1_code":"18.0",
    "gn:asciiname":"Kougouna",
    "gn:country_code":"TD",
    "gn:dem":290,
    "gn:feature_class":"P",
    "gn:feature_code":"PPL",
    "gn:name":"Kougouna",
    "gn:population":0,
    "gn:timezone":"Africa/Ndjamena",
    "iso:country":"TD",
    "name:und_x_variant":[
        "Kongona",
        "Kougouna"
    ],
    "wof:name":"Kougouna",
    "wof:placetype":"locality"
},
  "geometry": {"coordinates":[15.43839,12.93305],"type":"Point"}
}