{
  "type": "Feature",
  "properties": {
    "gn:admin1_code":"7.0",
    "gn:asciiname":"Bounanay",
    "gn:country_code":"TD",
    "gn:dem":306,
    "gn:feature_class":"P",
    "gn:feature_code":"PPL",
    "gn:name":"Bounanay",
    "gn:population":0,
    "gn:timezone":"Africa/Ndjamena",
    "iso:country":"TD",
    "wof:name":"Bounanay",
    "wof:placetype":"locality"
},
  "geometry": {"coordinates":[15.14667,13.70071],"type":"Point"}
}