{
  "type": "Feature",
  "properties": {
    "gn:admin1_code":"18.0",
    "gn:asciiname":"Al Alouis",
    "gn:country_code":"TD",
    "gn:dem":292,
    "gn:feature_class":"P",
    "gn:feature_code":"PPL",
    "gn:name":"Al Alouis",
    "gn:population":0,
    "gn:timezone":"Africa/Ndjamena",
    "iso:country":"TD",
    "name:und_x_variant":[
        "Al Alaouis",
        "Al Alouis"
    ],
    "wof:name":"Al Alouis",
    "wof:placetype":"locality"
},
  "geometry": {"coordinates":[15.88514,12.50556],"type":"Point"}
}