{
  "type": "Feature",
  "properties": {
    "gn:admin1_code":"15.0",
    "gn:asciiname":"Al Fas",
    "gn:country_code":"TD",
    "gn:dem":298,
    "gn:feature_class":"P",
    "gn:feature_code":"PPL",
    "gn:name":"Al Fas",
    "gn:population":0,
    "gn:timezone":"Africa/Ndjamena",
    "iso:country":"TD",
    "name:und_x_variant":[
        "El Fas",
        "Al Fa\u00ef",
        "Al Fas"
    ],
    "wof:name":"Al Fas",
    "wof:placetype":"locality"
},
  "geometry": {"coordinates":[15.22609,12.02771],"type":"Point"}
}