{
  "type": "Feature",
  "properties": {
    "gn:admin1_code":"16.0",
    "gn:asciiname":"Kakale",
    "gn:country_code":"TD",
    "gn:dem":320,
    "gn:feature_class":"P",
    "gn:feature_code":"PPL",
    "gn:name":"Kakal\u00e9",
    "gn:population":0,
    "gn:timezone":"Africa/Ndjamena",
    "iso:country":"TD",
    "name:und_x_variant":[
        "Kakel\u00e9",
        "Kakal\u00e9"
    ],
    "wof:name":"Kakale",
    "wof:placetype":"locality"
},
  "geometry": {"coordinates":[15.59613,10.89862],"type":"Point"}
}