{
  "type": "Feature",
  "properties": {
    "gn:admin1_code":"15.0",
    "gn:asciiname":"Maibo Tchoumou",
    "gn:country_code":"TD",
    "gn:dem":341,
    "gn:feature_class":"P",
    "gn:feature_code":"PPL",
    "gn:name":"Ma\u00efbo Tchoumou",
    "gn:population":0,
    "gn:timezone":"Africa/Ndjamena",
    "iso:country":"TD",
    "wof:name":"Maibo Tchoumou",
    "wof:placetype":"locality"
},
  "geometry": {"coordinates":[17.21221,10.65173],"type":"Point"}
}