{
  "type": "Feature",
  "properties": {
    "gn:admin1_code":"15.0",
    "gn:asciiname":"Madjonka",
    "gn:country_code":"TD",
    "gn:dem":334,
    "gn:feature_class":"P",
    "gn:feature_code":"PPL",
    "gn:name":"Madjonka",
    "gn:population":0,
    "gn:timezone":"Africa/Ndjamena",
    "iso:country":"TD",
    "wof:name":"Madjonka",
    "wof:placetype":"locality"
},
  "geometry": {"coordinates":[16.1601,10.382],"type":"Point"}
}