{
  "type": "Feature",
  "properties": {
    "gn:admin1_code":"14.0",
    "gn:asciiname":"Dalona",
    "gn:country_code":"TD",
    "gn:dem":361,
    "gn:feature_class":"P",
    "gn:feature_code":"PPL",
    "gn:name":"Dalona",
    "gn:population":0,
    "gn:timezone":"Africa/Ndjamena",
    "iso:country":"TD",
    "wof:name":"Dalona",
    "wof:placetype":"locality"
},
  "geometry": {"coordinates":[16.2678,9.2799],"type":"Point"}
}