{
  "type": "Feature",
  "properties": {
    "gn:admin1_code":"12.0",
    "gn:asciiname":"Goudoumi",
    "gn:country_code":"TD",
    "gn:dem":821,
    "gn:feature_class":"P",
    "gn:feature_code":"PPL",
    "gn:name":"Goudoumi",
    "gn:population":0,
    "gn:timezone":"Africa/Ndjamena",
    "iso:country":"TD",
    "wof:name":"Goudoumi",
    "wof:placetype":"locality"
},
  "geometry": {"coordinates":[21.98817,13.30853],"type":"Point"}
}