{
  "type": "Feature",
  "properties": {
    "gn:admin1_code":"15.0",
    "gn:asciiname":"Guederi",
    "gn:country_code":"TD",
    "gn:dem":337,
    "gn:feature_class":"P",
    "gn:feature_code":"PPL",
    "gn:name":"Gu\u00e9d\u00e9ri",
    "gn:population":0,
    "gn:timezone":"Africa/Ndjamena",
    "iso:country":"TD",
    "name:und_x_variant":[
        "G\u00e9d\u00e9ri",
        "Gu\u00e9d\u00e9ri"
    ],
    "wof:name":"Guederi",
    "wof:placetype":"locality"
},
  "geometry": {"coordinates":[16.0889,11.6498],"type":"Point"}
}