{
  "type": "Feature",
  "properties": {
    "gn:admin1_code":"19.0",
    "gn:asciiname":"Gango",
    "gn:country_code":"TD",
    "gn:dem":419,
    "gn:feature_class":"P",
    "gn:feature_code":"PPL",
    "gn:name":"Gango",
    "gn:population":0,
    "gn:timezone":"Africa/Ndjamena",
    "iso:country":"TD",
    "wof:name":"Gango",
    "wof:placetype":"locality"
},
  "geometry": {"coordinates":[17.70772000000001,9.00313],"type":"Point"}
}