{
  "type": "Feature",
  "properties": {
    "gn:admin1_code":"9.0",
    "gn:asciiname":"Dagbao",
    "gn:country_code":"TD",
    "gn:dem":621,
    "gn:feature_class":"P",
    "gn:feature_code":"PPL",
    "gn:name":"Dagbao",
    "gn:population":0,
    "gn:timezone":"Africa/Ndjamena",
    "iso:country":"TD",
    "wof:name":"Dagbao",
    "wof:placetype":"locality"
},
  "geometry": {"coordinates":[15.8854,7.6508],"type":"Point"}
}