{
  "type": "Feature",
  "properties": {
    "gn:admin1_code":"25.0",
    "gn:asciiname":"Bouroukou",
    "gn:country_code":"TD",
    "gn:dem":632,
    "gn:feature_class":"P",
    "gn:feature_code":"PPL",
    "gn:name":"Bouroukou",
    "gn:population":0,
    "gn:timezone":"Africa/Ndjamena",
    "iso:country":"TD",
    "name:und_x_variant":[
        "Borokou",
        "Bouroukou"
    ],
    "wof:name":"Bouroukou",
    "wof:placetype":"locality"
},
  "geometry": {"coordinates":[21.55,12.43333],"type":"Point"}
}