{
  "type": "Feature",
  "properties": {
    "gn:admin1_code":"19.0",
    "gn:asciiname":"Bekamba",
    "gn:country_code":"TD",
    "gn:dem":376,
    "gn:feature_class":"P",
    "gn:feature_code":"PPL",
    "gn:name":"B\u00e9kamba",
    "gn:population":0,
    "gn:timezone":"Africa/Ndjamena",
    "iso:country":"TD",
    "name:und_x_variant":[
        "Bakamba",
        "Bekoumbo",
        "B\u00e9kamba"
    ],
    "wof:name":"Bekamba",
    "wof:placetype":"locality"
},
  "geometry": {"coordinates":[17.3877,8.7101],"type":"Point"}
}