{
  "type": "Feature",
  "properties": {
    "gn:admin1_code":"9.0",
    "gn:asciiname":"Kilanga",
    "gn:country_code":"TD",
    "gn:dem":422,
    "gn:feature_class":"P",
    "gn:feature_code":"PPL",
    "gn:name":"Kilanga",
    "gn:population":0,
    "gn:timezone":"Africa/Ndjamena",
    "iso:country":"TD",
    "wof:name":"Kilanga",
    "wof:placetype":"locality"
},
  "geometry": {"coordinates":[16.30642000000001,8.60921],"type":"Point"}
}