{
  "type": "Feature",
  "properties": {
    "gn:admin1_code":"2.0",
    "gn:asciiname":"Damere",
    "gn:country_code":"TD",
    "gn:dem":887,
    "gn:feature_class":"P",
    "gn:feature_code":"PPL",
    "gn:name":"Dam\u00e9r\u00e9",
    "gn:population":0,
    "gn:timezone":"Africa/Ndjamena",
    "iso:country":"TD",
    "name:fra_x_preferred":[
        "Dam\u00e9r\u00e9"
    ],
    "wof:name":"Damere",
    "wof:placetype":"locality"
},
  "geometry": {"coordinates":[21.36571,14.326],"type":"Point"}
}