{
  "type": "Feature",
  "properties": {
    "gn:admin1_code":"1.0",
    "gn:asciiname":"Metame",
    "gn:country_code":"TD",
    "gn:dem":416,
    "gn:feature_class":"P",
    "gn:feature_code":"PPL",
    "gn:name":"M\u00e9tam\u00e9",
    "gn:population":0,
    "gn:timezone":"Africa/Ndjamena",
    "iso:country":"TD",
    "name:fra_x_preferred":[
        "M\u00e9tam\u00e9"
    ],
    "wof:name":"Metame",
    "wof:placetype":"locality"
},
  "geometry": {"coordinates":[20.07558,13.83652],"type":"Point"}
}