{
  "type": "Feature",
  "properties": {
    "gn:admin1_code":"8.0",
    "gn:asciiname":"Lao",
    "gn:country_code":"TD",
    "gn:dem":457,
    "gn:feature_class":"P",
    "gn:feature_code":"PPL",
    "gn:name":"Lao",
    "gn:population":0,
    "gn:timezone":"Africa/Ndjamena",
    "iso:country":"TD",
    "name:cat_x_preferred":[
        "Lao"
    ],
    "name:ceb_x_preferred":[
        "Lao"
    ],
    "name:cym_x_preferred":[
        "Lao"
    ],
    "name:fin_x_preferred":[
        "Lao"
    ],
    "name:fra_x_preferred":[
        "Lao"
    ],
    "name:hrv_x_preferred":[
        "Lao"
    ],
    "name:nld_x_preferred":[
        "Lao"
    ],
    "name:pol_x_preferred":[
        "Lao"
    ],
    "name:por_x_preferred":[
        "Lao"
    ],
    "name:spa_x_preferred":[
        "Lao"
    ],
    "name:swe_x_preferred":[
        "Lao"
    ],
    "name:uzb_x_preferred":[
        "Lao"
    ],
    "name:vie_x_preferred":[
        "Lao"
    ],
    "wof:name":"Lao",
    "wof:placetype":"locality"
},
  "geometry": {"coordinates":[15.93333,8.83333],"type":"Point"}
}