{
  "type": "Feature",
  "properties": {
    "gn:admin1_code":"14.0",
    "gn:asciiname":"Kaimi",
    "gn:country_code":"TD",
    "gn:dem":358,
    "gn:feature_class":"P",
    "gn:feature_code":"PPL",
    "gn:name":"Ka\u00efmi",
    "gn:population":0,
    "gn:timezone":"Africa/Ndjamena",
    "iso:country":"TD",
    "name:ceb_x_preferred":[
        "Kaimi"
    ],
    "name:est_x_preferred":[
        "Kaimi"
    ],
    "name:hye_x_preferred":[
        "\u053f\u0561\u056b\u0574\u056b"
    ],
    "name:pol_x_preferred":[
        "Kaimi"
    ],
    "name:spa_x_preferred":[
        "Kaimi"
    ],
    "name:swe_x_preferred":[
        "Kaimi"
    ],
    "name:ukr_x_preferred":[
        "\u041a\u0430\u0439\u043c\u0456"
    ],
    "name:vol_x_preferred":[
        "Kaimi"
    ],
    "wof:name":"Kaimi",
    "wof:placetype":"locality"
},
  "geometry": {"coordinates":[16.8839,9.2825],"type":"Point"}
}