{
  "type": "Feature",
  "properties": {
    "gn:admin1_code":"18.0",
    "gn:asciiname":"El Haouich",
    "gn:country_code":"TD",
    "gn:dem":293,
    "gn:feature_class":"P",
    "gn:feature_code":"PPL",
    "gn:name":"El Haouich",
    "gn:population":0,
    "gn:timezone":"Africa/Ndjamena",
    "iso:country":"TD",
    "name:und_x_variant":[
        "El Haouish",
        "El Haouich"
    ],
    "wof:name":"El Haouich",
    "wof:placetype":"locality"
},
  "geometry": {"coordinates":[15.38579,12.56899],"type":"Point"}
}