{
  "type": "Feature",
  "properties": {
    "gn:admin1_code":"17.0",
    "gn:asciiname":"Kemkaba",
    "gn:country_code":"TD",
    "gn:dem":371,
    "gn:feature_class":"P",
    "gn:feature_code":"PPL",
    "gn:name":"Kemkaba",
    "gn:population":0,
    "gn:timezone":"Africa/Ndjamena",
    "iso:country":"TD",
    "wof:name":"Kemkaba",
    "wof:placetype":"locality"
},
  "geometry": {"coordinates":[18.66667,8.81667],"type":"Point"}
}