{
  "type": "Feature",
  "properties": {
    "gn:admin1_code":"15.0",
    "gn:asciiname":"Hidjilidje",
    "gn:country_code":"TD",
    "gn:dem":299,
    "gn:feature_class":"P",
    "gn:feature_code":"PPL",
    "gn:name":"Hidjilidj\u00e9",
    "gn:population":0,
    "gn:timezone":"Africa/Ndjamena",
    "iso:country":"TD",
    "name:und_x_variant":[
        "Hidjelidj",
        "Hidjilidj\u00e9"
    ],
    "wof:name":"Hidjilidje",
    "wof:placetype":"locality"
},
  "geometry": {"coordinates":[15.87375,12.15739],"type":"Point"}
}