{
  "type": "Feature",
  "properties": {
    "gn:admin1_code":"16.0",
    "gn:asciiname":"Maillim",
    "gn:country_code":"TD",
    "gn:dem":312,
    "gn:feature_class":"P",
    "gn:feature_code":"PPL",
    "gn:name":"Ma\u00efllim",
    "gn:population":0,
    "gn:timezone":"Africa/Ndjamena",
    "iso:country":"TD",
    "name:und_x_variant":[
        "Ma\u00eflem",
        "Ma\u00efllim"
    ],
    "wof:name":"Maillim",
    "wof:placetype":"locality"
},
  "geometry": {"coordinates":[15.37015,11.1592],"type":"Point"}
}