{
  "type": "Feature",
  "properties": {
    "gn:admin1_code":"19.0",
    "gn:asciiname":"Kiran",
    "gn:country_code":"TD",
    "gn:dem":391,
    "gn:feature_class":"P",
    "gn:feature_code":"PPL",
    "gn:name":"Kiran",
    "gn:population":0,
    "gn:timezone":"Africa/Ndjamena",
    "iso:country":"TD",
    "name:ceb_x_preferred":[
        "Kiran"
    ],
    "name:deu_x_preferred":[
        "Kiran"
    ],
    "name:hin_x_preferred":[
        "\u0915\u093f\u0930\u0923"
    ],
    "wof:name":"Kiran",
    "wof:placetype":"locality"
},
  "geometry": {"coordinates":[17.52139,8.28221],"type":"Point"}
}