{
  "type": "Feature",
  "properties": {
    "gn:admin1_code":"19.0",
    "gn:asciiname":"Maikan",
    "gn:country_code":"TD",
    "gn:dem":387,
    "gn:feature_class":"P",
    "gn:feature_code":"PPL",
    "gn:name":"Ma\u00efkan",
    "gn:population":0,
    "gn:timezone":"Africa/Ndjamena",
    "iso:country":"TD",
    "wof:name":"Maikan",
    "wof:placetype":"locality"
},
  "geometry": {"coordinates":[17.764,8.3786],"type":"Point"}
}