{
  "type": "Feature",
  "properties": {
    "gn:admin1_code":"5.0",
    "gn:asciiname":"Am Bourtouk Bandar",
    "gn:country_code":"TD",
    "gn:dem":397,
    "gn:feature_class":"P",
    "gn:feature_code":"PPL",
    "gn:name":"Am Bourtouk Bandar",
    "gn:population":0,
    "gn:timezone":"Africa/Ndjamena",
    "iso:country":"TD",
    "wof:name":"Am Bourtouk Bandar",
    "wof:placetype":"locality"
},
  "geometry": {"coordinates":[19.5585,12.8575],"type":"Point"}
}