{
  "type": "Feature",
  "properties": {
    "gn:admin1_code":"17.0",
    "gn:asciiname":"Kalmouna",
    "gn:country_code":"TD",
    "gn:dem":361,
    "gn:feature_class":"P",
    "gn:feature_code":"PPL",
    "gn:name":"Kalmouna",
    "gn:population":0,
    "gn:timezone":"Africa/Ndjamena",
    "iso:country":"TD",
    "wof:name":"Kalmouna",
    "wof:placetype":"locality"
},
  "geometry": {"coordinates":[17.79952,9.97003],"type":"Point"}
}