{
  "type": "Feature",
  "properties": {
    "gn:admin1_code":"17.0",
    "gn:asciiname":"Yanga",
    "gn:country_code":"TD",
    "gn:dem":386,
    "gn:feature_class":"P",
    "gn:feature_code":"PPL",
    "gn:name":"Yanga",
    "gn:population":0,
    "gn:timezone":"Africa/Ndjamena",
    "iso:country":"TD",
    "name:ceb_x_preferred":[
        "Yanga"
    ],
    "name:deu_x_preferred":[
        "Yanga"
    ],
    "name:fra_x_preferred":[
        "Yanga"
    ],
    "name:rus_x_preferred":[
        "\u042f\u043d\u0433\u0430"
    ],
    "name:swe_x_preferred":[
        "Yanga"
    ],
    "wof:name":"Yanga",
    "wof:placetype":"locality"
},
  "geometry": {"coordinates":[18.9257,9.9806],"type":"Point"}
}