{
  "type": "Feature",
  "properties": {
    "gn:admin1_code":"15.0",
    "gn:asciiname":"Djokhine",
    "gn:country_code":"TD",
    "gn:dem":298,
    "gn:feature_class":"P",
    "gn:feature_code":"PPL",
    "gn:name":"Djokhin\u00e9",
    "gn:population":0,
    "gn:timezone":"Africa/Ndjamena",
    "iso:country":"TD",
    "name:und_x_variant":[
        "Diokhin\u00e9",
        "Djokhin\u00e9"
    ],
    "wof:name":"Djokhine",
    "wof:placetype":"locality"
},
  "geometry": {"coordinates":[15.42588,12.06606],"type":"Point"}
}