{
  "type": "Feature",
  "properties": {
    "gn:admin1_code":"12.0",
    "gn:asciiname":"Djiminofou",
    "gn:country_code":"TD",
    "gn:dem":545,
    "gn:feature_class":"P",
    "gn:feature_code":"PPL",
    "gn:name":"Djiminofou",
    "gn:population":0,
    "gn:timezone":"Africa/Ndjamena",
    "iso:country":"TD",
    "name:fra_x_preferred":[
        "Djiminofou"
    ],
    "wof:name":"Djiminofou",
    "wof:placetype":"locality"
},
  "geometry": {"coordinates":[20.83167000000001,13.80864],"type":"Point"}
}