{
  "type": "Feature",
  "properties": {
    "gn:admin1_code":"22.0",
    "gn:asciiname":"Eri",
    "gn:country_code":"TD",
    "gn:dem":310,
    "gn:feature_class":"P",
    "gn:feature_code":"PPL",
    "gn:name":"Eri",
    "gn:population":0,
    "gn:timezone":"Africa/Ndjamena",
    "iso:country":"TD",
    "name:ceb_x_preferred":[
        "Eri"
    ],
    "name:fra_x_preferred":[
        "Eri"
    ],
    "name:hun_x_preferred":[
        "\u00c9ri"
    ],
    "name:pol_x_preferred":[
        "Eri"
    ],
    "name:por_x_preferred":[
        "Eri"
    ],
    "name:ron_x_preferred":[
        "Eri"
    ],
    "name:swe_x_preferred":[
        "Eri"
    ],
    "name:tha_x_preferred":[
        "\u0e40\u0e2d\u0e23\u0e34"
    ],
    "wof:name":"Eri",
    "wof:placetype":"locality"
},
  "geometry": {"coordinates":[15.74861,13.99356],"type":"Point"}
}