{
  "type": "Feature",
  "properties": {
    "gn:admin1_code":"12.0",
    "gn:asciiname":"Badine",
    "gn:country_code":"TD",
    "gn:dem":451,
    "gn:feature_class":"P",
    "gn:feature_code":"PPL",
    "gn:name":"Badin\u00e9",
    "gn:population":0,
    "gn:timezone":"Africa/Ndjamena",
    "iso:country":"TD",
    "name:fra_x_preferred":[
        "Badin\u00e9"
    ],
    "wof:name":"Badine",
    "wof:placetype":"locality"
},
  "geometry": {"coordinates":[20.40395,13.81665],"type":"Point"}
}