{
  "type": "Feature",
  "properties": {
    "gn:admin1_code":"2.0",
    "gn:asciiname":"Nimeringa",
    "gn:country_code":"TD",
    "gn:dem":881,
    "gn:feature_class":"P",
    "gn:feature_code":"PPL",
    "gn:name":"Nim\u00e9ringa",
    "gn:population":0,
    "gn:timezone":"Africa/Ndjamena",
    "iso:country":"TD",
    "name:fra_x_preferred":[
        "Nim\u00e9ringa"
    ],
    "wof:name":"Nimeringa",
    "wof:placetype":"locality"
},
  "geometry": {"coordinates":[21.38105,14.3365],"type":"Point"}
}