{
  "type": "Feature",
  "properties": {
    "gn:admin1_code":"9.0",
    "gn:asciiname":"Kagroue",
    "gn:country_code":"TD",
    "gn:dem":389,
    "gn:feature_class":"P",
    "gn:feature_code":"PPL",
    "gn:name":"Kagrou\u00e9",
    "gn:population":0,
    "gn:timezone":"Africa/Ndjamena",
    "iso:country":"TD",
    "wof:name":"Kagroue",
    "wof:placetype":"locality"
},
  "geometry": {"coordinates":[16.73514,8.58444],"type":"Point"}
}