{
  "type": "Feature",
  "properties": {
    "gn:admin1_code":"1.0",
    "gn:asciiname":"Ad Dehera",
    "gn:country_code":"TD",
    "gn:dem":337,
    "gn:feature_class":"P",
    "gn:feature_code":"PPL",
    "gn:name":"Ad Dehera",
    "gn:population":0,
    "gn:timezone":"Africa/Ndjamena",
    "iso:country":"TD",
    "wof:name":"Ad Dehera",
    "wof:placetype":"locality"
},
  "geometry": {"coordinates":[18.2711,13.2054],"type":"Point"}
}