{
  "type": "Feature",
  "properties": {
    "gn:admin1_code":"7.0",
    "gn:asciiname":"Mourzougi",
    "gn:country_code":"TD",
    "gn:dem":292,
    "gn:feature_class":"P",
    "gn:feature_code":"PPL",
    "gn:name":"Mourzougi",
    "gn:population":0,
    "gn:timezone":"Africa/Ndjamena",
    "iso:country":"TD",
    "name:und_x_variant":[
        "Merzoug",
        "Mourzougi"
    ],
    "wof:name":"Mourzougi",
    "wof:placetype":"locality"
},
  "geometry": {"coordinates":[15.70908,13.64283],"type":"Point"}
}