{
  "type": "Feature",
  "properties": {
    "gn:admin1_code":"25.0",
    "gn:asciiname":"Dourti",
    "gn:country_code":"TD",
    "gn:dem":508,
    "gn:feature_class":"P",
    "gn:feature_code":"PPL",
    "gn:name":"Dourti",
    "gn:population":0,
    "gn:timezone":"Africa/Ndjamena",
    "iso:country":"TD",
    "wof:name":"Dourti",
    "wof:placetype":"locality"
},
  "geometry": {"coordinates":[21.58496,11.96912],"type":"Point"}
}