{
  "type": "Feature",
  "properties": {
    "gn:admin1_code":"2.0",
    "gn:asciiname":"Maraba",
    "gn:country_code":"TD",
    "gn:dem":948,
    "gn:feature_class":"P",
    "gn:feature_code":"PPL",
    "gn:name":"Maraba",
    "gn:population":0,
    "gn:timezone":"Africa/Ndjamena",
    "iso:country":"TD",
    "name:fra_x_preferred":[
        "Maraba"
    ],
    "wof:name":"Maraba",
    "wof:placetype":"locality"
},
  "geometry": {"coordinates":[21.92619,14.18541],"type":"Point"}
}