{
  "type": "Feature",
  "properties": {
    "gn:admin1_code":"12.0",
    "gn:asciiname":"Chokolki",
    "gn:country_code":"TD",
    "gn:dem":522,
    "gn:feature_class":"P",
    "gn:feature_code":"PPL",
    "gn:name":"Chokolki",
    "gn:population":0,
    "gn:timezone":"Africa/Ndjamena",
    "iso:country":"TD",
    "wof:name":"Chokolki",
    "wof:placetype":"locality"
},
  "geometry": {"coordinates":[21.25,12.95],"type":"Point"}
}