{
  "type": "Feature",
  "properties": {
    "gn:admin1_code":"9.0",
    "gn:asciiname":"Gongtou",
    "gn:country_code":"TD",
    "gn:dem":407,
    "gn:feature_class":"P",
    "gn:feature_code":"PPL",
    "gn:name":"Gongtou",
    "gn:population":0,
    "gn:timezone":"Africa/Ndjamena",
    "iso:country":"TD",
    "name:fra_x_preferred":[
        "Gongtou"
    ],
    "wof:name":"Gongtou",
    "wof:placetype":"locality"
},
  "geometry": {"coordinates":[16.42358,8.39821],"type":"Point"}
}