{
  "type": "Feature",
  "properties": {
    "gn:admin1_code":"12.0",
    "gn:asciiname":"Faral",
    "gn:country_code":"TD",
    "gn:dem":650,
    "gn:feature_class":"P",
    "gn:feature_code":"PPL",
    "gn:name":"Faral",
    "gn:population":0,
    "gn:timezone":"Africa/Ndjamena",
    "iso:country":"TD",
    "wof:name":"Faral",
    "wof:placetype":"locality"
},
  "geometry": {"coordinates":[21.11566,13.49049],"type":"Point"}
}