{
  "type": "Feature",
  "properties": {
    "gn:admin1_code":"26.0",
    "gn:asciiname":"Youryour",
    "gn:country_code":"TD",
    "gn:dem":1017,
    "gn:feature_class":"P",
    "gn:feature_code":"PPL",
    "gn:name":"Youryour",
    "gn:population":0,
    "gn:timezone":"Africa/Ndjamena",
    "iso:country":"TD",
    "wof:name":"Youryour",
    "wof:placetype":"locality"
},
  "geometry": {"coordinates":[16.98333,21.35],"type":"Point"}
}