{
  "type": "Feature",
  "properties": {
    "gn:admin1_code":"1.0",
    "gn:asciiname":"Yeli",
    "gn:country_code":"TD",
    "gn:dem":388,
    "gn:feature_class":"P",
    "gn:feature_code":"PPL",
    "gn:name":"Y\u00e9li",
    "gn:population":0,
    "gn:timezone":"Africa/Ndjamena",
    "iso:country":"TD",
    "name:ceb_x_preferred":[
        "Yeli"
    ],
    "name:swe_x_preferred":[
        "Yeli"
    ],
    "wof:name":"Yeli",
    "wof:placetype":"locality"
},
  "geometry": {"coordinates":[19.7167,13.8406],"type":"Point"}
}