{
  "type": "Feature",
  "properties": {
    "gn:admin1_code":"17.0",
    "gn:asciiname":"Kamkigna",
    "gn:country_code":"TD",
    "gn:dem":400,
    "gn:feature_class":"P",
    "gn:feature_code":"PPL",
    "gn:name":"Kamkigna",
    "gn:population":0,
    "gn:timezone":"Africa/Ndjamena",
    "iso:country":"TD",
    "name:und_x_variant":[
        "Kenkignan",
        "Kamkigna"
    ],
    "wof:name":"Kamkigna",
    "wof:placetype":"locality"
},
  "geometry": {"coordinates":[17.80613,9.65903],"type":"Point"}
}