{
  "type": "Feature",
  "properties": {
    "gn:admin1_code":"5.0",
    "gn:asciiname":"Sobo",
    "gn:country_code":"TD",
    "gn:dem":462,
    "gn:feature_class":"P",
    "gn:feature_code":"PPL",
    "gn:name":"Sobo",
    "gn:population":0,
    "gn:timezone":"Africa/Ndjamena",
    "iso:country":"TD",
    "name:hat_x_preferred":[
        "Sobo"
    ],
    "wof:name":"Sobo",
    "wof:placetype":"locality"
},
  "geometry": {"coordinates":[18.46667,10.71667],"type":"Point"}
}