{
  "type": "Feature",
  "properties": {
    "gn:admin1_code":"2.0",
    "gn:asciiname":"Anguioro",
    "gn:country_code":"TD",
    "gn:dem":783,
    "gn:feature_class":"P",
    "gn:feature_code":"PPL",
    "gn:name":"Anguioro",
    "gn:population":0,
    "gn:timezone":"Africa/Ndjamena",
    "iso:country":"TD",
    "name:fra_x_preferred":[
        "Anguioro"
    ],
    "name:fra_x_variant":[
        "Angioro"
    ],
    "wof:name":"Anguioro",
    "wof:placetype":"locality"
},
  "geometry": {"coordinates":[21.22256,14.13299],"type":"Point"}
}