{
  "type": "Feature",
  "properties": {
    "gn:admin1_code":"19.0",
    "gn:asciiname":"Gonbe",
    "gn:country_code":"TD",
    "gn:dem":375,
    "gn:feature_class":"P",
    "gn:feature_code":"PPL",
    "gn:name":"Gonb\u00e9",
    "gn:population":0,
    "gn:timezone":"Africa/Ndjamena",
    "iso:country":"TD",
    "name:und_x_variant":[
        "Gon\u00e9b\u00e9",
        "Gonb\u00e9"
    ],
    "wof:name":"Gonbe",
    "wof:placetype":"locality"
},
  "geometry": {"coordinates":[17.81441000000001,8.74169],"type":"Point"}
}