{
  "type": "Feature",
  "properties": {
    "gn:admin1_code":"19.0",
    "gn:asciiname":"Gatounou",
    "gn:country_code":"TD",
    "gn:dem":383,
    "gn:feature_class":"P",
    "gn:feature_code":"PPL",
    "gn:name":"Gatounou",
    "gn:population":0,
    "gn:timezone":"Africa/Ndjamena",
    "iso:country":"TD",
    "wof:name":"Gatounou",
    "wof:placetype":"locality"
},
  "geometry": {"coordinates":[17.38838,8.90819],"type":"Point"}
}