{
  "type": "Feature",
  "properties": {
    "gn:admin1_code":"7.0",
    "gn:asciiname":"Foufoua",
    "gn:country_code":"TD",
    "gn:dem":303,
    "gn:feature_class":"P",
    "gn:feature_code":"PPL",
    "gn:name":"Foufoua",
    "gn:population":0,
    "gn:timezone":"Africa/Ndjamena",
    "iso:country":"TD",
    "wof:name":"Foufoua",
    "wof:placetype":"locality"
},
  "geometry": {"coordinates":[15.71243,13.53636],"type":"Point"}
}