{
  "type": "Feature",
  "properties": {
    "gn:admin1_code":"19.0",
    "gn:asciiname":"Kakode",
    "gn:country_code":"TD",
    "gn:dem":407,
    "gn:feature_class":"P",
    "gn:feature_code":"PPL",
    "gn:name":"Kakod\u00e9",
    "gn:population":0,
    "gn:timezone":"Africa/Ndjamena",
    "iso:country":"TD",
    "wof:name":"Kakode",
    "wof:placetype":"locality"
},
  "geometry": {"coordinates":[17.23202,9.11225],"type":"Point"}
}