{
  "type": "Feature",
  "properties": {
    "gn:admin1_code":"8.0",
    "gn:asciiname":"Bendjiamonn",
    "gn:country_code":"TD",
    "gn:dem":375,
    "gn:feature_class":"P",
    "gn:feature_code":"PPL",
    "gn:name":"Bendjiamonn",
    "gn:population":0,
    "gn:timezone":"Africa/Ndjamena",
    "iso:country":"TD",
    "name:fra_x_preferred":[
        "Bendjamou"
    ],
    "name:und_x_variant":[
        "Bendjamou"
    ],
    "wof:name":"Bendjiamonn",
    "wof:placetype":"locality"
},
  "geometry": {"coordinates":[16.5375,8.9564],"type":"Point"}
}