{
  "type": "Feature",
  "properties": {
    "gn:admin1_code":"9.0",
    "gn:asciiname":"Mabi",
    "gn:country_code":"TD",
    "gn:dem":500,
    "gn:feature_class":"P",
    "gn:feature_code":"PPL",
    "gn:name":"Mabi",
    "gn:population":0,
    "gn:timezone":"Africa/Ndjamena",
    "iso:country":"TD",
    "wof:name":"Mabi",
    "wof:placetype":"locality"
},
  "geometry": {"coordinates":[15.85,7.76667],"type":"Point"}
}