{
  "type": "Feature",
  "properties": {
    "gn:admin1_code":"16.0",
    "gn:asciiname":"Dore",
    "gn:country_code":"TD",
    "gn:dem":370,
    "gn:feature_class":"P",
    "gn:feature_code":"PPL",
    "gn:name":"Dor\u00e9",
    "gn:population":0,
    "gn:timezone":"Africa/Ndjamena",
    "iso:country":"TD",
    "name:fra_x_preferred":[
        "Dore"
    ],
    "name:pol_x_preferred":[
        "Dore"
    ],
    "name:swe_x_preferred":[
        "Dore"
    ],
    "wof:name":"Dore",
    "wof:placetype":"locality"
},
  "geometry": {"coordinates":[15.1093,9.8591],"type":"Point"}
}