{
  "type": "Feature",
  "properties": {
    "gn:admin1_code":"17.0",
    "gn:asciiname":"Mai Kobo",
    "gn:country_code":"TD",
    "gn:dem":386,
    "gn:feature_class":"P",
    "gn:feature_code":"PPL",
    "gn:name":"Mai Kobo",
    "gn:population":0,
    "gn:timezone":"Africa/Ndjamena",
    "iso:country":"TD",
    "wof:name":"Mai Kobo",
    "wof:placetype":"locality"
},
  "geometry": {"coordinates":[18.5819,8.6699],"type":"Point"}
}