{
  "type": "Feature",
  "properties": {
    "gn:admin1_code":"12.0",
    "gn:asciiname":"Khachim el Djarad",
    "gn:country_code":"TD",
    "gn:dem":592,
    "gn:feature_class":"P",
    "gn:feature_code":"PPL",
    "gn:name":"Khachim el Djarad",
    "gn:population":0,
    "gn:timezone":"Africa/Ndjamena",
    "iso:country":"TD",
    "wof:name":"Khachim el Djarad",
    "wof:placetype":"locality"
},
  "geometry": {"coordinates":[21.04392,13.36565],"type":"Point"}
}