{
  "type": "Feature",
  "properties": {
    "gn:admin1_code":"15.0",
    "gn:asciiname":"Maguili",
    "gn:country_code":"TD",
    "gn:dem":332,
    "gn:feature_class":"P",
    "gn:feature_code":"PPL",
    "gn:name":"Maguili",
    "gn:population":0,
    "gn:timezone":"Africa/Ndjamena",
    "iso:country":"TD",
    "name:und_x_variant":[
        "Magili",
        "Maguili"
    ],
    "wof:name":"Maguili",
    "wof:placetype":"locality"
},
  "geometry": {"coordinates":[16.5119,11.4234],"type":"Point"}
}