{
  "type": "Feature",
  "properties": {
    "gn:admin1_code":"13.0",
    "gn:asciiname":"Am Beldi",
    "gn:country_code":"TD",
    "gn:dem":473,
    "gn:feature_class":"P",
    "gn:feature_code":"PPL",
    "gn:name":"Am Beldi",
    "gn:population":0,
    "gn:timezone":"Africa/Ndjamena",
    "iso:country":"TD",
    "wof:name":"Am Beldi",
    "wof:placetype":"locality"
},
  "geometry": {"coordinates":[20.98333,11.51667],"type":"Point"}
}