{
  "type": "Feature",
  "properties": {
    "gn:admin1_code":"9.0",
    "gn:asciiname":"Gatouambassa",
    "gn:country_code":"TD",
    "gn:dem":380,
    "gn:feature_class":"P",
    "gn:feature_code":"PPL",
    "gn:name":"Gatouambassa",
    "gn:population":0,
    "gn:timezone":"Africa/Ndjamena",
    "iso:country":"TD",
    "name:und_x_variant":[
        "Gatom-Bassa",
        "Gatouambassa"
    ],
    "wof:name":"Gatouambassa",
    "wof:placetype":"locality"
},
  "geometry": {"coordinates":[17.08359,8.89883],"type":"Point"}
}