{
  "type": "Feature",
  "properties": {
    "gn:admin1_code":"14.0",
    "gn:asciiname":"Moni",
    "gn:country_code":"TD",
    "gn:dem":372,
    "gn:feature_class":"P",
    "gn:feature_code":"PPL",
    "gn:name":"Moni",
    "gn:population":0,
    "gn:timezone":"Africa/Ndjamena",
    "iso:country":"TD",
    "name:und_x_variant":[
        "Mony",
        "Moni"
    ],
    "wof:name":"Moni",
    "wof:placetype":"locality"
},
  "geometry": {"coordinates":[16.4512,9.1386],"type":"Point"}
}