{
  "type": "Feature",
  "properties": {
    "gn:admin1_code":"5.0",
    "gn:asciiname":"Timan",
    "gn:country_code":"TD",
    "gn:dem":425,
    "gn:feature_class":"P",
    "gn:feature_code":"PPL",
    "gn:name":"Timan",
    "gn:population":0,
    "gn:timezone":"Africa/Ndjamena",
    "iso:country":"TD",
    "name:und_x_variant":[
        "Timane",
        "Timman",
        "Timam",
        "Timan"
    ],
    "wof:name":"Timan",
    "wof:placetype":"locality"
},
  "geometry": {"coordinates":[18.5939,10.3115],"type":"Point"}
}