{
  "type": "Feature",
  "properties": {
    "gn:admin1_code":"1.0",
    "gn:asciiname":"Haskanit",
    "gn:country_code":"TD",
    "gn:dem":337,
    "gn:feature_class":"P",
    "gn:feature_code":"PPL",
    "gn:name":"Haskanit",
    "gn:population":0,
    "gn:timezone":"Africa/Ndjamena",
    "iso:country":"TD",
    "wof:name":"Haskanit",
    "wof:placetype":"locality"
},
  "geometry": {"coordinates":[18.2926,13.133],"type":"Point"}
}