{
  "type": "Feature",
  "properties": {
    "gn:admin1_code":"16.0",
    "gn:asciiname":"Tinla",
    "gn:country_code":"TD",
    "gn:dem":342,
    "gn:feature_class":"P",
    "gn:feature_code":"PPL",
    "gn:name":"Tinla",
    "gn:population":0,
    "gn:timezone":"Africa/Ndjamena",
    "iso:country":"TD",
    "wof:name":"Tinla",
    "wof:placetype":"locality"
},
  "geometry": {"coordinates":[15.11667,9.75],"type":"Point"}
}