{
  "type": "Feature",
  "properties": {
    "gn:admin1_code":"7.0",
    "gn:asciiname":"Sirnanga Keleri",
    "gn:country_code":"TD",
    "gn:dem":304,
    "gn:feature_class":"P",
    "gn:feature_code":"PPL",
    "gn:name":"Sirnanga K\u00e9l\u00e9ri",
    "gn:population":0,
    "gn:timezone":"Africa/Ndjamena",
    "iso:country":"TD",
    "wof:name":"Sirnanga Keleri",
    "wof:placetype":"locality"
},
  "geometry": {"coordinates":[15.46929,13.56473],"type":"Point"}
}