{
  "type": "Feature",
  "properties": {
    "gn:admin1_code":"14.0",
    "gn:asciiname":"Toguior Mbassa",
    "gn:country_code":"TD",
    "gn:dem":353,
    "gn:feature_class":"P",
    "gn:feature_code":"PPL",
    "gn:name":"Toguior Mbassa",
    "gn:population":0,
    "gn:timezone":"Africa/Ndjamena",
    "iso:country":"TD",
    "wof:name":"Toguior Mbassa",
    "wof:placetype":"locality"
},
  "geometry": {"coordinates":[16.0607,9.4559],"type":"Point"}
}