{
  "type": "Feature",
  "properties": {
    "gn:admin1_code":"14.0",
    "gn:asciiname":"Be Kordou",
    "gn:country_code":"TD",
    "gn:dem":392,
    "gn:feature_class":"P",
    "gn:feature_code":"PPL",
    "gn:name":"B\u00e9 Kordou",
    "gn:population":0,
    "gn:timezone":"Africa/Ndjamena",
    "iso:country":"TD",
    "wof:name":"Be Kordou",
    "wof:placetype":"locality"
},
  "geometry": {"coordinates":[16.7831,9.1679],"type":"Point"}
}