{
  "type": "Feature",
  "properties": {
    "gn:admin1_code":"9.0",
    "gn:asciiname":"Kidi",
    "gn:country_code":"TD",
    "gn:dem":502,
    "gn:feature_class":"P",
    "gn:feature_code":"PPL",
    "gn:name":"Kidi",
    "gn:population":0,
    "gn:timezone":"Africa/Ndjamena",
    "iso:country":"TD",
    "name:fra_x_preferred":[
        "Kidi"
    ],
    "wof:name":"Kidi",
    "wof:placetype":"locality"
},
  "geometry": {"coordinates":[16.13975,8.31683],"type":"Point"}
}