{
  "type": "Feature",
  "properties": {
    "gn:admin1_code":"25.0",
    "gn:asciiname":"Belalo",
    "gn:country_code":"TD",
    "gn:dem":493,
    "gn:feature_class":"P",
    "gn:feature_code":"PPL",
    "gn:name":"B\u00e9lalo",
    "gn:population":0,
    "gn:timezone":"Africa/Ndjamena",
    "iso:country":"TD",
    "wof:name":"Belalo",
    "wof:placetype":"locality"
},
  "geometry": {"coordinates":[21.2896,11.7235],"type":"Point"}
}