{
  "type": "Feature",
  "properties": {
    "gn:admin1_code":"12.0",
    "gn:asciiname":"Am Himede",
    "gn:country_code":"TD",
    "gn:dem":438,
    "gn:feature_class":"P",
    "gn:feature_code":"PPL",
    "gn:name":"Am Him\u00e9d\u00e9",
    "gn:population":0,
    "gn:timezone":"Africa/Ndjamena",
    "iso:country":"TD",
    "name:fra_x_preferred":[
        "Am Him\u00e9d\u00e9"
    ],
    "wof:name":"Am Himede",
    "wof:placetype":"locality"
},
  "geometry": {"coordinates":[20.36474,13.93748],"type":"Point"}
}