{
  "type": "Feature",
  "properties": {
    "gn:admin1_code":"5.0",
    "gn:asciiname":"Koubi",
    "gn:country_code":"TD",
    "gn:dem":363,
    "gn:feature_class":"P",
    "gn:feature_code":"PPL",
    "gn:name":"Koubi",
    "gn:population":0,
    "gn:timezone":"Africa/Ndjamena",
    "iso:country":"TD",
    "wof:name":"Koubi",
    "wof:placetype":"locality"
},
  "geometry": {"coordinates":[17.8762,10.5348],"type":"Point"}
}