{
  "type": "Feature",
  "properties": {
    "gn:admin1_code":"5.0",
    "gn:asciiname":"Tokodi",
    "gn:country_code":"TD",
    "gn:dem":462,
    "gn:feature_class":"P",
    "gn:feature_code":"PPL",
    "gn:name":"Tokodi",
    "gn:population":0,
    "gn:timezone":"Africa/Ndjamena",
    "iso:country":"TD",
    "wof:name":"Tokodi",
    "wof:placetype":"locality"
},
  "geometry": {"coordinates":[18.105,11.5866],"type":"Point"}
}