{
  "type": "Feature",
  "properties": {
    "gn:admin1_code":"1.0",
    "gn:asciiname":"Atimed",
    "gn:country_code":"TD",
    "gn:dem":421,
    "gn:feature_class":"P",
    "gn:feature_code":"PPL",
    "gn:name":"Atimed",
    "gn:population":0,
    "gn:timezone":"Africa/Ndjamena",
    "iso:country":"TD",
    "wof:name":"Atimed",
    "wof:placetype":"locality"
},
  "geometry": {"coordinates":[19.9791,13.0792],"type":"Point"}
}