{
  "type": "Feature",
  "properties": {
    "gn:admin1_code":"25.0",
    "gn:asciiname":"Dourti Souar",
    "gn:country_code":"TD",
    "gn:dem":511,
    "gn:feature_class":"P",
    "gn:feature_code":"PPL",
    "gn:name":"Dourti Souar",
    "gn:population":0,
    "gn:timezone":"Africa/Ndjamena",
    "iso:country":"TD",
    "wof:name":"Dourti Souar",
    "wof:placetype":"locality"
},
  "geometry": {"coordinates":[21.606,11.9636],"type":"Point"}
}