{
  "type": "Feature",
  "properties": {
    "gn:admin1_code":"7.0",
    "gn:asciiname":"Nga",
    "gn:country_code":"TD",
    "gn:dem":290,
    "gn:feature_class":"P",
    "gn:feature_code":"PPL",
    "gn:name":"Nga",
    "gn:population":0,
    "gn:timezone":"Africa/Ndjamena",
    "iso:country":"TD",
    "wof:name":"Nga",
    "wof:placetype":"locality"
},
  "geometry": {"coordinates":[15.23333,13.23333],"type":"Point"}
}