{
  "type": "Feature",
  "properties": {
    "gn:admin1_code":"5.0",
    "gn:asciiname":"Dasingue",
    "gn:country_code":"TD",
    "gn:dem":365,
    "gn:feature_class":"P",
    "gn:feature_code":"PPL",
    "gn:name":"Dasingu\u00e9",
    "gn:population":0,
    "gn:timezone":"Africa/Ndjamena",
    "iso:country":"TD",
    "name:und_x_variant":[
        "Dasing\u00e9",
        "Dasingu\u00e9"
    ],
    "wof:name":"Dasingue",
    "wof:placetype":"locality"
},
  "geometry": {"coordinates":[17.762,11.2423],"type":"Point"}
}