{
  "type": "Feature",
  "properties": {
    "gn:admin1_code":"5.0",
    "gn:asciiname":"Dorli Barandifa",
    "gn:country_code":"TD",
    "gn:dem":530,
    "gn:feature_class":"P",
    "gn:feature_code":"PPL",
    "gn:name":"Dorli Barandifa",
    "gn:population":0,
    "gn:timezone":"Africa/Ndjamena",
    "iso:country":"TD",
    "name:und_x_variant":[
        "Dorli Barandifi",
        "Dorli Barandifa"
    ],
    "wof:name":"Dorli Barandifa",
    "wof:placetype":"locality"
},
  "geometry": {"coordinates":[18.3896,11.8881],"type":"Point"}
}