{
  "type": "Feature",
  "properties": {
    "gn:admin1_code":"15.0",
    "gn:asciiname":"Dolori",
    "gn:country_code":"TD",
    "gn:dem":324,
    "gn:feature_class":"P",
    "gn:feature_code":"PPL",
    "gn:name":"Dolori",
    "gn:population":0,
    "gn:timezone":"Africa/Ndjamena",
    "iso:country":"TD",
    "wof:name":"Dolori",
    "wof:placetype":"locality"
},
  "geometry": {"coordinates":[15.9217,11.02279],"type":"Point"}
}