{
  "type": "Feature",
  "properties": {
    "gn:admin1_code":"7.0",
    "gn:asciiname":"Dianga",
    "gn:country_code":"TD",
    "gn:dem":303,
    "gn:feature_class":"P",
    "gn:feature_code":"PPL",
    "gn:name":"Dianga",
    "gn:population":0,
    "gn:timezone":"Africa/Ndjamena",
    "iso:country":"TD",
    "wof:name":"Dianga",
    "wof:placetype":"locality"
},
  "geometry": {"coordinates":[15.25666,13.63394],"type":"Point"}
}