{
  "type": "Feature",
  "properties": {
    "gn:admin1_code":"9.0",
    "gn:asciiname":"Madana",
    "gn:country_code":"TD",
    "gn:dem":432,
    "gn:feature_class":"P",
    "gn:feature_code":"PPL",
    "gn:name":"Madana",
    "gn:population":0,
    "gn:timezone":"Africa/Ndjamena",
    "iso:country":"TD",
    "name:ceb_x_preferred":[
        "Madana"
    ],
    "name:swe_x_preferred":[
        "Madana"
    ],
    "wof:name":"Madana",
    "wof:placetype":"locality"
},
  "geometry": {"coordinates":[16.91237000000001,8.27185],"type":"Point"}
}