{
  "type": "Feature",
  "properties": {
    "gn:admin1_code":"15.0",
    "gn:asciiname":"Abougoui Fellata",
    "gn:country_code":"TD",
    "gn:dem":319,
    "gn:feature_class":"P",
    "gn:feature_code":"PPL",
    "gn:name":"Abougoui F\u00e9llata",
    "gn:population":0,
    "gn:timezone":"Africa/Ndjamena",
    "iso:country":"TD",
    "wof:name":"Abougoui Fellata",
    "wof:placetype":"locality"
},
  "geometry": {"coordinates":[16.1511,11.8017],"type":"Point"}
}