{
  "type": "Feature",
  "properties": {
    "gn:admin1_code":"2.0",
    "gn:asciiname":"Teredina",
    "gn:country_code":"TD",
    "gn:dem":961,
    "gn:feature_class":"P",
    "gn:feature_code":"PPL",
    "gn:name":"T\u00e9r\u00e9dina",
    "gn:population":0,
    "gn:timezone":"Africa/Ndjamena",
    "iso:country":"TD",
    "name:fra_x_preferred":[
        "T\u00e9r\u00e9dina"
    ],
    "wof:name":"Teredina",
    "wof:placetype":"locality"
},
  "geometry": {"coordinates":[21.73431,14.45102],"type":"Point"}
}