{
  "type": "Feature",
  "properties": {
    "gn:admin1_code":"19.0",
    "gn:asciiname":"Kangte II",
    "gn:country_code":"TD",
    "gn:dem":403,
    "gn:feature_class":"P",
    "gn:feature_code":"PPL",
    "gn:name":"Kangt\u00e9 II",
    "gn:population":0,
    "gn:timezone":"Africa/Ndjamena",
    "iso:country":"TD",
    "wof:name":"Kangte II",
    "wof:placetype":"locality"
},
  "geometry": {"coordinates":[17.26783,9.0965],"type":"Point"}
}