{
  "type": "Feature",
  "properties": {
    "gn:admin1_code":"12.0",
    "gn:asciiname":"Tondjon",
    "gn:country_code":"TD",
    "gn:dem":692,
    "gn:feature_class":"P",
    "gn:feature_code":"PPL",
    "gn:name":"Tondjon",
    "gn:population":0,
    "gn:timezone":"Africa/Ndjamena",
    "iso:country":"TD",
    "wof:name":"Tondjon",
    "wof:placetype":"locality"
},
  "geometry": {"coordinates":[21.50183,13.54017],"type":"Point"}
}