{
  "type": "Feature",
  "properties": {
    "gn:admin1_code":"18.0",
    "gn:asciiname":"Djar Konkia",
    "gn:country_code":"TD",
    "gn:dem":289,
    "gn:feature_class":"P",
    "gn:feature_code":"PPL",
    "gn:name":"Djar Konkia",
    "gn:population":0,
    "gn:timezone":"Africa/Ndjamena",
    "iso:country":"TD",
    "wof:name":"Djar Konkia",
    "wof:placetype":"locality"
},
  "geometry": {"coordinates":[15.46344,13.00262],"type":"Point"}
}