{
  "type": "Feature",
  "properties": {
    "gn:admin1_code":"2.0",
    "gn:asciiname":"Keyramara",
    "gn:country_code":"TD",
    "gn:dem":907,
    "gn:feature_class":"P",
    "gn:feature_code":"PPL",
    "gn:name":"Keyramara",
    "gn:population":0,
    "gn:timezone":"Africa/Ndjamena",
    "iso:country":"TD",
    "wof:name":"Keyramara",
    "wof:placetype":"locality"
},
  "geometry": {"coordinates":[22.51667,15.48333],"type":"Point"}
}