{
  "type": "Feature",
  "properties": {
    "gn:admin1_code":"18.0",
    "gn:asciiname":"Ideloi",
    "gn:country_code":"TD",
    "gn:dem":299,
    "gn:feature_class":"P",
    "gn:feature_code":"PPL",
    "gn:name":"Id\u00e9lo\u00ef",
    "gn:population":0,
    "gn:timezone":"Africa/Ndjamena",
    "iso:country":"TD",
    "wof:name":"Ideloi",
    "wof:placetype":"locality"
},
  "geometry": {"coordinates":[17.19128,12.43169],"type":"Point"}
}