{
  "type": "Feature",
  "properties": {
    "gn:admin1_code":"19.0",
    "gn:asciiname":"Dominga",
    "gn:country_code":"TD",
    "gn:dem":413,
    "gn:feature_class":"P",
    "gn:feature_code":"PPL",
    "gn:name":"Dominga",
    "gn:population":0,
    "gn:timezone":"Africa/Ndjamena",
    "iso:country":"TD",
    "wof:name":"Dominga",
    "wof:placetype":"locality"
},
  "geometry": {"coordinates":[17.29807000000001,7.96596],"type":"Point"}
}