{
  "type": "Feature",
  "properties": {
    "gn:admin1_code":"8.0",
    "gn:asciiname":"Nanda Tangourou",
    "gn:country_code":"TD",
    "gn:dem":439,
    "gn:feature_class":"P",
    "gn:feature_code":"PPL",
    "gn:name":"Nanda Tangourou",
    "gn:population":0,
    "gn:timezone":"Africa/Ndjamena",
    "iso:country":"TD",
    "wof:name":"Nanda Tangourou",
    "wof:placetype":"locality"
},
  "geometry": {"coordinates":[15.9367,8.846],"type":"Point"}
}