{
  "type": "Feature",
  "properties": {
    "gn:admin1_code":"9.0",
    "gn:asciiname":"Begone",
    "gn:country_code":"TD",
    "gn:dem":446,
    "gn:feature_class":"P",
    "gn:feature_code":"PPL",
    "gn:name":"B\u00e9gone",
    "gn:population":0,
    "gn:timezone":"Africa/Ndjamena",
    "iso:country":"TD",
    "wof:name":"Begone",
    "wof:placetype":"locality"
},
  "geometry": {"coordinates":[16.36248,7.7301],"type":"Point"}
}