{
  "type": "Feature",
  "properties": {
    "gn:admin1_code":"5.0",
    "gn:asciiname":"Alogue",
    "gn:country_code":"TD",
    "gn:dem":527,
    "gn:feature_class":"P",
    "gn:feature_code":"PPL",
    "gn:name":"Alogu\u00e9",
    "gn:population":0,
    "gn:timezone":"Africa/Ndjamena",
    "iso:country":"TD",
    "wof:name":"Alogue",
    "wof:placetype":"locality"
},
  "geometry": {"coordinates":[18.7297,11.9725],"type":"Point"}
}