{
  "type": "Feature",
  "properties": {
    "gn:admin1_code":"14.0",
    "gn:asciiname":"Dar Gandil",
    "gn:country_code":"TD",
    "gn:dem":365,
    "gn:feature_class":"P",
    "gn:feature_code":"PPL",
    "gn:name":"Dar Gandil",
    "gn:population":0,
    "gn:timezone":"Africa/Ndjamena",
    "iso:country":"TD",
    "wof:name":"Dar Gandil",
    "wof:placetype":"locality"
},
  "geometry": {"coordinates":[17.07832,9.32844],"type":"Point"}
}