{
  "type": "Feature",
  "properties": {
    "gn:admin1_code":"14.0",
    "gn:asciiname":"Mabatam",
    "gn:country_code":"TD",
    "gn:dem":343,
    "gn:feature_class":"P",
    "gn:feature_code":"PPL",
    "gn:name":"Mabatam",
    "gn:population":0,
    "gn:timezone":"Africa/Ndjamena",
    "iso:country":"TD",
    "wof:name":"Mabatam",
    "wof:placetype":"locality"
},
  "geometry": {"coordinates":[15.81667,9.61667],"type":"Point"}
}