{
  "type": "Feature",
  "properties": {
    "gn:admin1_code":"16.0",
    "gn:asciiname":"Kouroup",
    "gn:country_code":"TD",
    "gn:dem":341,
    "gn:feature_class":"P",
    "gn:feature_code":"PPL",
    "gn:name":"Kouroup",
    "gn:population":0,
    "gn:timezone":"Africa/Ndjamena",
    "iso:country":"TD",
    "wof:name":"Kouroup",
    "wof:placetype":"locality"
},
  "geometry": {"coordinates":[15.8636,9.8788],"type":"Point"}
}