{
  "type": "Feature",
  "properties": {
    "gn:admin1_code":"7.0",
    "gn:asciiname":"Ali Bilari",
    "gn:country_code":"TD",
    "gn:dem":301,
    "gn:feature_class":"P",
    "gn:feature_code":"PPL",
    "gn:name":"Ali Bilari",
    "gn:population":0,
    "gn:timezone":"Africa/Ndjamena",
    "iso:country":"TD",
    "wof:name":"Ali Bilari",
    "wof:placetype":"locality"
},
  "geometry": {"coordinates":[15.62252,13.52807],"type":"Point"}
}