{
  "type": "Feature",
  "properties": {
    "gn:admin1_code":"17.0",
    "gn:asciiname":"Kira",
    "gn:country_code":"TD",
    "gn:dem":378,
    "gn:feature_class":"P",
    "gn:feature_code":"PPL",
    "gn:name":"Kira",
    "gn:population":0,
    "gn:timezone":"Africa/Ndjamena",
    "iso:country":"TD",
    "name:ceb_x_preferred":[
        "Kira"
    ],
    "name:deu_x_preferred":[
        "Kira"
    ],
    "name:epo_x_preferred":[
        "Kira"
    ],
    "name:est_x_preferred":[
        "Kira"
    ],
    "name:fra_x_preferred":[
        "Kira"
    ],
    "name:hun_x_preferred":[
        "Kira"
    ],
    "name:isl_x_preferred":[
        "Kira"
    ],
    "name:ita_x_preferred":[
        "Kira"
    ],
    "name:lat_x_preferred":[
        "Kira"
    ],
    "name:lug_x_preferred":[
        "Kira"
    ],
    "name:nld_x_preferred":[
        "Kira"
    ],
    "name:pol_x_preferred":[
        "Kira"
    ],
    "name:por_x_preferred":[
        "Kira"
    ],
    "name:ron_x_preferred":[
        "Kira"
    ],
    "name:rus_x_preferred":[
        "\u041a\u0438\u0440\u0430"
    ],
    "name:spa_x_preferred":[
        "Kira"
    ],
    "name:srp_x_preferred":[
        "\u041a\u0438\u0440\u0430"
    ],
    "name:swe_x_preferred":[
        "Kira"
    ],
    "wof:name":"Kira",
    "wof:placetype":"locality"
},
  "geometry": {"coordinates":[18.4515,8.67967],"type":"Point"}
}