{
  "type": "Feature",
  "properties": {
    "gn:admin1_code":"1.0",
    "gn:asciiname":"Am Times",
    "gn:country_code":"TD",
    "gn:dem":334,
    "gn:feature_class":"P",
    "gn:feature_code":"PPL",
    "gn:name":"Am Tim\u00e8s",
    "gn:population":0,
    "gn:timezone":"Africa/Ndjamena",
    "iso:country":"TD",
    "wof:name":"Am Times",
    "wof:placetype":"locality"
},
  "geometry": {"coordinates":[18.1821,13.2823],"type":"Point"}
}