{
  "type": "Feature",
  "properties": {
    "gn:admin1_code":"12.0",
    "gn:asciiname":"Dayem",
    "gn:country_code":"TD",
    "gn:dem":591,
    "gn:feature_class":"P",
    "gn:feature_code":"PPL",
    "gn:name":"Dayem",
    "gn:population":0,
    "gn:timezone":"Africa/Ndjamena",
    "iso:country":"TD",
    "wof:name":"Dayem",
    "wof:placetype":"locality"
},
  "geometry": {"coordinates":[21.13216,13.30765],"type":"Point"}
}