{
  "type": "Feature",
  "properties": {
    "gn:admin1_code":"14.0",
    "gn:asciiname":"Broum Langue",
    "gn:country_code":"TD",
    "gn:dem":377,
    "gn:feature_class":"P",
    "gn:feature_code":"PPL",
    "gn:name":"Broum Langu\u00e9",
    "gn:population":0,
    "gn:timezone":"Africa/Ndjamena",
    "iso:country":"TD",
    "name:und_x_variant":[
        "Langu\u00e9",
        "Broum Langu\u00e9"
    ],
    "wof:name":"Broum Langue",
    "wof:placetype":"locality"
},
  "geometry": {"coordinates":[16.0415,9.2002],"type":"Point"}
}