{
  "type": "Feature",
  "properties": {
    "gn:admin1_code":"1.0",
    "gn:asciiname":"Ab Amsouar",
    "gn:country_code":"TD",
    "gn:dem":339,
    "gn:feature_class":"P",
    "gn:feature_code":"PPL",
    "gn:name":"Ab Amsouar",
    "gn:population":0,
    "gn:timezone":"Africa/Ndjamena",
    "iso:country":"TD",
    "wof:name":"Ab Amsouar",
    "wof:placetype":"locality"
},
  "geometry": {"coordinates":[18.4264,13.1702],"type":"Point"}
}