{
  "type": "Feature",
  "properties": {
    "gn:admin1_code":"19.0",
    "gn:asciiname":"Mainon",
    "gn:country_code":"TD",
    "gn:dem":379,
    "gn:feature_class":"P",
    "gn:feature_code":"PPL",
    "gn:name":"Ma\u00efnon",
    "gn:population":0,
    "gn:timezone":"Africa/Ndjamena",
    "iso:country":"TD",
    "wof:name":"Mainon",
    "wof:placetype":"locality"
},
  "geometry": {"coordinates":[17.7882,8.4827],"type":"Point"}
}