{
  "type": "Feature",
  "properties": {
    "gn:admin1_code":"17.0",
    "gn:asciiname":"Nodjimala",
    "gn:country_code":"TD",
    "gn:dem":379,
    "gn:feature_class":"P",
    "gn:feature_code":"PPL",
    "gn:name":"Nodjimala",
    "gn:population":0,
    "gn:timezone":"Africa/Ndjamena",
    "iso:country":"TD",
    "name:und_x_variant":[
        "Madjimala",
        "Nodjimala"
    ],
    "wof:name":"Nodjimala",
    "wof:placetype":"locality"
},
  "geometry": {"coordinates":[18.4478,8.6867],"type":"Point"}
}