{
  "type": "Feature",
  "properties": {
    "gn:admin1_code":"9.0",
    "gn:asciiname":"Manboe",
    "gn:country_code":"TD",
    "gn:dem":416,
    "gn:feature_class":"P",
    "gn:feature_code":"PPL",
    "gn:name":"Manbo\u00e9",
    "gn:population":0,
    "gn:timezone":"Africa/Ndjamena",
    "iso:country":"TD",
    "wof:name":"Manboe",
    "wof:placetype":"locality"
},
  "geometry": {"coordinates":[16.4918,8.501],"type":"Point"}
}