{
  "type": "Feature",
  "properties": {
    "gn:admin1_code":"17.0",
    "gn:asciiname":"Singaseri",
    "gn:country_code":"TD",
    "gn:dem":393,
    "gn:feature_class":"P",
    "gn:feature_code":"PPL",
    "gn:name":"Singas\u00e9ri",
    "gn:population":0,
    "gn:timezone":"Africa/Ndjamena",
    "iso:country":"TD",
    "wof:name":"Singaseri",
    "wof:placetype":"locality"
},
  "geometry": {"coordinates":[19.3665,9.8596],"type":"Point"}
}