{
  "type": "Feature",
  "properties": {
    "gn:admin1_code":"9.0",
    "gn:asciiname":"Koumati",
    "gn:country_code":"TD",
    "gn:dem":391,
    "gn:feature_class":"P",
    "gn:feature_code":"PPL",
    "gn:name":"Koumati",
    "gn:population":0,
    "gn:timezone":"Africa/Ndjamena",
    "iso:country":"TD",
    "name:fra_x_preferred":[
        "Koumatou"
    ],
    "wof:name":"Koumati",
    "wof:placetype":"locality"
},
  "geometry": {"coordinates":[16.98938,8.54527],"type":"Point"}
}