{
  "type": "Feature",
  "properties": {
    "gn:admin1_code":"18.0",
    "gn:asciiname":"Amalgueit",
    "gn:country_code":"TD",
    "gn:dem":291,
    "gn:feature_class":"P",
    "gn:feature_code":"PPL",
    "gn:name":"Amalgueit",
    "gn:population":0,
    "gn:timezone":"Africa/Ndjamena",
    "iso:country":"TD",
    "name:eng_x_preferred":[
        "Amalgueit"
    ],
    "name:eng_x_variant":[
        "Amalget"
    ],
    "wof:name":"Amalgueit",
    "wof:placetype":"locality"
},
  "geometry": {"coordinates":[14.59333,12.79825],"type":"Point"}
}