{
  "type": "Feature",
  "properties": {
    "gn:admin1_code":"9.0",
    "gn:asciiname":"Donankas",
    "gn:country_code":"TD",
    "gn:dem":507,
    "gn:feature_class":"P",
    "gn:feature_code":"PPL",
    "gn:name":"Donankas",
    "gn:population":0,
    "gn:timezone":"Africa/Ndjamena",
    "iso:country":"TD",
    "wof:name":"Donankas",
    "wof:placetype":"locality"
},
  "geometry": {"coordinates":[15.3853,8.301],"type":"Point"}
}