{
  "type": "Feature",
  "properties": {
    "gn:admin1_code":"5.0",
    "gn:asciiname":"Sadaga",
    "gn:country_code":"TD",
    "gn:dem":338,
    "gn:feature_class":"P",
    "gn:feature_code":"PPL",
    "gn:name":"Sadaga",
    "gn:population":0,
    "gn:timezone":"Africa/Ndjamena",
    "iso:country":"TD",
    "wof:name":"Sadaga",
    "wof:placetype":"locality"
},
  "geometry": {"coordinates":[17.60536,12.17876],"type":"Point"}
}