{
  "type": "Feature",
  "properties": {
    "gn:admin1_code":"17.0",
    "gn:asciiname":"Tor Djiguel",
    "gn:country_code":"TD",
    "gn:dem":397,
    "gn:feature_class":"P",
    "gn:feature_code":"PPL",
    "gn:name":"Tor Djiguel",
    "gn:population":0,
    "gn:timezone":"Africa/Ndjamena",
    "iso:country":"TD",
    "name:und_x_variant":[
        "Tor Djiguil",
        "Tardjiguel",
        "Tor Djaguil",
        "Tor Djigel",
        "Tor Djiguel"
    ],
    "wof:name":"Tor Djiguel",
    "wof:placetype":"locality"
},
  "geometry": {"coordinates":[19.4544,10.2183],"type":"Point"}
}