{
  "type": "Feature",
  "properties": {
    "gn:admin1_code":"12.0",
    "gn:asciiname":"Lolo",
    "gn:country_code":"TD",
    "gn:dem":736,
    "gn:feature_class":"P",
    "gn:feature_code":"PPL",
    "gn:name":"Lolo",
    "gn:population":0,
    "gn:timezone":"Africa/Ndjamena",
    "iso:country":"TD",
    "wof:name":"Lolo",
    "wof:placetype":"locality"
},
  "geometry": {"coordinates":[21.39729,13.96758],"type":"Point"}
}