{
  "type": "Feature",
  "properties": {
    "gn:admin1_code":"13.0",
    "gn:asciiname":"Al Koudo",
    "gn:country_code":"TD",
    "gn:dem":433,
    "gn:feature_class":"P",
    "gn:feature_code":"PPL",
    "gn:name":"Al Koudo",
    "gn:population":0,
    "gn:timezone":"Africa/Ndjamena",
    "iso:country":"TD",
    "name:und_x_variant":[
        "El Koudor",
        "Al Koudo"
    ],
    "wof:name":"Al Koudo",
    "wof:placetype":"locality"
},
  "geometry": {"coordinates":[20.1605,11.4121],"type":"Point"}
}