{
  "type": "Feature",
  "properties": {
    "gn:admin1_code":"13.0",
    "gn:asciiname":"El Ogna",
    "gn:country_code":"TD",
    "gn:dem":418,
    "gn:feature_class":"P",
    "gn:feature_code":"PPL",
    "gn:name":"El Ogna",
    "gn:population":0,
    "gn:timezone":"Africa/Ndjamena",
    "iso:country":"TD",
    "wof:name":"El Ogna",
    "wof:placetype":"locality"
},
  "geometry": {"coordinates":[19.75609,11.06982],"type":"Point"}
}