{
  "type": "Feature",
  "properties": {
    "gn:admin1_code":"14.0",
    "gn:asciiname":"Agnagui",
    "gn:country_code":"TD",
    "gn:dem":348,
    "gn:feature_class":"P",
    "gn:feature_code":"PPL",
    "gn:name":"Agnagui",
    "gn:population":0,
    "gn:timezone":"Africa/Ndjamena",
    "iso:country":"TD",
    "wof:name":"Agnagui",
    "wof:placetype":"locality"
},
  "geometry": {"coordinates":[16.595,9.6384],"type":"Point"}
}