{
  "type": "Feature",
  "properties": {
    "gn:admin1_code":"15.0",
    "gn:asciiname":"Sari",
    "gn:country_code":"TD",
    "gn:dem":293,
    "gn:feature_class":"P",
    "gn:feature_code":"PPL",
    "gn:name":"Sari",
    "gn:population":0,
    "gn:timezone":"Africa/Ndjamena",
    "iso:country":"TD",
    "wof:name":"Sari",
    "wof:placetype":"locality"
},
  "geometry": {"coordinates":[15.44254,12.26519],"type":"Point"}
}