{
  "type": "Feature",
  "properties": {
    "gn:admin1_code":"15.0",
    "gn:asciiname":"Markaba",
    "gn:country_code":"TD",
    "gn:dem":334,
    "gn:feature_class":"P",
    "gn:feature_code":"PPL",
    "gn:name":"Markaba",
    "gn:population":0,
    "gn:timezone":"Africa/Ndjamena",
    "iso:country":"TD",
    "name:ara_x_preferred":[
        "\u0645\u0631\u0643\u0628\u0627"
    ],
    "name:ceb_x_preferred":[
        "Markaba"
    ],
    "name:fra_x_preferred":[
        "Markaba"
    ],
    "name:ita_x_preferred":[
        "Markaba"
    ],
    "name:nno_x_preferred":[
        "Markaba"
    ],
    "name:nor_x_preferred":[
        "Markaba"
    ],
    "name:pol_x_preferred":[
        "Markaba"
    ],
    "name:swe_x_preferred":[
        "Markaba"
    ],
    "wof:name":"Markaba",
    "wof:placetype":"locality"
},
  "geometry": {"coordinates":[17.1306,11.2921],"type":"Point"}
}