{
  "type": "Feature",
  "properties": {
    "gn:admin1_code":"13.0",
    "gn:asciiname":"Takalaou",
    "gn:country_code":"TD",
    "gn:dem":410,
    "gn:feature_class":"P",
    "gn:feature_code":"PPL",
    "gn:name":"Takalaou",
    "gn:population":0,
    "gn:timezone":"Africa/Ndjamena",
    "iso:country":"TD",
    "name:und_x_variant":[
        "Takalo",
        "Takalao",
        "Takalaou"
    ],
    "wof:name":"Takalaou",
    "wof:placetype":"locality"
},
  "geometry": {"coordinates":[19.8182,10.1849],"type":"Point"}
}