{
  "type": "Feature",
  "properties": {
    "gn:admin1_code":"12.0",
    "gn:asciiname":"Bousgouyanga",
    "gn:country_code":"TD",
    "gn:dem":730,
    "gn:feature_class":"P",
    "gn:feature_code":"PPL",
    "gn:name":"Bousgouyanga",
    "gn:population":0,
    "gn:timezone":"Africa/Ndjamena",
    "iso:country":"TD",
    "name:fra_x_preferred":[
        "Bousgouyanga"
    ],
    "wof:name":"Bousgouyanga",
    "wof:placetype":"locality"
},
  "geometry": {"coordinates":[21.34171,14.01559],"type":"Point"}
}