{
  "type": "Feature",
  "properties": {
    "gn:admin1_code":"14.0",
    "gn:asciiname":"Sabou",
    "gn:country_code":"TD",
    "gn:dem":348,
    "gn:feature_class":"P",
    "gn:feature_code":"PPL",
    "gn:name":"Sabou",
    "gn:population":0,
    "gn:timezone":"Africa/Ndjamena",
    "iso:country":"TD",
    "name:azb_x_preferred":[
        "\u0633\u0627\u0628\u0648"
    ],
    "name:fas_x_preferred":[
        "\u0633\u0627\u0628\u0648"
    ],
    "name:fra_x_preferred":[
        "Sabou"
    ],
    "name:urd_x_preferred":[
        "\u0633\u0628\u0648"
    ],
    "wof:name":"Sabou",
    "wof:placetype":"locality"
},
  "geometry": {"coordinates":[16.3384,9.7718],"type":"Point"}
}