{
  "type": "Feature",
  "properties": {
    "gn:admin1_code":"18.0",
    "gn:asciiname":"Kindjiri Malorom",
    "gn:country_code":"TD",
    "gn:dem":297,
    "gn:feature_class":"P",
    "gn:feature_code":"PPL",
    "gn:name":"Kindjiri Malorom",
    "gn:population":0,
    "gn:timezone":"Africa/Ndjamena",
    "iso:country":"TD",
    "name:und_x_variant":[
        "Kindjiri Malarom",
        "Kindjiri Malorom"
    ],
    "wof:name":"Kindjiri Malorom",
    "wof:placetype":"locality"
},
  "geometry": {"coordinates":[15.48737,13.16727],"type":"Point"}
}