{
  "type": "Feature",
  "properties": {
    "gn:admin1_code":"8.0",
    "gn:asciiname":"Gueldobo",
    "gn:country_code":"TD",
    "gn:dem":426,
    "gn:feature_class":"P",
    "gn:feature_code":"PPL",
    "gn:name":"Gueldobo",
    "gn:population":0,
    "gn:timezone":"Africa/Ndjamena",
    "iso:country":"TD",
    "wof:name":"Gueldobo",
    "wof:placetype":"locality"
},
  "geometry": {"coordinates":[16.23811,9.00344],"type":"Point"}
}