{
  "type": "Feature",
  "properties": {
    "gn:admin1_code":"12.0",
    "gn:asciiname":"Arak Tignari",
    "gn:country_code":"TD",
    "gn:dem":537,
    "gn:feature_class":"P",
    "gn:feature_code":"PPL",
    "gn:name":"Arak Tignari",
    "gn:population":0,
    "gn:timezone":"Africa/Ndjamena",
    "iso:country":"TD",
    "name:fra_x_preferred":[
        "Arak Tignari"
    ],
    "wof:name":"Arak Tignari",
    "wof:placetype":"locality"
},
  "geometry": {"coordinates":[20.8001,13.4176],"type":"Point"}
}