{
  "type": "Feature",
  "properties": {
    "gn:admin1_code":"17.0",
    "gn:asciiname":"Dik",
    "gn:country_code":"TD",
    "gn:dem":351,
    "gn:feature_class":"P",
    "gn:feature_code":"PPL",
    "gn:name":"Dik",
    "gn:population":0,
    "gn:timezone":"Africa/Ndjamena",
    "iso:country":"TD",
    "name:ceb_x_preferred":[
        "Dik"
    ],
    "name:deu_x_preferred":[
        "Dik"
    ],
    "name:nld_x_preferred":[
        "Dik"
    ],
    "name:swe_x_preferred":[
        "Dik"
    ],
    "name:und_x_variant":[
        "Dik\u00e9"
    ],
    "wof:name":"Dik",
    "wof:placetype":"locality"
},
  "geometry": {"coordinates":[17.51383,9.95928],"type":"Point"}
}