{
  "type": "Feature",
  "properties": {
    "gn:admin1_code":"12.0",
    "gn:asciiname":"Arar",
    "gn:country_code":"TD",
    "gn:dem":647,
    "gn:feature_class":"P",
    "gn:feature_code":"PPL",
    "gn:name":"Arar",
    "gn:population":0,
    "gn:timezone":"Africa/Ndjamena",
    "iso:country":"TD",
    "name:ben_x_preferred":[
        "\u0986\u09b0\u09be\u09b0"
    ],
    "name:ceb_x_preferred":[
        "Arar"
    ],
    "name:deu_x_preferred":[
        "Arar"
    ],
    "name:ell_x_preferred":[
        "\u0391\u03c1\u03ac\u03c1"
    ],
    "name:est_x_preferred":[
        "Arar"
    ],
    "name:hin_x_preferred":[
        "\u0905\u0930\u093e\u0930"
    ],
    "name:hun_x_preferred":[
        "Arar"
    ],
    "name:ind_x_preferred":[
        "Arar"
    ],
    "name:spa_x_preferred":[
        "Arar"
    ],
    "name:swe_x_preferred":[
        "Arar"
    ],
    "wof:name":"Arar",
    "wof:placetype":"locality"
},
  "geometry": {"coordinates":[21.58798,13.1768],"type":"Point"}
}