{
  "type": "Feature",
  "properties": {
    "gn:admin1_code":"12.0",
    "gn:asciiname":"Arar",
    "gn:country_code":"TD",
    "gn:dem":647,
    "gn:feature_class":"P",
    "gn:feature_code":"PPL",
    "gn:name":"Arar",
    "gn:population":0,
    "gn:timezone":"Africa/Ndjamena",
    "iso:country":"TD",
    "name:ceb_x_preferred":[
        "Arar"
    ],
    "name:deu_x_preferred":[
        "Arar"
    ],
    "name:est_x_preferred":[
        "Arar"
    ],
    "name:spa_x_preferred":[
        "Arar"
    ],
    "wof:name":"Arar",
    "wof:placetype":"locality"
},
  "geometry": {"coordinates":[21.58798,13.1768],"type":"Point"}
}