{
  "type": "Feature",
  "properties": {
    "gn:admin1_code":"12.0",
    "gn:asciiname":"Niatogon",
    "gn:country_code":"TD",
    "gn:dem":488,
    "gn:feature_class":"P",
    "gn:feature_code":"PPL",
    "gn:name":"Niatogon",
    "gn:population":0,
    "gn:timezone":"Africa/Ndjamena",
    "iso:country":"TD",
    "name:fra_x_preferred":[
        "Niatogon"
    ],
    "wof:name":"Niatogon",
    "wof:placetype":"locality"
},
  "geometry": {"coordinates":[20.64989,13.3249],"type":"Point"}
}