{
  "type": "Feature",
  "properties": {
    "gn:admin1_code":"17.0",
    "gn:asciiname":"Moyemtoro",
    "gn:country_code":"TD",
    "gn:dem":388,
    "gn:feature_class":"P",
    "gn:feature_code":"PPL",
    "gn:name":"Moyemtoro",
    "gn:population":0,
    "gn:timezone":"Africa/Ndjamena",
    "iso:country":"TD",
    "wof:name":"Moyemtoro",
    "wof:placetype":"locality"
},
  "geometry": {"coordinates":[18.50076,8.52428],"type":"Point"}
}