{
  "type": "Feature",
  "properties": {
    "gn:admin1_code":"2.0",
    "gn:asciiname":"Dourdafo",
    "gn:country_code":"TD",
    "gn:dem":528,
    "gn:feature_class":"P",
    "gn:feature_code":"PPL",
    "gn:name":"Dourdafo",
    "gn:population":0,
    "gn:timezone":"Africa/Ndjamena",
    "iso:country":"TD",
    "name:fra_x_preferred":[
        "Dourdafo"
    ],
    "wof:name":"Dourdafo",
    "wof:placetype":"locality"
},
  "geometry": {"coordinates":[21.0264,14.82409],"type":"Point"}
}