{
  "type": "Feature",
  "properties": {
    "gn:admin1_code":"6.0",
    "gn:asciiname":"Keliganga",
    "gn:country_code":"TD",
    "gn:dem":322,
    "gn:feature_class":"P",
    "gn:feature_code":"PPL",
    "gn:name":"K\u00e9liganga",
    "gn:population":0,
    "gn:timezone":"Africa/Ndjamena",
    "iso:country":"TD",
    "name:und_x_variant":[
        "K\u00e9lihanga",
        "K\u00e9liganga"
    ],
    "wof:name":"Keliganga",
    "wof:placetype":"locality"
},
  "geometry": {"coordinates":[15.0496,13.86899],"type":"Point"}
}