{
  "type": "Feature",
  "properties": {
    "gn:admin1_code":"9.0",
    "gn:asciiname":"Jamy",
    "gn:country_code":"TD",
    "gn:dem":498,
    "gn:feature_class":"P",
    "gn:feature_code":"PPL",
    "gn:name":"Jamy",
    "gn:population":0,
    "gn:timezone":"Africa/Ndjamena",
    "iso:country":"TD",
    "name:deu_x_preferred":[
        "Jamy"
    ],
    "name:fra_x_preferred":[
        "Jamy"
    ],
    "name:hye_x_preferred":[
        "\u0545\u0561\u0574\u056b"
    ],
    "name:pol_x_preferred":[
        "Jamy"
    ],
    "name:rus_x_preferred":[
        "\u042f\u043c\u044b"
    ],
    "name:ukr_x_preferred":[
        "\u042f\u043c\u0438"
    ],
    "wof:name":"Jamy",
    "wof:placetype":"locality"
},
  "geometry": {"coordinates":[15.82456,7.72421],"type":"Point"}
}