{
  "type": "Feature",
  "properties": {
    "gn:admin1_code":"9.0",
    "gn:asciiname":"Jamy",
    "gn:country_code":"TD",
    "gn:dem":498,
    "gn:feature_class":"P",
    "gn:feature_code":"PPL",
    "gn:name":"Jamy",
    "gn:population":0,
    "gn:timezone":"Africa/Ndjamena",
    "iso:country":"TD",
    "wof:name":"Jamy",
    "wof:placetype":"locality"
},
  "geometry": {"coordinates":[15.82456,7.72421],"type":"Point"}
}