{
  "type": "Feature",
  "properties": {
    "gn:admin1_code":"23.0",
    "gn:asciiname":"Tioro",
    "gn:country_code":"TD",
    "gn:dem":1520,
    "gn:feature_class":"P",
    "gn:feature_code":"PPL",
    "gn:name":"Tioro",
    "gn:population":0,
    "gn:timezone":"Africa/Ndjamena",
    "iso:country":"TD",
    "wof:name":"Tioro",
    "wof:placetype":"locality"
},
  "geometry": {"coordinates":[18.45,20.53333],"type":"Point"}
}