{
  "type": "Feature",
  "properties": {
    "gn:admin1_code":"12.0",
    "gn:asciiname":"Meser",
    "gn:country_code":"TD",
    "gn:dem":607,
    "gn:feature_class":"P",
    "gn:feature_code":"PPL",
    "gn:name":"M\u00e9ser",
    "gn:population":0,
    "gn:timezone":"Africa/Ndjamena",
    "iso:country":"TD",
    "name:und_x_variant":[
        "Messer",
        "M\u00e9ser"
    ],
    "wof:name":"Meser",
    "wof:placetype":"locality"
},
  "geometry": {"coordinates":[21.04711,13.81813],"type":"Point"}
}