{
  "type": "Feature",
  "properties": {
    "gn:admin1_code":"19.0",
    "gn:asciiname":"Bili",
    "gn:country_code":"TD",
    "gn:dem":381,
    "gn:feature_class":"P",
    "gn:feature_code":"PPL",
    "gn:name":"Bili",
    "gn:population":0,
    "gn:timezone":"Africa/Ndjamena",
    "iso:country":"TD",
    "name:bre_x_preferred":[
        "Bili"
    ],
    "name:ceb_x_preferred":[
        "Bili"
    ],
    "name:fra_x_preferred":[
        "Bili"
    ],
    "name:kat_x_preferred":[
        "\u10d1\u10d8\u10da\u10d8"
    ],
    "name:swe_x_preferred":[
        "Bili"
    ],
    "wof:name":"Bili",
    "wof:placetype":"locality"
},
  "geometry": {"coordinates":[17.90496,8.57858],"type":"Point"}
}