{
  "type": "Feature",
  "properties": {
    "gn:admin1_code":"19.0",
    "gn:asciiname":"Ndiltayo",
    "gn:country_code":"TD",
    "gn:dem":363,
    "gn:feature_class":"P",
    "gn:feature_code":"PPL",
    "gn:name":"Ndiltayo",
    "gn:population":0,
    "gn:timezone":"Africa/Ndjamena",
    "iso:country":"TD",
    "wof:name":"Ndiltayo",
    "wof:placetype":"locality"
},
  "geometry": {"coordinates":[17.35362000000001,9.41983],"type":"Point"}
}