{
  "type": "Feature",
  "properties": {
    "gn:admin1_code":"12.0",
    "gn:asciiname":"Djanehane",
    "gn:country_code":"TD",
    "gn:dem":451,
    "gn:feature_class":"P",
    "gn:feature_code":"PPL",
    "gn:name":"Djan\u00e9han\u00e9",
    "gn:population":0,
    "gn:timezone":"Africa/Ndjamena",
    "iso:country":"TD",
    "name:fra_x_preferred":[
        "Djan\u00e9han\u00e9"
    ],
    "wof:name":"Djanehane",
    "wof:placetype":"locality"
},
  "geometry": {"coordinates":[20.40768,13.79664],"type":"Point"}
}