{
  "type": "Feature",
  "properties": {
    "gn:admin1_code":"15.0",
    "gn:asciiname":"Albala",
    "gn:country_code":"TD",
    "gn:dem":329,
    "gn:feature_class":"P",
    "gn:feature_code":"PPL",
    "gn:name":"Albala",
    "gn:population":0,
    "gn:timezone":"Africa/Ndjamena",
    "iso:country":"TD",
    "wof:name":"Albala",
    "wof:placetype":"locality"
},
  "geometry": {"coordinates":[16.7916,11.8155],"type":"Point"}
}