{
  "type": "Feature",
  "properties": {
    "gn:admin1_code":"12.0",
    "gn:asciiname":"Ibn del Ralam",
    "gn:country_code":"TD",
    "gn:dem":405,
    "gn:feature_class":"P",
    "gn:feature_code":"PPL",
    "gn:name":"Ibn del Ralam",
    "gn:population":0,
    "gn:timezone":"Africa/Ndjamena",
    "iso:country":"TD",
    "wof:name":"Ibn del Ralam",
    "wof:placetype":"locality"
},
  "geometry": {"coordinates":[20.07615,14.15748],"type":"Point"}
}