{
  "type": "Feature",
  "properties": {
    "gn:admin1_code":"20.0",
    "gn:asciiname":"Maoutehaye",
    "gn:country_code":"TD",
    "gn:dem":353,
    "gn:feature_class":"P",
    "gn:feature_code":"PPL",
    "gn:name":"Maoutehaye",
    "gn:population":0,
    "gn:timezone":"Africa/Ndjamena",
    "iso:country":"TD",
    "name:und_x_variant":[
        "Maout\u00e9hai",
        "Maoutehaye"
    ],
    "wof:name":"Maoutehaye",
    "wof:placetype":"locality"
},
  "geometry": {"coordinates":[14.5963,9.4106],"type":"Point"}
}