{
  "type": "Feature",
  "properties": {
    "gn:admin1_code":"19.0",
    "gn:asciiname":"Mayamtor",
    "gn:country_code":"TD",
    "gn:dem":372,
    "gn:feature_class":"P",
    "gn:feature_code":"PPL",
    "gn:name":"Mayamtor",
    "gn:population":0,
    "gn:timezone":"Africa/Ndjamena",
    "iso:country":"TD",
    "wof:name":"Mayamtor",
    "wof:placetype":"locality"
},
  "geometry": {"coordinates":[17.38479,9.31013],"type":"Point"}
}