{
  "type": "Feature",
  "properties": {
    "gn:admin1_code":"8.0",
    "gn:asciiname":"Tapol II",
    "gn:country_code":"TD",
    "gn:dem":529,
    "gn:feature_class":"P",
    "gn:feature_code":"PPL",
    "gn:name":"Tapol II",
    "gn:population":0,
    "gn:timezone":"Africa/Ndjamena",
    "iso:country":"TD",
    "wof:name":"Tapol II",
    "wof:placetype":"locality"
},
  "geometry": {"coordinates":[15.38333,8.48333],"type":"Point"}
}