{
  "type": "Feature",
  "properties": {
    "gn:admin1_code":"5.0",
    "gn:asciiname":"Tandjam",
    "gn:country_code":"TD",
    "gn:dem":729,
    "gn:feature_class":"P",
    "gn:feature_code":"PPL",
    "gn:name":"Tandjam",
    "gn:population":0,
    "gn:timezone":"Africa/Ndjamena",
    "iso:country":"TD",
    "wof:name":"Tandjam",
    "wof:placetype":"locality"
},
  "geometry": {"coordinates":[19.00003,12.10001],"type":"Point"}
}