{
  "type": "Feature",
  "properties": {
    "gn:admin1_code":"15.0",
    "gn:asciiname":"Modjourou",
    "gn:country_code":"TD",
    "gn:dem":325,
    "gn:feature_class":"P",
    "gn:feature_code":"PPL",
    "gn:name":"Modjourou",
    "gn:population":0,
    "gn:timezone":"Africa/Ndjamena",
    "iso:country":"TD",
    "wof:name":"Modjourou",
    "wof:placetype":"locality"
},
  "geometry": {"coordinates":[16.08333,10.98333],"type":"Point"}
}