{
  "type": "Feature",
  "properties": {
    "gn:admin1_code":"15.0",
    "gn:asciiname":"Madogore",
    "gn:country_code":"TD",
    "gn:dem":305,
    "gn:feature_class":"P",
    "gn:feature_code":"PPL",
    "gn:name":"Madogor\u00e9",
    "gn:population":0,
    "gn:timezone":"Africa/Ndjamena",
    "iso:country":"TD",
    "wof:name":"Madogore",
    "wof:placetype":"locality"
},
  "geometry": {"coordinates":[15.4226,11.60188],"type":"Point"}
}