{
  "type": "Feature",
  "properties": {
    "gn:admin1_code":"14.0",
    "gn:asciiname":"Boumo",
    "gn:country_code":"TD",
    "gn:dem":346,
    "gn:feature_class":"P",
    "gn:feature_code":"PPL",
    "gn:name":"Boumo",
    "gn:population":0,
    "gn:timezone":"Africa/Ndjamena",
    "iso:country":"TD",
    "wof:name":"Boumo",
    "wof:placetype":"locality"
},
  "geometry": {"coordinates":[16.0848,9.6073],"type":"Point"}
}