{
  "type": "Feature",
  "properties": {
    "gn:admin1_code":"14.0",
    "gn:asciiname":"Manairaidi",
    "gn:country_code":"TD",
    "gn:dem":417,
    "gn:feature_class":"P",
    "gn:feature_code":"PPL",
    "gn:name":"Mana\u00efra\u00efdi",
    "gn:population":0,
    "gn:timezone":"Africa/Ndjamena",
    "iso:country":"TD",
    "wof:name":"Manairaidi",
    "wof:placetype":"locality"
},
  "geometry": {"coordinates":[16.658,9.1727],"type":"Point"}
}