{
  "type": "Feature",
  "properties": {
    "gn:admin1_code":"9.0",
    "gn:asciiname":"Mboura",
    "gn:country_code":"TD",
    "gn:dem":521,
    "gn:feature_class":"P",
    "gn:feature_code":"PPL",
    "gn:name":"Mboura",
    "gn:population":0,
    "gn:timezone":"Africa/Ndjamena",
    "iso:country":"TD",
    "wof:name":"Mboura",
    "wof:placetype":"locality"
},
  "geometry": {"coordinates":[15.59492,7.59619],"type":"Point"}
}