{
  "type": "Feature",
  "properties": {
    "gn:admin1_code":"22.0",
    "gn:asciiname":"El Bedia",
    "gn:country_code":"TD",
    "gn:dem":292,
    "gn:feature_class":"P",
    "gn:feature_code":"PPL",
    "gn:name":"El B\u00e9dia",
    "gn:population":0,
    "gn:timezone":"Africa/Ndjamena",
    "iso:country":"TD",
    "wof:name":"El Bedia",
    "wof:placetype":"locality"
},
  "geometry": {"coordinates":[17.0122,13.2013],"type":"Point"}
}