{
  "type": "Feature",
  "properties": {
    "gn:admin1_code":"2.0",
    "gn:asciiname":"Kelki",
    "gn:country_code":"TD",
    "gn:dem":886,
    "gn:feature_class":"P",
    "gn:feature_code":"PPL",
    "gn:name":"K\u00e9lki",
    "gn:population":0,
    "gn:timezone":"Africa/Ndjamena",
    "iso:country":"TD",
    "name:fra_x_preferred":[
        "K\u00e9lki"
    ],
    "wof:name":"Kelki",
    "wof:placetype":"locality"
},
  "geometry": {"coordinates":[21.33987,14.39314],"type":"Point"}
}