{
  "type": "Feature",
  "properties": {
    "gn:admin1_code":"17.0",
    "gn:asciiname":"Morombi",
    "gn:country_code":"TD",
    "gn:dem":383,
    "gn:feature_class":"P",
    "gn:feature_code":"PPL",
    "gn:name":"Morombi",
    "gn:population":0,
    "gn:timezone":"Africa/Ndjamena",
    "iso:country":"TD",
    "wof:name":"Morombi",
    "wof:placetype":"locality"
},
  "geometry": {"coordinates":[18.5511,8.6763],"type":"Point"}
}