{
  "type": "Feature",
  "properties": {
    "gn:admin1_code":"2.0",
    "gn:asciiname":"Kandabor",
    "gn:country_code":"TD",
    "gn:dem":459,
    "gn:feature_class":"P",
    "gn:feature_code":"PPL",
    "gn:name":"Kandabor",
    "gn:population":0,
    "gn:timezone":"Africa/Ndjamena",
    "iso:country":"TD",
    "wof:name":"Kandabor",
    "wof:placetype":"locality"
},
  "geometry": {"coordinates":[20.59939,14.54175],"type":"Point"}
}