{
  "type": "Feature",
  "properties": {
    "gn:admin1_code":"15.0",
    "gn:asciiname":"Goria",
    "gn:country_code":"TD",
    "gn:dem":341,
    "gn:feature_class":"P",
    "gn:feature_code":"PPL",
    "gn:name":"Goria",
    "gn:population":0,
    "gn:timezone":"Africa/Ndjamena",
    "iso:country":"TD",
    "wof:name":"Goria",
    "wof:placetype":"locality"
},
  "geometry": {"coordinates":[17.3124,10.3585],"type":"Point"}
}