{
  "type": "Feature",
  "properties": {
    "gn:admin1_code":"1.0",
    "gn:asciiname":"Kererip",
    "gn:country_code":"TD",
    "gn:dem":345,
    "gn:feature_class":"P",
    "gn:feature_code":"PPL",
    "gn:name":"K\u00e9r\u00e9rip",
    "gn:population":0,
    "gn:timezone":"Africa/Ndjamena",
    "iso:country":"TD",
    "name:und_x_variant":[
        "Dombori",
        "K\u00e9r\u00e9rip"
    ],
    "wof:name":"Kererip",
    "wof:placetype":"locality"
},
  "geometry": {"coordinates":[18.6786,13.4473],"type":"Point"}
}