{
  "type": "Feature",
  "properties": {
    "gn:admin1_code":"9.0",
    "gn:asciiname":"Bebou",
    "gn:country_code":"TD",
    "gn:dem":518,
    "gn:feature_class":"P",
    "gn:feature_code":"PPL",
    "gn:name":"B\u00e9bou",
    "gn:population":0,
    "gn:timezone":"Africa/Ndjamena",
    "iso:country":"TD",
    "name:und_x_variant":[
        "B\u00e9bouladji",
        "B\u00e9bou"
    ],
    "wof:name":"Bebou",
    "wof:placetype":"locality"
},
  "geometry": {"coordinates":[16.1033,7.59959],"type":"Point"}
}