{
  "type": "Feature",
  "properties": {
    "gn:admin1_code":"19.0",
    "gn:asciiname":"Bebian",
    "gn:country_code":"TD",
    "gn:dem":391,
    "gn:feature_class":"P",
    "gn:feature_code":"PPL",
    "gn:name":"Bebian",
    "gn:population":0,
    "gn:timezone":"Africa/Ndjamena",
    "iso:country":"TD",
    "wof:name":"Bebian",
    "wof:placetype":"locality"
},
  "geometry": {"coordinates":[17.69656,8.00987],"type":"Point"}
}