{
  "type": "Feature",
  "properties": {
    "gn:admin1_code":"15.0",
    "gn:asciiname":"Gofa",
    "gn:country_code":"TD",
    "gn:dem":309,
    "gn:feature_class":"P",
    "gn:feature_code":"PPL",
    "gn:name":"Gofa",
    "gn:population":0,
    "gn:timezone":"Africa/Ndjamena",
    "iso:country":"TD",
    "wof:name":"Gofa",
    "wof:placetype":"locality"
},
  "geometry": {"coordinates":[15.06995,11.41463],"type":"Point"}
}