{
  "type": "Feature",
  "properties": {
    "gn:admin1_code":"1.0",
    "gn:asciiname":"Souene",
    "gn:country_code":"TD",
    "gn:dem":332,
    "gn:feature_class":"P",
    "gn:feature_code":"PPL",
    "gn:name":"Sou\u00e9ne",
    "gn:population":0,
    "gn:timezone":"Africa/Ndjamena",
    "iso:country":"TD",
    "name:und_x_variant":[
        "Su\u00e8n\u00e9",
        "Sou\u00e9ne"
    ],
    "wof:name":"Souene",
    "wof:placetype":"locality"
},
  "geometry": {"coordinates":[18.35863,12.96811],"type":"Point"}
}