{
  "type": "Feature",
  "properties": {
    "gn:admin1_code":"18.0",
    "gn:asciiname":"Tagaga",
    "gn:country_code":"TD",
    "gn:dem":288,
    "gn:feature_class":"P",
    "gn:feature_code":"PPL",
    "gn:name":"Tagaga",
    "gn:population":0,
    "gn:timezone":"Africa/Ndjamena",
    "iso:country":"TD",
    "wof:name":"Tagaga",
    "wof:placetype":"locality"
},
  "geometry": {"coordinates":[15.45637,13.01233],"type":"Point"}
}