{
  "type": "Feature",
  "properties": {
    "gn:admin1_code":"9.0",
    "gn:asciiname":"Bero",
    "gn:country_code":"TD",
    "gn:dem":420,
    "gn:feature_class":"P",
    "gn:feature_code":"PPL",
    "gn:name":"B\u00e9ro",
    "gn:population":0,
    "gn:timezone":"Africa/Ndjamena",
    "iso:country":"TD",
    "name:ceb_x_preferred":[
        "Bero"
    ],
    "name:deu_x_preferred":[
        "Bero"
    ],
    "name:fra_x_preferred":[
        "Bero"
    ],
    "name:ita_x_preferred":[
        "Bero"
    ],
    "name:nld_x_preferred":[
        "Bero"
    ],
    "name:swe_x_preferred":[
        "Bero"
    ],
    "name:ukr_x_preferred":[
        "\u0411\u0435\u0440\u043e"
    ],
    "wof:name":"Bero",
    "wof:placetype":"locality"
},
  "geometry": {"coordinates":[17.08952,8.34382],"type":"Point"}
}