{
  "type": "Feature",
  "properties": {
    "gn:admin1_code":"15.0",
    "gn:asciiname":"Amoud al Ridjal",
    "gn:country_code":"TD",
    "gn:dem":304,
    "gn:feature_class":"P",
    "gn:feature_code":"PPL",
    "gn:name":"Amoud al Ridjal",
    "gn:population":0,
    "gn:timezone":"Africa/Ndjamena",
    "iso:country":"TD",
    "name:und_x_variant":[
        "Hamoud al Ridjal",
        "Amoud al Ridjal"
    ],
    "wof:name":"Amoud al Ridjal",
    "wof:placetype":"locality"
},
  "geometry": {"coordinates":[15.46727,11.63609],"type":"Point"}
}