{
  "type": "Feature",
  "properties": {
    "gn:admin1_code":"14.0",
    "gn:asciiname":"Zamre Anday",
    "gn:country_code":"TD",
    "gn:dem":366,
    "gn:feature_class":"P",
    "gn:feature_code":"PPL",
    "gn:name":"Zamre Anday",
    "gn:population":0,
    "gn:timezone":"Africa/Ndjamena",
    "iso:country":"TD",
    "wof:name":"Zamre Anday",
    "wof:placetype":"locality"
},
  "geometry": {"coordinates":[15.58238,9.34982],"type":"Point"}
}