{
  "type": "Feature",
  "properties": {
    "gn:admin1_code":"7.0",
    "gn:asciiname":"Sourtide",
    "gn:country_code":"TD",
    "gn:dem":296,
    "gn:feature_class":"P",
    "gn:feature_code":"PPL",
    "gn:name":"Sourtid\u00e9",
    "gn:population":0,
    "gn:timezone":"Africa/Ndjamena",
    "iso:country":"TD",
    "wof:name":"Sourtide",
    "wof:placetype":"locality"
},
  "geometry": {"coordinates":[15.79391,13.25218],"type":"Point"}
}