{
  "type": "Feature",
  "properties": {
    "gn:admin1_code":"25.0",
    "gn:asciiname":"Am Loubia",
    "gn:country_code":"TD",
    "gn:dem":429,
    "gn:feature_class":"P",
    "gn:feature_code":"PPL",
    "gn:name":"Am Loubia",
    "gn:population":0,
    "gn:timezone":"Africa/Ndjamena",
    "iso:country":"TD",
    "wof:name":"Am Loubia",
    "wof:placetype":"locality"
},
  "geometry": {"coordinates":[20.26667,12.95],"type":"Point"}
}