{
  "type": "Feature",
  "properties": {
    "gn:admin1_code":"18.0",
    "gn:asciiname":"Malamousa",
    "gn:country_code":"TD",
    "gn:dem":289,
    "gn:feature_class":"P",
    "gn:feature_code":"PPL",
    "gn:name":"Malamousa",
    "gn:population":0,
    "gn:timezone":"Africa/Ndjamena",
    "iso:country":"TD",
    "wof:name":"Malamousa",
    "wof:placetype":"locality"
},
  "geometry": {"coordinates":[15.72869,13.02859],"type":"Point"}
}