{
  "type": "Feature",
  "properties": {
    "gn:admin1_code":"16.0",
    "gn:asciiname":"Dafa",
    "gn:country_code":"TD",
    "gn:dem":316,
    "gn:feature_class":"P",
    "gn:feature_code":"PPL",
    "gn:name":"Dafa",
    "gn:population":0,
    "gn:timezone":"Africa/Ndjamena",
    "iso:country":"TD",
    "wof:name":"Dafa",
    "wof:placetype":"locality"
},
  "geometry": {"coordinates":[15.27891,10.51998],"type":"Point"}
}