{
  "type": "Feature",
  "properties": {
    "gn:admin1_code":"12.0",
    "gn:asciiname":"Kouchoulou",
    "gn:country_code":"TD",
    "gn:dem":473,
    "gn:feature_class":"P",
    "gn:feature_code":"PPL",
    "gn:name":"Kouchoulou",
    "gn:population":0,
    "gn:timezone":"Africa/Ndjamena",
    "iso:country":"TD",
    "name:fra_x_preferred":[
        "Kouchoulou"
    ],
    "wof:name":"Kouchoulou",
    "wof:placetype":"locality"
},
  "geometry": {"coordinates":[20.63137,13.24136],"type":"Point"}
}