{
  "type": "Feature",
  "properties": {
    "gn:admin1_code":"18.0",
    "gn:asciiname":"Malaouaya",
    "gn:country_code":"TD",
    "gn:dem":293,
    "gn:feature_class":"P",
    "gn:feature_code":"PPL",
    "gn:name":"Malaouaya",
    "gn:population":0,
    "gn:timezone":"Africa/Ndjamena",
    "iso:country":"TD",
    "name:und_x_variant":[
        "Malawaya"
    ],
    "wof:name":"Malaouaya",
    "wof:placetype":"locality"
},
  "geometry": {"coordinates":[14.95201,12.53655],"type":"Point"}
}