{
  "type": "Feature",
  "properties": {
    "gn:admin1_code":"25.0",
    "gn:asciiname":"Ouere",
    "gn:country_code":"TD",
    "gn:dem":659,
    "gn:feature_class":"P",
    "gn:feature_code":"PPL",
    "gn:name":"Ou\u00e9r\u00e9",
    "gn:population":0,
    "gn:timezone":"Africa/Ndjamena",
    "iso:country":"TD",
    "name:und_x_variant":[
        "Ouir\u00e9",
        "Ou\u00e9r\u00e9"
    ],
    "wof:name":"Ouere",
    "wof:placetype":"locality"
},
  "geometry": {"coordinates":[22.11667000000001,12.31667],"type":"Point"}
}