{
  "type": "Feature",
  "properties": {
    "gn:admin1_code":"5.0",
    "gn:asciiname":"Kieke",
    "gn:country_code":"TD",
    "gn:dem":379,
    "gn:feature_class":"P",
    "gn:feature_code":"PPL",
    "gn:name":"Ki\u00e9k\u00e9",
    "gn:population":0,
    "gn:timezone":"Africa/Ndjamena",
    "iso:country":"TD",
    "wof:name":"Kieke",
    "wof:placetype":"locality"
},
  "geometry": {"coordinates":[19.3579,12.7866],"type":"Point"}
}