{
  "type": "Feature",
  "properties": {
    "gn:admin1_code":"9.0",
    "gn:asciiname":"Kaba",
    "gn:country_code":"TD",
    "gn:dem":396,
    "gn:feature_class":"P",
    "gn:feature_code":"PPL",
    "gn:name":"Kaba",
    "gn:population":0,
    "gn:timezone":"Africa/Ndjamena",
    "iso:country":"TD",
    "name:ceb_x_preferred":[
        "Kaba"
    ],
    "name:deu_x_preferred":[
        "Kaba"
    ],
    "name:fin_x_preferred":[
        "Kaba"
    ],
    "name:fra_x_preferred":[
        "Kaba"
    ],
    "name:hrv_x_preferred":[
        "Kaba"
    ],
    "name:swe_x_preferred":[
        "Kaba"
    ],
    "wof:name":"Kaba",
    "wof:placetype":"locality"
},
  "geometry": {"coordinates":[16.7301,8.4381],"type":"Point"}
}