{
  "type": "Feature",
  "properties": {
    "gn:admin1_code":"12.0",
    "gn:asciiname":"Dembe",
    "gn:country_code":"TD",
    "gn:dem":497,
    "gn:feature_class":"P",
    "gn:feature_code":"PPL",
    "gn:name":"Demb\u00e9",
    "gn:population":0,
    "gn:timezone":"Africa/Ndjamena",
    "iso:country":"TD",
    "name:ceb_x_preferred":[
        "Dembe"
    ],
    "name:swe_x_preferred":[
        "Dembe"
    ],
    "wof:name":"Dembe",
    "wof:placetype":"locality"
},
  "geometry": {"coordinates":[20.77652,14.34856],"type":"Point"}
}