{
  "type": "Feature",
  "properties": {
    "gn:admin1_code":"12.0",
    "gn:asciiname":"Chinini",
    "gn:country_code":"TD",
    "gn:dem":532,
    "gn:feature_class":"P",
    "gn:feature_code":"PPL",
    "gn:name":"Chinini",
    "gn:population":0,
    "gn:timezone":"Africa/Ndjamena",
    "iso:country":"TD",
    "wof:name":"Chinini",
    "wof:placetype":"locality"
},
  "geometry": {"coordinates":[21.28333,12.96667],"type":"Point"}
}