{
  "type": "Feature",
  "properties": {
    "gn:admin1_code":"25.0",
    "gn:asciiname":"Djimez Arourou",
    "gn:country_code":"TD",
    "gn:dem":545,
    "gn:feature_class":"P",
    "gn:feature_code":"PPL",
    "gn:name":"Djim\u00e8z Arourou",
    "gn:population":0,
    "gn:timezone":"Africa/Ndjamena",
    "iso:country":"TD",
    "wof:name":"Djimez Arourou",
    "wof:placetype":"locality"
},
  "geometry": {"coordinates":[22.23829,11.98859],"type":"Point"}
}