{
  "type": "Feature",
  "properties": {
    "gn:admin1_code":"25.0",
    "gn:asciiname":"Hadjer Beida",
    "gn:country_code":"TD",
    "gn:dem":618,
    "gn:feature_class":"P",
    "gn:feature_code":"PPL",
    "gn:name":"Hadjer B\u00e9\u00efda",
    "gn:population":0,
    "gn:timezone":"Africa/Ndjamena",
    "iso:country":"TD",
    "wof:name":"Hadjer Beida",
    "wof:placetype":"locality"
},
  "geometry": {"coordinates":[22.31667,12.45],"type":"Point"}
}