{
  "type": "Feature",
  "properties": {
    "gn:admin1_code":"16.0",
    "gn:asciiname":"Soudio",
    "gn:country_code":"TD",
    "gn:dem":325,
    "gn:feature_class":"P",
    "gn:feature_code":"PPL",
    "gn:name":"Soudio",
    "gn:population":0,
    "gn:timezone":"Africa/Ndjamena",
    "iso:country":"TD",
    "wof:name":"Soudio",
    "wof:placetype":"locality"
},
  "geometry": {"coordinates":[15.72442,10.48513],"type":"Point"}
}