{
  "type": "Feature",
  "properties": {
    "gn:admin1_code":"1.0",
    "gn:asciiname":"Am Dourban",
    "gn:country_code":"TD",
    "gn:dem":379,
    "gn:feature_class":"P",
    "gn:feature_code":"PPL",
    "gn:name":"Am Dourban",
    "gn:population":0,
    "gn:timezone":"Africa/Ndjamena",
    "iso:country":"TD",
    "name:und_x_variant":[
        "Am Dourbane",
        "Am Dourban"
    ],
    "wof:name":"Am Dourban",
    "wof:placetype":"locality"
},
  "geometry": {"coordinates":[19.5329,13.2453],"type":"Point"}
}