{
  "type": "Feature",
  "properties": {
    "gn:admin1_code":"12.0",
    "gn:asciiname":"Matabono",
    "gn:country_code":"TD",
    "gn:dem":563,
    "gn:feature_class":"P",
    "gn:feature_code":"PPL",
    "gn:name":"Matabono",
    "gn:population":0,
    "gn:timezone":"Africa/Ndjamena",
    "iso:country":"TD",
    "name:fra_x_preferred":[
        "Matabono"
    ],
    "wof:name":"Matabono",
    "wof:placetype":"locality"
},
  "geometry": {"coordinates":[20.9635,13.51089],"type":"Point"}
}