{
  "type": "Feature",
  "properties": {
    "gn:admin1_code":"9.0",
    "gn:asciiname":"Bedane",
    "gn:country_code":"TD",
    "gn:dem":456,
    "gn:feature_class":"P",
    "gn:feature_code":"PPL",
    "gn:name":"Bedane",
    "gn:population":0,
    "gn:timezone":"Africa/Ndjamena",
    "iso:country":"TD",
    "wof:name":"Bedane",
    "wof:placetype":"locality"
},
  "geometry": {"coordinates":[16.33333,8.01667],"type":"Point"}
}