{
  "type": "Feature",
  "properties": {
    "gn:admin1_code":"9.0",
    "gn:asciiname":"Dangdil",
    "gn:country_code":"TD",
    "gn:dem":400,
    "gn:feature_class":"P",
    "gn:feature_code":"PPL",
    "gn:name":"Dangdil",
    "gn:population":0,
    "gn:timezone":"Africa/Ndjamena",
    "iso:country":"TD",
    "wof:name":"Dangdil",
    "wof:placetype":"locality"
},
  "geometry": {"coordinates":[16.44924,8.61165],"type":"Point"}
}