{
  "type": "Feature",
  "properties": {
    "gn:admin1_code":"15.0",
    "gn:asciiname":"Kerce",
    "gn:country_code":"TD",
    "gn:dem":305,
    "gn:feature_class":"P",
    "gn:feature_code":"PPL",
    "gn:name":"Kerc\u00e9",
    "gn:population":0,
    "gn:timezone":"Africa/Ndjamena",
    "iso:country":"TD",
    "name:und_x_variant":[
        "Kerse",
        "Kerc\u00e9"
    ],
    "wof:name":"Kerce",
    "wof:placetype":"locality"
},
  "geometry": {"coordinates":[15.2809,11.21477],"type":"Point"}
}