{
  "type": "Feature",
  "properties": {
    "gn:admin1_code":"12.0",
    "gn:asciiname":"Idjeyne",
    "gn:country_code":"TD",
    "gn:dem":411,
    "gn:feature_class":"P",
    "gn:feature_code":"PPL",
    "gn:name":"Idjeyn\u00e9",
    "gn:population":0,
    "gn:timezone":"Africa/Ndjamena",
    "iso:country":"TD",
    "wof:name":"Idjeyne",
    "wof:placetype":"locality"
},
  "geometry": {"coordinates":[20.21129,14.23781],"type":"Point"}
}