{
  "type": "Feature",
  "properties": {
    "gn:admin1_code":"20.0",
    "gn:asciiname":"Delhou Soule",
    "gn:country_code":"TD",
    "gn:dem":322,
    "gn:feature_class":"P",
    "gn:feature_code":"PPL",
    "gn:name":"Delhou Soul\u00e9",
    "gn:population":0,
    "gn:timezone":"Africa/Ndjamena",
    "iso:country":"TD",
    "wof:name":"Delhou Soule",
    "wof:placetype":"locality"
},
  "geometry": {"coordinates":[14.4057,9.2978],"type":"Point"}
}