{
  "type": "Feature",
  "properties": {
    "gn:admin1_code":"18.0",
    "gn:asciiname":"Boholo",
    "gn:country_code":"TD",
    "gn:dem":298,
    "gn:feature_class":"P",
    "gn:feature_code":"PPL",
    "gn:name":"Boholo",
    "gn:population":0,
    "gn:timezone":"Africa/Ndjamena",
    "iso:country":"TD",
    "wof:name":"Boholo",
    "wof:placetype":"locality"
},
  "geometry": {"coordinates":[16.63303,12.35559],"type":"Point"}
}