{
  "type": "Feature",
  "properties": {
    "gn:admin1_code":"14.0",
    "gn:asciiname":"Koblague",
    "gn:country_code":"TD",
    "gn:dem":345,
    "gn:feature_class":"P",
    "gn:feature_code":"PPL",
    "gn:name":"Koblagu\u00e9",
    "gn:population":0,
    "gn:timezone":"Africa/Ndjamena",
    "iso:country":"TD",
    "name:und_x_variant":[
        "Koblag\u00e9",
        "Koblag",
        "Koblagu\u00e9"
    ],
    "wof:name":"Koblague",
    "wof:placetype":"locality"
},
  "geometry": {"coordinates":[16.71,9.7961],"type":"Point"}
}