{
  "type": "Feature",
  "properties": {
    "gn:admin1_code":"1.0",
    "gn:asciiname":"Ab Kous",
    "gn:country_code":"TD",
    "gn:dem":366,
    "gn:feature_class":"P",
    "gn:feature_code":"PPL",
    "gn:name":"Ab Kous",
    "gn:population":0,
    "gn:timezone":"Africa/Ndjamena",
    "iso:country":"TD",
    "name:und_x_variant":[
        "Ap Kouss",
        "Ab Kous"
    ],
    "wof:name":"Ab Kous",
    "wof:placetype":"locality"
},
  "geometry": {"coordinates":[19.1755,13.6027],"type":"Point"}
}