{
  "type": "Feature",
  "properties": {
    "gn:admin1_code":"12.0",
    "gn:asciiname":"Achkitin",
    "gn:country_code":"TD",
    "gn:dem":530,
    "gn:feature_class":"P",
    "gn:feature_code":"PPL",
    "gn:name":"Achkitin",
    "gn:population":0,
    "gn:timezone":"Africa/Ndjamena",
    "iso:country":"TD",
    "name:fra_x_preferred":[
        "Achkitin"
    ],
    "wof:name":"Achkitin",
    "wof:placetype":"locality"
},
  "geometry": {"coordinates":[20.75745,13.98016],"type":"Point"}
}