{
  "type": "Feature",
  "properties": {
    "gn:admin1_code":"16.0",
    "gn:asciiname":"Kourgou",
    "gn:country_code":"TD",
    "gn:dem":343,
    "gn:feature_class":"P",
    "gn:feature_code":"PPL",
    "gn:name":"Kourgou",
    "gn:population":0,
    "gn:timezone":"Africa/Ndjamena",
    "iso:country":"TD",
    "name:ceb_x_preferred":[
        "Kourgou"
    ],
    "name:swe_x_preferred":[
        "Kourgou"
    ],
    "wof:name":"Kourgou",
    "wof:placetype":"locality"
},
  "geometry": {"coordinates":[16.0527,10.0468],"type":"Point"}
}