{
  "type": "Feature",
  "properties": {
    "gn:admin1_code":"14.0",
    "gn:asciiname":"Kolsiri",
    "gn:country_code":"TD",
    "gn:dem":477,
    "gn:feature_class":"P",
    "gn:feature_code":"PPL",
    "gn:name":"Kolsiri",
    "gn:population":0,
    "gn:timezone":"Africa/Ndjamena",
    "iso:country":"TD",
    "wof:name":"Kolsiri",
    "wof:placetype":"locality"
},
  "geometry": {"coordinates":[16.7369,9.0791],"type":"Point"}
}