{
  "type": "Feature",
  "properties": {
    "gn:admin1_code":"18.0",
    "gn:asciiname":"Am Igerib",
    "gn:country_code":"TD",
    "gn:dem":296,
    "gn:feature_class":"P",
    "gn:feature_code":"PPL",
    "gn:name":"Am Ig\u00e9rib",
    "gn:population":0,
    "gn:timezone":"Africa/Ndjamena",
    "iso:country":"TD",
    "wof:name":"Am Igerib",
    "wof:placetype":"locality"
},
  "geometry": {"coordinates":[17.13998,12.53156],"type":"Point"}
}