{
  "type": "Feature",
  "properties": {
    "gn:admin1_code":"20.0",
    "gn:asciiname":"Mayel Ngam",
    "gn:country_code":"TD",
    "gn:dem":335,
    "gn:feature_class":"P",
    "gn:feature_code":"PPL",
    "gn:name":"Mayel Ngam",
    "gn:population":0,
    "gn:timezone":"Africa/Ndjamena",
    "iso:country":"TD",
    "name:und_x_variant":[
        "Mayel Gam",
        "Mayel Ngam"
    ],
    "wof:name":"Mayel Ngam",
    "wof:placetype":"locality"
},
  "geometry": {"coordinates":[14.44159,9.94325],"type":"Point"}
}