{
  "type": "Feature",
  "properties": {
    "gn:admin1_code":"5.0",
    "gn:asciiname":"Tasono",
    "gn:country_code":"TD",
    "gn:dem":404,
    "gn:feature_class":"P",
    "gn:feature_code":"PPL",
    "gn:name":"Tasono",
    "gn:population":0,
    "gn:timezone":"Africa/Ndjamena",
    "iso:country":"TD",
    "wof:name":"Tasono",
    "wof:placetype":"locality"
},
  "geometry": {"coordinates":[19.6436,12.8524],"type":"Point"}
}