{
  "type": "Feature",
  "properties": {
    "gn:admin1_code":"14.0",
    "gn:asciiname":"Tchire Moussei",
    "gn:country_code":"TD",
    "gn:dem":347,
    "gn:feature_class":"P",
    "gn:feature_code":"PPL",
    "gn:name":"Tchir\u00e9 Mousse\u00ef",
    "gn:population":0,
    "gn:timezone":"Africa/Ndjamena",
    "iso:country":"TD",
    "wof:name":"Tchire Moussei",
    "wof:placetype":"locality"
},
  "geometry": {"coordinates":[15.85,9.58333],"type":"Point"}
}