{
  "type": "Feature",
  "properties": {
    "gn:admin1_code":"18.0",
    "gn:asciiname":"Falirom",
    "gn:country_code":"TD",
    "gn:dem":288,
    "gn:feature_class":"P",
    "gn:feature_code":"PPL",
    "gn:name":"Falirom",
    "gn:population":0,
    "gn:timezone":"Africa/Ndjamena",
    "iso:country":"TD",
    "wof:name":"Falirom",
    "wof:placetype":"locality"
},
  "geometry": {"coordinates":[15.4801,12.89256],"type":"Point"}
}