{
  "type": "Feature",
  "properties": {
    "gn:admin1_code":"1.0",
    "gn:asciiname":"Djokhana",
    "gn:country_code":"TD",
    "gn:dem":289,
    "gn:feature_class":"P",
    "gn:feature_code":"PPL",
    "gn:name":"Djokhana",
    "gn:population":0,
    "gn:timezone":"Africa/Ndjamena",
    "iso:country":"TD",
    "wof:name":"Djokhana",
    "wof:placetype":"locality"
},
  "geometry": {"coordinates":[17.17538,12.70209],"type":"Point"}
}