{
  "type": "Feature",
  "properties": {
    "gn:admin1_code":"18.0",
    "gn:asciiname":"Am Senete",
    "gn:country_code":"TD",
    "gn:dem":293,
    "gn:feature_class":"P",
    "gn:feature_code":"PPL",
    "gn:name":"Am S\u00e9n\u00e9t\u00e9",
    "gn:population":0,
    "gn:timezone":"Africa/Ndjamena",
    "iso:country":"TD",
    "name:und_x_variant":[
        "S\u00e9n\u00e9t\u00e9",
        "Am S\u00e9n\u00e9t\u00e9"
    ],
    "wof:name":"Am Senete",
    "wof:placetype":"locality"
},
  "geometry": {"coordinates":[15.52369,12.55115],"type":"Point"}
}