{
  "type": "Feature",
  "properties": {
    "gn:admin1_code":"25.0",
    "gn:asciiname":"Am Derese",
    "gn:country_code":"TD",
    "gn:dem":505,
    "gn:feature_class":"P",
    "gn:feature_code":"PPL",
    "gn:name":"Am D\u00e9r\u00e9s\u00e9",
    "gn:population":0,
    "gn:timezone":"Africa/Ndjamena",
    "iso:country":"TD",
    "wof:name":"Am Derese",
    "wof:placetype":"locality"
},
  "geometry": {"coordinates":[21.5033,11.9874],"type":"Point"}
}