{
  "type": "Feature",
  "properties": {
    "gn:admin1_code":"8.0",
    "gn:asciiname":"Begoumara",
    "gn:country_code":"TD",
    "gn:dem":506,
    "gn:feature_class":"P",
    "gn:feature_code":"PPL",
    "gn:name":"B\u00e9goumara",
    "gn:population":0,
    "gn:timezone":"Africa/Ndjamena",
    "iso:country":"TD",
    "wof:name":"Begoumara",
    "wof:placetype":"locality"
},
  "geometry": {"coordinates":[16.28909,8.90873],"type":"Point"}
}