{
  "type": "Feature",
  "properties": {
    "gn:admin1_code":"6.0",
    "gn:asciiname":"Faraye",
    "gn:country_code":"TD",
    "gn:dem":327,
    "gn:feature_class":"P",
    "gn:feature_code":"PPL",
    "gn:name":"Faray\u00e9",
    "gn:population":0,
    "gn:timezone":"Africa/Ndjamena",
    "iso:country":"TD",
    "wof:name":"Faraye",
    "wof:placetype":"locality"
},
  "geometry": {"coordinates":[15.23313,14.24395],"type":"Point"}
}