{
  "type": "Feature",
  "properties": {
    "gn:admin1_code":"18.0",
    "gn:asciiname":"Fale",
    "gn:country_code":"TD",
    "gn:dem":295,
    "gn:feature_class":"P",
    "gn:feature_code":"PPL",
    "gn:name":"Fal\u00e9",
    "gn:population":0,
    "gn:timezone":"Africa/Ndjamena",
    "iso:country":"TD",
    "name:ceb_x_preferred":[
        "Fale"
    ],
    "name:deu_x_preferred":[
        "Fale"
    ],
    "name:nld_x_preferred":[
        "Fale"
    ],
    "name:pol_x_preferred":[
        "Fale"
    ],
    "name:por_x_preferred":[
        "Fale"
    ],
    "name:swe_x_preferred":[
        "Fale"
    ],
    "name:und_x_variant":[
        "Folle",
        "Fall\u00e9",
        "Fal\u00e9"
    ],
    "wof:name":"Fale",
    "wof:placetype":"locality"
},
  "geometry": {"coordinates":[16.9418,13.0746],"type":"Point"}
}