{
  "type": "Feature",
  "properties": {
    "gn:admin1_code":"18.0",
    "gn:asciiname":"Nguieto",
    "gn:country_code":"TD",
    "gn:dem":319,
    "gn:feature_class":"P",
    "gn:feature_code":"PPL",
    "gn:name":"Ngui\u00e9to",
    "gn:population":0,
    "gn:timezone":"Africa/Ndjamena",
    "iso:country":"TD",
    "name:und_x_variant":[
        "Ngi\u00e9to",
        "Ngui\u00e9to"
    ],
    "wof:name":"Nguieto",
    "wof:placetype":"locality"
},
  "geometry": {"coordinates":[17.1791,11.8843],"type":"Point"}
}