{
  "type": "Feature",
  "properties": {
    "gn:admin1_code":"12.0",
    "gn:asciiname":"Magarin Saba",
    "gn:country_code":"TD",
    "gn:dem":437,
    "gn:feature_class":"P",
    "gn:feature_code":"PPL",
    "gn:name":"Magarin Saba",
    "gn:population":0,
    "gn:timezone":"Africa/Ndjamena",
    "iso:country":"TD",
    "name:fra_x_preferred":[
        "Magarin Saba"
    ],
    "wof:name":"Magarin Saba",
    "wof:placetype":"locality"
},
  "geometry": {"coordinates":[20.29629,13.96989],"type":"Point"}
}