{
  "type": "Feature",
  "properties": {
    "gn:admin1_code":"26.0",
    "gn:asciiname":"Ore",
    "gn:country_code":"TD",
    "gn:dem":1215,
    "gn:feature_class":"P",
    "gn:feature_code":"PPL",
    "gn:name":"Or\u00e9",
    "gn:population":0,
    "gn:timezone":"Africa/Ndjamena",
    "iso:country":"TD",
    "wof:name":"Ore",
    "wof:placetype":"locality"
},
  "geometry": {"coordinates":[17.36667000000001,21.25],"type":"Point"}
}