{
  "type": "Feature",
  "properties": {
    "gn:admin1_code":"18.0",
    "gn:asciiname":"Bachoum",
    "gn:country_code":"TD",
    "gn:dem":291,
    "gn:feature_class":"P",
    "gn:feature_code":"PPL",
    "gn:name":"Bachoum",
    "gn:population":0,
    "gn:timezone":"Africa/Ndjamena",
    "iso:country":"TD",
    "name:und_x_variant":[
        "Batchoum",
        "Bachoum"
    ],
    "wof:name":"Bachoum",
    "wof:placetype":"locality"
},
  "geometry": {"coordinates":[15.65556,12.84247],"type":"Point"}
}