{
  "type": "Feature",
  "properties": {
    "gn:admin1_code":"14.0",
    "gn:asciiname":"Doboung",
    "gn:country_code":"TD",
    "gn:dem":368,
    "gn:feature_class":"P",
    "gn:feature_code":"PPL",
    "gn:name":"Doboung",
    "gn:population":0,
    "gn:timezone":"Africa/Ndjamena",
    "iso:country":"TD",
    "wof:name":"Doboung",
    "wof:placetype":"locality"
},
  "geometry": {"coordinates":[15.83957,9.33907],"type":"Point"}
}