{
  "type": "Feature",
  "properties": {
    "gn:admin1_code":"18.0",
    "gn:asciiname":"Krenoua",
    "gn:country_code":"TD",
    "gn:dem":292,
    "gn:feature_class":"P",
    "gn:feature_code":"PPL",
    "gn:name":"Krenoua",
    "gn:population":0,
    "gn:timezone":"Africa/Ndjamena",
    "iso:country":"TD",
    "name:und_x_variant":[
        "Kr\u00e9noua"
    ],
    "wof:name":"Krenoua",
    "wof:placetype":"locality"
},
  "geometry": {"coordinates":[14.97676,12.56951],"type":"Point"}
}