{
  "type": "Feature",
  "properties": {
    "gn:admin1_code":"14.0",
    "gn:asciiname":"Doangui",
    "gn:country_code":"TD",
    "gn:dem":350,
    "gn:feature_class":"P",
    "gn:feature_code":"PPL",
    "gn:name":"Doangui",
    "gn:population":0,
    "gn:timezone":"Africa/Ndjamena",
    "iso:country":"TD",
    "wof:name":"Doangui",
    "wof:placetype":"locality"
},
  "geometry": {"coordinates":[16.6941,9.5468],"type":"Point"}
}