{
  "type": "Feature",
  "properties": {
    "gn:admin1_code":"15.0",
    "gn:asciiname":"Mankin",
    "gn:country_code":"TD",
    "gn:dem":308,
    "gn:feature_class":"P",
    "gn:feature_code":"PPL",
    "gn:name":"Mankin",
    "gn:population":0,
    "gn:timezone":"Africa/Ndjamena",
    "iso:country":"TD",
    "name:deu_x_preferred":[
        "Mankin"
    ],
    "name:heb_x_preferred":[
        "\u05de\u05e0\u05e7\u05d9\u05df"
    ],
    "wof:name":"Mankin",
    "wof:placetype":"locality"
},
  "geometry": {"coordinates":[15.23368,11.47729],"type":"Point"}
}