{
  "type": "Feature",
  "properties": {
    "gn:admin1_code":"14.0",
    "gn:asciiname":"Tamion Ngolo",
    "gn:country_code":"TD",
    "gn:dem":362,
    "gn:feature_class":"P",
    "gn:feature_code":"PPL",
    "gn:name":"Tamion Ngolo",
    "gn:population":0,
    "gn:timezone":"Africa/Ndjamena",
    "iso:country":"TD",
    "name:und_x_variant":[
        "Tamian Ngolo",
        "Tamion Ngolo"
    ],
    "wof:name":"Tamion Ngolo",
    "wof:placetype":"locality"
},
  "geometry": {"coordinates":[16.2899,9.243],"type":"Point"}
}