{
  "type": "Feature",
  "properties": {
    "gn:admin1_code":"17.0",
    "gn:asciiname":"Badi",
    "gn:country_code":"TD",
    "gn:dem":403,
    "gn:feature_class":"P",
    "gn:feature_code":"PPL",
    "gn:name":"Badi",
    "gn:population":0,
    "gn:timezone":"Africa/Ndjamena",
    "iso:country":"TD",
    "wof:name":"Badi",
    "wof:placetype":"locality"
},
  "geometry": {"coordinates":[19.4844,10.5026],"type":"Point"}
}