{
  "type": "Feature",
  "properties": {
    "gn:admin1_code":"20.0",
    "gn:asciiname":"Oindaga",
    "gn:country_code":"TD",
    "gn:dem":398,
    "gn:feature_class":"P",
    "gn:feature_code":"PPL",
    "gn:name":"Oindaga",
    "gn:population":0,
    "gn:timezone":"Africa/Ndjamena",
    "iso:country":"TD",
    "name:und_x_variant":[
        "Wa\u00eflega",
        "Wil\u00e9ka",
        "Oindaga"
    ],
    "wof:name":"Oindaga",
    "wof:placetype":"locality"
},
  "geometry": {"coordinates":[14.8596,8.8646],"type":"Point"}
}