{
  "type": "Feature",
  "properties": {
    "gn:admin1_code":"16.0",
    "gn:asciiname":"Loboum",
    "gn:country_code":"TD",
    "gn:dem":315,
    "gn:feature_class":"P",
    "gn:feature_code":"PPL",
    "gn:name":"Loboum",
    "gn:population":0,
    "gn:timezone":"Africa/Ndjamena",
    "iso:country":"TD",
    "wof:name":"Loboum",
    "wof:placetype":"locality"
},
  "geometry": {"coordinates":[15.16346,11.01921],"type":"Point"}
}