{
  "type": "Feature",
  "properties": {
    "gn:admin1_code":"5.0",
    "gn:asciiname":"Temki",
    "gn:country_code":"TD",
    "gn:dem":484,
    "gn:feature_class":"P",
    "gn:feature_code":"PPL",
    "gn:name":"Temki",
    "gn:population":0,
    "gn:timezone":"Africa/Ndjamena",
    "iso:country":"TD",
    "wof:name":"Temki",
    "wof:placetype":"locality"
},
  "geometry": {"coordinates":[18.21651,11.48996],"type":"Point"}
}