{
  "type": "Feature",
  "properties": {
    "gn:admin1_code":"18.0",
    "gn:asciiname":"Geletie",
    "gn:country_code":"TD",
    "gn:dem":314,
    "gn:feature_class":"P",
    "gn:feature_code":"PPL",
    "gn:name":"G\u00e9l\u00e9ti\u00e9",
    "gn:population":0,
    "gn:timezone":"Africa/Ndjamena",
    "iso:country":"TD",
    "wof:name":"Geletie",
    "wof:placetype":"locality"
},
  "geometry": {"coordinates":[17.2621,12.1735],"type":"Point"}
}