{
  "type": "Feature",
  "properties": {
    "gn:admin1_code":"6.0",
    "gn:asciiname":"Ouagam",
    "gn:country_code":"TD",
    "gn:dem":342,
    "gn:feature_class":"P",
    "gn:feature_code":"PPL",
    "gn:name":"Ouagam",
    "gn:population":0,
    "gn:timezone":"Africa/Ndjamena",
    "iso:country":"TD",
    "wof:name":"Ouagam",
    "wof:placetype":"locality"
},
  "geometry": {"coordinates":[14.69284,14.35648],"type":"Point"}
}