{
  "type": "Feature",
  "properties": {
    "gn:admin1_code":"14.0",
    "gn:asciiname":"Leguem",
    "gn:country_code":"TD",
    "gn:dem":365,
    "gn:feature_class":"P",
    "gn:feature_code":"PPL",
    "gn:name":"Leguem",
    "gn:population":0,
    "gn:timezone":"Africa/Ndjamena",
    "iso:country":"TD",
    "wof:name":"Leguem",
    "wof:placetype":"locality"
},
  "geometry": {"coordinates":[16.016,9.1668],"type":"Point"}
}