{
  "type": "Feature",
  "properties": {
    "gn:admin1_code":"19.0",
    "gn:asciiname":"Goulol",
    "gn:country_code":"TD",
    "gn:dem":359,
    "gn:feature_class":"P",
    "gn:feature_code":"PPL",
    "gn:name":"Goulol",
    "gn:population":0,
    "gn:timezone":"Africa/Ndjamena",
    "iso:country":"TD",
    "wof:name":"Goulol",
    "wof:placetype":"locality"
},
  "geometry": {"coordinates":[17.33573,9.37103],"type":"Point"}
}