{
  "type": "Feature",
  "properties": {
    "gn:admin1_code":"7.0",
    "gn:asciiname":"Boul",
    "gn:country_code":"TD",
    "gn:dem":284,
    "gn:feature_class":"P",
    "gn:feature_code":"PPL",
    "gn:name":"Boul",
    "gn:population":0,
    "gn:timezone":"Africa/Ndjamena",
    "iso:country":"TD",
    "wof:name":"Boul",
    "wof:placetype":"locality"
},
  "geometry": {"coordinates":[13.9215,14.10049],"type":"Point"}
}