{
  "type": "Feature",
  "properties": {
    "gn:admin1_code":"25.0",
    "gn:asciiname":"Am Saterna",
    "gn:country_code":"TD",
    "gn:dem":516,
    "gn:feature_class":"P",
    "gn:feature_code":"PPL",
    "gn:name":"Am Saterna",
    "gn:population":0,
    "gn:timezone":"Africa/Ndjamena",
    "iso:country":"TD",
    "wof:name":"Am Saterna",
    "wof:placetype":"locality"
},
  "geometry": {"coordinates":[21.7322,11.9712],"type":"Point"}
}