{
  "type": "Feature",
  "properties": {
    "gn:admin1_code":"8.0",
    "gn:asciiname":"Koutou II",
    "gn:country_code":"TD",
    "gn:dem":365,
    "gn:feature_class":"P",
    "gn:feature_code":"PPL",
    "gn:name":"Koutou II",
    "gn:population":0,
    "gn:timezone":"Africa/Ndjamena",
    "iso:country":"TD",
    "name:und_x_variant":[
        "Koutou",
        "Koutou II"
    ],
    "wof:name":"Koutou II",
    "wof:placetype":"locality"
},
  "geometry": {"coordinates":[16.3934,9.1501],"type":"Point"}
}