{
  "type": "Feature",
  "properties": {
    "gn:admin1_code":"16.0",
    "gn:asciiname":"Roufou",
    "gn:cc2":"TD",
    "gn:country_code":"TD",
    "gn:dem":317,
    "gn:feature_class":"P",
    "gn:feature_code":"PPL",
    "gn:name":"Roufou",
    "gn:population":0,
    "gn:timezone":"Africa/Ndjamena",
    "iso:country":"TD",
    "name:und_x_variant":[
        "Bufu",
        "Boufou",
        "Rufu",
        "Roufou"
    ],
    "wof:name":"Roufou",
    "wof:placetype":"locality"
},
  "geometry": {"coordinates":[15.36667,10.83333],"type":"Point"}
}