{
  "type": "Feature",
  "properties": {
    "gn:admin1_code":"15.0",
    "gn:asciiname":"Atchinga",
    "gn:country_code":"TD",
    "gn:dem":295,
    "gn:feature_class":"P",
    "gn:feature_code":"PPL",
    "gn:name":"Atchinga",
    "gn:population":0,
    "gn:timezone":"Africa/Ndjamena",
    "iso:country":"TD",
    "wof:name":"Atchinga",
    "wof:placetype":"locality"
},
  "geometry": {"coordinates":[16.17864,12.32137],"type":"Point"}
}