{
  "type": "Feature",
  "properties": {
    "gn:admin1_code":"13.0",
    "gn:asciiname":"Bilayo",
    "gn:country_code":"TD",
    "gn:dem":481,
    "gn:feature_class":"P",
    "gn:feature_code":"PPL",
    "gn:name":"Bilayo",
    "gn:population":0,
    "gn:timezone":"Africa/Ndjamena",
    "iso:country":"TD",
    "name:und_x_variant":[
        "Bibayo",
        "Bilayo"
    ],
    "wof:name":"Bilayo",
    "wof:placetype":"locality"
},
  "geometry": {"coordinates":[19.1537,11.3522],"type":"Point"}
}