{
  "type": "Feature",
  "properties": {
    "gn:admin1_code":"7.0",
    "gn:asciiname":"Wadrati Soutoa",
    "gn:country_code":"TD",
    "gn:dem":301,
    "gn:feature_class":"P",
    "gn:feature_code":"PPL",
    "gn:name":"Wadrati Soutoa",
    "gn:population":0,
    "gn:timezone":"Africa/Ndjamena",
    "iso:country":"TD",
    "wof:name":"Wadrati Soutoa",
    "wof:placetype":"locality"
},
  "geometry": {"coordinates":[15.75837,13.48434],"type":"Point"}
}