{
  "type": "Feature",
  "properties": {
    "gn:admin1_code":"13.0",
    "gn:asciiname":"Sehep",
    "gn:country_code":"TD",
    "gn:dem":450,
    "gn:feature_class":"P",
    "gn:feature_code":"PPL",
    "gn:name":"S\u00e9hep",
    "gn:population":0,
    "gn:timezone":"Africa/Ndjamena",
    "iso:country":"TD",
    "name:und_x_variant":[
        "Cehep",
        "S\u00e9hep"
    ],
    "wof:name":"Sehep",
    "wof:placetype":"locality"
},
  "geometry": {"coordinates":[20.5773,11.2361],"type":"Point"}
}