{
  "type": "Feature",
  "properties": {
    "gn:admin1_code":"18.0",
    "gn:asciiname":"Douguina",
    "gn:country_code":"TD",
    "gn:dem":295,
    "gn:feature_class":"P",
    "gn:feature_code":"PPL",
    "gn:name":"Douguina",
    "gn:population":0,
    "gn:timezone":"Africa/Ndjamena",
    "iso:country":"TD",
    "name:und_x_variant":[
        "Dougia"
    ],
    "wof:name":"Douguina",
    "wof:placetype":"locality"
},
  "geometry": {"coordinates":[14.82548,12.64131],"type":"Point"}
}