{
  "type": "Feature",
  "properties": {
    "gn:admin1_code":"12.0",
    "gn:asciiname":"Kongo",
    "gn:country_code":"TD",
    "gn:dem":736,
    "gn:feature_class":"P",
    "gn:feature_code":"PPL",
    "gn:name":"Kongo",
    "gn:population":0,
    "gn:timezone":"Africa/Ndjamena",
    "iso:country":"TD",
    "wof:name":"Kongo",
    "wof:placetype":"locality"
},
  "geometry": {"coordinates":[21.62138,13.63812],"type":"Point"}
}