{
  "type": "Feature",
  "properties": {
    "gn:admin1_code":"12.0",
    "gn:asciiname":"Bir Malik",
    "gn:country_code":"TD",
    "gn:dem":435,
    "gn:feature_class":"P",
    "gn:feature_code":"PPL",
    "gn:name":"Bir Malik",
    "gn:population":0,
    "gn:timezone":"Africa/Ndjamena",
    "iso:country":"TD",
    "name:fra_x_preferred":[
        "Bir Malik"
    ],
    "wof:name":"Bir Malik",
    "wof:placetype":"locality"
},
  "geometry": {"coordinates":[20.30002,13.90578],"type":"Point"}
}