{
  "type": "Feature",
  "properties": {
    "gn:admin1_code":"7.0",
    "gn:asciiname":"Koulkoulia",
    "gn:country_code":"TD",
    "gn:dem":302,
    "gn:feature_class":"P",
    "gn:feature_code":"PPL",
    "gn:name":"Koulkoulia",
    "gn:population":0,
    "gn:timezone":"Africa/Ndjamena",
    "iso:country":"TD",
    "name:und_x_variant":[
        "Mabol Kouloulia",
        "Koulkoulaya",
        "Koulkoulia"
    ],
    "wof:name":"Koulkoulia",
    "wof:placetype":"locality"
},
  "geometry": {"coordinates":[15.72161,13.4403],"type":"Point"}
}