{
  "type": "Feature",
  "properties": {
    "gn:admin1_code":"2.0",
    "gn:asciiname":"Tarakoune",
    "gn:country_code":"TD",
    "gn:dem":922,
    "gn:feature_class":"P",
    "gn:feature_code":"PPL",
    "gn:name":"Tarakoun\u00e9",
    "gn:population":0,
    "gn:timezone":"Africa/Ndjamena",
    "iso:country":"TD",
    "name:fra_x_preferred":[
        "Tarakoun\u00e9"
    ],
    "wof:name":"Tarakoune",
    "wof:placetype":"locality"
},
  "geometry": {"coordinates":[21.64912,14.44608],"type":"Point"}
}