{
  "type": "Feature",
  "properties": {
    "gn:admin1_code":"9.0",
    "gn:asciiname":"Dobouroum",
    "gn:country_code":"TD",
    "gn:dem":417,
    "gn:feature_class":"P",
    "gn:feature_code":"PPL",
    "gn:name":"Dobouroum",
    "gn:population":0,
    "gn:timezone":"Africa/Ndjamena",
    "iso:country":"TD",
    "wof:name":"Dobouroum",
    "wof:placetype":"locality"
},
  "geometry": {"coordinates":[16.36557,8.60568],"type":"Point"}
}