{
  "type": "Feature",
  "properties": {
    "gn:admin1_code":"9.0",
    "gn:asciiname":"Larabaguang",
    "gn:country_code":"TD",
    "gn:dem":548,
    "gn:feature_class":"P",
    "gn:feature_code":"PPL",
    "gn:name":"Larabaguang",
    "gn:population":0,
    "gn:timezone":"Africa/Ndjamena",
    "iso:country":"TD",
    "name:und_x_variant":[
        "Lara Bagana",
        "Larabaguang"
    ],
    "wof:name":"Larabaguang",
    "wof:placetype":"locality"
},
  "geometry": {"coordinates":[15.548,7.8818],"type":"Point"}
}