{
  "type": "Feature",
  "properties": {
    "gn:admin1_code":"12.0",
    "gn:asciiname":"Kipdelfi",
    "gn:country_code":"TD",
    "gn:dem":596,
    "gn:feature_class":"P",
    "gn:feature_code":"PPL",
    "gn:name":"Kipdelfi",
    "gn:population":0,
    "gn:timezone":"Africa/Ndjamena",
    "iso:country":"TD",
    "wof:name":"Kipdelfi",
    "wof:placetype":"locality"
},
  "geometry": {"coordinates":[21.38039,13.15163],"type":"Point"}
}