{
  "type": "Feature",
  "properties": {
    "gn:admin1_code":"13.0",
    "gn:asciiname":"Dioran",
    "gn:country_code":"TD",
    "gn:dem":432,
    "gn:feature_class":"P",
    "gn:feature_code":"PPL",
    "gn:name":"Dioran",
    "gn:population":0,
    "gn:timezone":"Africa/Ndjamena",
    "iso:country":"TD",
    "wof:name":"Dioran",
    "wof:placetype":"locality"
},
  "geometry": {"coordinates":[19.8478,11.5921],"type":"Point"}
}