{
  "type": "Feature",
  "properties": {
    "gn:admin1_code":"8.0",
    "gn:asciiname":"Bani",
    "gn:country_code":"TD",
    "gn:dem":416,
    "gn:feature_class":"P",
    "gn:feature_code":"PPL",
    "gn:name":"Bani",
    "gn:population":0,
    "gn:timezone":"Africa/Ndjamena",
    "iso:country":"TD",
    "name:ben_x_preferred":[
        "\u09ac\u09be\u09a8\u09bf"
    ],
    "name:cat_x_preferred":[
        "Bani"
    ],
    "name:ceb_x_preferred":[
        "Bani"
    ],
    "name:ces_x_preferred":[
        "Bani"
    ],
    "name:deu_x_preferred":[
        "Bani"
    ],
    "name:ell_x_preferred":[
        "\u039c\u03c0\u03ac\u03bd\u03b9"
    ],
    "name:fas_x_preferred":[
        "\u0628\u0627\u0646\u06cc"
    ],
    "name:fra_x_preferred":[
        "Bani"
    ],
    "name:heb_x_preferred":[
        "\u05d1\u05d0\u05e0\u05d9"
    ],
    "name:hin_x_preferred":[
        "\u092c\u0928\u093f"
    ],
    "name:hun_x_preferred":[
        "Bani"
    ],
    "name:ind_x_preferred":[
        "Bani"
    ],
    "name:ita_x_preferred":[
        "Bani"
    ],
    "name:kat_x_preferred":[
        "\u10d1\u10d0\u10dc\u10d8"
    ],
    "name:nld_x_preferred":[
        "Bani"
    ],
    "name:por_x_preferred":[
        "Bani"
    ],
    "name:rus_x_preferred":[
        "\u0411\u0430\u043d\u0438"
    ],
    "name:spa_x_preferred":[
        "Bani"
    ],
    "name:swe_x_preferred":[
        "Bani"
    ],
    "name:tur_x_preferred":[
        "Bani"
    ],
    "name:urd_x_preferred":[
        "\u0628\u0627\u0646\u06cc"
    ],
    "name:vie_x_preferred":[
        "S\u00f4ng Bani"
    ],
    "name:war_x_preferred":[
        "Bani"
    ],
    "wof:name":"Bani",
    "wof:placetype":"locality"
},
  "geometry": {"coordinates":[15.78473,8.72745],"type":"Point"}
}