{
  "type": "Feature",
  "properties": {
    "gn:admin1_code":"13.0",
    "gn:asciiname":"Goz Togoula II",
    "gn:country_code":"TD",
    "gn:dem":416,
    "gn:feature_class":"P",
    "gn:feature_code":"PPL",
    "gn:name":"Goz Togoula II",
    "gn:population":0,
    "gn:timezone":"Africa/Ndjamena",
    "iso:country":"TD",
    "name:fra_x_preferred":[
        "Goz Togoula"
    ],
    "name:fra_x_variant":[
        "Goz Togoula II"
    ],
    "wof:name":"Goz Togoula II",
    "wof:placetype":"locality"
},
  "geometry": {"coordinates":[20.67408,9.93799],"type":"Point"}
}