{
  "type": "Feature",
  "properties": {
    "gn:admin1_code":"18.0",
    "gn:asciiname":"Omo",
    "gn:country_code":"TD",
    "gn:dem":307,
    "gn:feature_class":"P",
    "gn:feature_code":"PPL",
    "gn:name":"Omo",
    "gn:population":0,
    "gn:timezone":"Africa/Ndjamena",
    "iso:country":"TD",
    "name:ben_x_preferred":[
        "\u0993\u09ae\u09cb"
    ],
    "name:ceb_x_preferred":[
        "Omo"
    ],
    "name:deu_x_preferred":[
        "Omo"
    ],
    "name:nld_x_preferred":[
        "Omo"
    ],
    "name:pol_x_preferred":[
        "Omo"
    ],
    "name:por_x_preferred":[
        "Omo"
    ],
    "name:spa_x_preferred":[
        "Omo"
    ],
    "name:swe_x_preferred":[
        "Omo"
    ],
    "name:urd_x_preferred":[
        "\u0627\u0648\u0645\u0648"
    ],
    "wof:name":"Omo",
    "wof:placetype":"locality"
},
  "geometry": {"coordinates":[16.81903,12.20468],"type":"Point"}
}