{
  "type": "Feature",
  "properties": {
    "gn:admin1_code":"1.0",
    "gn:asciiname":"Kazam",
    "gn:country_code":"TD",
    "gn:dem":369,
    "gn:feature_class":"P",
    "gn:feature_code":"PPL",
    "gn:name":"Kazam",
    "gn:population":0,
    "gn:timezone":"Africa/Ndjamena",
    "iso:country":"TD",
    "name:azb_x_preferred":[
        "\u06a9\u0627\u0632\u0645"
    ],
    "name:fas_x_preferred":[
        "\u06a9\u0627\u0632\u0645"
    ],
    "wof:name":"Kazam",
    "wof:placetype":"locality"
},
  "geometry": {"coordinates":[19.4615,13.9895],"type":"Point"}
}