{
  "type": "Feature",
  "properties": {
    "gn:admin1_code":"17.0",
    "gn:asciiname":"Maikouma",
    "gn:country_code":"TD",
    "gn:dem":379,
    "gn:feature_class":"P",
    "gn:feature_code":"PPL",
    "gn:name":"Ma\u00efkouma",
    "gn:population":0,
    "gn:timezone":"Africa/Ndjamena",
    "iso:country":"TD",
    "wof:name":"Maikouma",
    "wof:placetype":"locality"
},
  "geometry": {"coordinates":[18.7521,8.7895],"type":"Point"}
}