{
  "type": "Feature",
  "properties": {
    "gn:admin1_code":"2.0",
    "gn:asciiname":"Aydougoun",
    "gn:country_code":"TD",
    "gn:dem":823,
    "gn:feature_class":"P",
    "gn:feature_code":"PPL",
    "gn:name":"Aydougoun",
    "gn:population":0,
    "gn:timezone":"Africa/Ndjamena",
    "iso:country":"TD",
    "name:fra_x_preferred":[
        "Aydougoun"
    ],
    "wof:name":"Aydougoun",
    "wof:placetype":"locality"
},
  "geometry": {"coordinates":[21.47199,14.21121],"type":"Point"}
}