{
  "type": "Feature",
  "properties": {
    "gn:admin1_code":"19.0",
    "gn:asciiname":"Kotongoro",
    "gn:country_code":"TD",
    "gn:dem":401,
    "gn:feature_class":"P",
    "gn:feature_code":"PPL",
    "gn:name":"Kotongoro",
    "gn:population":0,
    "gn:timezone":"Africa/Ndjamena",
    "iso:country":"TD",
    "wof:name":"Kotongoro",
    "wof:placetype":"locality"
},
  "geometry": {"coordinates":[17.26262,8.4363],"type":"Point"}
}