{
  "type": "Feature",
  "properties": {
    "gn:admin1_code":"26.0",
    "gn:asciiname":"Zoui",
    "gn:country_code":"TD",
    "gn:dem":1046,
    "gn:feature_class":"P",
    "gn:feature_code":"PPL",
    "gn:name":"Zou\u00ef",
    "gn:population":0,
    "gn:timezone":"Africa/Ndjamena",
    "iso:country":"TD",
    "wof:name":"Zoui",
    "wof:placetype":"locality"
},
  "geometry": {"coordinates":[17.06667,21.33333],"type":"Point"}
}