{
  "type": "Feature",
  "properties": {
    "gn:admin1_code":"12.0",
    "gn:asciiname":"Mangarna",
    "gn:country_code":"TD",
    "gn:dem":532,
    "gn:feature_class":"P",
    "gn:feature_code":"PPL",
    "gn:name":"Mangarna",
    "gn:population":0,
    "gn:timezone":"Africa/Ndjamena",
    "iso:country":"TD",
    "name:fra_x_preferred":[
        "Mangarna"
    ],
    "wof:name":"Mangarna",
    "wof:placetype":"locality"
},
  "geometry": {"coordinates":[20.62698,13.19796],"type":"Point"}
}