{
  "type": "Feature",
  "properties": {
    "gn:admin1_code":"7.0",
    "gn:asciiname":"Kalerom",
    "gn:country_code":"TD",
    "gn:dem":297,
    "gn:feature_class":"P",
    "gn:feature_code":"PPL",
    "gn:name":"Kal\u00e9rom",
    "gn:population":0,
    "gn:timezone":"Africa/Ndjamena",
    "iso:country":"TD",
    "wof:name":"Kalerom",
    "wof:placetype":"locality"
},
  "geometry": {"coordinates":[15.39918,13.62565],"type":"Point"}
}