{
  "type": "Feature",
  "properties": {
    "gn:admin1_code":"25.0",
    "gn:asciiname":"Tamos",
    "gn:country_code":"TD",
    "gn:dem":633,
    "gn:feature_class":"P",
    "gn:feature_code":"PPL",
    "gn:name":"Tamos",
    "gn:population":0,
    "gn:timezone":"Africa/Ndjamena",
    "iso:country":"TD",
    "wof:name":"Tamos",
    "wof:placetype":"locality"
},
  "geometry": {"coordinates":[22.03333,12.31667],"type":"Point"}
}