{
  "type": "Feature",
  "properties": {
    "gn:admin1_code":"18.0",
    "gn:asciiname":"Am Kouakib",
    "gn:country_code":"TD",
    "gn:dem":294,
    "gn:feature_class":"P",
    "gn:feature_code":"PPL",
    "gn:name":"Am Kouakib",
    "gn:population":0,
    "gn:timezone":"Africa/Ndjamena",
    "iso:country":"TD",
    "name:und_x_variant":[
        "Am Koabib",
        "Ab Koabib",
        "Am Kouakib"
    ],
    "wof:name":"Am Kouakib",
    "wof:placetype":"locality"
},
  "geometry": {"coordinates":[16.60862,12.95557],"type":"Point"}
}