{
  "type": "Feature",
  "properties": {
    "gn:admin1_code":"7.0",
    "gn:asciiname":"Lande",
    "gn:country_code":"TD",
    "gn:dem":300,
    "gn:feature_class":"P",
    "gn:feature_code":"PPL",
    "gn:name":"Land\u00e9",
    "gn:population":0,
    "gn:timezone":"Africa/Ndjamena",
    "iso:country":"TD",
    "name:bre_x_preferred":[
        "Lande"
    ],
    "name:deu_x_preferred":[
        "Lande"
    ],
    "name:nor_x_preferred":[
        "Lande"
    ],
    "name:rus_x_preferred":[
        "\u041b\u0430\u043d\u0434\u0435"
    ],
    "name:ukr_x_preferred":[
        "\u041b\u0430\u043d\u0434\u0435"
    ],
    "wof:name":"Lande",
    "wof:placetype":"locality"
},
  "geometry": {"coordinates":[15.2559,13.56281],"type":"Point"}
}