{
  "type": "Feature",
  "properties": {
    "gn:admin1_code":"20.0",
    "gn:asciiname":"Guelo",
    "gn:country_code":"TD",
    "gn:dem":324,
    "gn:feature_class":"P",
    "gn:feature_code":"PPL",
    "gn:name":"Gu\u00e9lo",
    "gn:population":0,
    "gn:timezone":"Africa/Ndjamena",
    "iso:country":"TD",
    "name:und_x_variant":[
        "G\u00e9lo",
        "Gu\u00e9lo"
    ],
    "wof:name":"Guelo",
    "wof:placetype":"locality"
},
  "geometry": {"coordinates":[14.2753,9.5431],"type":"Point"}
}