{
  "type": "Feature",
  "properties": {
    "gn:admin1_code":"8.0",
    "gn:asciiname":"Bonguigni",
    "gn:country_code":"TD",
    "gn:dem":470,
    "gn:feature_class":"P",
    "gn:feature_code":"PPL",
    "gn:name":"Bonguigni",
    "gn:population":0,
    "gn:timezone":"Africa/Ndjamena",
    "iso:country":"TD",
    "wof:name":"Bonguigni",
    "wof:placetype":"locality"
},
  "geometry": {"coordinates":[15.35,8.58333],"type":"Point"}
}