{
  "type": "Feature",
  "properties": {
    "gn:admin1_code":"1.0",
    "gn:asciiname":"Ab Djouet",
    "gn:country_code":"TD",
    "gn:dem":339,
    "gn:feature_class":"P",
    "gn:feature_code":"PPL",
    "gn:name":"Ab Djouet",
    "gn:population":0,
    "gn:timezone":"Africa/Ndjamena",
    "iso:country":"TD",
    "name:und_x_variant":[
        "Abjouet",
        "Ab Djouet"
    ],
    "wof:name":"Ab Djouet",
    "wof:placetype":"locality"
},
  "geometry": {"coordinates":[18.3706,13.2101],"type":"Point"}
}