{
  "type": "Feature",
  "properties": {
    "gn:admin1_code":"5.0",
    "gn:asciiname":"Berouet",
    "gn:country_code":"TD",
    "gn:dem":532,
    "gn:feature_class":"P",
    "gn:feature_code":"PPL",
    "gn:name":"B\u00e9rouet",
    "gn:population":0,
    "gn:timezone":"Africa/Ndjamena",
    "iso:country":"TD",
    "wof:name":"Berouet",
    "wof:placetype":"locality"
},
  "geometry": {"coordinates":[18.6484,11.6666],"type":"Point"}
}