{
  "type": "Feature",
  "properties": {
    "gn:admin1_code":"9.0",
    "gn:asciiname":"Libaya",
    "gn:country_code":"TD",
    "gn:dem":516,
    "gn:feature_class":"P",
    "gn:feature_code":"PPL",
    "gn:name":"Libaya",
    "gn:population":0,
    "gn:timezone":"Africa/Ndjamena",
    "iso:country":"TD",
    "name:amh_x_preferred":[
        "\u120a\u1263\u12eb"
    ],
    "name:ara_x_preferred":[
        "\u0644\u064a\u0628\u0627\u064a\u0627"
    ],
    "name:cat_x_preferred":[
        "Libaia"
    ],
    "name:heb_x_preferred":[
        "\u05dc\u05d9\u05d1\u05d0\u05d9\u05d4"
    ],
    "name:ind_x_preferred":[
        "Libaya"
    ],
    "name:kat_x_preferred":[
        "\u10da\u10d8\u10d1\u10d0\u10d8\u10d0"
    ],
    "name:spa_x_preferred":[
        "Libaia"
    ],
    "name:ukr_x_preferred":[
        "\u041b\u0456\u0431\u0430\u044f"
    ],
    "wof:name":"Libaya",
    "wof:placetype":"locality"
},
  "geometry": {"coordinates":[16.06401,7.75597],"type":"Point"}
}