{
  "type": "Feature",
  "properties": {
    "gn:admin1_code":"15.0",
    "gn:asciiname":"Masera",
    "gn:country_code":"TD",
    "gn:dem":307,
    "gn:feature_class":"P",
    "gn:feature_code":"PPL",
    "gn:name":"Masera",
    "gn:population":0,
    "gn:timezone":"Africa/Ndjamena",
    "iso:country":"TD",
    "name:azb_x_preferred":[
        "\u0645\u0627\u0632\u0631\u0627"
    ],
    "name:bel_x_preferred":[
        "\u041c\u0430\u0437\u0435\u0440\u0430"
    ],
    "name:bul_x_preferred":[
        "\u041c\u0430\u0437\u0435\u0440\u0430"
    ],
    "name:ceb_x_preferred":[
        "Masera"
    ],
    "name:deu_x_preferred":[
        "Masera"
    ],
    "name:epo_x_preferred":[
        "Masera"
    ],
    "name:eus_x_preferred":[
        "Masera"
    ],
    "name:fas_x_preferred":[
        "\u0645\u0627\u0632\u0631\u0627"
    ],
    "name:fin_x_preferred":[
        "Masera"
    ],
    "name:fra_x_preferred":[
        "Masera"
    ],
    "name:hun_x_preferred":[
        "Masera"
    ],
    "name:hye_x_preferred":[
        "\u0544\u0561\u0566\u0565\u0580\u0561"
    ],
    "name:ita_x_preferred":[
        "Masera"
    ],
    "name:jpn_x_preferred":[
        "\u30de\u30bc\u30fc\u30e9"
    ],
    "name:kaz_x_preferred":[
        "\u041c\u0430\u0437\u0435\u0440\u0430"
    ],
    "name:lat_x_preferred":[
        "Maceria"
    ],
    "name:lmo_x_preferred":[
        "Mascira"
    ],
    "name:msa_x_preferred":[
        "Masera"
    ],
    "name:nap_x_preferred":[
        "Masera"
    ],
    "name:nld_x_preferred":[
        "Masera"
    ],
    "name:pms_x_preferred":[
        "Masera"
    ],
    "name:pol_x_preferred":[
        "Masera"
    ],
    "name:por_x_preferred":[
        "Masera"
    ],
    "name:ron_x_preferred":[
        "Masera"
    ],
    "name:rus_x_preferred":[
        "\u041c\u0430\u0437\u0435\u0440\u0430"
    ],
    "name:scn_x_preferred":[
        "Masera"
    ],
    "name:spa_x_preferred":[
        "Masera"
    ],
    "name:srp_x_preferred":[
        "\u041c\u0430\u0437\u0435\u0440\u0430"
    ],
    "name:tgl_x_preferred":[
        "Masera"
    ],
    "name:tur_x_preferred":[
        "Masera"
    ],
    "name:ukr_x_preferred":[
        "\u041c\u0430\u0437\u0435\u0440\u0430"
    ],
    "name:uzb_x_preferred":[
        "Masera"
    ],
    "name:vie_x_preferred":[
        "Masera"
    ],
    "name:vol_x_preferred":[
        "Masera"
    ],
    "name:war_x_preferred":[
        "Masera"
    ],
    "name:zho_x_preferred":[
        "\u9a6c\u585e\u62c9"
    ],
    "wof:name":"Masera",
    "wof:placetype":"locality"
},
  "geometry": {"coordinates":[15.25588,11.22279],"type":"Point"}
}