{
  "type": "Feature",
  "properties": {
    "gn:admin1_code":"15.0",
    "gn:asciiname":"Masera",
    "gn:country_code":"TD",
    "gn:dem":307,
    "gn:feature_class":"P",
    "gn:feature_code":"PPL",
    "gn:name":"Masera",
    "gn:population":0,
    "gn:timezone":"Africa/Ndjamena",
    "iso:country":"TD",
    "wof:name":"Masera",
    "wof:placetype":"locality"
},
  "geometry": {"coordinates":[15.25588,11.22279],"type":"Point"}
}