{
  "type": "Feature",
  "properties": {
    "gn:admin1_code":"14.0",
    "gn:asciiname":"Elle",
    "gn:country_code":"TD",
    "gn:dem":354,
    "gn:feature_class":"P",
    "gn:feature_code":"PPL",
    "gn:name":"Ell\u00e9",
    "gn:population":0,
    "gn:timezone":"Africa/Ndjamena",
    "iso:country":"TD",
    "name:ceb_x_preferred":[
        "Elle"
    ],
    "name:dan_x_preferred":[
        "Elle"
    ],
    "name:deu_x_preferred":[
        "Elle"
    ],
    "name:fra_x_preferred":[
        "Elle"
    ],
    "name:ita_x_preferred":[
        "Elle"
    ],
    "name:nld_x_preferred":[
        "Elle"
    ],
    "name:nor_x_preferred":[
        "Elle"
    ],
    "name:pol_x_preferred":[
        "Elle"
    ],
    "name:rus_x_preferred":[
        "\u042d\u043b\u043b\u044c"
    ],
    "name:swe_x_preferred":[
        "Elle"
    ],
    "name:tur_x_preferred":[
        "Elle"
    ],
    "wof:name":"Elle",
    "wof:placetype":"locality"
},
  "geometry": {"coordinates":[15.76667,9.55],"type":"Point"}
}