{
  "type": "Feature",
  "properties": {
    "gn:admin1_code":"5.0",
    "gn:asciiname":"Pani Dabera",
    "gn:country_code":"TD",
    "gn:dem":466,
    "gn:feature_class":"P",
    "gn:feature_code":"PPL",
    "gn:name":"Pani Dab\u00e9ra",
    "gn:population":0,
    "gn:timezone":"Africa/Ndjamena",
    "iso:country":"TD",
    "name:und_x_variant":[
        "Pami Dab\u00e9ra",
        "Pani Dab\u00e9ra"
    ],
    "wof:name":"Pani Dabera",
    "wof:placetype":"locality"
},
  "geometry": {"coordinates":[18.5282,11.9669],"type":"Point"}
}