{
  "type": "Feature",
  "properties": {
    "gn:admin1_code":"1.0",
    "gn:asciiname":"Bota",
    "gn:country_code":"TD",
    "gn:dem":300,
    "gn:feature_class":"P",
    "gn:feature_code":"PPL",
    "gn:name":"Bota",
    "gn:population":0,
    "gn:timezone":"Africa/Ndjamena",
    "iso:country":"TD",
    "wof:name":"Bota",
    "wof:placetype":"locality"
},
  "geometry": {"coordinates":[17.76801,12.7428],"type":"Point"}
}