{
  "type": "Feature",
  "properties": {
    "gn:admin1_code":"9.0",
    "gn:asciiname":"Doromane",
    "gn:country_code":"TD",
    "gn:dem":385,
    "gn:feature_class":"P",
    "gn:feature_code":"PPL",
    "gn:name":"Doroman\u00e9",
    "gn:population":0,
    "gn:timezone":"Africa/Ndjamena",
    "iso:country":"TD",
    "wof:name":"Doromane",
    "wof:placetype":"locality"
},
  "geometry": {"coordinates":[16.76289,8.88584],"type":"Point"}
}