{
  "type": "Feature",
  "properties": {
    "gn:admin1_code":"15.0",
    "gn:asciiname":"Arsi Dabono",
    "gn:country_code":"TD",
    "gn:dem":308,
    "gn:feature_class":"P",
    "gn:feature_code":"PPL",
    "gn:name":"Arsi Dabono",
    "gn:population":0,
    "gn:timezone":"Africa/Ndjamena",
    "iso:country":"TD",
    "wof:name":"Arsi Dabono",
    "wof:placetype":"locality"
},
  "geometry": {"coordinates":[15.3611,11.44759],"type":"Point"}
}