{
  "type": "Feature",
  "properties": {
    "gn:admin1_code":"20.0",
    "gn:asciiname":"Baida Djerassim",
    "gn:country_code":"TD",
    "gn:dem":386,
    "gn:feature_class":"P",
    "gn:feature_code":"PPL",
    "gn:name":"Ba\u00efda Dj\u00e9rassim",
    "gn:population":0,
    "gn:timezone":"Africa/Ndjamena",
    "iso:country":"TD",
    "name:und_x_variant":[
        "Ba\u00efda Djerasim",
        "Ba\u00efda Dj\u00e9rassim"
    ],
    "wof:name":"Baida Djerassim",
    "wof:placetype":"locality"
},
  "geometry": {"coordinates":[14.9033,9.1367],"type":"Point"}
}