{
  "type": "Feature",
  "properties": {
    "gn:admin1_code":"14.0",
    "gn:asciiname":"Aparia",
    "gn:country_code":"TD",
    "gn:dem":360,
    "gn:feature_class":"P",
    "gn:feature_code":"PPL",
    "gn:name":"Aparia",
    "gn:population":0,
    "gn:timezone":"Africa/Ndjamena",
    "iso:country":"TD",
    "wof:name":"Aparia",
    "wof:placetype":"locality"
},
  "geometry": {"coordinates":[16.0189,9.3764],"type":"Point"}
}