{
  "type": "Feature",
  "properties": {
    "gn:admin1_code":"8.0",
    "gn:asciiname":"Guelkeb",
    "gn:country_code":"TD",
    "gn:dem":399,
    "gn:feature_class":"P",
    "gn:feature_code":"PPL",
    "gn:name":"Guelkeb",
    "gn:population":0,
    "gn:timezone":"Africa/Ndjamena",
    "iso:country":"TD",
    "wof:name":"Guelkeb",
    "wof:placetype":"locality"
},
  "geometry": {"coordinates":[16.0483,9.0765],"type":"Point"}
}