{
  "type": "Feature",
  "properties": {
    "gn:admin1_code":"1.0",
    "gn:asciiname":"Cherim",
    "gn:country_code":"TD",
    "gn:dem":381,
    "gn:feature_class":"P",
    "gn:feature_code":"PPL",
    "gn:name":"Ch\u00e9rim",
    "gn:population":0,
    "gn:timezone":"Africa/Ndjamena",
    "iso:country":"TD",
    "name:und_x_variant":[
        "Ch\u00e9erim",
        "Ch\u00e9rim"
    ],
    "wof:name":"Cherim",
    "wof:placetype":"locality"
},
  "geometry": {"coordinates":[19.5369,13.1226],"type":"Point"}
}