{
  "type": "Feature",
  "properties": {
    "gn:admin1_code":"15.0",
    "gn:asciiname":"Bage",
    "gn:country_code":"TD",
    "gn:dem":301,
    "gn:feature_class":"P",
    "gn:feature_code":"PPL",
    "gn:name":"Bage",
    "gn:population":0,
    "gn:timezone":"Africa/Ndjamena",
    "iso:country":"TD",
    "name:ceb_x_preferred":[
        "Bage"
    ],
    "name:nld_x_preferred":[
        "Bage"
    ],
    "name:swe_x_preferred":[
        "Bage"
    ],
    "wof:name":"Bage",
    "wof:placetype":"locality"
},
  "geometry": {"coordinates":[15.2089,11.7256],"type":"Point"}
}