{
  "type": "Feature",
  "properties": {
    "gn:admin1_code":"2.0",
    "gn:asciiname":"Kourdi",
    "gn:country_code":"TD",
    "gn:dem":849,
    "gn:feature_class":"P",
    "gn:feature_code":"PPL",
    "gn:name":"Kourdi",
    "gn:population":0,
    "gn:timezone":"Africa/Ndjamena",
    "iso:country":"TD",
    "wof:name":"Kourdi",
    "wof:placetype":"locality"
},
  "geometry": {"coordinates":[22.73333,15.76667],"type":"Point"}
}