{
  "type": "Feature",
  "properties": {
    "gn:admin1_code":"14.0",
    "gn:asciiname":"Delbian",
    "gn:country_code":"TD",
    "gn:dem":376,
    "gn:feature_class":"P",
    "gn:feature_code":"PPL",
    "gn:name":"Delbian",
    "gn:population":0,
    "gn:timezone":"Africa/Ndjamena",
    "iso:country":"TD",
    "name:ita_x_preferred":[
        "Delbian"
    ],
    "name:und_x_variant":[
        "Delbien",
        "Delbiane",
        "Delbian"
    ],
    "wof:name":"Delbian",
    "wof:placetype":"locality"
},
  "geometry": {"coordinates":[16.1941,9.1904],"type":"Point"}
}