{
  "type": "Feature",
  "properties": {
    "gn:admin1_code":"1.0",
    "gn:asciiname":"Baouda",
    "gn:country_code":"TD",
    "gn:dem":309,
    "gn:feature_class":"P",
    "gn:feature_code":"PPL",
    "gn:name":"Baouda",
    "gn:population":0,
    "gn:timezone":"Africa/Ndjamena",
    "iso:country":"TD",
    "wof:name":"Baouda",
    "wof:placetype":"locality"
},
  "geometry": {"coordinates":[17.92543,12.85368],"type":"Point"}
}