{
  "type": "Feature",
  "properties": {
    "gn:admin1_code":"19.0",
    "gn:asciiname":"Kademari",
    "gn:country_code":"TD",
    "gn:dem":399,
    "gn:feature_class":"P",
    "gn:feature_code":"PPL",
    "gn:name":"Kademari",
    "gn:population":0,
    "gn:timezone":"Africa/Ndjamena",
    "iso:country":"TD",
    "wof:name":"Kademari",
    "wof:placetype":"locality"
},
  "geometry": {"coordinates":[17.48443,9.12423],"type":"Point"}
}