{
  "type": "Feature",
  "properties": {
    "gn:admin1_code":"18.0",
    "gn:asciiname":"Moutenak",
    "gn:country_code":"TD",
    "gn:dem":292,
    "gn:feature_class":"P",
    "gn:feature_code":"PPL",
    "gn:name":"Moutenak",
    "gn:population":0,
    "gn:timezone":"Africa/Ndjamena",
    "iso:country":"TD",
    "wof:name":"Moutenak",
    "wof:placetype":"locality"
},
  "geometry": {"coordinates":[15.01924,12.4241],"type":"Point"}
}