{
  "type": "Feature",
  "properties": {
    "gn:admin1_code":"7.0",
    "gn:asciiname":"Ngefia",
    "gn:country_code":"TD",
    "gn:dem":285,
    "gn:feature_class":"P",
    "gn:feature_code":"PPL",
    "gn:name":"Ngefia",
    "gn:population":0,
    "gn:timezone":"Africa/Ndjamena",
    "iso:country":"TD",
    "wof:name":"Ngefia",
    "wof:placetype":"locality"
},
  "geometry": {"coordinates":[15.0915,13.47165],"type":"Point"}
}