{
  "type": "Feature",
  "properties": {
    "gn:admin1_code":"14.0",
    "gn:asciiname":"Monogoy Djiou",
    "gn:country_code":"TD",
    "gn:dem":381,
    "gn:feature_class":"P",
    "gn:feature_code":"PPL",
    "gn:name":"Monogoy Djiou",
    "gn:population":0,
    "gn:timezone":"Africa/Ndjamena",
    "iso:country":"TD",
    "name:und_x_variant":[
        "Monogoye Djiou",
        "Monogoy Djiou"
    ],
    "wof:name":"Monogoy Djiou",
    "wof:placetype":"locality"
},
  "geometry": {"coordinates":[15.66845,9.36367],"type":"Point"}
}