{
  "type": "Feature",
  "properties": {
    "gn:admin1_code":"25.0",
    "gn:asciiname":"Djangoul",
    "gn:country_code":"TD",
    "gn:dem":439,
    "gn:feature_class":"P",
    "gn:feature_code":"PPL",
    "gn:name":"Djangoul",
    "gn:population":0,
    "gn:timezone":"Africa/Ndjamena",
    "iso:country":"TD",
    "wof:name":"Djangoul",
    "wof:placetype":"locality"
},
  "geometry": {"coordinates":[20.21667,12.85],"type":"Point"}
}