{
  "type": "Feature",
  "properties": {
    "gn:admin1_code":"25.0",
    "gn:asciiname":"Djabel",
    "gn:country_code":"TD",
    "gn:dem":577,
    "gn:feature_class":"P",
    "gn:feature_code":"PPL",
    "gn:name":"Djabel",
    "gn:population":0,
    "gn:timezone":"Africa/Ndjamena",
    "iso:country":"TD",
    "wof:name":"Djabel",
    "wof:placetype":"locality"
},
  "geometry": {"coordinates":[21.38333,12.23333],"type":"Point"}
}