{
  "type": "Feature",
  "properties": {
    "gn:admin1_code":"9.0",
    "gn:asciiname":"Dokou",
    "gn:country_code":"TD",
    "gn:dem":417,
    "gn:feature_class":"P",
    "gn:feature_code":"PPL",
    "gn:name":"Dokou",
    "gn:population":0,
    "gn:timezone":"Africa/Ndjamena",
    "iso:country":"TD",
    "wof:name":"Dokou",
    "wof:placetype":"locality"
},
  "geometry": {"coordinates":[16.96761,8.11293],"type":"Point"}
}