{
  "type": "Feature",
  "properties": {
    "gn:admin1_code":"12.0",
    "gn:asciiname":"Korodom",
    "gn:country_code":"TD",
    "gn:dem":797,
    "gn:feature_class":"P",
    "gn:feature_code":"PPL",
    "gn:name":"Korodom",
    "gn:population":0,
    "gn:timezone":"Africa/Ndjamena",
    "iso:country":"TD",
    "wof:name":"Korodom",
    "wof:placetype":"locality"
},
  "geometry": {"coordinates":[21.7152,13.91301],"type":"Point"}
}