{
  "type": "Feature",
  "properties": {
    "gn:admin1_code":"7.0",
    "gn:asciiname":"Keliganga",
    "gn:country_code":"TD",
    "gn:dem":296,
    "gn:feature_class":"P",
    "gn:feature_code":"PPL",
    "gn:name":"K\u00e9liganga",
    "gn:population":0,
    "gn:timezone":"Africa/Ndjamena",
    "iso:country":"TD",
    "wof:name":"Keliganga",
    "wof:placetype":"locality"
},
  "geometry": {"coordinates":[15.78505,13.28797],"type":"Point"}
}