{
  "type": "Feature",
  "properties": {
    "gn:admin1_code":"18.0",
    "gn:asciiname":"Oumar",
    "gn:country_code":"TD",
    "gn:dem":295,
    "gn:feature_class":"P",
    "gn:feature_code":"PPL",
    "gn:name":"Oumar",
    "gn:population":0,
    "gn:timezone":"Africa/Ndjamena",
    "iso:country":"TD",
    "wof:name":"Oumar",
    "wof:placetype":"locality"
},
  "geometry": {"coordinates":[15.93301,12.37544],"type":"Point"}
}