{
  "type": "Feature",
  "properties": {
    "gn:admin1_code":"12.0",
    "gn:asciiname":"Makarou",
    "gn:country_code":"TD",
    "gn:dem":739,
    "gn:feature_class":"P",
    "gn:feature_code":"PPL",
    "gn:name":"Makarou",
    "gn:population":0,
    "gn:timezone":"Africa/Ndjamena",
    "iso:country":"TD",
    "wof:name":"Makarou",
    "wof:placetype":"locality"
},
  "geometry": {"coordinates":[21.49405,13.67002],"type":"Point"}
}