{
  "type": "Feature",
  "properties": {
    "gn:admin1_code":"5.0",
    "gn:asciiname":"Kosselili",
    "gn:country_code":"TD",
    "gn:dem":510,
    "gn:feature_class":"P",
    "gn:feature_code":"PPL",
    "gn:name":"Kosselili",
    "gn:population":0,
    "gn:timezone":"Africa/Ndjamena",
    "iso:country":"TD",
    "wof:name":"Kosselili",
    "wof:placetype":"locality"
},
  "geometry": {"coordinates":[18.4552,11.8643],"type":"Point"}
}