{
  "type": "Feature",
  "properties": {
    "gn:admin1_code":"8.0",
    "gn:asciiname":"Bagala",
    "gn:country_code":"TD",
    "gn:dem":444,
    "gn:feature_class":"P",
    "gn:feature_code":"PPL",
    "gn:name":"Bagala",
    "gn:population":0,
    "gn:timezone":"Africa/Ndjamena",
    "iso:country":"TD",
    "wof:name":"Bagala",
    "wof:placetype":"locality"
},
  "geometry": {"coordinates":[15.68872,8.62867],"type":"Point"}
}