{
  "type": "Feature",
  "properties": {
    "gn:admin1_code":"18.0",
    "gn:asciiname":"Ilta el Khanain",
    "gn:country_code":"TD",
    "gn:dem":296,
    "gn:feature_class":"P",
    "gn:feature_code":"PPL",
    "gn:name":"Ilta el Khana\u00efn",
    "gn:population":0,
    "gn:timezone":"Africa/Ndjamena",
    "iso:country":"TD",
    "wof:name":"Ilta el Khanain",
    "wof:placetype":"locality"
},
  "geometry": {"coordinates":[15.48106,12.2633],"type":"Point"}
}