{
  "type": "Feature",
  "properties": {
    "gn:admin1_code":"2.0",
    "gn:asciiname":"Koure",
    "gn:country_code":"TD",
    "gn:dem":857,
    "gn:feature_class":"P",
    "gn:feature_code":"PPL",
    "gn:name":"Kour\u00e9",
    "gn:population":0,
    "gn:timezone":"Africa/Ndjamena",
    "iso:country":"TD",
    "name:ceb_x_preferred":[
        "Kour\u00e9"
    ],
    "name:deu_x_preferred":[
        "Kour\u00e9"
    ],
    "name:fra_x_preferred":[
        "Kour\u00e9"
    ],
    "name:swe_x_preferred":[
        "Kour\u00e9"
    ],
    "wof:name":"Koure",
    "wof:placetype":"locality"
},
  "geometry": {"coordinates":[21.60349,14.29521],"type":"Point"}
}