{
  "type": "Feature",
  "properties": {
    "gn:admin1_code":"1.0",
    "gn:asciiname":"Beptongo",
    "gn:country_code":"TD",
    "gn:dem":296,
    "gn:feature_class":"P",
    "gn:feature_code":"PPL",
    "gn:name":"Beptongo",
    "gn:population":0,
    "gn:timezone":"Africa/Ndjamena",
    "iso:country":"TD",
    "wof:name":"Beptongo",
    "wof:placetype":"locality"
},
  "geometry": {"coordinates":[17.73106,12.8854],"type":"Point"}
}