{
  "type": "Feature",
  "properties": {
    "gn:admin1_code":"15.0",
    "gn:asciiname":"Guerguer",
    "gn:country_code":"TD",
    "gn:dem":297,
    "gn:feature_class":"P",
    "gn:feature_code":"PPL",
    "gn:name":"Guerguer",
    "gn:population":0,
    "gn:timezone":"Africa/Ndjamena",
    "iso:country":"TD",
    "name:und_x_variant":[
        "Gergeir el Goz",
        "Guerguer"
    ],
    "wof:name":"Guerguer",
    "wof:placetype":"locality"
},
  "geometry": {"coordinates":[15.44244,12.19272],"type":"Point"}
}