{
  "type": "Feature",
  "properties": {
    "gn:admin1_code":"12.0",
    "gn:asciiname":"Galgas",
    "gn:country_code":"TD",
    "gn:dem":568,
    "gn:feature_class":"P",
    "gn:feature_code":"PPL",
    "gn:name":"Galgas",
    "gn:population":0,
    "gn:timezone":"Africa/Ndjamena",
    "iso:country":"TD",
    "wof:name":"Galgas",
    "wof:placetype":"locality"
},
  "geometry": {"coordinates":[21.24464,13.27251],"type":"Point"}
}