{
  "type": "Feature",
  "properties": {
    "gn:admin1_code":"17.0",
    "gn:asciiname":"Roukou",
    "gn:country_code":"TD",
    "gn:dem":387,
    "gn:feature_class":"P",
    "gn:feature_code":"PPL",
    "gn:name":"Roukou",
    "gn:population":0,
    "gn:timezone":"Africa/Ndjamena",
    "iso:country":"TD",
    "wof:name":"Roukou",
    "wof:placetype":"locality"
},
  "geometry": {"coordinates":[19.2375,9.663],"type":"Point"}
}