{
  "type": "Feature",
  "properties": {
    "gn:admin1_code":"18.0",
    "gn:asciiname":"Djoumarti",
    "gn:country_code":"TD",
    "gn:dem":286,
    "gn:feature_class":"P",
    "gn:feature_code":"PPL",
    "gn:name":"Djoumarti",
    "gn:population":0,
    "gn:timezone":"Africa/Ndjamena",
    "iso:country":"TD",
    "wof:name":"Djoumarti",
    "wof:placetype":"locality"
},
  "geometry": {"coordinates":[15.70262,13.06818],"type":"Point"}
}