{
  "type": "Feature",
  "properties": {
    "gn:admin1_code":"6.0",
    "gn:asciiname":"Metil",
    "gn:country_code":"TD",
    "gn:dem":337,
    "gn:feature_class":"P",
    "gn:feature_code":"PPL",
    "gn:name":"Metil",
    "gn:population":0,
    "gn:timezone":"Africa/Ndjamena",
    "iso:country":"TD",
    "wof:name":"Metil",
    "wof:placetype":"locality"
},
  "geometry": {"coordinates":[15.16305,14.10162],"type":"Point"}
}