{
  "type": "Feature",
  "properties": {
    "gn:admin1_code":"15.0",
    "gn:asciiname":"Goniori",
    "gn:country_code":"TD",
    "gn:dem":326,
    "gn:feature_class":"P",
    "gn:feature_code":"PPL",
    "gn:name":"Goniori",
    "gn:population":0,
    "gn:timezone":"Africa/Ndjamena",
    "iso:country":"TD",
    "wof:name":"Goniori",
    "wof:placetype":"locality"
},
  "geometry": {"coordinates":[16.1012,10.7827],"type":"Point"}
}