{
  "type": "Feature",
  "properties": {
    "gn:admin1_code":"13.0",
    "gn:asciiname":"Moudjoud",
    "gn:country_code":"TD",
    "gn:dem":479,
    "gn:feature_class":"P",
    "gn:feature_code":"PPL",
    "gn:name":"Moudjoud",
    "gn:population":0,
    "gn:timezone":"Africa/Ndjamena",
    "iso:country":"TD",
    "name:und_x_variant":[
        "Moudjout",
        "Moudjoud"
    ],
    "wof:name":"Moudjoud",
    "wof:placetype":"locality"
},
  "geometry": {"coordinates":[21.0061,11.6161],"type":"Point"}
}