{
  "type": "Feature",
  "properties": {
    "gn:admin1_code":"14.0",
    "gn:asciiname":"Kobo",
    "gn:country_code":"TD",
    "gn:dem":367,
    "gn:feature_class":"P",
    "gn:feature_code":"PPL",
    "gn:name":"Kobo",
    "gn:population":0,
    "gn:timezone":"Africa/Ndjamena",
    "iso:country":"TD",
    "name:ceb_x_preferred":[
        "Kobo"
    ],
    "name:deu_x_preferred":[
        "Kobo"
    ],
    "name:epo_x_preferred":[
        "Kobo"
    ],
    "name:fra_x_preferred":[
        "Kobo"
    ],
    "name:swe_x_preferred":[
        "Kobo"
    ],
    "name:ukr_x_preferred":[
        "\u041a\u043e\u0431\u043e"
    ],
    "wof:name":"Kobo",
    "wof:placetype":"locality"
},
  "geometry": {"coordinates":[16.0555,9.2799],"type":"Point"}
}