{
  "type": "Feature",
  "properties": {
    "gn:admin1_code":"15.0",
    "gn:asciiname":"Hollom",
    "gn:country_code":"TD",
    "gn:dem":310,
    "gn:feature_class":"P",
    "gn:feature_code":"PPL",
    "gn:name":"Hollom",
    "gn:population":0,
    "gn:timezone":"Africa/Ndjamena",
    "iso:country":"TD",
    "name:und_x_variant":[
        "Kholem",
        "Holom",
        "Cholem",
        "Valloum",
        "Hollom"
    ],
    "wof:name":"Hollom",
    "wof:placetype":"locality"
},
  "geometry": {"coordinates":[15.06667,11.33769],"type":"Point"}
}