{
  "type": "Feature",
  "properties": {
    "gn:admin1_code":"16.0",
    "gn:asciiname":"Dole",
    "gn:country_code":"TD",
    "gn:dem":329,
    "gn:feature_class":"P",
    "gn:feature_code":"PPL",
    "gn:name":"Dol\u00e9",
    "gn:population":0,
    "gn:timezone":"Africa/Ndjamena",
    "iso:country":"TD",
    "name:als_x_preferred":[
        "Dole"
    ],
    "name:bos_x_preferred":[
        "Dole"
    ],
    "name:cat_x_preferred":[
        "Dole"
    ],
    "name:ceb_x_preferred":[
        "Dole"
    ],
    "name:deu_x_preferred":[
        "Dole"
    ],
    "name:fra_x_preferred":[
        "Dole"
    ],
    "name:heb_x_preferred":[
        "\u05d3\u05d5\u05dc"
    ],
    "name:hrv_x_preferred":[
        "Dole"
    ],
    "name:hun_x_preferred":[
        "Dole"
    ],
    "name:ita_x_preferred":[
        "Dole"
    ],
    "name:jpn_x_preferred":[
        "\u30c9\u30fc\u30eb"
    ],
    "name:kor_x_preferred":[
        "\ub3cc"
    ],
    "name:lav_x_preferred":[
        "Dole"
    ],
    "name:nds_x_preferred":[
        "Dole"
    ],
    "name:nld_x_preferred":[
        "Dole"
    ],
    "name:nno_x_preferred":[
        "Dole"
    ],
    "name:nor_x_preferred":[
        "Dole"
    ],
    "name:por_x_preferred":[
        "Dole"
    ],
    "name:ron_x_preferred":[
        "Dole"
    ],
    "name:rus_x_preferred":[
        "\u0414\u043e\u043b\u044c"
    ],
    "name:sco_x_preferred":[
        "Dole"
    ],
    "name:slk_x_preferred":[
        "Dole"
    ],
    "name:slv_x_preferred":[
        "Dole"
    ],
    "name:spa_x_preferred":[
        "Dole"
    ],
    "name:swe_x_preferred":[
        "Dole"
    ],
    "name:und_x_variant":[
        "Dore",
        "Dol\u00e9"
    ],
    "wof:name":"Dole",
    "wof:placetype":"locality"
},
  "geometry": {"coordinates":[15.0713,9.8723],"type":"Point"}
}