{
  "type": "Feature",
  "properties": {
    "gn:admin1_code":"16.0",
    "gn:asciiname":"Dole",
    "gn:country_code":"TD",
    "gn:dem":329,
    "gn:feature_class":"P",
    "gn:feature_code":"PPL",
    "gn:name":"Dol\u00e9",
    "gn:population":0,
    "gn:timezone":"Africa/Ndjamena",
    "iso:country":"TD",
    "name:und_x_variant":[
        "Dore",
        "Dol\u00e9"
    ],
    "wof:name":"Dole",
    "wof:placetype":"locality"
},
  "geometry": {"coordinates":[15.0713,9.8723],"type":"Point"}
}