{
  "type": "Feature",
  "properties": {
    "gn:admin1_code":"15.0",
    "gn:asciiname":"Gredaya",
    "gn:country_code":"TD",
    "gn:dem":295,
    "gn:feature_class":"P",
    "gn:feature_code":"PPL",
    "gn:name":"Gr\u00e9daya",
    "gn:population":0,
    "gn:timezone":"Africa/Ndjamena",
    "iso:country":"TD",
    "wof:name":"Gredaya",
    "wof:placetype":"locality"
},
  "geometry": {"coordinates":[15.37613,12.30184],"type":"Point"}
}