{
  "type": "Feature",
  "properties": {
    "gn:admin1_code":"18.0",
    "gn:asciiname":"Kairi",
    "gn:country_code":"TD",
    "gn:dem":289,
    "gn:feature_class":"P",
    "gn:feature_code":"PPL",
    "gn:name":"Ka\u00efri",
    "gn:population":0,
    "gn:timezone":"Africa/Ndjamena",
    "iso:country":"TD",
    "name:ceb_x_preferred":[
        "Kairi"
    ],
    "name:deu_x_preferred":[
        "Kairi"
    ],
    "name:ita_x_preferred":[
        "Kairi"
    ],
    "name:kor_x_preferred":[
        "\uce74\uc774\ub9ac"
    ],
    "wof:name":"Kairi",
    "wof:placetype":"locality"
},
  "geometry": {"coordinates":[15.42158,12.87173],"type":"Point"}
}