{
  "type": "Feature",
  "properties": {
    "gn:admin1_code":"18.0",
    "gn:asciiname":"Kelekele Maloumari",
    "gn:country_code":"TD",
    "gn:dem":298,
    "gn:feature_class":"P",
    "gn:feature_code":"PPL",
    "gn:name":"K\u00e9l\u00e9k\u00e9l\u00e9 Maloumari",
    "gn:population":0,
    "gn:timezone":"Africa/Ndjamena",
    "iso:country":"TD",
    "wof:name":"Kelekele Maloumari",
    "wof:placetype":"locality"
},
  "geometry": {"coordinates":[15.61667,13.2002],"type":"Point"}
}