{
  "type": "Feature",
  "properties": {
    "gn:admin1_code":"5.0",
    "gn:asciiname":"Delep",
    "gn:country_code":"TD",
    "gn:dem":361,
    "gn:feature_class":"P",
    "gn:feature_code":"PPL",
    "gn:name":"D\u00e9l\u00e9p",
    "gn:population":0,
    "gn:timezone":"Africa/Ndjamena",
    "iso:country":"TD",
    "name:und_x_variant":[
        "Am Deleb",
        "D\u00e9l\u00e9b\u00e9",
        "D\u00e9l\u00e9p",
        "Delep"
    ],
    "wof:name":"Delep",
    "wof:placetype":"locality"
},
  "geometry": {"coordinates":[18.63749,12.67554],"type":"Point"}
}