{
  "type": "Feature",
  "properties": {
    "gn:admin1_code":"8.0",
    "gn:asciiname":"Massipoussou",
    "gn:country_code":"TD",
    "gn:dem":368,
    "gn:feature_class":"P",
    "gn:feature_code":"PPL",
    "gn:name":"Massipoussou",
    "gn:population":0,
    "gn:timezone":"Africa/Ndjamena",
    "iso:country":"TD",
    "name:und_x_variant":[
        "Massi",
        "Massipoussou"
    ],
    "wof:name":"Massipoussou",
    "wof:placetype":"locality"
},
  "geometry": {"coordinates":[16.475,9.0418],"type":"Point"}
}