{
  "type": "Feature",
  "properties": {
    "gn:admin1_code":"6.0",
    "gn:asciiname":"Tapi",
    "gn:country_code":"TD",
    "gn:dem":332,
    "gn:feature_class":"P",
    "gn:feature_code":"PPL",
    "gn:name":"Tapi",
    "gn:population":0,
    "gn:timezone":"Africa/Ndjamena",
    "iso:country":"TD",
    "name:ell_x_preferred":[
        "\u03a4\u03ac\u03c0\u03b9"
    ],
    "name:hun_x_preferred":[
        "Tapi"
    ],
    "name:ind_x_preferred":[
        "Tapi"
    ],
    "name:kor_x_preferred":[
        "\ud0c0\ud53c"
    ],
    "name:por_x_preferred":[
        "Tapi"
    ],
    "name:tur_x_preferred":[
        "Tapi"
    ],
    "name:ukr_x_preferred":[
        "\u0422\u0430\u043f\u0456"
    ],
    "wof:name":"Tapi",
    "wof:placetype":"locality"
},
  "geometry": {"coordinates":[15.31737,13.97677],"type":"Point"}
}