{
  "type": "Feature",
  "properties": {
    "gn:admin1_code":"6.0",
    "gn:asciiname":"Tapi",
    "gn:country_code":"TD",
    "gn:dem":332,
    "gn:feature_class":"P",
    "gn:feature_code":"PPL",
    "gn:name":"Tapi",
    "gn:population":0,
    "gn:timezone":"Africa/Ndjamena",
    "iso:country":"TD",
    "wof:name":"Tapi",
    "wof:placetype":"locality"
},
  "geometry": {"coordinates":[15.31737,13.97677],"type":"Point"}
}