{
  "type": "Feature",
  "properties": {
    "gn:admin1_code":"19.0",
    "gn:asciiname":"Kemdili",
    "gn:country_code":"TD",
    "gn:dem":369,
    "gn:feature_class":"P",
    "gn:feature_code":"PPL",
    "gn:name":"Kemdili",
    "gn:population":0,
    "gn:timezone":"Africa/Ndjamena",
    "iso:country":"TD",
    "wof:name":"Kemdili",
    "wof:placetype":"locality"
},
  "geometry": {"coordinates":[18.0522,8.6224],"type":"Point"}
}