{
  "type": "Feature",
  "properties": {
    "gn:admin1_code":"18.0",
    "gn:asciiname":"Djimeze",
    "gn:country_code":"TD",
    "gn:dem":309,
    "gn:feature_class":"P",
    "gn:feature_code":"PPL",
    "gn:name":"Djim\u00e9z\u00e9",
    "gn:population":0,
    "gn:timezone":"Africa/Ndjamena",
    "iso:country":"TD",
    "wof:name":"Djimeze",
    "wof:placetype":"locality"
},
  "geometry": {"coordinates":[17.03333,12.16667],"type":"Point"}
}