{
  "type": "Feature",
  "properties": {
    "gn:admin1_code":"17.0",
    "gn:asciiname":"Alako",
    "gn:country_code":"TD",
    "gn:dem":384,
    "gn:feature_class":"P",
    "gn:feature_code":"PPL",
    "gn:name":"Alako",
    "gn:population":0,
    "gn:timezone":"Africa/Ndjamena",
    "iso:country":"TD",
    "name:ita_x_preferred":[
        "Alako"
    ],
    "wof:name":"Alako",
    "wof:placetype":"locality"
},
  "geometry": {"coordinates":[18.88132,9.79525],"type":"Point"}
}