{
  "type": "Feature",
  "properties": {
    "gn:admin1_code":"25.0",
    "gn:asciiname":"Himede",
    "gn:country_code":"TD",
    "gn:dem":645,
    "gn:feature_class":"P",
    "gn:feature_code":"PPL",
    "gn:name":"Him\u00e9d\u00e9",
    "gn:population":0,
    "gn:timezone":"Africa/Ndjamena",
    "iso:country":"TD",
    "wof:name":"Himede",
    "wof:placetype":"locality"
},
  "geometry": {"coordinates":[22.33333,12.63333],"type":"Point"}
}