{
  "type": "Feature",
  "properties": {
    "gn:admin1_code":"16.0",
    "gn:asciiname":"Matassi",
    "gn:country_code":"TD",
    "gn:dem":308,
    "gn:feature_class":"P",
    "gn:feature_code":"PPL",
    "gn:name":"Matassi",
    "gn:population":0,
    "gn:timezone":"Africa/Ndjamena",
    "iso:country":"TD",
    "name:und_x_variant":[
        "Matasi",
        "Matassi"
    ],
    "wof:name":"Matassi",
    "wof:placetype":"locality"
},
  "geometry": {"coordinates":[15.36171,11.17855],"type":"Point"}
}