{
  "type": "Feature",
  "properties": {
    "gn:admin1_code":"14.0",
    "gn:asciiname":"Kolon Kasere",
    "gn:country_code":"TD",
    "gn:dem":370,
    "gn:feature_class":"P",
    "gn:feature_code":"PPL",
    "gn:name":"Kolon Kas\u00e9r\u00e9",
    "gn:population":0,
    "gn:timezone":"Africa/Ndjamena",
    "iso:country":"TD",
    "wof:name":"Kolon Kasere",
    "wof:placetype":"locality"
},
  "geometry": {"coordinates":[15.8164,9.3518],"type":"Point"}
}