{
  "type": "Feature",
  "properties": {
    "gn:admin1_code":"20.0",
    "gn:asciiname":"Louga",
    "gn:country_code":"TD",
    "gn:dem":311,
    "gn:feature_class":"P",
    "gn:feature_code":"PPL",
    "gn:name":"Louga",
    "gn:population":0,
    "gn:timezone":"Africa/Ndjamena",
    "iso:country":"TD",
    "name:bel_x_preferred":[
        "\u041b\u0443\u0433\u0430"
    ],
    "name:cat_x_preferred":[
        "Louga"
    ],
    "name:ceb_x_preferred":[
        "Louga"
    ],
    "name:deu_x_preferred":[
        "Louga"
    ],
    "name:eus_x_preferred":[
        "Louga"
    ],
    "name:fas_x_preferred":[
        "\u0644\u0648\u06af\u0627"
    ],
    "name:fra_x_preferred":[
        "Louga"
    ],
    "name:frr_x_preferred":[
        "Louga"
    ],
    "name:ita_x_preferred":[
        "Louga"
    ],
    "name:jpn_x_preferred":[
        "\u30eb\u30fc\u30ac"
    ],
    "name:kor_x_preferred":[
        "\ub8e8\uac00"
    ],
    "name:lit_x_preferred":[
        "Luga"
    ],
    "name:nld_x_preferred":[
        "Louga"
    ],
    "name:pol_x_preferred":[
        "Louga"
    ],
    "name:ron_x_preferred":[
        "Louga"
    ],
    "name:rus_x_preferred":[
        "\u041b\u0443\u0433\u0430"
    ],
    "name:swe_x_preferred":[
        "Louga"
    ],
    "name:urd_x_preferred":[
        "\u0644\u0624\u06af\u0627"
    ],
    "name:wol_x_preferred":[
        "Luga"
    ],
    "name:zho_x_preferred":[
        "\u76e7\u52a0"
    ],
    "wof:name":"Louga",
    "wof:placetype":"locality"
},
  "geometry": {"coordinates":[14.3894,9.1691],"type":"Point"}
}