{
  "type": "Feature",
  "properties": {
    "gn:admin1_code":"20.0",
    "gn:asciiname":"Louga",
    "gn:country_code":"TD",
    "gn:dem":311,
    "gn:feature_class":"P",
    "gn:feature_code":"PPL",
    "gn:name":"Louga",
    "gn:population":0,
    "gn:timezone":"Africa/Ndjamena",
    "iso:country":"TD",
    "wof:name":"Louga",
    "wof:placetype":"locality"
},
  "geometry": {"coordinates":[14.3894,9.1691],"type":"Point"}
}