{
  "type": "Feature",
  "properties": {
    "gn:admin1_code":"19.0",
    "gn:asciiname":"Beboukata",
    "gn:country_code":"TD",
    "gn:dem":383,
    "gn:feature_class":"P",
    "gn:feature_code":"PPL",
    "gn:name":"B\u00e9boukata",
    "gn:population":0,
    "gn:timezone":"Africa/Ndjamena",
    "iso:country":"TD",
    "wof:name":"Beboukata",
    "wof:placetype":"locality"
},
  "geometry": {"coordinates":[17.1932,8.628],"type":"Point"}
}