{
  "type": "Feature",
  "properties": {
    "gn:admin1_code":"1.0",
    "gn:asciiname":"Azaraf",
    "gn:country_code":"TD",
    "gn:dem":347,
    "gn:feature_class":"P",
    "gn:feature_code":"PPL",
    "gn:name":"Azaraf",
    "gn:population":0,
    "gn:timezone":"Africa/Ndjamena",
    "iso:country":"TD",
    "wof:name":"Azaraf",
    "wof:placetype":"locality"
},
  "geometry": {"coordinates":[18.63333,13.16667],"type":"Point"}
}