{
  "type": "Feature",
  "properties": {
    "gn:admin1_code":"15.0",
    "gn:asciiname":"Narabase II",
    "gn:country_code":"TD",
    "gn:dem":330,
    "gn:feature_class":"P",
    "gn:feature_code":"PPL",
    "gn:name":"Narabas\u00e9 II",
    "gn:population":0,
    "gn:timezone":"Africa/Ndjamena",
    "iso:country":"TD",
    "wof:name":"Narabase II",
    "wof:placetype":"locality"
},
  "geometry": {"coordinates":[16.5134,10.6655],"type":"Point"}
}