{
  "type": "Feature",
  "properties": {
    "gn:admin1_code":"5.0",
    "gn:asciiname":"Deleng",
    "gn:country_code":"TD",
    "gn:dem":402,
    "gn:feature_class":"P",
    "gn:feature_code":"PPL",
    "gn:name":"Deleng",
    "gn:population":0,
    "gn:timezone":"Africa/Ndjamena",
    "iso:country":"TD",
    "wof:name":"Deleng",
    "wof:placetype":"locality"
},
  "geometry": {"coordinates":[17.5397,11.5235],"type":"Point"}
}