{
  "type": "Feature",
  "properties": {
    "gn:admin1_code":"14.0",
    "gn:asciiname":"Mimindi",
    "gn:country_code":"TD",
    "gn:dem":357,
    "gn:feature_class":"P",
    "gn:feature_code":"PPL",
    "gn:name":"Mimindi",
    "gn:population":0,
    "gn:timezone":"Africa/Ndjamena",
    "iso:country":"TD",
    "wof:name":"Mimindi",
    "wof:placetype":"locality"
},
  "geometry": {"coordinates":[16.1353,9.4267],"type":"Point"}
}