{
  "type": "Feature",
  "properties": {
    "gn:admin1_code":"9.0",
    "gn:asciiname":"Malila",
    "gn:country_code":"TD",
    "gn:dem":494,
    "gn:feature_class":"P",
    "gn:feature_code":"PPL",
    "gn:name":"Malila",
    "gn:population":0,
    "gn:timezone":"Africa/Ndjamena",
    "iso:country":"TD",
    "wof:name":"Malila",
    "wof:placetype":"locality"
},
  "geometry": {"coordinates":[16.14413,8.46321],"type":"Point"}
}