{
  "type": "Feature",
  "properties": {
    "gn:admin1_code":"14.0",
    "gn:asciiname":"Mokolo Kambaya",
    "gn:country_code":"TD",
    "gn:dem":385,
    "gn:feature_class":"P",
    "gn:feature_code":"PPL",
    "gn:name":"Mokolo Kambaya",
    "gn:population":0,
    "gn:timezone":"Africa/Ndjamena",
    "iso:country":"TD",
    "wof:name":"Mokolo Kambaya",
    "wof:placetype":"locality"
},
  "geometry": {"coordinates":[16.9353,9.1615],"type":"Point"}
}