{
  "type": "Feature",
  "properties": {
    "gn:admin1_code":"12.0",
    "gn:asciiname":"Mandaba",
    "gn:country_code":"TD",
    "gn:dem":505,
    "gn:feature_class":"P",
    "gn:feature_code":"PPL",
    "gn:name":"Mandaba",
    "gn:population":0,
    "gn:timezone":"Africa/Ndjamena",
    "iso:country":"TD",
    "wof:name":"Mandaba",
    "wof:placetype":"locality"
},
  "geometry": {"coordinates":[20.70994,14.25886],"type":"Point"}
}