{
  "type": "Feature",
  "properties": {
    "gn:admin1_code":"22.0",
    "gn:asciiname":"Toulousanga",
    "gn:country_code":"TD",
    "gn:dem":302,
    "gn:feature_class":"P",
    "gn:feature_code":"PPL",
    "gn:name":"Toulousanga",
    "gn:population":0,
    "gn:timezone":"Africa/Ndjamena",
    "iso:country":"TD",
    "wof:name":"Toulousanga",
    "wof:placetype":"locality"
},
  "geometry": {"coordinates":[16.2629,13.3191],"type":"Point"}
}