{
  "type": "Feature",
  "properties": {
    "gn:admin1_code":"1.0",
    "gn:asciiname":"Kachako Guemis",
    "gn:country_code":"TD",
    "gn:dem":365,
    "gn:feature_class":"P",
    "gn:feature_code":"PPL",
    "gn:name":"Kachako Guemis",
    "gn:population":0,
    "gn:timezone":"Africa/Ndjamena",
    "iso:country":"TD",
    "name:und_x_variant":[
        "Kachako Gemis",
        "Kachako Guemis"
    ],
    "wof:name":"Kachako Guemis",
    "wof:placetype":"locality"
},
  "geometry": {"coordinates":[19.2426,13.7663],"type":"Point"}
}