{
  "type": "Feature",
  "properties": {
    "gn:admin1_code":"1.0",
    "gn:asciiname":"Abgoada",
    "gn:country_code":"TD",
    "gn:dem":292,
    "gn:feature_class":"P",
    "gn:feature_code":"PPL",
    "gn:name":"Abgoada",
    "gn:population":0,
    "gn:timezone":"Africa/Ndjamena",
    "iso:country":"TD",
    "wof:name":"Abgoada",
    "wof:placetype":"locality"
},
  "geometry": {"coordinates":[17.15672,12.6626],"type":"Point"}
}