{
  "type": "Feature",
  "properties": {
    "gn:admin1_code":"7.0",
    "gn:asciiname":"Kelboua",
    "gn:country_code":"TD",
    "gn:dem":286,
    "gn:feature_class":"P",
    "gn:feature_code":"PPL",
    "gn:name":"K\u00e9lboua",
    "gn:population":0,
    "gn:timezone":"Africa/Ndjamena",
    "iso:country":"TD",
    "wof:name":"Kelboua",
    "wof:placetype":"locality"
},
  "geometry": {"coordinates":[14.33486,13.34772],"type":"Point"}
}