{
  "type": "Feature",
  "properties": {
    "gn:admin1_code":"7.0",
    "gn:asciiname":"Ngilimi",
    "gn:cc2":"TD",
    "gn:country_code":"TD",
    "gn:dem":280,
    "gn:feature_class":"P",
    "gn:feature_code":"PPL",
    "gn:name":"Ngilimi",
    "gn:population":0,
    "gn:timezone":"Africa/Ndjamena",
    "iso:country":"TD",
    "name:und_x_variant":[
        "N\u2019Guilima",
        "N\u2019Guilimi",
        "Ngilimi"
    ],
    "wof:name":"Ngilimi",
    "wof:placetype":"locality"
},
  "geometry": {"coordinates":[14.16667,13.73333],"type":"Point"}
}