{
  "type": "Feature",
  "properties": {
    "gn:admin1_code":"16.0",
    "gn:asciiname":"Mirviding",
    "gn:country_code":"TD",
    "gn:dem":314,
    "gn:feature_class":"P",
    "gn:feature_code":"PPL",
    "gn:name":"Mirviding",
    "gn:population":0,
    "gn:timezone":"Africa/Ndjamena",
    "iso:country":"TD",
    "name:und_x_variant":[
        "Mirvidin",
        "Mirviding"
    ],
    "wof:name":"Mirviding",
    "wof:placetype":"locality"
},
  "geometry": {"coordinates":[15.09724,10.90276],"type":"Point"}
}