{
  "type": "Feature",
  "properties": {
    "gn:admin1_code":"2.0",
    "gn:asciiname":"Benena",
    "gn:country_code":"TD",
    "gn:dem":926,
    "gn:feature_class":"P",
    "gn:feature_code":"PPL",
    "gn:name":"B\u00e9n\u00e9na",
    "gn:population":0,
    "gn:timezone":"Africa/Ndjamena",
    "iso:country":"TD",
    "name:fra_x_preferred":[
        "B\u00e9n\u00e9na"
    ],
    "wof:name":"Benena",
    "wof:placetype":"locality"
},
  "geometry": {"coordinates":[21.47215,14.37447],"type":"Point"}
}