{
  "type": "Feature",
  "properties": {
    "gn:admin1_code":"1.0",
    "gn:asciiname":"Am Guerine",
    "gn:country_code":"TD",
    "gn:dem":395,
    "gn:feature_class":"P",
    "gn:feature_code":"PPL",
    "gn:name":"Am Gu\u00e9rin\u00e9",
    "gn:population":0,
    "gn:timezone":"Africa/Ndjamena",
    "iso:country":"TD",
    "name:und_x_variant":[
        "Am G\u00e9rin\u00e9",
        "Am Gu\u00e9rin\u00e9"
    ],
    "wof:name":"Am Guerine",
    "wof:placetype":"locality"
},
  "geometry": {"coordinates":[19.8204,13.6093],"type":"Point"}
}