{
  "type": "Feature",
  "properties": {
    "gn:admin1_code":"19.0",
    "gn:asciiname":"Bara I",
    "gn:country_code":"TD",
    "gn:dem":379,
    "gn:feature_class":"P",
    "gn:feature_code":"PPL",
    "gn:name":"Bara I",
    "gn:population":0,
    "gn:timezone":"Africa/Ndjamena",
    "iso:country":"TD",
    "wof:name":"Bara I",
    "wof:placetype":"locality"
},
  "geometry": {"coordinates":[17.5248,8.5084],"type":"Point"}
}