{
  "type": "Feature",
  "properties": {
    "gn:admin1_code":"9.0",
    "gn:asciiname":"Gatouambele",
    "gn:country_code":"TD",
    "gn:dem":394,
    "gn:feature_class":"P",
    "gn:feature_code":"PPL",
    "gn:name":"Gatouamb\u00e9l\u00e9",
    "gn:population":0,
    "gn:timezone":"Africa/Ndjamena",
    "iso:country":"TD",
    "wof:name":"Gatouambele",
    "wof:placetype":"locality"
},
  "geometry": {"coordinates":[17.12442,8.96118],"type":"Point"}
}