{
  "type": "Feature",
  "properties": {
    "gn:admin1_code":"16.0",
    "gn:asciiname":"Koumadabeye",
    "gn:country_code":"TD",
    "gn:dem":318,
    "gn:feature_class":"P",
    "gn:feature_code":"PPL",
    "gn:name":"Koumadabeye",
    "gn:population":0,
    "gn:timezone":"Africa/Ndjamena",
    "iso:country":"TD",
    "wof:name":"Koumadabeye",
    "wof:placetype":"locality"
},
  "geometry": {"coordinates":[15.23333,10.56667],"type":"Point"}
}