{
  "type": "Feature",
  "properties": {
    "gn:admin1_code":"9.0",
    "gn:asciiname":"Dobemmiti",
    "gn:country_code":"TD",
    "gn:dem":395,
    "gn:feature_class":"P",
    "gn:feature_code":"PPL",
    "gn:name":"Dob\u00e9mmiti",
    "gn:population":0,
    "gn:timezone":"Africa/Ndjamena",
    "iso:country":"TD",
    "name:fra_x_preferred":[
        "Dob\u00e9mmiti"
    ],
    "wof:name":"Dobemmiti",
    "wof:placetype":"locality"
},
  "geometry": {"coordinates":[16.6119,8.6183],"type":"Point"}
}