{
  "type": "Feature",
  "properties": {
    "gn:admin1_code":"12.0",
    "gn:asciiname":"Maboukime",
    "gn:country_code":"TD",
    "gn:dem":744,
    "gn:feature_class":"P",
    "gn:feature_code":"PPL",
    "gn:name":"Maboukim\u00e9",
    "gn:population":0,
    "gn:timezone":"Africa/Ndjamena",
    "iso:country":"TD",
    "name:fra_x_preferred":[
        "Maboukim\u00e9"
    ],
    "wof:name":"Maboukime",
    "wof:placetype":"locality"
},
  "geometry": {"coordinates":[21.2171,14.02634],"type":"Point"}
}