{
  "type": "Feature",
  "properties": {
    "gn:admin1_code":"17.0",
    "gn:asciiname":"Hori",
    "gn:country_code":"TD",
    "gn:dem":374,
    "gn:feature_class":"P",
    "gn:feature_code":"PPL",
    "gn:name":"Hori",
    "gn:population":0,
    "gn:timezone":"Africa/Ndjamena",
    "iso:country":"TD",
    "name:ceb_x_preferred":[
        "Hori"
    ],
    "name:deu_x_preferred":[
        "Hori"
    ],
    "name:fra_x_preferred":[
        "Hori"
    ],
    "name:hun_x_preferred":[
        "Hori"
    ],
    "name:ita_x_preferred":[
        "Hori"
    ],
    "name:por_x_preferred":[
        "Hori"
    ],
    "name:swe_x_preferred":[
        "Hori"
    ],
    "wof:name":"Hori",
    "wof:placetype":"locality"
},
  "geometry": {"coordinates":[18.398,8.7831],"type":"Point"}
}