{
  "type": "Feature",
  "properties": {
    "gn:admin1_code":"12.0",
    "gn:asciiname":"Abkar Djombo",
    "gn:country_code":"TD",
    "gn:dem":557,
    "gn:feature_class":"P",
    "gn:feature_code":"PPL",
    "gn:name":"Abkar Djombo",
    "gn:population":0,
    "gn:timezone":"Africa/Ndjamena",
    "iso:country":"TD",
    "name:ita_x_preferred":[
        "Abkar Djombo"
    ],
    "name:und_x_variant":[
        "Abkaro Djonbo",
        "Adkar Djombo"
    ],
    "wof:name":"Abkar Djombo",
    "wof:placetype":"locality"
},
  "geometry": {"coordinates":[21.08192,13.1802],"type":"Point"}
}