{
  "type": "Feature",
  "properties": {
    "gn:admin1_code":"25.0",
    "gn:asciiname":"Tcharo",
    "gn:country_code":"TD",
    "gn:dem":580,
    "gn:feature_class":"P",
    "gn:feature_code":"PPL",
    "gn:name":"Tcharo",
    "gn:population":0,
    "gn:timezone":"Africa/Ndjamena",
    "iso:country":"TD",
    "wof:name":"Tcharo",
    "wof:placetype":"locality"
},
  "geometry": {"coordinates":[21.53333,12.28333],"type":"Point"}
}