{
  "type": "Feature",
  "properties": {
    "gn:admin1_code":"25.0",
    "gn:asciiname":"Idel Asat Saba",
    "gn:country_code":"TD",
    "gn:dem":458,
    "gn:feature_class":"P",
    "gn:feature_code":"PPL",
    "gn:name":"Idel Asat Saba",
    "gn:population":0,
    "gn:timezone":"Africa/Ndjamena",
    "iso:country":"TD",
    "name:und_x_variant":[
        "Id el Asset",
        "Idel Asat Saba"
    ],
    "wof:name":"Idel Asat Saba",
    "wof:placetype":"locality"
},
  "geometry": {"coordinates":[20.45,12.46667],"type":"Point"}
}