{
  "type": "Feature",
  "properties": {
    "gn:admin1_code":"1.0",
    "gn:asciiname":"Abou Koulam",
    "gn:country_code":"TD",
    "gn:dem":407,
    "gn:feature_class":"P",
    "gn:feature_code":"PPL",
    "gn:name":"Abou Koulam",
    "gn:population":0,
    "gn:timezone":"Africa/Ndjamena",
    "iso:country":"TD",
    "wof:name":"Abou Koulam",
    "wof:placetype":"locality"
},
  "geometry": {"coordinates":[19.9763,13.9801],"type":"Point"}
}