{
  "type": "Feature",
  "properties": {
    "gn:admin1_code":"12.0",
    "gn:asciiname":"Linye Matar",
    "gn:country_code":"TD",
    "gn:dem":892,
    "gn:feature_class":"P",
    "gn:feature_code":"PPL",
    "gn:name":"Liny\u00e9 Matar",
    "gn:population":0,
    "gn:timezone":"Africa/Ndjamena",
    "iso:country":"TD",
    "wof:name":"Linye Matar",
    "wof:placetype":"locality"
},
  "geometry": {"coordinates":[22.08497,13.40339],"type":"Point"}
}