{
  "type": "Feature",
  "properties": {
    "gn:admin1_code":"16.0",
    "gn:asciiname":"Goulang",
    "gn:country_code":"TD",
    "gn:dem":317,
    "gn:feature_class":"P",
    "gn:feature_code":"PPL",
    "gn:name":"Goulang",
    "gn:population":0,
    "gn:timezone":"Africa/Ndjamena",
    "iso:country":"TD",
    "wof:name":"Goulang",
    "wof:placetype":"locality"
},
  "geometry": {"coordinates":[15.48549,10.86174],"type":"Point"}
}