{
  "type": "Feature",
  "properties": {
    "gn:admin1_code":"15.0",
    "gn:asciiname":"Et Taouil",
    "gn:country_code":"TD",
    "gn:dem":294,
    "gn:feature_class":"P",
    "gn:feature_code":"PPL",
    "gn:name":"Et Taouil",
    "gn:population":0,
    "gn:timezone":"Africa/Ndjamena",
    "iso:country":"TD",
    "wof:name":"Et Taouil",
    "wof:placetype":"locality"
},
  "geometry": {"coordinates":[15.28426,12.24537],"type":"Point"}
}