{
  "type": "Feature",
  "properties": {
    "gn:admin1_code":"9.0",
    "gn:asciiname":"Bekolo",
    "gn:country_code":"TD",
    "gn:dem":411,
    "gn:feature_class":"P",
    "gn:feature_code":"PPL",
    "gn:name":"Bekolo",
    "gn:population":0,
    "gn:timezone":"Africa/Ndjamena",
    "iso:country":"TD",
    "wof:name":"Bekolo",
    "wof:placetype":"locality"
},
  "geometry": {"coordinates":[17.1227,8.1927],"type":"Point"}
}