{
  "type": "Feature",
  "properties": {
    "gn:admin1_code":"2.0",
    "gn:asciiname":"Orok",
    "gn:country_code":"TD",
    "gn:dem":702,
    "gn:feature_class":"P",
    "gn:feature_code":"PPL",
    "gn:name":"Orok",
    "gn:population":0,
    "gn:timezone":"Africa/Ndjamena",
    "iso:country":"TD",
    "name:fra_x_preferred":[
        "Orok"
    ],
    "wof:name":"Orok",
    "wof:placetype":"locality"
},
  "geometry": {"coordinates":[21.2003,14.43467],"type":"Point"}
}