{
  "type": "Feature",
  "properties": {
    "gn:admin1_code":"14.0",
    "gn:asciiname":"Nerebi",
    "gn:country_code":"TD",
    "gn:dem":346,
    "gn:feature_class":"P",
    "gn:feature_code":"PPL",
    "gn:name":"N\u00e9r\u00e9bi",
    "gn:population":0,
    "gn:timezone":"Africa/Ndjamena",
    "iso:country":"TD",
    "wof:name":"Nerebi",
    "wof:placetype":"locality"
},
  "geometry": {"coordinates":[16.2318,9.6763],"type":"Point"}
}