{
  "type": "Feature",
  "properties": {
    "gn:admin1_code":"9.0",
    "gn:asciiname":"Bikoua",
    "gn:country_code":"TD",
    "gn:dem":448,
    "gn:feature_class":"P",
    "gn:feature_code":"PPL",
    "gn:name":"Bikoua",
    "gn:population":0,
    "gn:timezone":"Africa/Ndjamena",
    "iso:country":"TD",
    "wof:name":"Bikoua",
    "wof:placetype":"locality"
},
  "geometry": {"coordinates":[15.9123,8.1797],"type":"Point"}
}