{
  "type": "Feature",
  "properties": {
    "gn:admin1_code":"1.0",
    "gn:asciiname":"Am Sayala",
    "gn:country_code":"TD",
    "gn:dem":301,
    "gn:feature_class":"P",
    "gn:feature_code":"PPL",
    "gn:name":"Am Sayala",
    "gn:population":0,
    "gn:timezone":"Africa/Ndjamena",
    "iso:country":"TD",
    "wof:name":"Am Sayala",
    "wof:placetype":"locality"
},
  "geometry": {"coordinates":[17.8063,13.1462],"type":"Point"}
}