{
  "type": "Feature",
  "properties": {
    "gn:admin1_code":"9.0",
    "gn:asciiname":"Kagopal",
    "gn:country_code":"TD",
    "gn:dem":456,
    "gn:feature_class":"P",
    "gn:feature_code":"PPL",
    "gn:name":"Kagopal",
    "gn:population":0,
    "gn:timezone":"Africa/Ndjamena",
    "iso:country":"TD",
    "name:fra_x_preferred":[
        "Kagopal"
    ],
    "name:fra_x_variant":[
        "Kagopa\u00ef",
        "Kagopa"
    ],
    "name:und_x_variant":[
        "Kagopa\u00ef",
        "Kagopa"
    ],
    "wof:name":"Kagopal",
    "wof:placetype":"locality"
},
  "geometry": {"coordinates":[16.44472,8.27781],"type":"Point"}
}