{
  "type": "Feature",
  "properties": {
    "gn:admin1_code":"1.0",
    "gn:asciiname":"Erdebe",
    "gn:country_code":"TD",
    "gn:dem":358,
    "gn:feature_class":"P",
    "gn:feature_code":"PPL",
    "gn:name":"Erd\u00e9b\u00e9",
    "gn:population":0,
    "gn:timezone":"Africa/Ndjamena",
    "iso:country":"TD",
    "name:und_x_variant":[
        "Ard\u00e9b\u00e9",
        "Erd\u00e9b\u00e9"
    ],
    "wof:name":"Erdebe",
    "wof:placetype":"locality"
},
  "geometry": {"coordinates":[19.2055,13.8562],"type":"Point"}
}