{
  "type": "Feature",
  "properties": {
    "gn:admin1_code":"7.0",
    "gn:asciiname":"Tchongole",
    "gn:country_code":"TD",
    "gn:dem":287,
    "gn:feature_class":"P",
    "gn:feature_code":"PPL",
    "gn:name":"Tchongol\u00e9",
    "gn:population":0,
    "gn:timezone":"Africa/Ndjamena",
    "iso:country":"TD",
    "wof:name":"Tchongole",
    "wof:placetype":"locality"
},
  "geometry": {"coordinates":[14.85,13.31667],"type":"Point"}
}