{
  "type": "Feature",
  "properties": {
    "gn:admin1_code":"19.0",
    "gn:asciiname":"Matade",
    "gn:country_code":"TD",
    "gn:dem":371,
    "gn:feature_class":"P",
    "gn:feature_code":"PPL",
    "gn:name":"Matad\u00e9",
    "gn:population":0,
    "gn:timezone":"Africa/Ndjamena",
    "iso:country":"TD",
    "wof:name":"Matade",
    "wof:placetype":"locality"
},
  "geometry": {"coordinates":[17.847,8.8588],"type":"Point"}
}