{
  "type": "Feature",
  "properties": {
    "gn:admin1_code":"9.0",
    "gn:asciiname":"Pipigne",
    "gn:country_code":"TD",
    "gn:dem":541,
    "gn:feature_class":"P",
    "gn:feature_code":"PPL",
    "gn:name":"Pipigne",
    "gn:population":0,
    "gn:timezone":"Africa/Ndjamena",
    "iso:country":"TD",
    "wof:name":"Pipigne",
    "wof:placetype":"locality"
},
  "geometry": {"coordinates":[15.66667,8.08333],"type":"Point"}
}