{
  "type": "Feature",
  "properties": {
    "gn:admin1_code":"9.0",
    "gn:asciiname":"Koutoutou",
    "gn:country_code":"TD",
    "gn:dem":386,
    "gn:feature_class":"P",
    "gn:feature_code":"PPL",
    "gn:name":"Koutoutou",
    "gn:population":0,
    "gn:timezone":"Africa/Ndjamena",
    "iso:country":"TD",
    "name:fra_x_preferred":[
        "Koutoutou"
    ],
    "name:fra_x_variant":[
        "Koutou"
    ],
    "name:und_x_variant":[
        "Koutou"
    ],
    "wof:name":"Koutoutou",
    "wof:placetype":"locality"
},
  "geometry": {"coordinates":[16.8684,8.95718],"type":"Point"}
}