{
  "type": "Feature",
  "properties": {
    "gn:admin1_code":"17.0",
    "gn:asciiname":"Oumatili",
    "gn:country_code":"TD",
    "gn:dem":362,
    "gn:feature_class":"P",
    "gn:feature_code":"PPL",
    "gn:name":"Oumatili",
    "gn:population":0,
    "gn:timezone":"Africa/Ndjamena",
    "iso:country":"TD",
    "wof:name":"Oumatili",
    "wof:placetype":"locality"
},
  "geometry": {"coordinates":[17.97462,9.93333],"type":"Point"}
}