{
  "type": "Feature",
  "properties": {
    "gn:admin1_code":"15.0",
    "gn:asciiname":"Abere",
    "gn:country_code":"TD",
    "gn:dem":334,
    "gn:feature_class":"P",
    "gn:feature_code":"PPL",
    "gn:name":"Ab\u00e9r\u00e9",
    "gn:population":0,
    "gn:timezone":"Africa/Ndjamena",
    "iso:country":"TD",
    "name:eus_x_preferred":[
        "Abere"
    ],
    "name:fra_x_preferred":[
        "Abere"
    ],
    "name:por_x_preferred":[
        "Abere"
    ],
    "name:spa_x_preferred":[
        "Abere"
    ],
    "wof:name":"Abere",
    "wof:placetype":"locality"
},
  "geometry": {"coordinates":[16.7999,11.5397],"type":"Point"}
}