{
  "type": "Feature",
  "properties": {
    "gn:admin1_code":"15.0",
    "gn:asciiname":"Gourle",
    "gn:country_code":"TD",
    "gn:dem":304,
    "gn:feature_class":"P",
    "gn:feature_code":"PPL",
    "gn:name":"Gourle",
    "gn:population":0,
    "gn:timezone":"Africa/Ndjamena",
    "iso:country":"TD",
    "wof:name":"Gourle",
    "wof:placetype":"locality"
},
  "geometry": {"coordinates":[16.1022,12.0458],"type":"Point"}
}