{
  "type": "Feature",
  "properties": {
    "gn:admin1_code":"15.0",
    "gn:asciiname":"Bougoumene",
    "gn:country_code":"TD",
    "gn:dem":310,
    "gn:feature_class":"P",
    "gn:feature_code":"PPL",
    "gn:name":"Bougoum\u00e8ne",
    "gn:population":0,
    "gn:timezone":"Africa/Ndjamena",
    "iso:country":"TD",
    "name:und_x_variant":[
        "Bougoman",
        "Bougoum\u00e8ne"
    ],
    "wof:name":"Bougoumene",
    "wof:placetype":"locality"
},
  "geometry": {"coordinates":[15.33639,11.46674],"type":"Point"}
}