{
  "type": "Feature",
  "properties": {
    "gn:admin1_code":"9.0",
    "gn:asciiname":"Gouri",
    "gn:country_code":"TD",
    "gn:dem":401,
    "gn:feature_class":"P",
    "gn:feature_code":"PPL",
    "gn:name":"Gouri",
    "gn:population":0,
    "gn:timezone":"Africa/Ndjamena",
    "iso:country":"TD",
    "wof:name":"Gouri",
    "wof:placetype":"locality"
},
  "geometry": {"coordinates":[17.19052000000001,8.31115],"type":"Point"}
}