{
  "type": "Feature",
  "properties": {
    "gn:admin1_code":"20.0",
    "gn:asciiname":"Lere",
    "gn:country_code":"TD",
    "gn:dem":231,
    "gn:feature_class":"P",
    "gn:feature_code":"PPL",
    "gn:name":"L\u00e9r\u00e9",
    "gn:population":0,
    "gn:timezone":"Africa/Ndjamena",
    "iso:country":"TD",
    "name:und_x_variant":[
        "L\u00e9r\u00e9"
    ],
    "wof:name":"Lere",
    "wof:placetype":"locality"
},
  "geometry": {"coordinates":[14.2151,9.6447],"type":"Point"}
}