{
  "type": "Feature",
  "properties": {
    "gn:admin1_code":"2.0",
    "gn:asciiname":"Koudigui",
    "gn:country_code":"TD",
    "gn:dem":735,
    "gn:feature_class":"P",
    "gn:feature_code":"PPL",
    "gn:name":"Koudigui",
    "gn:population":0,
    "gn:timezone":"Africa/Ndjamena",
    "iso:country":"TD",
    "name:fra_x_preferred":[
        "Koudigui"
    ],
    "name:fra_x_variant":[
        "Koudigi"
    ],
    "wof:name":"Koudigui",
    "wof:placetype":"locality"
},
  "geometry": {"coordinates":[21.08805,14.22652],"type":"Point"}
}