{
  "type": "Feature",
  "properties": {
    "gn:admin1_code":"14.0",
    "gn:asciiname":"Biecou",
    "gn:country_code":"TD",
    "gn:dem":397,
    "gn:feature_class":"P",
    "gn:feature_code":"PPL",
    "gn:name":"Biecou",
    "gn:population":0,
    "gn:timezone":"Africa/Ndjamena",
    "iso:country":"TD",
    "wof:name":"Biecou",
    "wof:placetype":"locality"
},
  "geometry": {"coordinates":[16.48333,9.11667],"type":"Point"}
}