{
  "type": "Feature",
  "properties": {
    "gn:admin1_code":"16.0",
    "gn:asciiname":"Petit Goulmoun",
    "gn:country_code":"TD",
    "gn:dem":327,
    "gn:feature_class":"P",
    "gn:feature_code":"PPL",
    "gn:name":"Petit Goulmoun",
    "gn:population":0,
    "gn:timezone":"Africa/Ndjamena",
    "iso:country":"TD",
    "wof:name":"Petit Goulmoun",
    "wof:placetype":"locality"
},
  "geometry": {"coordinates":[15.16725,9.85959],"type":"Point"}
}