{
  "type": "Feature",
  "properties": {
    "gn:admin1_code":"16.0",
    "gn:asciiname":"Magouaye",
    "gn:country_code":"TD",
    "gn:dem":315,
    "gn:feature_class":"P",
    "gn:feature_code":"PPL",
    "gn:name":"Magouaye",
    "gn:population":0,
    "gn:timezone":"Africa/Ndjamena",
    "iso:country":"TD",
    "name:und_x_variant":[
        "Magou\u00e9",
        "Magoua",
        "Magouaye"
    ],
    "wof:name":"Magouaye",
    "wof:placetype":"locality"
},
  "geometry": {"coordinates":[15.32021,10.74502],"type":"Point"}
}