{
  "type": "Feature",
  "properties": {
    "gn:admin1_code":"18.0",
    "gn:asciiname":"Lawa",
    "gn:country_code":"TD",
    "gn:dem":327,
    "gn:feature_class":"P",
    "gn:feature_code":"PPL",
    "gn:name":"Lawa",
    "gn:population":0,
    "gn:timezone":"Africa/Ndjamena",
    "iso:country":"TD",
    "name:ceb_x_preferred":[
        "Lawa"
    ],
    "name:deu_x_preferred":[
        "Lawa"
    ],
    "name:fra_x_preferred":[
        "Lawa"
    ],
    "name:ita_x_preferred":[
        "Lawa"
    ],
    "name:swe_x_preferred":[
        "Lawa"
    ],
    "wof:name":"Lawa",
    "wof:placetype":"locality"
},
  "geometry": {"coordinates":[17.2034,11.7318],"type":"Point"}
}