{
  "type": "Feature",
  "properties": {
    "gn:admin1_code":"15.0",
    "gn:asciiname":"El Arba",
    "gn:country_code":"TD",
    "gn:dem":303,
    "gn:feature_class":"P",
    "gn:feature_code":"PPL",
    "gn:name":"El Arba",
    "gn:population":0,
    "gn:timezone":"Africa/Ndjamena",
    "iso:country":"TD",
    "name:und_x_variant":[
        "Larba",
        "El Arba"
    ],
    "wof:name":"El Arba",
    "wof:placetype":"locality"
},
  "geometry": {"coordinates":[15.43751,11.71316],"type":"Point"}
}