{
  "type": "Feature",
  "properties": {
    "gn:admin1_code":"5.0",
    "gn:asciiname":"Loda",
    "gn:country_code":"TD",
    "gn:dem":422,
    "gn:feature_class":"P",
    "gn:feature_code":"PPL",
    "gn:name":"Loda",
    "gn:population":0,
    "gn:timezone":"Africa/Ndjamena",
    "iso:country":"TD",
    "name:ceb_x_preferred":[
        "Loda"
    ],
    "name:deu_x_preferred":[
        "Loda"
    ],
    "name:fra_x_preferred":[
        "Loda"
    ],
    "name:ita_x_preferred":[
        "Loda"
    ],
    "name:nld_x_preferred":[
        "Loda"
    ],
    "name:pol_x_preferred":[
        "Loda"
    ],
    "name:srp_x_preferred":[
        "Loda"
    ],
    "name:swe_x_preferred":[
        "Loda"
    ],
    "wof:name":"Loda",
    "wof:placetype":"locality"
},
  "geometry": {"coordinates":[18.0422,11.2776],"type":"Point"}
}