{
  "type": "Feature",
  "properties": {
    "gn:admin1_code":"19.0",
    "gn:asciiname":"Sako",
    "gn:country_code":"TD",
    "gn:dem":385,
    "gn:feature_class":"P",
    "gn:feature_code":"PPL",
    "gn:name":"Sako",
    "gn:population":0,
    "gn:timezone":"Africa/Ndjamena",
    "iso:country":"TD",
    "wof:name":"Sako",
    "wof:placetype":"locality"
},
  "geometry": {"coordinates":[17.40569,8.38204],"type":"Point"}
}