{
  "type": "Feature",
  "properties": {
    "gn:admin1_code":"19.0",
    "gn:asciiname":"Sako",
    "gn:country_code":"TD",
    "gn:dem":385,
    "gn:feature_class":"P",
    "gn:feature_code":"PPL",
    "gn:name":"Sako",
    "gn:population":0,
    "gn:timezone":"Africa/Ndjamena",
    "iso:country":"TD",
    "name:ceb_x_preferred":[
        "Sako"
    ],
    "name:deu_x_preferred":[
        "Sako"
    ],
    "name:fra_x_preferred":[
        "Sako"
    ],
    "name:ido_x_preferred":[
        "Sako"
    ],
    "name:nld_x_preferred":[
        "Sako"
    ],
    "name:rus_x_preferred":[
        "\u0421\u0430\u043a\u043e"
    ],
    "name:srp_x_preferred":[
        "\u0421\u0430\u043a\u043e"
    ],
    "name:swe_x_preferred":[
        "Sako"
    ],
    "name:ukr_x_preferred":[
        "\u0421\u0430\u043a\u043e"
    ],
    "wof:name":"Sako",
    "wof:placetype":"locality"
},
  "geometry": {"coordinates":[17.40569,8.38204],"type":"Point"}
}