{
  "type": "Feature",
  "properties": {
    "gn:admin1_code":"14.0",
    "gn:asciiname":"Modiogou",
    "gn:country_code":"TD",
    "gn:dem":348,
    "gn:feature_class":"P",
    "gn:feature_code":"PPL",
    "gn:name":"Modiogou",
    "gn:population":0,
    "gn:timezone":"Africa/Ndjamena",
    "iso:country":"TD",
    "wof:name":"Modiogou",
    "wof:placetype":"locality"
},
  "geometry": {"coordinates":[16.6595,9.6534],"type":"Point"}
}