{
  "type": "Feature",
  "properties": {
    "gn:admin1_code":"18.0",
    "gn:asciiname":"Balaia",
    "gn:country_code":"TD",
    "gn:dem":288,
    "gn:feature_class":"P",
    "gn:feature_code":"PPL",
    "gn:name":"Bala\u00efa",
    "gn:population":0,
    "gn:timezone":"Africa/Ndjamena",
    "iso:country":"TD",
    "wof:name":"Balaia",
    "wof:placetype":"locality"
},
  "geometry": {"coordinates":[15.45965,12.97592],"type":"Point"}
}