{
  "type": "Feature",
  "properties": {
    "gn:admin1_code":"13.0",
    "gn:asciiname":"Ghichghich",
    "gn:country_code":"TD",
    "gn:dem":406,
    "gn:feature_class":"P",
    "gn:feature_code":"PPL",
    "gn:name":"Ghichghich",
    "gn:population":0,
    "gn:timezone":"Africa/Ndjamena",
    "iso:country":"TD",
    "name:und_x_variant":[
        "Rhichrhich",
        "Ghichghich"
    ],
    "wof:name":"Ghichghich",
    "wof:placetype":"locality"
},
  "geometry": {"coordinates":[19.7295,10.2867],"type":"Point"}
}