{
  "type": "Feature",
  "properties": {
    "gn:admin1_code":"20.0",
    "gn:asciiname":"Bindjom",
    "gn:country_code":"TD",
    "gn:dem":333,
    "gn:feature_class":"P",
    "gn:feature_code":"PPL",
    "gn:name":"Bindjom",
    "gn:population":0,
    "gn:timezone":"Africa/Ndjamena",
    "iso:country":"TD",
    "wof:name":"Bindjom",
    "wof:placetype":"locality"
},
  "geometry": {"coordinates":[14.63333,9.45],"type":"Point"}
}