{
  "type": "Feature",
  "properties": {
    "gn:admin1_code":"7.0",
    "gn:asciiname":"Goui",
    "gn:country_code":"TD",
    "gn:dem":287,
    "gn:feature_class":"P",
    "gn:feature_code":"PPL",
    "gn:name":"Goui",
    "gn:population":0,
    "gn:timezone":"Africa/Ndjamena",
    "iso:country":"TD",
    "wof:name":"Goui",
    "wof:placetype":"locality"
},
  "geometry": {"coordinates":[15.0003,13.49341],"type":"Point"}
}