{
  "type": "Feature",
  "properties": {
    "gn:admin1_code":"12.0",
    "gn:asciiname":"Bir Kedouas",
    "gn:country_code":"TD",
    "gn:dem":657,
    "gn:feature_class":"P",
    "gn:feature_code":"PPL",
    "gn:name":"Bir K\u00e9douas",
    "gn:population":0,
    "gn:timezone":"Africa/Ndjamena",
    "iso:country":"TD",
    "wof:name":"Bir Kedouas",
    "wof:placetype":"locality"
},
  "geometry": {"coordinates":[21.85,12.86667],"type":"Point"}
}