{
  "type": "Feature",
  "properties": {
    "gn:admin1_code":"22.0",
    "gn:asciiname":"Tchibou",
    "gn:country_code":"TD",
    "gn:dem":306,
    "gn:feature_class":"P",
    "gn:feature_code":"PPL",
    "gn:name":"Tchibou",
    "gn:population":0,
    "gn:timezone":"Africa/Ndjamena",
    "iso:country":"TD",
    "wof:name":"Tchibou",
    "wof:placetype":"locality"
},
  "geometry": {"coordinates":[16.8554,13.3576],"type":"Point"}
}