{
  "type": "Feature",
  "properties": {
    "gn:admin1_code":"8.0",
    "gn:asciiname":"Goura",
    "gn:country_code":"TD",
    "gn:dem":507,
    "gn:feature_class":"P",
    "gn:feature_code":"PPL",
    "gn:name":"Goura",
    "gn:population":0,
    "gn:timezone":"Africa/Ndjamena",
    "iso:country":"TD",
    "wof:name":"Goura",
    "wof:placetype":"locality"
},
  "geometry": {"coordinates":[15.3245,8.4587],"type":"Point"}
}