{
  "type": "Feature",
  "properties": {
    "gn:admin1_code":"16.0",
    "gn:asciiname":"Ngam",
    "gn:country_code":"TD",
    "gn:dem":338,
    "gn:feature_class":"P",
    "gn:feature_code":"PPL",
    "gn:name":"Ngam",
    "gn:population":0,
    "gn:timezone":"Africa/Ndjamena",
    "iso:country":"TD",
    "name:und_x_variant":[
        "Gam",
        "Ngam"
    ],
    "wof:name":"Ngam",
    "wof:placetype":"locality"
},
  "geometry": {"coordinates":[16.15482,10.19833],"type":"Point"}
}