{
  "type": "Feature",
  "properties": {
    "gn:admin1_code":"12.0",
    "gn:asciiname":"Garaday",
    "gn:country_code":"TD",
    "gn:dem":552,
    "gn:feature_class":"P",
    "gn:feature_code":"PPL",
    "gn:name":"Garaday",
    "gn:population":0,
    "gn:timezone":"Africa/Ndjamena",
    "iso:country":"TD",
    "wof:name":"Garaday",
    "wof:placetype":"locality"
},
  "geometry": {"coordinates":[20.878,13.35871],"type":"Point"}
}