{
  "type": "Feature",
  "properties": {
    "gn:admin1_code":"1.0",
    "gn:asciiname":"Alay",
    "gn:country_code":"TD",
    "gn:dem":330,
    "gn:feature_class":"P",
    "gn:feature_code":"PPL",
    "gn:name":"Alay",
    "gn:population":0,
    "gn:timezone":"Africa/Ndjamena",
    "iso:country":"TD",
    "name:ind_x_preferred":[
        "Alay"
    ],
    "name:und_x_variant":[
        "Go\u00efmo"
    ],
    "wof:name":"Alay",
    "wof:placetype":"locality"
},
  "geometry": {"coordinates":[18.14903,12.90931],"type":"Point"}
}