{
  "type": "Feature",
  "properties": {
    "gn:admin1_code":"7.0",
    "gn:asciiname":"Ilouwe",
    "gn:country_code":"TD",
    "gn:dem":314,
    "gn:feature_class":"P",
    "gn:feature_code":"PPL",
    "gn:name":"Ilouw\u00e9",
    "gn:population":0,
    "gn:timezone":"Africa/Ndjamena",
    "iso:country":"TD",
    "wof:name":"Ilouwe",
    "wof:placetype":"locality"
},
  "geometry": {"coordinates":[15.58616,13.80484],"type":"Point"}
}