{
  "type": "Feature",
  "properties": {
    "gn:admin1_code":"19.0",
    "gn:asciiname":"Kaba",
    "gn:country_code":"TD",
    "gn:dem":436,
    "gn:feature_class":"P",
    "gn:feature_code":"PPL",
    "gn:name":"Kaba",
    "gn:population":0,
    "gn:timezone":"Africa/Ndjamena",
    "iso:country":"TD",
    "wof:name":"Kaba",
    "wof:placetype":"locality"
},
  "geometry": {"coordinates":[17.19674,9.01626],"type":"Point"}
}