{
  "type": "Feature",
  "properties": {
    "gn:admin1_code":"2.0",
    "gn:asciiname":"Maganine",
    "gn:country_code":"TD",
    "gn:dem":746,
    "gn:feature_class":"P",
    "gn:feature_code":"PPL",
    "gn:name":"Maganin\u00e9",
    "gn:population":0,
    "gn:timezone":"Africa/Ndjamena",
    "iso:country":"TD",
    "name:fra_x_preferred":[
        "Maganin\u00e9"
    ],
    "wof:name":"Maganine",
    "wof:placetype":"locality"
},
  "geometry": {"coordinates":[21.1578,14.33497],"type":"Point"}
}