{
  "type": "Feature",
  "properties": {
    "gn:admin1_code":"15.0",
    "gn:asciiname":"Sadao",
    "gn:country_code":"TD",
    "gn:dem":331,
    "gn:feature_class":"P",
    "gn:feature_code":"PPL",
    "gn:name":"Sadao",
    "gn:population":0,
    "gn:timezone":"Africa/Ndjamena",
    "iso:country":"TD",
    "name:und_x_variant":[
        "Saadou",
        "Sadou",
        "Sadaou",
        "Sadao"
    ],
    "wof:name":"Sadao",
    "wof:placetype":"locality"
},
  "geometry": {"coordinates":[16.6664,11.3847],"type":"Point"}
}