{
  "type": "Feature",
  "properties": {
    "gn:admin1_code":"8.0",
    "gn:asciiname":"Bougarou",
    "gn:country_code":"TD",
    "gn:dem":466,
    "gn:feature_class":"P",
    "gn:feature_code":"PPL",
    "gn:name":"Bougarou",
    "gn:population":0,
    "gn:timezone":"Africa/Ndjamena",
    "iso:country":"TD",
    "wof:name":"Bougarou",
    "wof:placetype":"locality"
},
  "geometry": {"coordinates":[16.40924,8.81898],"type":"Point"}
}