{
  "type": "Feature",
  "properties": {
    "gn:admin1_code":"16.0",
    "gn:asciiname":"Bidimene",
    "gn:country_code":"TD",
    "gn:dem":317,
    "gn:feature_class":"P",
    "gn:feature_code":"PPL",
    "gn:name":"Bidim\u00e8ne",
    "gn:population":0,
    "gn:timezone":"Africa/Ndjamena",
    "iso:country":"TD",
    "wof:name":"Bidimene",
    "wof:placetype":"locality"
},
  "geometry": {"coordinates":[15.4858,10.80294],"type":"Point"}
}