{
  "type": "Feature",
  "properties": {
    "gn:admin1_code":"5.0",
    "gn:asciiname":"Kasira",
    "gn:country_code":"TD",
    "gn:dem":435,
    "gn:feature_class":"P",
    "gn:feature_code":"PPL",
    "gn:name":"Kasira",
    "gn:population":0,
    "gn:timezone":"Africa/Ndjamena",
    "iso:country":"TD",
    "wof:name":"Kasira",
    "wof:placetype":"locality"
},
  "geometry": {"coordinates":[19.538,12.4813],"type":"Point"}
}