{
  "type": "Feature",
  "properties": {
    "gn:admin1_code":"12.0",
    "gn:asciiname":"Kodolok",
    "gn:country_code":"TD",
    "gn:dem":865,
    "gn:feature_class":"P",
    "gn:feature_code":"PPL",
    "gn:name":"Kodolok",
    "gn:population":0,
    "gn:timezone":"Africa/Ndjamena",
    "iso:country":"TD",
    "wof:name":"Kodolok",
    "wof:placetype":"locality"
},
  "geometry": {"coordinates":[21.88266,13.47474],"type":"Point"}
}