{
  "type": "Feature",
  "properties": {
    "gn:admin1_code":"20.0",
    "gn:asciiname":"Keuni",
    "gn:country_code":"TD",
    "gn:dem":479,
    "gn:feature_class":"P",
    "gn:feature_code":"PPL",
    "gn:name":"K\u00e9uni",
    "gn:population":0,
    "gn:timezone":"Africa/Ndjamena",
    "iso:country":"TD",
    "name:und_x_variant":[
        "Keun",
        "K\u00e9uni"
    ],
    "wof:name":"Keuni",
    "wof:placetype":"locality"
},
  "geometry": {"coordinates":[15.32298,8.7396],"type":"Point"}
}