{
  "type": "Feature",
  "properties": {
    "gn:admin1_code":"1.0",
    "gn:asciiname":"Abd er Rasoul",
    "gn:country_code":"TD",
    "gn:dem":345,
    "gn:feature_class":"P",
    "gn:feature_code":"PPL",
    "gn:name":"Abd er Rasoul",
    "gn:population":0,
    "gn:timezone":"Africa/Ndjamena",
    "iso:country":"TD",
    "name:und_x_variant":[
        "Abd en Rasou",
        "Abd er Rasoul"
    ],
    "wof:name":"Abd er Rasoul",
    "wof:placetype":"locality"
},
  "geometry": {"coordinates":[18.64667,13.50556],"type":"Point"}
}