{
  "type": "Feature",
  "properties": {
    "gn:admin1_code":"16.0",
    "gn:asciiname":"Fressou",
    "gn:country_code":"TD",
    "gn:dem":325,
    "gn:feature_class":"P",
    "gn:feature_code":"PPL",
    "gn:name":"Fressou",
    "gn:population":0,
    "gn:timezone":"Africa/Ndjamena",
    "iso:country":"TD",
    "name:und_x_variant":[
        "Fiaraissou",
        "Fressou"
    ],
    "wof:name":"Fressou",
    "wof:placetype":"locality"
},
  "geometry": {"coordinates":[15.27846,10.41298],"type":"Point"}
}