{
  "type": "Feature",
  "properties": {
    "gn:admin1_code":"6.0",
    "gn:asciiname":"Ganasanga",
    "gn:country_code":"TD",
    "gn:dem":352,
    "gn:feature_class":"P",
    "gn:feature_code":"PPL",
    "gn:name":"Ganasanga",
    "gn:population":0,
    "gn:timezone":"Africa/Ndjamena",
    "iso:country":"TD",
    "wof:name":"Ganasanga",
    "wof:placetype":"locality"
},
  "geometry": {"coordinates":[14.82941,14.47273],"type":"Point"}
}