{
  "type": "Feature",
  "properties": {
    "gn:admin1_code":"25.0",
    "gn:asciiname":"Kaio",
    "gn:country_code":"TD",
    "gn:dem":552,
    "gn:feature_class":"P",
    "gn:feature_code":"PPL",
    "gn:name":"Kaio",
    "gn:population":0,
    "gn:timezone":"Africa/Ndjamena",
    "iso:country":"TD",
    "name:ceb_x_preferred":[
        "Kaio"
    ],
    "name:fra_x_preferred":[
        "Kaio"
    ],
    "name:ita_x_preferred":[
        "Kaio"
    ],
    "name:swe_x_preferred":[
        "Kaio"
    ],
    "name:und_x_variant":[
        "Kayo",
        "Keiso"
    ],
    "wof:name":"Kaio",
    "wof:placetype":"locality"
},
  "geometry": {"coordinates":[21.06667,12.33333],"type":"Point"}
}