{
  "type": "Feature",
  "properties": {
    "gn:admin1_code":"17.0",
    "gn:asciiname":"Garou",
    "gn:country_code":"TD",
    "gn:dem":393,
    "gn:feature_class":"P",
    "gn:feature_code":"PPL",
    "gn:name":"Garou",
    "gn:population":0,
    "gn:timezone":"Africa/Ndjamena",
    "iso:country":"TD",
    "name:ceb_x_preferred":[
        "Garou"
    ],
    "name:deu_x_preferred":[
        "Garou"
    ],
    "name:fra_x_preferred":[
        "Garou"
    ],
    "name:por_x_preferred":[
        "Garou"
    ],
    "name:ron_x_preferred":[
        "Garou"
    ],
    "name:spa_x_preferred":[
        "Garou"
    ],
    "name:swe_x_preferred":[
        "Garou"
    ],
    "wof:name":"Garou",
    "wof:placetype":"locality"
},
  "geometry": {"coordinates":[19.082,9.6218],"type":"Point"}
}