{
  "type": "Feature",
  "properties": {
    "gn:admin1_code":"7.0",
    "gn:asciiname":"Gala Sangada",
    "gn:country_code":"TD",
    "gn:dem":312,
    "gn:feature_class":"P",
    "gn:feature_code":"PPL",
    "gn:name":"Gala Sangada",
    "gn:population":0,
    "gn:timezone":"Africa/Ndjamena",
    "iso:country":"TD",
    "wof:name":"Gala Sangada",
    "wof:placetype":"locality"
},
  "geometry": {"coordinates":[15.24405,13.71616],"type":"Point"}
}