{
  "type": "Feature",
  "properties": {
    "gn:admin1_code":"13.0",
    "gn:asciiname":"Hadjer Meram",
    "gn:country_code":"TD",
    "gn:dem":485,
    "gn:feature_class":"P",
    "gn:feature_code":"PPL",
    "gn:name":"Hadjer M\u00e9ram",
    "gn:population":0,
    "gn:timezone":"Africa/Ndjamena",
    "iso:country":"TD",
    "name:und_x_variant":[
        "Hadjer Meyram",
        "Hadjer M\u00e9ram"
    ],
    "wof:name":"Hadjer Meram",
    "wof:placetype":"locality"
},
  "geometry": {"coordinates":[21.80392,11.48042],"type":"Point"}
}