{
  "type": "Feature",
  "properties": {
    "gn:admin1_code":"9.0",
    "gn:asciiname":"Bekia",
    "gn:country_code":"TD",
    "gn:dem":421,
    "gn:feature_class":"P",
    "gn:feature_code":"PPL",
    "gn:name":"B\u00e9kia",
    "gn:population":0,
    "gn:timezone":"Africa/Ndjamena",
    "iso:country":"TD",
    "name:fra_x_preferred":[
        "B\u00e9kia"
    ],
    "wof:name":"Bekia",
    "wof:placetype":"locality"
},
  "geometry": {"coordinates":[16.53855,8.4621],"type":"Point"}
}