{
  "type": "Feature",
  "properties": {
    "gn:admin1_code":"13.0",
    "gn:asciiname":"Badie",
    "gn:country_code":"TD",
    "gn:dem":416,
    "gn:feature_class":"P",
    "gn:feature_code":"PPL",
    "gn:name":"Badi\u00e9",
    "gn:population":0,
    "gn:timezone":"Africa/Ndjamena",
    "iso:country":"TD",
    "name:ceb_x_preferred":[
        "Badie"
    ],
    "name:deu_x_preferred":[
        "Badie"
    ],
    "name:fra_x_preferred":[
        "Badie"
    ],
    "name:swe_x_preferred":[
        "Badie"
    ],
    "name:und_x_variant":[
        "Badji",
        "Badi\u00e9"
    ],
    "wof:name":"Badie",
    "wof:placetype":"locality"
},
  "geometry": {"coordinates":[20.9083,10.0403],"type":"Point"}
}