{
  "type": "Feature",
  "properties": {
    "gn:admin1_code":"2.0",
    "gn:asciiname":"Omena",
    "gn:country_code":"TD",
    "gn:dem":938,
    "gn:feature_class":"P",
    "gn:feature_code":"PPL",
    "gn:name":"Om\u00e9na",
    "gn:population":0,
    "gn:timezone":"Africa/Ndjamena",
    "iso:country":"TD",
    "name:fra_x_preferred":[
        "Om\u00e9na"
    ],
    "name:fra_x_variant":[
        "Omona"
    ],
    "wof:name":"Omena",
    "wof:placetype":"locality"
},
  "geometry": {"coordinates":[21.90248,14.09987],"type":"Point"}
}