{
  "type": "Feature",
  "properties": {
    "gn:admin1_code":"20.0",
    "gn:asciiname":"Baguenda",
    "gn:country_code":"TD",
    "gn:dem":394,
    "gn:feature_class":"P",
    "gn:feature_code":"PPL",
    "gn:name":"Baguenda",
    "gn:population":0,
    "gn:timezone":"Africa/Ndjamena",
    "iso:country":"TD",
    "name:und_x_variant":[
        "Bagenda",
        "Baguenda"
    ],
    "wof:name":"Baguenda",
    "wof:placetype":"locality"
},
  "geometry": {"coordinates":[15.11446,9.02089],"type":"Point"}
}