{
  "type": "Feature",
  "properties": {
    "gn:admin1_code":"9.0",
    "gn:asciiname":"Nara",
    "gn:country_code":"TD",
    "gn:dem":397,
    "gn:feature_class":"P",
    "gn:feature_code":"PPL",
    "gn:name":"Nara",
    "gn:population":0,
    "gn:timezone":"Africa/Ndjamena",
    "iso:country":"TD",
    "wof:name":"Nara",
    "wof:placetype":"locality"
},
  "geometry": {"coordinates":[16.64779,8.62936],"type":"Point"}
}