{
  "type": "Feature",
  "properties": {
    "gn:admin1_code":"15.0",
    "gn:asciiname":"El Birke",
    "gn:country_code":"TD",
    "gn:dem":296,
    "gn:feature_class":"P",
    "gn:feature_code":"PPL",
    "gn:name":"El Birk\u00e9",
    "gn:population":0,
    "gn:timezone":"Africa/Ndjamena",
    "iso:country":"TD",
    "name:und_x_variant":[
        "Eberike",
        "El Birk\u00e9"
    ],
    "wof:name":"El Birke",
    "wof:placetype":"locality"
},
  "geometry": {"coordinates":[15.78502,12.24276],"type":"Point"}
}