{
  "type": "Feature",
  "properties": {
    "gn:admin1_code":"14.0",
    "gn:asciiname":"Nangda",
    "gn:country_code":"TD",
    "gn:dem":345,
    "gn:feature_class":"P",
    "gn:feature_code":"PPL",
    "gn:name":"Nangda",
    "gn:population":0,
    "gn:timezone":"Africa/Ndjamena",
    "iso:country":"TD",
    "wof:name":"Nangda",
    "wof:placetype":"locality"
},
  "geometry": {"coordinates":[16.7071,9.6264],"type":"Point"}
}