{
  "type": "Feature",
  "properties": {
    "gn:admin1_code":"7.0",
    "gn:asciiname":"Kadar",
    "gn:country_code":"TD",
    "gn:dem":297,
    "gn:feature_class":"P",
    "gn:feature_code":"PPL",
    "gn:name":"Kadar",
    "gn:population":0,
    "gn:timezone":"Africa/Ndjamena",
    "iso:country":"TD",
    "name:ceb_x_preferred":[
        "Kadar"
    ],
    "name:fra_x_preferred":[
        "Kadar"
    ],
    "name:kor_x_preferred":[
        "\uce74\ub2e4\ub974"
    ],
    "name:swe_x_preferred":[
        "Kadar"
    ],
    "wof:name":"Kadar",
    "wof:placetype":"locality"
},
  "geometry": {"coordinates":[15.77383,13.60222],"type":"Point"}
}