{
  "type": "Feature",
  "properties": {
    "gn:admin1_code":"17.0",
    "gn:asciiname":"Ouarouan",
    "gn:country_code":"TD",
    "gn:dem":411,
    "gn:feature_class":"P",
    "gn:feature_code":"PPL",
    "gn:name":"Ouarouan",
    "gn:population":0,
    "gn:timezone":"Africa/Ndjamena",
    "iso:country":"TD",
    "name:und_x_variant":[
        "Ouariouan",
        "Ouarouan"
    ],
    "wof:name":"Ouarouan",
    "wof:placetype":"locality"
},
  "geometry": {"coordinates":[18.06367,9.24867],"type":"Point"}
}