{
  "type": "Feature",
  "properties": {
    "gn:admin1_code":"9.0",
    "gn:asciiname":"Mbiri",
    "gn:country_code":"TD",
    "gn:dem":557,
    "gn:feature_class":"P",
    "gn:feature_code":"PPL",
    "gn:name":"Mbiri",
    "gn:population":0,
    "gn:timezone":"Africa/Ndjamena",
    "iso:country":"TD",
    "wof:name":"Mbiri",
    "wof:placetype":"locality"
},
  "geometry": {"coordinates":[15.57025,7.87672],"type":"Point"}
}