{
  "type": "Feature",
  "properties": {
    "gn:admin1_code":"5.0",
    "gn:asciiname":"Bitchotchi Himera",
    "gn:country_code":"TD",
    "gn:dem":396,
    "gn:feature_class":"P",
    "gn:feature_code":"PPL",
    "gn:name":"Bitchotchi Him\u00e9ra",
    "gn:population":0,
    "gn:timezone":"Africa/Ndjamena",
    "iso:country":"TD",
    "name:und_x_variant":[
        "Bitchochi Him\u00e9ra",
        "Bitchotchi Him\u00e9ra"
    ],
    "wof:name":"Bitchotchi Himera",
    "wof:placetype":"locality"
},
  "geometry": {"coordinates":[19.5886,12.7919],"type":"Point"}
}