{
  "type": "Feature",
  "properties": {
    "gn:admin1_code":"19.0",
    "gn:asciiname":"Guidikouti",
    "gn:country_code":"TD",
    "gn:dem":397,
    "gn:feature_class":"P",
    "gn:feature_code":"PPL",
    "gn:name":"Guidikouti",
    "gn:population":0,
    "gn:timezone":"Africa/Ndjamena",
    "iso:country":"TD",
    "name:und_x_variant":[
        "Guidikoutou",
        "Gu\u00e9dikouti",
        "Guidikouti"
    ],
    "wof:name":"Guidikouti",
    "wof:placetype":"locality"
},
  "geometry": {"coordinates":[17.6909,8.0609],"type":"Point"}
}