{
  "type": "Feature",
  "properties": {
    "gn:admin1_code":"1.0",
    "gn:asciiname":"Ngara Ouandi",
    "gn:country_code":"TD",
    "gn:dem":346,
    "gn:feature_class":"P",
    "gn:feature_code":"PPL",
    "gn:name":"Ngara Ouandi",
    "gn:population":0,
    "gn:timezone":"Africa/Ndjamena",
    "iso:country":"TD",
    "name:und_x_variant":[
        "Am Garouendi",
        "Garouendi",
        "Ngara Ouandi"
    ],
    "wof:name":"Ngara Ouandi",
    "wof:placetype":"locality"
},
  "geometry": {"coordinates":[18.6312,13.2767],"type":"Point"}
}