{
  "type": "Feature",
  "properties": {
    "gn:admin1_code":"12.0",
    "gn:asciiname":"Kamnagan",
    "gn:country_code":"TD",
    "gn:dem":430,
    "gn:feature_class":"P",
    "gn:feature_code":"PPL",
    "gn:name":"Kamnagan",
    "gn:population":0,
    "gn:timezone":"Africa/Ndjamena",
    "iso:country":"TD",
    "name:und_x_variant":[
        "Kamana",
        "Kamnagan"
    ],
    "wof:name":"Kamnagan",
    "wof:placetype":"locality"
},
  "geometry": {"coordinates":[20.22363,13.67204],"type":"Point"}
}