{
  "type": "Feature",
  "properties": {
    "gn:admin1_code":"17.0",
    "gn:asciiname":"Mangara",
    "gn:country_code":"TD",
    "gn:dem":371,
    "gn:feature_class":"P",
    "gn:feature_code":"PPL",
    "gn:name":"Mangara",
    "gn:population":0,
    "gn:timezone":"Africa/Ndjamena",
    "iso:country":"TD",
    "wof:name":"Mangara",
    "wof:placetype":"locality"
},
  "geometry": {"coordinates":[18.07573,8.99437],"type":"Point"}
}