{
  "type": "Feature",
  "properties": {
    "gn:admin1_code":"16.0",
    "gn:asciiname":"Domo Dalao",
    "gn:country_code":"TD",
    "gn:dem":354,
    "gn:feature_class":"P",
    "gn:feature_code":"PPL",
    "gn:name":"Domo Dalao",
    "gn:population":0,
    "gn:timezone":"Africa/Ndjamena",
    "iso:country":"TD",
    "name:und_x_variant":[
        "Dalao",
        "Domo Dalao"
    ],
    "wof:name":"Domo Dalao",
    "wof:placetype":"locality"
},
  "geometry": {"coordinates":[15.63284,9.57271],"type":"Point"}
}