{
  "type": "Feature",
  "properties": {
    "gn:admin1_code":"25.0",
    "gn:asciiname":"Damre",
    "gn:country_code":"TD",
    "gn:dem":507,
    "gn:feature_class":"P",
    "gn:feature_code":"PPL",
    "gn:name":"Damr\u00e9",
    "gn:population":0,
    "gn:timezone":"Africa/Ndjamena",
    "iso:country":"TD",
    "wof:name":"Damre",
    "wof:placetype":"locality"
},
  "geometry": {"coordinates":[21.61711,11.98539],"type":"Point"}
}