{
  "type": "Feature",
  "properties": {
    "gn:admin1_code":"16.0",
    "gn:asciiname":"Sondogo",
    "gn:country_code":"TD",
    "gn:dem":341,
    "gn:feature_class":"P",
    "gn:feature_code":"PPL",
    "gn:name":"Sondogo",
    "gn:population":0,
    "gn:timezone":"Africa/Ndjamena",
    "iso:country":"TD",
    "wof:name":"Sondogo",
    "wof:placetype":"locality"
},
  "geometry": {"coordinates":[15.9747,9.9862],"type":"Point"}
}