{
  "type": "Feature",
  "properties": {
    "gn:admin1_code":"18.0",
    "gn:asciiname":"Tordona",
    "gn:country_code":"TD",
    "gn:dem":332,
    "gn:feature_class":"P",
    "gn:feature_code":"PPL",
    "gn:name":"Tordona",
    "gn:population":0,
    "gn:timezone":"Africa/Ndjamena",
    "iso:country":"TD",
    "wof:name":"Tordona",
    "wof:placetype":"locality"
},
  "geometry": {"coordinates":[17.2829,11.875],"type":"Point"}
}