{
  "type": "Feature",
  "properties": {
    "gn:admin1_code":"2.0",
    "gn:asciiname":"Tazere",
    "gn:country_code":"TD",
    "gn:dem":479,
    "gn:feature_class":"P",
    "gn:feature_code":"PPL",
    "gn:name":"Taz\u00e9r\u00e9",
    "gn:population":0,
    "gn:timezone":"Africa/Ndjamena",
    "iso:country":"TD",
    "name:und_x_variant":[
        "Taj\u00e9r\u00e9",
        "Taz\u00e9r\u00e9"
    ],
    "wof:name":"Tazere",
    "wof:placetype":"locality"
},
  "geometry": {"coordinates":[20.7169,14.78652],"type":"Point"}
}