{
  "type": "Feature",
  "properties": {
    "gn:admin1_code":"17.0",
    "gn:asciiname":"Ngam",
    "gn:country_code":"TD",
    "gn:dem":375,
    "gn:feature_class":"P",
    "gn:feature_code":"PPL",
    "gn:name":"Ngam",
    "gn:population":0,
    "gn:timezone":"Africa/Ndjamena",
    "iso:country":"TD",
    "wof:name":"Ngam",
    "wof:placetype":"locality"
},
  "geometry": {"coordinates":[18.1681,8.6619],"type":"Point"}
}