{
  "type": "Feature",
  "properties": {
    "gn:admin1_code":"5.0",
    "gn:asciiname":"Sombolo",
    "gn:country_code":"TD",
    "gn:dem":482,
    "gn:feature_class":"P",
    "gn:feature_code":"PPL",
    "gn:name":"Sombolo",
    "gn:population":0,
    "gn:timezone":"Africa/Ndjamena",
    "iso:country":"TD",
    "name:und_x_variant":[
        "Sambolo",
        "Sombolo"
    ],
    "wof:name":"Sombolo",
    "wof:placetype":"locality"
},
  "geometry": {"coordinates":[18.23067,11.15381],"type":"Point"}
}