{
  "type": "Feature",
  "properties": {
    "gn:admin1_code":"6.0",
    "gn:asciiname":"Lar",
    "gn:country_code":"TD",
    "gn:dem":302,
    "gn:feature_class":"P",
    "gn:feature_code":"PPL",
    "gn:name":"Lar",
    "gn:population":0,
    "gn:timezone":"Africa/Ndjamena",
    "iso:country":"TD",
    "wof:name":"Lar",
    "wof:placetype":"locality"
},
  "geometry": {"coordinates":[14.21703,14.26324],"type":"Point"}
}