{
  "type": "Feature",
  "properties": {
    "gn:admin1_code":"25.0",
    "gn:asciiname":"Abilelay",
    "gn:country_code":"TD",
    "gn:dem":564,
    "gn:feature_class":"P",
    "gn:feature_code":"PPL",
    "gn:name":"Abil\u00e9lay",
    "gn:population":0,
    "gn:timezone":"Africa/Ndjamena",
    "iso:country":"TD",
    "name:und_x_variant":[
        "Abilelaye",
        "Abil\u00e9lay"
    ],
    "wof:name":"Abilelay",
    "wof:placetype":"locality"
},
  "geometry": {"coordinates":[22.11667000000001,12.06667],"type":"Point"}
}