{
  "type": "Feature",
  "properties": {
    "gn:admin1_code":"18.0",
    "gn:asciiname":"Ouroulla",
    "gn:country_code":"TD",
    "gn:dem":293,
    "gn:feature_class":"P",
    "gn:feature_code":"PPL",
    "gn:name":"Ouroulla",
    "gn:population":0,
    "gn:timezone":"Africa/Ndjamena",
    "iso:country":"TD",
    "name:und_x_variant":[
        "Ouroula",
        "Ouroulla"
    ],
    "wof:name":"Ouroulla",
    "wof:placetype":"locality"
},
  "geometry": {"coordinates":[15.31327,12.51199],"type":"Point"}
}