{
  "type": "Feature",
  "properties": {
    "gn:admin1_code":"15.0",
    "gn:asciiname":"Kaba",
    "gn:country_code":"TD",
    "gn:dem":331,
    "gn:feature_class":"P",
    "gn:feature_code":"PPL",
    "gn:name":"Kaba",
    "gn:population":0,
    "gn:timezone":"Africa/Ndjamena",
    "iso:country":"TD",
    "name:und_x_variant":[
        "Koba",
        "Kaba"
    ],
    "wof:name":"Kaba",
    "wof:placetype":"locality"
},
  "geometry": {"coordinates":[16.3162,10.697],"type":"Point"}
}