{
  "type": "Feature",
  "properties": {
    "gn:admin1_code":"2.0",
    "gn:asciiname":"Niabourne",
    "gn:country_code":"TD",
    "gn:dem":1026,
    "gn:feature_class":"P",
    "gn:feature_code":"PPL",
    "gn:name":"Niabourn\u00e9",
    "gn:population":0,
    "gn:timezone":"Africa/Ndjamena",
    "iso:country":"TD",
    "wof:name":"Niabourne",
    "wof:placetype":"locality"
},
  "geometry": {"coordinates":[22.06667,14.36667],"type":"Point"}
}