{
  "type": "Feature",
  "properties": {
    "gn:admin1_code":"17.0",
    "gn:asciiname":"Make",
    "gn:country_code":"TD",
    "gn:dem":465,
    "gn:feature_class":"P",
    "gn:feature_code":"PPL",
    "gn:name":"Mak\u00e9",
    "gn:population":0,
    "gn:timezone":"Africa/Ndjamena",
    "iso:country":"TD",
    "name:ceb_x_preferred":[
        "Make"
    ],
    "name:dan_x_preferred":[
        "Make"
    ],
    "name:ita_x_preferred":[
        "Make"
    ],
    "name:jpn_x_preferred":[
        "\u30e1\u30a4\u30af"
    ],
    "name:kor_x_preferred":[
        "\uba54\uc774\ud06c"
    ],
    "name:nld_x_preferred":[
        "Make"
    ],
    "name:swe_x_preferred":[
        "Make"
    ],
    "wof:name":"Make",
    "wof:placetype":"locality"
},
  "geometry": {"coordinates":[18.86667000000001,9.51667],"type":"Point"}
}