{
  "type": "Feature",
  "properties": {
    "gn:admin1_code":"7.0",
    "gn:asciiname":"Kirom",
    "gn:country_code":"TD",
    "gn:dem":302,
    "gn:feature_class":"P",
    "gn:feature_code":"PPL",
    "gn:name":"Kirom",
    "gn:population":0,
    "gn:timezone":"Africa/Ndjamena",
    "iso:country":"TD",
    "wof:name":"Kirom",
    "wof:placetype":"locality"
},
  "geometry": {"coordinates":[15.60828,13.49584],"type":"Point"}
}