{
  "type": "Feature",
  "properties": {
    "gn:admin1_code":"12.0",
    "gn:asciiname":"Metie",
    "gn:country_code":"TD",
    "gn:dem":745,
    "gn:feature_class":"P",
    "gn:feature_code":"PPL",
    "gn:name":"M\u00e9ti\u00e9",
    "gn:population":0,
    "gn:timezone":"Africa/Ndjamena",
    "iso:country":"TD",
    "wof:name":"Metie",
    "wof:placetype":"locality"
},
  "geometry": {"coordinates":[21.89922,13.21143],"type":"Point"}
}