{
  "type": "Feature",
  "properties": {
    "gn:admin1_code":"15.0",
    "gn:asciiname":"Bourou",
    "gn:country_code":"TD",
    "gn:dem":303,
    "gn:feature_class":"P",
    "gn:feature_code":"PPL",
    "gn:name":"Bourou",
    "gn:population":0,
    "gn:timezone":"Africa/Ndjamena",
    "iso:country":"TD",
    "name:azb_x_preferred":[
        "\u0628\u0648\u0631\u0648"
    ],
    "name:ceb_x_preferred":[
        "Bourou"
    ],
    "name:fas_x_preferred":[
        "\u0628\u0648\u0631\u0648"
    ],
    "name:fra_x_preferred":[
        "Bourou"
    ],
    "name:ita_x_preferred":[
        "Bourou"
    ],
    "name:swe_x_preferred":[
        "Bourou"
    ],
    "wof:name":"Bourou",
    "wof:placetype":"locality"
},
  "geometry": {"coordinates":[15.46749,11.80309],"type":"Point"}
}