{
  "type": "Feature",
  "properties": {
    "gn:admin1_code":"9.0",
    "gn:asciiname":"Bembaida",
    "gn:country_code":"TD",
    "gn:dem":438,
    "gn:feature_class":"P",
    "gn:feature_code":"PPL",
    "gn:name":"B\u00e8mba\u00efda",
    "gn:population":0,
    "gn:timezone":"Africa/Ndjamena",
    "iso:country":"TD",
    "wof:name":"Bembaida",
    "wof:placetype":"locality"
},
  "geometry": {"coordinates":[15.9082,8.1359],"type":"Point"}
}