{
  "type": "Feature",
  "properties": {
    "gn:admin1_code":"1.0",
    "gn:asciiname":"Matabgue",
    "gn:country_code":"TD",
    "gn:dem":352,
    "gn:feature_class":"P",
    "gn:feature_code":"PPL",
    "gn:name":"Matabgue",
    "gn:population":0,
    "gn:timezone":"Africa/Ndjamena",
    "iso:country":"TD",
    "name:und_x_variant":[
        "Matabge",
        "Matabgue"
    ],
    "wof:name":"Matabgue",
    "wof:placetype":"locality"
},
  "geometry": {"coordinates":[18.85193,12.99311],"type":"Point"}
}