{
  "type": "Feature",
  "properties": {
    "gn:admin1_code":"1.0",
    "gn:asciiname":"Al Mahagar",
    "gn:country_code":"TD",
    "gn:dem":340,
    "gn:feature_class":"P",
    "gn:feature_code":"PPL",
    "gn:name":"Al Mahagar",
    "gn:population":0,
    "gn:timezone":"Africa/Ndjamena",
    "iso:country":"TD",
    "name:und_x_variant":[
        "Mahaggar",
        "Al Mahagar"
    ],
    "wof:name":"Al Mahagar",
    "wof:placetype":"locality"
},
  "geometry": {"coordinates":[18.4924,13.197],"type":"Point"}
}