{
  "type": "Feature",
  "properties": {
    "gn:admin1_code":"12.0",
    "gn:asciiname":"Guendour",
    "gn:country_code":"TD",
    "gn:dem":583,
    "gn:feature_class":"P",
    "gn:feature_code":"PPL",
    "gn:name":"Guendour",
    "gn:population":0,
    "gn:timezone":"Africa/Ndjamena",
    "iso:country":"TD",
    "name:und_x_variant":[
        "Gendour"
    ],
    "wof:name":"Guendour",
    "wof:placetype":"locality"
},
  "geometry": {"coordinates":[21.3455,13.2288],"type":"Point"}
}