{
  "type": "Feature",
  "properties": {
    "gn:admin1_code":"14.0",
    "gn:asciiname":"Pounabaye",
    "gn:country_code":"TD",
    "gn:dem":348,
    "gn:feature_class":"P",
    "gn:feature_code":"PPL",
    "gn:name":"Pounabaye",
    "gn:population":0,
    "gn:timezone":"Africa/Ndjamena",
    "iso:country":"TD",
    "wof:name":"Pounabaye",
    "wof:placetype":"locality"
},
  "geometry": {"coordinates":[16.7553,9.6113],"type":"Point"}
}