{
  "type": "Feature",
  "properties": {
    "gn:admin1_code":"19.0",
    "gn:asciiname":"Moussongouli",
    "gn:country_code":"TD",
    "gn:dem":398,
    "gn:feature_class":"P",
    "gn:feature_code":"PPL",
    "gn:name":"Moussongouli",
    "gn:population":0,
    "gn:timezone":"Africa/Ndjamena",
    "iso:country":"TD",
    "name:und_x_variant":[
        "Moussogoli",
        "Moussongouli"
    ],
    "wof:name":"Moussongouli",
    "wof:placetype":"locality"
},
  "geometry": {"coordinates":[17.69501,8.86677],"type":"Point"}
}