{
  "type": "Feature",
  "properties": {
    "gn:admin1_code":"22.0",
    "gn:asciiname":"Koremanga",
    "gn:country_code":"TD",
    "gn:dem":305,
    "gn:feature_class":"P",
    "gn:feature_code":"PPL",
    "gn:name":"Koremanga",
    "gn:population":0,
    "gn:timezone":"Africa/Ndjamena",
    "iso:country":"TD",
    "wof:name":"Koremanga",
    "wof:placetype":"locality"
},
  "geometry": {"coordinates":[15.69067,13.79383],"type":"Point"}
}