{
  "type": "Feature",
  "properties": {
    "gn:admin1_code":"14.0",
    "gn:asciiname":"Tchaka",
    "gn:country_code":"TD",
    "gn:dem":393,
    "gn:feature_class":"P",
    "gn:feature_code":"PPL",
    "gn:name":"Tchaka",
    "gn:population":0,
    "gn:timezone":"Africa/Ndjamena",
    "iso:country":"TD",
    "wof:name":"Tchaka",
    "wof:placetype":"locality"
},
  "geometry": {"coordinates":[16.1262,9.0853],"type":"Point"}
}