{
  "type": "Feature",
  "properties": {
    "gn:admin1_code":"25.0",
    "gn:asciiname":"Abjer",
    "gn:country_code":"TD",
    "gn:dem":469,
    "gn:feature_class":"P",
    "gn:feature_code":"PPL",
    "gn:name":"Abjer",
    "gn:population":0,
    "gn:timezone":"Africa/Ndjamena",
    "iso:country":"TD",
    "wof:name":"Abjer",
    "wof:placetype":"locality"
},
  "geometry": {"coordinates":[20.53333,12.63333],"type":"Point"}
}