{
  "type": "Feature",
  "properties": {
    "gn:admin1_code":"14.0",
    "gn:asciiname":"Baguidi",
    "gn:country_code":"TD",
    "gn:dem":419,
    "gn:feature_class":"P",
    "gn:feature_code":"PPL",
    "gn:name":"Baguidi",
    "gn:population":0,
    "gn:timezone":"Africa/Ndjamena",
    "iso:country":"TD",
    "wof:name":"Baguidi",
    "wof:placetype":"locality"
},
  "geometry": {"coordinates":[16.531,9.1392],"type":"Point"}
}