{
  "type": "Feature",
  "properties": {
    "gn:admin1_code":"18.0",
    "gn:asciiname":"Arad",
    "gn:country_code":"TD",
    "gn:dem":322,
    "gn:feature_class":"P",
    "gn:feature_code":"PPL",
    "gn:name":"Arad",
    "gn:population":0,
    "gn:timezone":"Africa/Ndjamena",
    "iso:country":"TD",
    "name:bel_x_preferred":[
        "\u0410\u0440\u0430\u0434"
    ],
    "name:bul_x_preferred":[
        "\u0410\u0440\u0430\u0434"
    ],
    "name:cat_x_preferred":[
        "Arad"
    ],
    "name:ceb_x_preferred":[
        "Arad"
    ],
    "name:ces_x_preferred":[
        "Arad"
    ],
    "name:deu_x_preferred":[
        "Arad"
    ],
    "name:epo_x_preferred":[
        "Arad"
    ],
    "name:fas_x_preferred":[
        "\u0622\u0631\u0627\u062f"
    ],
    "name:fin_x_preferred":[
        "Arad"
    ],
    "name:fra_x_preferred":[
        "Arad"
    ],
    "name:fry_x_preferred":[
        "Arad"
    ],
    "name:glg_x_preferred":[
        "Arad"
    ],
    "name:heb_x_preferred":[
        "\u05d0\u05e8\u05d3"
    ],
    "name:hrv_x_preferred":[
        "Arad"
    ],
    "name:hun_x_preferred":[
        "Arad"
    ],
    "name:ido_x_preferred":[
        "Arad"
    ],
    "name:ind_x_preferred":[
        "Arad"
    ],
    "name:ita_x_preferred":[
        "Arad"
    ],
    "name:jpn_x_preferred":[
        "\u30a2\u30e9\u30c9"
    ],
    "name:kor_x_preferred":[
        "\uc544\ub77c\ub4dc"
    ],
    "name:min_x_preferred":[
        "Arad"
    ],
    "name:nld_x_preferred":[
        "Arad"
    ],
    "name:nor_x_preferred":[
        "Arad"
    ],
    "name:pol_x_preferred":[
        "Arad"
    ],
    "name:por_x_preferred":[
        "Arad"
    ],
    "name:ron_x_preferred":[
        "Arad"
    ],
    "name:rus_x_preferred":[
        "\u0410\u0440\u0430\u0434"
    ],
    "name:sco_x_preferred":[
        "Arad"
    ],
    "name:slk_x_preferred":[
        "Arad"
    ],
    "name:spa_x_preferred":[
        "Arad"
    ],
    "name:swe_x_preferred":[
        "Arad"
    ],
    "name:ukr_x_preferred":[
        "\u0410\u0440\u0430\u0434"
    ],
    "name:vie_x_preferred":[
        "Arad"
    ],
    "name:zho_x_preferred":[
        "\u963f\u62c9\u5fb7"
    ],
    "wof:name":"Arad",
    "wof:placetype":"locality"
},
  "geometry": {"coordinates":[17.1711,11.9128],"type":"Point"}
}