{
  "type": "Feature",
  "properties": {
    "gn:admin1_code":"6.0",
    "gn:asciiname":"Kalia",
    "gn:country_code":"TD",
    "gn:dem":343,
    "gn:feature_class":"P",
    "gn:feature_code":"PPL",
    "gn:name":"Kalia",
    "gn:population":0,
    "gn:timezone":"Africa/Ndjamena",
    "iso:country":"TD",
    "name:ceb_x_preferred":[
        "Kalia"
    ],
    "name:fra_x_preferred":[
        "Kalia"
    ],
    "name:ind_x_preferred":[
        "Kalia"
    ],
    "name:nld_x_preferred":[
        "Kalia"
    ],
    "name:swe_x_preferred":[
        "Kalia"
    ],
    "wof:name":"Kalia",
    "wof:placetype":"locality"
},
  "geometry": {"coordinates":[14.89611,14.31222],"type":"Point"}
}