{
  "type": "Feature",
  "properties": {
    "gn:admin1_code":"5.0",
    "gn:asciiname":"Likine",
    "gn:country_code":"TD",
    "gn:dem":480,
    "gn:feature_class":"P",
    "gn:feature_code":"PPL",
    "gn:name":"Likine",
    "gn:population":0,
    "gn:timezone":"Africa/Ndjamena",
    "iso:country":"TD",
    "name:und_x_variant":[
        "Likkin",
        "Likkine",
        "Likine"
    ],
    "wof:name":"Likine",
    "wof:placetype":"locality"
},
  "geometry": {"coordinates":[18.1591,11.3637],"type":"Point"}
}