{
  "type": "Feature",
  "properties": {
    "gn:admin1_code":"16.0",
    "gn:asciiname":"Miogoye",
    "gn:country_code":"TD",
    "gn:dem":329,
    "gn:feature_class":"P",
    "gn:feature_code":"PPL",
    "gn:name":"Miogoye",
    "gn:population":0,
    "gn:timezone":"Africa/Ndjamena",
    "iso:country":"TD",
    "name:und_x_variant":[
        "Mioga\u00ef",
        "Miogaye",
        "Miogoye"
    ],
    "wof:name":"Miogoye",
    "wof:placetype":"locality"
},
  "geometry": {"coordinates":[15.44016,10.27164],"type":"Point"}
}