{
  "type": "Feature",
  "properties": {
    "gn:admin1_code":"9.0",
    "gn:asciiname":"Berre",
    "gn:country_code":"TD",
    "gn:dem":436,
    "gn:feature_class":"P",
    "gn:feature_code":"PPL",
    "gn:name":"Berr\u00e9",
    "gn:population":0,
    "gn:timezone":"Africa/Ndjamena",
    "iso:country":"TD",
    "name:ceb_x_preferred":[
        "Berre"
    ],
    "name:deu_x_preferred":[
        "Berre"
    ],
    "name:fra_x_preferred":[
        "Berre"
    ],
    "name:ita_x_preferred":[
        "Berre"
    ],
    "name:nld_x_preferred":[
        "Berre"
    ],
    "name:oci_x_preferred":[
        "B\u00e8rra"
    ],
    "name:swe_x_preferred":[
        "Berre"
    ],
    "wof:name":"Berre",
    "wof:placetype":"locality"
},
  "geometry": {"coordinates":[16.56667,7.95],"type":"Point"}
}