{
  "type": "Feature",
  "properties": {
    "gn:admin1_code":"9.0",
    "gn:asciiname":"Berre",
    "gn:country_code":"TD",
    "gn:dem":436,
    "gn:feature_class":"P",
    "gn:feature_code":"PPL",
    "gn:name":"Berr\u00e9",
    "gn:population":0,
    "gn:timezone":"Africa/Ndjamena",
    "iso:country":"TD",
    "wof:name":"Berre",
    "wof:placetype":"locality"
},
  "geometry": {"coordinates":[16.56667,7.95],"type":"Point"}
}