{
  "type": "Feature",
  "properties": {
    "gn:admin1_code":"14.0",
    "gn:asciiname":"Bilaka Keni",
    "gn:country_code":"TD",
    "gn:dem":401,
    "gn:feature_class":"P",
    "gn:feature_code":"PPL",
    "gn:name":"Bilaka K\u00e9ni",
    "gn:population":0,
    "gn:timezone":"Africa/Ndjamena",
    "iso:country":"TD",
    "wof:name":"Bilaka Keni",
    "wof:placetype":"locality"
},
  "geometry": {"coordinates":[15.69843,9.05387],"type":"Point"}
}