{
  "type": "Feature",
  "properties": {
    "gn:admin1_code":"15.0",
    "gn:asciiname":"Balday",
    "gn:country_code":"TD",
    "gn:dem":308,
    "gn:feature_class":"P",
    "gn:feature_code":"PPL",
    "gn:name":"Balday",
    "gn:population":0,
    "gn:timezone":"Africa/Ndjamena",
    "iso:country":"TD",
    "wof:name":"Balday",
    "wof:placetype":"locality"
},
  "geometry": {"coordinates":[16.2508,11.9356],"type":"Point"}
}