{
  "type": "Feature",
  "properties": {
    "gn:admin1_code":"25.0",
    "gn:asciiname":"Toundousa",
    "gn:country_code":"TD",
    "gn:dem":698,
    "gn:feature_class":"P",
    "gn:feature_code":"PPL",
    "gn:name":"Toundousa",
    "gn:population":0,
    "gn:timezone":"Africa/Ndjamena",
    "iso:country":"TD",
    "wof:name":"Toundousa",
    "wof:placetype":"locality"
},
  "geometry": {"coordinates":[21.75,12.75],"type":"Point"}
}