{
  "type": "Feature",
  "properties": {
    "gn:admin1_code":"9.0",
    "gn:asciiname":"Doungabo",
    "gn:country_code":"TD",
    "gn:dem":395,
    "gn:feature_class":"P",
    "gn:feature_code":"PPL",
    "gn:name":"Doungabo",
    "gn:population":0,
    "gn:timezone":"Africa/Ndjamena",
    "iso:country":"TD",
    "wof:name":"Doungabo",
    "wof:placetype":"locality"
},
  "geometry": {"coordinates":[16.65897,8.68079],"type":"Point"}
}