{
  "type": "Feature",
  "properties": {
    "gn:admin1_code":"5.0",
    "gn:asciiname":"Dabakay Sofera",
    "gn:country_code":"TD",
    "gn:dem":382,
    "gn:feature_class":"P",
    "gn:feature_code":"PPL",
    "gn:name":"Dabakay Sof\u00e9ra",
    "gn:population":0,
    "gn:timezone":"Africa/Ndjamena",
    "iso:country":"TD",
    "name:und_x_variant":[
        "Diabaca\u00ef",
        "Dabakay",
        "Dabaka\u00ef Sefer",
        "Dabakay Sof\u00e9ra"
    ],
    "wof:name":"Dabakay Sofera",
    "wof:placetype":"locality"
},
  "geometry": {"coordinates":[17.971,11.0656],"type":"Point"}
}