{
  "type": "Feature",
  "properties": {
    "gn:admin1_code":"17.0",
    "gn:asciiname":"Bar",
    "gn:country_code":"TD",
    "gn:dem":380,
    "gn:feature_class":"P",
    "gn:feature_code":"PPL",
    "gn:name":"Bar",
    "gn:population":0,
    "gn:timezone":"Africa/Ndjamena",
    "iso:country":"TD",
    "name:ara_x_preferred":[
        "\u0628\u0627\u0631"
    ],
    "name:azb_x_preferred":[
        "\u0628\u0627\u0631"
    ],
    "name:aze_x_preferred":[
        "Bar"
    ],
    "name:bel_x_preferred":[
        "\u0411\u0430\u0440"
    ],
    "name:bre_x_preferred":[
        "Tavarn"
    ],
    "name:cat_x_preferred":[
        "Bar"
    ],
    "name:ces_x_preferred":[
        "Bar"
    ],
    "name:cym_x_preferred":[
        "Bar"
    ],
    "name:dan_x_preferred":[
        "Bar"
    ],
    "name:deu_x_preferred":[
        "Bar"
    ],
    "name:diq_x_preferred":[
        "Bar"
    ],
    "name:epo_x_preferred":[
        "Trinkejo"
    ],
    "name:est_x_preferred":[
        "Baar"
    ],
    "name:eus_x_preferred":[
        "Taberna"
    ],
    "name:fas_x_preferred":[
        "\u0628\u0627\u0631"
    ],
    "name:fin_x_preferred":[
        "Baari"
    ],
    "name:fra_x_preferred":[
        "Bar"
    ],
    "name:fry_x_preferred":[
        "Kafee"
    ],
    "name:gla_x_preferred":[
        "B\u00e0r"
    ],
    "name:heb_x_preferred":[
        "\u05d1\u05e8"
    ],
    "name:hrv_x_preferred":[
        "Bar"
    ],
    "name:ind_x_preferred":[
        "Bar"
    ],
    "name:isl_x_preferred":[
        "Bar"
    ],
    "name:ita_x_preferred":[
        "Bar"
    ],
    "name:jpn_x_preferred":[
        "\u30d0\u30fc"
    ],
    "name:kat_x_preferred":[
        "\u10d1\u10d0\u10e0\u10d8"
    ],
    "name:kor_x_preferred":[
        "\ubc14"
    ],
    "name:lim_x_preferred":[
        "Kefee"
    ],
    "name:lit_x_preferred":[
        "Baras"
    ],
    "name:nah_x_preferred":[
        "Ocnamacoyan"
    ],
    "name:nld_x_preferred":[
        "Caf\u00e9"
    ],
    "name:nor_x_preferred":[
        "Bar"
    ],
    "name:oci_x_preferred":[
        "Bar"
    ],
    "name:pol_x_preferred":[
        "Bar"
    ],
    "name:por_x_preferred":[
        "Bar"
    ],
    "name:ron_x_preferred":[
        "Bar"
    ],
    "name:rus_x_preferred":[
        "\u0411\u0430\u0440"
    ],
    "name:slv_x_preferred":[
        "Bar"
    ],
    "name:spa_x_preferred":[
        "Bar"
    ],
    "name:srp_x_preferred":[
        "Bar"
    ],
    "name:sun_x_preferred":[
        "Bar"
    ],
    "name:swe_x_preferred":[
        "Barlokal"
    ],
    "name:tam_x_preferred":[
        "\u0bae\u0ba4\u0bc1 \u0b85\u0bb0\u0bc1\u0ba8\u0bcd\u0ba4\u0b95\u0bae\u0bcd"
    ],
    "name:tur_x_preferred":[
        "Bar"
    ],
    "name:ukr_x_preferred":[
        "\u0411\u0430\u0440"
    ],
    "name:vie_x_preferred":[
        "Qu\u00e1n bar"
    ],
    "name:wln_x_preferred":[
        "C\u00e5baret"
    ],
    "name:yid_x_preferred":[
        "\u05e9\u05e2\u05e0\u05e7"
    ],
    "wof:name":"Bar",
    "wof:placetype":"locality"
},
  "geometry": {"coordinates":[18.3594,10.0558],"type":"Point"}
}