{
  "type": "Feature",
  "properties": {
    "gn:admin1_code":"12.0",
    "gn:asciiname":"Tondong",
    "gn:country_code":"TD",
    "gn:dem":820,
    "gn:feature_class":"P",
    "gn:feature_code":"PPL",
    "gn:name":"Tondong",
    "gn:population":0,
    "gn:timezone":"Africa/Ndjamena",
    "iso:country":"TD",
    "wof:name":"Tondong",
    "wof:placetype":"locality"
},
  "geometry": {"coordinates":[22.00415,13.26062],"type":"Point"}
}