{
  "type": "Feature",
  "properties": {
    "gn:admin1_code":"5.0",
    "gn:asciiname":"Dabakay Zarga",
    "gn:country_code":"TD",
    "gn:dem":395,
    "gn:feature_class":"P",
    "gn:feature_code":"PPL",
    "gn:name":"Dabakay Zarga",
    "gn:population":0,
    "gn:timezone":"Africa/Ndjamena",
    "iso:country":"TD",
    "name:und_x_variant":[
        "Zarga",
        "Dabakay Zarga"
    ],
    "wof:name":"Dabakay Zarga",
    "wof:placetype":"locality"
},
  "geometry": {"coordinates":[17.9655,11.0838],"type":"Point"}
}