{
  "type": "Feature",
  "properties": {
    "gn:admin1_code":"12.0",
    "gn:asciiname":"Berte",
    "gn:country_code":"TD",
    "gn:dem":874,
    "gn:feature_class":"P",
    "gn:feature_code":"PPL",
    "gn:name":"Bert\u00e9",
    "gn:population":0,
    "gn:timezone":"Africa/Ndjamena",
    "iso:country":"TD",
    "wof:name":"Berte",
    "wof:placetype":"locality"
},
  "geometry": {"coordinates":[22.07961,13.71628],"type":"Point"}
}