{
  "type": "Feature",
  "properties": {
    "gn:admin1_code":"2.0",
    "gn:asciiname":"Ibeyde",
    "gn:country_code":"TD",
    "gn:dem":1016,
    "gn:feature_class":"P",
    "gn:feature_code":"PPL",
    "gn:name":"Ib\u00e9yd\u00e9",
    "gn:population":0,
    "gn:timezone":"Africa/Ndjamena",
    "iso:country":"TD",
    "wof:name":"Ibeyde",
    "wof:placetype":"locality"
},
  "geometry": {"coordinates":[22.33333,14.26667],"type":"Point"}
}