{
  "type": "Feature",
  "properties": {
    "gn:admin1_code":"19.0",
    "gn:asciiname":"Bedogo I",
    "gn:country_code":"TD",
    "gn:dem":388,
    "gn:feature_class":"P",
    "gn:feature_code":"PPL",
    "gn:name":"B\u00e9dogo I",
    "gn:population":0,
    "gn:timezone":"Africa/Ndjamena",
    "iso:country":"TD",
    "wof:name":"Bedogo I",
    "wof:placetype":"locality"
},
  "geometry": {"coordinates":[17.113,8.6489],"type":"Point"}
}