{
  "type": "Feature",
  "properties": {
    "gn:admin1_code":"8.0",
    "gn:asciiname":"Bita-Ndololo",
    "gn:country_code":"TD",
    "gn:dem":459,
    "gn:feature_class":"P",
    "gn:feature_code":"PPL",
    "gn:name":"Bita-Ndololo",
    "gn:population":0,
    "gn:timezone":"Africa/Ndjamena",
    "iso:country":"TD",
    "wof:name":"Bita-Ndololo",
    "wof:placetype":"locality"
},
  "geometry": {"coordinates":[16.20662,8.8153],"type":"Point"}
}