{
  "type": "Feature",
  "properties": {
    "gn:admin1_code":"16.0",
    "gn:asciiname":"Golio",
    "gn:country_code":"TD",
    "gn:dem":316,
    "gn:feature_class":"P",
    "gn:feature_code":"PPL",
    "gn:name":"Golio",
    "gn:population":0,
    "gn:timezone":"Africa/Ndjamena",
    "iso:country":"TD",
    "wof:name":"Golio",
    "wof:placetype":"locality"
},
  "geometry": {"coordinates":[15.29779,10.54493],"type":"Point"}
}