{
  "type": "Feature",
  "properties": {
    "gn:admin1_code":"2.0",
    "gn:asciiname":"Gourfounogo",
    "gn:country_code":"TD",
    "gn:dem":621,
    "gn:feature_class":"P",
    "gn:feature_code":"PPL",
    "gn:name":"Gourfounogo",
    "gn:population":0,
    "gn:timezone":"Africa/Ndjamena",
    "iso:country":"TD",
    "wof:name":"Gourfounogo",
    "wof:placetype":"locality"
},
  "geometry": {"coordinates":[21.56667,15.08333],"type":"Point"}
}