{
  "type": "Feature",
  "properties": {
    "gn:admin1_code":"9.0",
    "gn:asciiname":"Badila",
    "gn:country_code":"TD",
    "gn:dem":446,
    "gn:feature_class":"P",
    "gn:feature_code":"PPL",
    "gn:name":"Badila",
    "gn:population":0,
    "gn:timezone":"Africa/Ndjamena",
    "iso:country":"TD",
    "wof:name":"Badila",
    "wof:placetype":"locality"
},
  "geometry": {"coordinates":[16.28691,8.35343],"type":"Point"}
}