{
  "type": "Feature",
  "properties": {
    "gn:admin1_code":"7.0",
    "gn:asciiname":"Kouokouoy Boulasari",
    "gn:country_code":"TD",
    "gn:dem":303,
    "gn:feature_class":"P",
    "gn:feature_code":"PPL",
    "gn:name":"Kouokouoy Boulasari",
    "gn:population":0,
    "gn:timezone":"Africa/Ndjamena",
    "iso:country":"TD",
    "name:und_x_variant":[
        "Boulasari",
        "Kouokouoy",
        "Kouokouoy Boulasari"
    ],
    "wof:name":"Kouokouoy Boulasari",
    "wof:placetype":"locality"
},
  "geometry": {"coordinates":[15.76727,13.43101],"type":"Point"}
}