{
  "type": "Feature",
  "properties": {
    "gn:admin1_code":"9.0",
    "gn:asciiname":"Madana",
    "gn:country_code":"TD",
    "gn:dem":424,
    "gn:feature_class":"P",
    "gn:feature_code":"PPL",
    "gn:name":"Madana",
    "gn:population":0,
    "gn:timezone":"Africa/Ndjamena",
    "iso:country":"TD",
    "wof:name":"Madana",
    "wof:placetype":"locality"
},
  "geometry": {"coordinates":[16.8028,8.3172],"type":"Point"}
}