{
  "type": "Feature",
  "properties": {
    "gn:admin1_code":"15.0",
    "gn:asciiname":"Dol",
    "gn:country_code":"TD",
    "gn:dem":333,
    "gn:feature_class":"P",
    "gn:feature_code":"PPL",
    "gn:name":"Dol",
    "gn:population":0,
    "gn:timezone":"Africa/Ndjamena",
    "iso:country":"TD",
    "name:und_x_variant":[
        "Del",
        "Dol"
    ],
    "wof:name":"Dol",
    "wof:placetype":"locality"
},
  "geometry": {"coordinates":[16.5319,11.1565],"type":"Point"}
}