{
  "type": "Feature",
  "properties": {
    "gn:admin1_code":"15.0",
    "gn:asciiname":"Dol",
    "gn:country_code":"TD",
    "gn:dem":333,
    "gn:feature_class":"P",
    "gn:feature_code":"PPL",
    "gn:name":"Dol",
    "gn:population":0,
    "gn:timezone":"Africa/Ndjamena",
    "iso:country":"TD",
    "name:aze_x_preferred":[
        "Dol"
    ],
    "name:bos_x_preferred":[
        "Dol"
    ],
    "name:ceb_x_preferred":[
        "Dol"
    ],
    "name:ces_x_preferred":[
        "Dol"
    ],
    "name:deu_x_preferred":[
        "Dol"
    ],
    "name:fra_x_preferred":[
        "Dol"
    ],
    "name:hrv_x_preferred":[
        "Dol"
    ],
    "name:hun_x_preferred":[
        "Dol"
    ],
    "name:nld_x_preferred":[
        "Dol"
    ],
    "name:pol_x_preferred":[
        "Dol"
    ],
    "name:rus_x_preferred":[
        "\u0414\u043e\u043b"
    ],
    "name:slk_x_preferred":[
        "Dol"
    ],
    "name:slv_x_preferred":[
        "Dol"
    ],
    "name:srp_x_preferred":[
        "\u0414\u043e\u043b"
    ],
    "name:swe_x_preferred":[
        "Dol"
    ],
    "name:ukr_x_preferred":[
        "\u0414\u043e\u043b"
    ],
    "name:und_x_variant":[
        "Del",
        "Dol"
    ],
    "wof:name":"Dol",
    "wof:placetype":"locality"
},
  "geometry": {"coordinates":[16.5319,11.1565],"type":"Point"}
}