{
  "type": "Feature",
  "properties": {
    "gn:admin1_code":"1.0",
    "gn:asciiname":"Gabgamsa",
    "gn:country_code":"TD",
    "gn:dem":317,
    "gn:feature_class":"P",
    "gn:feature_code":"PPL",
    "gn:name":"Gabgamsa",
    "gn:population":0,
    "gn:timezone":"Africa/Ndjamena",
    "iso:country":"TD",
    "wof:name":"Gabgamsa",
    "wof:placetype":"locality"
},
  "geometry": {"coordinates":[17.97682,12.86181],"type":"Point"}
}