{
  "type": "Feature",
  "properties": {
    "gn:admin1_code":"2.0",
    "gn:asciiname":"Koulalangue",
    "gn:country_code":"TD",
    "gn:dem":801,
    "gn:feature_class":"P",
    "gn:feature_code":"PPL",
    "gn:name":"Koulalangu\u00e9",
    "gn:population":0,
    "gn:timezone":"Africa/Ndjamena",
    "iso:country":"TD",
    "name:fra_x_preferred":[
        "Koulalangu\u00e9"
    ],
    "name:fra_x_variant":[
        "Koulalang\u00e9"
    ],
    "wof:name":"Koulalangue",
    "wof:placetype":"locality"
},
  "geometry": {"coordinates":[21.50211,14.16394],"type":"Point"}
}