{
  "type": "Feature",
  "properties": {
    "gn:admin1_code":"17.0",
    "gn:asciiname":"Kira",
    "gn:country_code":"TD",
    "gn:dem":364,
    "gn:feature_class":"P",
    "gn:feature_code":"PPL",
    "gn:name":"Kira",
    "gn:population":0,
    "gn:timezone":"Africa/Ndjamena",
    "iso:country":"TD",
    "name:und_x_variant":[
        "K\u00e9ra",
        "Kira"
    ],
    "wof:name":"Kira",
    "wof:placetype":"locality"
},
  "geometry": {"coordinates":[18.28691,9.17717],"type":"Point"}
}