{
  "type": "Feature",
  "properties": {
    "gn:admin1_code":"5.0",
    "gn:asciiname":"Simbiro",
    "gn:country_code":"TD",
    "gn:dem":510,
    "gn:feature_class":"P",
    "gn:feature_code":"PPL",
    "gn:name":"Simbiro",
    "gn:population":0,
    "gn:timezone":"Africa/Ndjamena",
    "iso:country":"TD",
    "wof:name":"Simbiro",
    "wof:placetype":"locality"
},
  "geometry": {"coordinates":[18.5608,11.8922],"type":"Point"}
}