{
  "type": "Feature",
  "properties": {
    "gn:admin1_code":"16.0",
    "gn:asciiname":"Ouedda",
    "gn:country_code":"TD",
    "gn:dem":329,
    "gn:feature_class":"P",
    "gn:feature_code":"PPL",
    "gn:name":"Ouedda",
    "gn:population":0,
    "gn:timezone":"Africa/Ndjamena",
    "iso:country":"TD",
    "name:und_x_variant":[
        "Oualdda",
        "Ouedda"
    ],
    "wof:name":"Ouedda",
    "wof:placetype":"locality"
},
  "geometry": {"coordinates":[15.2332,9.9759],"type":"Point"}
}