{
  "type": "Feature",
  "properties": {
    "gn:admin1_code":"12.0",
    "gn:asciiname":"Darongol",
    "gn:country_code":"TD",
    "gn:dem":680,
    "gn:feature_class":"P",
    "gn:feature_code":"PPL",
    "gn:name":"Darongol",
    "gn:population":0,
    "gn:timezone":"Africa/Ndjamena",
    "iso:country":"TD",
    "wof:name":"Darongol",
    "wof:placetype":"locality"
},
  "geometry": {"coordinates":[21.73461,13.22124],"type":"Point"}
}