{
  "type": "Feature",
  "properties": {
    "gn:admin1_code":"20.0",
    "gn:asciiname":"Petchongrong",
    "gn:country_code":"TD",
    "gn:dem":406,
    "gn:feature_class":"P",
    "gn:feature_code":"PPL",
    "gn:name":"Petchongrong",
    "gn:population":0,
    "gn:timezone":"Africa/Ndjamena",
    "iso:country":"TD",
    "wof:name":"Petchongrong",
    "wof:placetype":"locality"
},
  "geometry": {"coordinates":[14.75,8.93333],"type":"Point"}
}