{
  "type": "Feature",
  "properties": {
    "gn:admin1_code":"9.0",
    "gn:asciiname":"Bebinda",
    "gn:country_code":"TD",
    "gn:dem":422,
    "gn:feature_class":"P",
    "gn:feature_code":"PPL",
    "gn:name":"B\u00e9b\u00efnda",
    "gn:population":0,
    "gn:timezone":"Africa/Ndjamena",
    "iso:country":"TD",
    "name:fra_x_preferred":[
        "Bobinda"
    ],
    "name:und_x_variant":[
        "B\u00e9b\u00efnda"
    ],
    "wof:name":"Bebinda",
    "wof:placetype":"locality"
},
  "geometry": {"coordinates":[16.43889,8.35896],"type":"Point"}
}