{
  "type": "Feature",
  "properties": {
    "gn:admin1_code":"12.0",
    "gn:asciiname":"Lilek",
    "gn:country_code":"TD",
    "gn:dem":906,
    "gn:feature_class":"P",
    "gn:feature_code":"PPL",
    "gn:name":"Lilek",
    "gn:population":0,
    "gn:timezone":"Africa/Ndjamena",
    "iso:country":"TD",
    "wof:name":"Lilek",
    "wof:placetype":"locality"
},
  "geometry": {"coordinates":[21.94576,13.82604],"type":"Point"}
}