{
  "type": "Feature",
  "properties": {
    "gn:admin1_code":"16.0",
    "gn:asciiname":"Zaba II",
    "gn:country_code":"TD",
    "gn:dem":351,
    "gn:feature_class":"P",
    "gn:feature_code":"PPL",
    "gn:name":"Zaba II",
    "gn:population":0,
    "gn:timezone":"Africa/Ndjamena",
    "iso:country":"TD",
    "name:und_x_variant":[
        "Zabba",
        "Zaba II"
    ],
    "wof:name":"Zaba II",
    "wof:placetype":"locality"
},
  "geometry": {"coordinates":[15.5268,9.5372],"type":"Point"}
}