{
  "type": "Feature",
  "properties": {
    "gn:admin1_code":"17.0",
    "gn:asciiname":"Gonkira",
    "gn:country_code":"TD",
    "gn:dem":378,
    "gn:feature_class":"P",
    "gn:feature_code":"PPL",
    "gn:name":"Gonkira",
    "gn:population":0,
    "gn:timezone":"Africa/Ndjamena",
    "iso:country":"TD",
    "wof:name":"Gonkira",
    "wof:placetype":"locality"
},
  "geometry": {"coordinates":[18.4164,8.6811],"type":"Point"}
}