{
  "type": "Feature",
  "properties": {
    "gn:admin1_code":"17.0",
    "gn:asciiname":"Kohe",
    "gn:country_code":"TD",
    "gn:dem":442,
    "gn:feature_class":"P",
    "gn:feature_code":"PPL",
    "gn:name":"Koh\u00e9",
    "gn:population":0,
    "gn:timezone":"Africa/Ndjamena",
    "iso:country":"TD",
    "name:und_x_variant":[
        "Ko\u00e9",
        "Koh\u00e9"
    ],
    "wof:name":"Kohe",
    "wof:placetype":"locality"
},
  "geometry": {"coordinates":[18.66664,9.58338],"type":"Point"}
}