{
  "type": "Feature",
  "properties": {
    "gn:admin1_code":"12.0",
    "gn:asciiname":"Abourtouno",
    "gn:country_code":"TD",
    "gn:dem":589,
    "gn:feature_class":"P",
    "gn:feature_code":"PPL",
    "gn:name":"Abourtouno",
    "gn:population":0,
    "gn:timezone":"Africa/Ndjamena",
    "iso:country":"TD",
    "wof:name":"Abourtouno",
    "wof:placetype":"locality"
},
  "geometry": {"coordinates":[21.17629,13.23551],"type":"Point"}
}