{
  "type": "Feature",
  "properties": {
    "gn:admin1_code":"9.0",
    "gn:asciiname":"Ndonambo",
    "gn:country_code":"TD",
    "gn:dem":390,
    "gn:feature_class":"P",
    "gn:feature_code":"PPL",
    "gn:name":"Ndonambo",
    "gn:population":0,
    "gn:timezone":"Africa/Ndjamena",
    "iso:country":"TD",
    "wof:name":"Ndonambo",
    "wof:placetype":"locality"
},
  "geometry": {"coordinates":[16.93691,8.63406],"type":"Point"}
}