{
  "type": "Feature",
  "properties": {
    "gn:admin1_code":"17.0",
    "gn:asciiname":"Gou",
    "gn:country_code":"TD",
    "gn:dem":371,
    "gn:feature_class":"P",
    "gn:feature_code":"PPL",
    "gn:name":"Gou",
    "gn:population":0,
    "gn:timezone":"Africa/Ndjamena",
    "iso:country":"TD",
    "name:ceb_x_preferred":[
        "Gou"
    ],
    "name:deu_x_preferred":[
        "Gou"
    ],
    "name:rus_x_preferred":[
        "\u0413\u043e\u0443"
    ],
    "name:swe_x_preferred":[
        "Gou"
    ],
    "wof:name":"Gou",
    "wof:placetype":"locality"
},
  "geometry": {"coordinates":[18.3954,10.2005],"type":"Point"}
}