{
  "type": "Feature",
  "properties": {
    "gn:admin1_code":"9.0",
    "gn:asciiname":"Makou",
    "gn:country_code":"TD",
    "gn:dem":447,
    "gn:feature_class":"P",
    "gn:feature_code":"PPL",
    "gn:name":"Makou",
    "gn:population":0,
    "gn:timezone":"Africa/Ndjamena",
    "iso:country":"TD",
    "name:fra_x_preferred":[
        "Makou"
    ],
    "name:fra_x_variant":[
        "Mankou"
    ],
    "wof:name":"Makou",
    "wof:placetype":"locality"
},
  "geometry": {"coordinates":[16.10939,8.47074],"type":"Point"}
}