{
  "type": "Feature",
  "properties": {
    "gn:admin1_code":"15.0",
    "gn:asciiname":"Bihia",
    "gn:country_code":"TD",
    "gn:dem":333,
    "gn:feature_class":"P",
    "gn:feature_code":"PPL",
    "gn:name":"Bihia",
    "gn:population":0,
    "gn:timezone":"Africa/Ndjamena",
    "iso:country":"TD",
    "wof:name":"Bihia",
    "wof:placetype":"locality"
},
  "geometry": {"coordinates":[16.2639,10.5615],"type":"Point"}
}