{
  "type": "Feature",
  "properties": {
    "gn:admin1_code":"9.0",
    "gn:asciiname":"Moyassan",
    "gn:country_code":"TD",
    "gn:dem":400,
    "gn:feature_class":"P",
    "gn:feature_code":"PPL",
    "gn:name":"Moyassan",
    "gn:population":0,
    "gn:timezone":"Africa/Ndjamena",
    "iso:country":"TD",
    "wof:name":"Moyassan",
    "wof:placetype":"locality"
},
  "geometry": {"coordinates":[16.6675,8.4189],"type":"Point"}
}