{
  "type": "Feature",
  "properties": {
    "gn:admin1_code":"5.0",
    "gn:asciiname":"Saour Galbak",
    "gn:country_code":"TD",
    "gn:dem":393,
    "gn:feature_class":"P",
    "gn:feature_code":"PPL",
    "gn:name":"Saour Galbak",
    "gn:population":0,
    "gn:timezone":"Africa/Ndjamena",
    "iso:country":"TD",
    "wof:name":"Saour Galbak",
    "wof:placetype":"locality"
},
  "geometry": {"coordinates":[18.95103,12.41561],"type":"Point"}
}