{
  "type": "Feature",
  "properties": {
    "gn:admin1_code":"1.0",
    "gn:asciiname":"Guernes",
    "gn:country_code":"TD",
    "gn:dem":360,
    "gn:feature_class":"P",
    "gn:feature_code":"PPL",
    "gn:name":"Guern\u00e8s",
    "gn:population":0,
    "gn:timezone":"Africa/Ndjamena",
    "iso:country":"TD",
    "name:bug_x_preferred":[
        "Guernes"
    ],
    "name:cat_x_preferred":[
        "Guernes"
    ],
    "name:ceb_x_preferred":[
        "Guernes"
    ],
    "name:ces_x_preferred":[
        "Guernes"
    ],
    "name:deu_x_preferred":[
        "Guernes"
    ],
    "name:eus_x_preferred":[
        "Guernes"
    ],
    "name:fra_x_preferred":[
        "Guernes"
    ],
    "name:hun_x_preferred":[
        "Guernes"
    ],
    "name:ita_x_preferred":[
        "Guernes"
    ],
    "name:kaz_x_preferred":[
        "\u0413\u0435\u0440\u043d"
    ],
    "name:lat_x_preferred":[
        "Guernes"
    ],
    "name:msa_x_preferred":[
        "Guernes"
    ],
    "name:nld_x_preferred":[
        "Guernes"
    ],
    "name:oci_x_preferred":[
        "Guernes"
    ],
    "name:pms_x_preferred":[
        "Guernes"
    ],
    "name:pol_x_preferred":[
        "Guernes"
    ],
    "name:por_x_preferred":[
        "Guernes"
    ],
    "name:slk_x_preferred":[
        "Guernes"
    ],
    "name:spa_x_preferred":[
        "Guernes"
    ],
    "name:swe_x_preferred":[
        "Guernes"
    ],
    "name:ukr_x_preferred":[
        "\u0413\u0435\u0440\u043d"
    ],
    "name:und_x_variant":[
        "Gern\u00e8s",
        "Guern\u00e8s"
    ],
    "name:vie_x_preferred":[
        "Guernes"
    ],
    "name:vol_x_preferred":[
        "Guernes"
    ],
    "name:war_x_preferred":[
        "Guernes"
    ],
    "wof:name":"Guernes",
    "wof:placetype":"locality"
},
  "geometry": {"coordinates":[19.10542,13.57229],"type":"Point"}
}