{
  "type": "Feature",
  "properties": {
    "gn:admin1_code":"1.0",
    "gn:asciiname":"Ab Labay",
    "gn:country_code":"TD",
    "gn:dem":369,
    "gn:feature_class":"P",
    "gn:feature_code":"PPL",
    "gn:name":"Ab Labay",
    "gn:population":0,
    "gn:timezone":"Africa/Ndjamena",
    "iso:country":"TD",
    "name:und_x_variant":[
        "Ablaba\u00ef",
        "Ab Labay"
    ],
    "wof:name":"Ab Labay",
    "wof:placetype":"locality"
},
  "geometry": {"coordinates":[19.3729,13.8871],"type":"Point"}
}