{
  "type": "Feature",
  "properties": {
    "gn:admin1_code":"15.0",
    "gn:asciiname":"Yolla",
    "gn:country_code":"TD",
    "gn:dem":343,
    "gn:feature_class":"P",
    "gn:feature_code":"PPL",
    "gn:name":"Yolla",
    "gn:population":0,
    "gn:timezone":"Africa/Ndjamena",
    "iso:country":"TD",
    "name:deu_x_preferred":[
        "Yolla"
    ],
    "wof:name":"Yolla",
    "wof:placetype":"locality"
},
  "geometry": {"coordinates":[17.053,10.3866],"type":"Point"}
}