{
  "type": "Feature",
  "properties": {
    "gn:admin1_code":"15.0",
    "gn:asciiname":"Gorokolon",
    "gn:country_code":"TD",
    "gn:dem":331,
    "gn:feature_class":"P",
    "gn:feature_code":"PPL",
    "gn:name":"Gorokolon",
    "gn:population":0,
    "gn:timezone":"Africa/Ndjamena",
    "iso:country":"TD",
    "wof:name":"Gorokolon",
    "wof:placetype":"locality"
},
  "geometry": {"coordinates":[16.6908,10.5674],"type":"Point"}
}