{
  "type": "Feature",
  "properties": {
    "gn:admin1_code":"25.0",
    "gn:asciiname":"Aourado",
    "gn:country_code":"TD",
    "gn:dem":582,
    "gn:feature_class":"P",
    "gn:feature_code":"PPL",
    "gn:name":"Aourado",
    "gn:population":0,
    "gn:timezone":"Africa/Ndjamena",
    "iso:country":"TD",
    "wof:name":"Aourado",
    "wof:placetype":"locality"
},
  "geometry": {"coordinates":[21.86667000000001,12.36667],"type":"Point"}
}