{
  "type": "Feature",
  "properties": {
    "gn:admin1_code":"18.0",
    "gn:asciiname":"Djipdjoumalak",
    "gn:country_code":"TD",
    "gn:dem":327,
    "gn:feature_class":"P",
    "gn:feature_code":"PPL",
    "gn:name":"Djipdjoumalak",
    "gn:population":0,
    "gn:timezone":"Africa/Ndjamena",
    "iso:country":"TD",
    "wof:name":"Djipdjoumalak",
    "wof:placetype":"locality"
},
  "geometry": {"coordinates":[17.2295,11.8604],"type":"Point"}
}