{
  "type": "Feature",
  "properties": {
    "gn:admin1_code":"12.0",
    "gn:asciiname":"Taouile",
    "gn:country_code":"TD",
    "gn:dem":763,
    "gn:feature_class":"P",
    "gn:feature_code":"PPL",
    "gn:name":"Taouil\u00e9",
    "gn:population":0,
    "gn:timezone":"Africa/Ndjamena",
    "iso:country":"TD",
    "name:fra_x_preferred":[
        "Taouil\u00e9"
    ],
    "name:und_x_variant":[
        "Rigil Tawi\u00e9",
        "Tawil\u00e9"
    ],
    "wof:name":"Taouile",
    "wof:placetype":"locality"
},
  "geometry": {"coordinates":[21.40404,14.10159],"type":"Point"}
}