{
  "type": "Feature",
  "properties": {
    "gn:admin1_code":"13.0",
    "gn:asciiname":"Deleima",
    "gn:country_code":"TD",
    "gn:dem":437,
    "gn:feature_class":"P",
    "gn:feature_code":"PPL",
    "gn:name":"D\u00e9l\u00e9\u00efma",
    "gn:population":0,
    "gn:timezone":"Africa/Ndjamena",
    "iso:country":"TD",
    "wof:name":"Deleima",
    "wof:placetype":"locality"
},
  "geometry": {"coordinates":[20.2876,11.0114],"type":"Point"}
}