{
  "type": "Feature",
  "properties": {
    "gn:admin1_code":"18.0",
    "gn:asciiname":"Ardebe",
    "gn:country_code":"TD",
    "gn:dem":325,
    "gn:feature_class":"P",
    "gn:feature_code":"PPL",
    "gn:name":"Ard\u00e9b\u00e9",
    "gn:population":0,
    "gn:timezone":"Africa/Ndjamena",
    "iso:country":"TD",
    "wof:name":"Ardebe",
    "wof:placetype":"locality"
},
  "geometry": {"coordinates":[17.2791,11.9015],"type":"Point"}
}