{
  "type": "Feature",
  "properties": {
    "gn:admin1_code":"20.0",
    "gn:asciiname":"Fama",
    "gn:country_code":"TD",
    "gn:dem":380,
    "gn:feature_class":"P",
    "gn:feature_code":"PPL",
    "gn:name":"Fama",
    "gn:population":0,
    "gn:timezone":"Africa/Ndjamena",
    "iso:country":"TD",
    "name:bre_x_preferred":[
        "Fama"
    ],
    "name:cat_x_preferred":[
        "Fama"
    ],
    "name:ceb_x_preferred":[
        "Fama"
    ],
    "name:deu_x_preferred":[
        "Fama"
    ],
    "name:epo_x_preferred":[
        "Fama"
    ],
    "name:eus_x_preferred":[
        "Fama"
    ],
    "name:fra_x_preferred":[
        "Fama"
    ],
    "name:ita_x_preferred":[
        "Fama"
    ],
    "name:lat_x_preferred":[
        "Fama"
    ],
    "name:nld_x_preferred":[
        "Fama"
    ],
    "name:nor_x_preferred":[
        "Fama"
    ],
    "name:por_x_preferred":[
        "Fama"
    ],
    "name:rus_x_preferred":[
        "\u0424\u0430\u043c\u0430"
    ],
    "name:spa_x_preferred":[
        "Fama"
    ],
    "name:swe_x_preferred":[
        "Fama"
    ],
    "wof:name":"Fama",
    "wof:placetype":"locality"
},
  "geometry": {"coordinates":[15.09294,9.58876],"type":"Point"}
}