{
  "type": "Feature",
  "properties": {
    "gn:admin1_code":"8.0",
    "gn:asciiname":"Koudangui",
    "gn:country_code":"TD",
    "gn:dem":430,
    "gn:feature_class":"P",
    "gn:feature_code":"PPL",
    "gn:name":"Koudangui",
    "gn:population":0,
    "gn:timezone":"Africa/Ndjamena",
    "iso:country":"TD",
    "wof:name":"Koudangui",
    "wof:placetype":"locality"
},
  "geometry": {"coordinates":[15.828,8.8253],"type":"Point"}
}