{
  "type": "Feature",
  "properties": {
    "gn:admin1_code":"15.0",
    "gn:asciiname":"Malemguida",
    "gn:country_code":"TD",
    "gn:dem":306,
    "gn:feature_class":"P",
    "gn:feature_code":"PPL",
    "gn:name":"Malemguida",
    "gn:population":0,
    "gn:timezone":"Africa/Ndjamena",
    "iso:country":"TD",
    "name:und_x_variant":[
        "Malemgida",
        "Malemguida"
    ],
    "wof:name":"Malemguida",
    "wof:placetype":"locality"
},
  "geometry": {"coordinates":[15.43592,11.58317],"type":"Point"}
}