{
  "type": "Feature",
  "properties": {
    "gn:admin1_code":"12.0",
    "gn:asciiname":"Siebat",
    "gn:country_code":"TD",
    "gn:dem":766,
    "gn:feature_class":"P",
    "gn:feature_code":"PPL",
    "gn:name":"Si\u00e9bat",
    "gn:population":0,
    "gn:timezone":"Africa/Ndjamena",
    "iso:country":"TD",
    "wof:name":"Siebat",
    "wof:placetype":"locality"
},
  "geometry": {"coordinates":[22.13567,13.21519],"type":"Point"}
}