{
  "type": "Feature",
  "properties": {
    "gn:admin1_code":"9.0",
    "gn:asciiname":"Beromana",
    "gn:country_code":"TD",
    "gn:dem":413,
    "gn:feature_class":"P",
    "gn:feature_code":"PPL",
    "gn:name":"B\u00e9romana",
    "gn:population":0,
    "gn:timezone":"Africa/Ndjamena",
    "iso:country":"TD",
    "wof:name":"Beromana",
    "wof:placetype":"locality"
},
  "geometry": {"coordinates":[16.5842,7.8895],"type":"Point"}
}