{
  "type": "Feature",
  "properties": {
    "gn:admin1_code":"7.0",
    "gn:asciiname":"Bede Dioul",
    "gn:country_code":"TD",
    "gn:dem":301,
    "gn:feature_class":"P",
    "gn:feature_code":"PPL",
    "gn:name":"B\u00e9d\u00e9 Dioul",
    "gn:population":0,
    "gn:timezone":"Africa/Ndjamena",
    "iso:country":"TD",
    "wof:name":"Bede Dioul",
    "wof:placetype":"locality"
},
  "geometry": {"coordinates":[15.702,13.61403],"type":"Point"}
}