{
  "type": "Feature",
  "properties": {
    "gn:admin1_code":"12.0",
    "gn:asciiname":"Dekoite",
    "gn:country_code":"TD",
    "gn:dem":827,
    "gn:feature_class":"P",
    "gn:feature_code":"PPL",
    "gn:name":"D\u00e9ko\u00eft\u00e9",
    "gn:population":0,
    "gn:timezone":"Africa/Ndjamena",
    "iso:country":"TD",
    "wof:name":"Dekoite",
    "wof:placetype":"locality"
},
  "geometry": {"coordinates":[22.13483,13.32905],"type":"Point"}
}