{
  "type": "Feature",
  "properties": {
    "gn:admin1_code":"1.0",
    "gn:asciiname":"Abgalouetch",
    "gn:country_code":"TD",
    "gn:dem":291,
    "gn:feature_class":"P",
    "gn:feature_code":"PPL",
    "gn:name":"Abgalouetch",
    "gn:population":0,
    "gn:timezone":"Africa/Ndjamena",
    "iso:country":"TD",
    "wof:name":"Abgalouetch",
    "wof:placetype":"locality"
},
  "geometry": {"coordinates":[17.08929,12.802],"type":"Point"}
}