{
  "type": "Feature",
  "properties": {
    "gn:admin1_code":"9.0",
    "gn:asciiname":"Bodo",
    "gn:country_code":"TD",
    "gn:dem":410,
    "gn:feature_class":"P",
    "gn:feature_code":"PPL",
    "gn:name":"Bodo",
    "gn:population":0,
    "gn:timezone":"Africa/Ndjamena",
    "iso:country":"TD",
    "name:bih_x_preferred":[
        "\u092c\u094b\u0921\u093c\u094b \u092d\u093e\u0937\u093e"
    ],
    "name:ceb_x_preferred":[
        "Bodo"
    ],
    "name:ces_x_preferred":[
        "Bodo"
    ],
    "name:deu_x_preferred":[
        "Bodo"
    ],
    "name:fin_x_preferred":[
        "Bodo"
    ],
    "name:fra_x_preferred":[
        "Bodo"
    ],
    "name:heb_x_preferred":[
        "\u05d1\u05d5\u05d3\u05d5"
    ],
    "name:hin_x_preferred":[
        "\u092c\u094b\u0921\u094b"
    ],
    "name:ita_x_preferred":[
        "Bodo"
    ],
    "name:nds_x_preferred":[
        "Bodo"
    ],
    "name:nld_x_preferred":[
        "Bodo"
    ],
    "name:pol_x_preferred":[
        "Bodo"
    ],
    "name:por_x_preferred":[
        "Bodo"
    ],
    "name:ron_x_preferred":[
        "Bodo"
    ],
    "name:rus_x_preferred":[
        "\u0411\u043e\u0434\u043e"
    ],
    "name:swe_x_preferred":[
        "Bodo"
    ],
    "name:ukr_x_preferred":[
        "\u0411\u043e\u0434\u043e"
    ],
    "wof:name":"Bodo",
    "wof:placetype":"locality"
},
  "geometry": {"coordinates":[17.1199,8.2955],"type":"Point"}
}