{
  "type": "Feature",
  "properties": {
    "gn:admin1_code":"20.0",
    "gn:asciiname":"Doindopina",
    "gn:country_code":"TD",
    "gn:dem":455,
    "gn:feature_class":"P",
    "gn:feature_code":"PPL",
    "gn:name":"Do\u00efndopina",
    "gn:population":0,
    "gn:timezone":"Africa/Ndjamena",
    "iso:country":"TD",
    "name:und_x_variant":[
        "Doindofina",
        "Do\u00efndopina"
    ],
    "wof:name":"Doindopina",
    "wof:placetype":"locality"
},
  "geometry": {"coordinates":[15.20372,8.93889],"type":"Point"}
}