{
  "type": "Feature",
  "properties": {
    "gn:admin1_code":"1.0",
    "gn:asciiname":"Atemede",
    "gn:country_code":"TD",
    "gn:dem":372,
    "gn:feature_class":"P",
    "gn:feature_code":"PPL",
    "gn:name":"At\u00e9m\u00e9d\u00e9",
    "gn:population":0,
    "gn:timezone":"Africa/Ndjamena",
    "iso:country":"TD",
    "wof:name":"Atemede",
    "wof:placetype":"locality"
},
  "geometry": {"coordinates":[19.4537,13.9363],"type":"Point"}
}