{
  "type": "Feature",
  "properties": {
    "gn:admin1_code":"17.0",
    "gn:asciiname":"Maibian",
    "gn:country_code":"TD",
    "gn:dem":384,
    "gn:feature_class":"P",
    "gn:feature_code":"PPL",
    "gn:name":"Ma\u00efbian",
    "gn:population":0,
    "gn:timezone":"Africa/Ndjamena",
    "iso:country":"TD",
    "wof:name":"Maibian",
    "wof:placetype":"locality"
},
  "geometry": {"coordinates":[18.5439,8.6282],"type":"Point"}
}