{
  "type": "Feature",
  "properties": {
    "gn:admin1_code":"15.0",
    "gn:asciiname":"Palamaeje",
    "gn:country_code":"TD",
    "gn:dem":323,
    "gn:feature_class":"P",
    "gn:feature_code":"PPL",
    "gn:name":"Palama\u00e8j\u00e9",
    "gn:population":0,
    "gn:timezone":"Africa/Ndjamena",
    "iso:country":"TD",
    "wof:name":"Palamaeje",
    "wof:placetype":"locality"
},
  "geometry": {"coordinates":[15.82502,11.02132],"type":"Point"}
}