{
  "type": "Feature",
  "properties": {
    "gn:admin1_code":"5.0",
    "gn:asciiname":"Magli",
    "gn:country_code":"TD",
    "gn:dem":535,
    "gn:feature_class":"P",
    "gn:feature_code":"PPL",
    "gn:name":"Magli",
    "gn:population":0,
    "gn:timezone":"Africa/Ndjamena",
    "iso:country":"TD",
    "wof:name":"Magli",
    "wof:placetype":"locality"
},
  "geometry": {"coordinates":[19.088,11.6806],"type":"Point"}
}