{
  "type": "Feature",
  "properties": {
    "gn:admin1_code":"7.0",
    "gn:asciiname":"Marawolili",
    "gn:country_code":"TD",
    "gn:dem":298,
    "gn:feature_class":"P",
    "gn:feature_code":"PPL",
    "gn:name":"Marawolili",
    "gn:population":0,
    "gn:timezone":"Africa/Ndjamena",
    "iso:country":"TD",
    "wof:name":"Marawolili",
    "wof:placetype":"locality"
},
  "geometry": {"coordinates":[15.63586,13.33979],"type":"Point"}
}