{
  "type": "Feature",
  "properties": {
    "gn:admin1_code":"12.0",
    "gn:asciiname":"Kolingue",
    "gn:country_code":"TD",
    "gn:dem":812,
    "gn:feature_class":"P",
    "gn:feature_code":"PPL",
    "gn:name":"Kolingu\u00e9",
    "gn:population":0,
    "gn:timezone":"Africa/Ndjamena",
    "iso:country":"TD",
    "name:und_x_variant":[
        "Kolingu\u00e9",
        "Koling\u00e9"
    ],
    "wof:name":"Kolingue",
    "wof:placetype":"locality"
},
  "geometry": {"coordinates":[22.11425,13.24815],"type":"Point"}
}