{
  "type": "Feature",
  "properties": {
    "gn:admin1_code":"12.0",
    "gn:asciiname":"Tene",
    "gn:country_code":"TD",
    "gn:dem":591,
    "gn:feature_class":"P",
    "gn:feature_code":"PPL",
    "gn:name":"T\u00e9n\u00e9",
    "gn:population":0,
    "gn:timezone":"Africa/Ndjamena",
    "iso:country":"TD",
    "name:ceb_x_preferred":[
        "Tene"
    ],
    "name:deu_x_preferred":[
        "Tene"
    ],
    "name:ita_x_preferred":[
        "Tene"
    ],
    "name:nld_x_preferred":[
        "Tene"
    ],
    "name:swe_x_preferred":[
        "Tene"
    ],
    "wof:name":"Tene",
    "wof:placetype":"locality"
},
  "geometry": {"coordinates":[21.02479,13.15113],"type":"Point"}
}