{
  "type": "Feature",
  "properties": {
    "gn:admin1_code":"23.0",
    "gn:asciiname":"Mani",
    "gn:country_code":"TD",
    "gn:dem":243,
    "gn:feature_class":"P",
    "gn:feature_code":"PPL",
    "gn:name":"Mani",
    "gn:population":0,
    "gn:timezone":"Africa/Ndjamena",
    "iso:country":"TD",
    "wof:name":"Mani",
    "wof:placetype":"locality"
},
  "geometry": {"coordinates":[18.88024,17.95484],"type":"Point"}
}