{
  "type": "Feature",
  "properties": {
    "gn:admin1_code":"13.0",
    "gn:asciiname":"Bibien",
    "gn:country_code":"TD",
    "gn:dem":405,
    "gn:feature_class":"P",
    "gn:feature_code":"PPL",
    "gn:name":"Bibi\u00e8n",
    "gn:population":0,
    "gn:timezone":"Africa/Ndjamena",
    "iso:country":"TD",
    "wof:name":"Bibien",
    "wof:placetype":"locality"
},
  "geometry": {"coordinates":[19.9205,10.1896],"type":"Point"}
}