{
  "type": "Feature",
  "properties": {
    "gn:admin1_code":"25.0",
    "gn:asciiname":"Tarre",
    "gn:country_code":"TD",
    "gn:dem":759,
    "gn:feature_class":"P",
    "gn:feature_code":"PPL",
    "gn:name":"Tarr\u00e9",
    "gn:population":0,
    "gn:timezone":"Africa/Ndjamena",
    "iso:country":"TD",
    "name:und_x_variant":[
        "Tor\u00e9",
        "Tarr\u00e9"
    ],
    "wof:name":"Tarre",
    "wof:placetype":"locality"
},
  "geometry": {"coordinates":[22.53333,11.55],"type":"Point"}
}