{
  "type": "Feature",
  "properties": {
    "gn:admin1_code":"18.0",
    "gn:asciiname":"Adeneou",
    "gn:country_code":"TD",
    "gn:dem":293,
    "gn:feature_class":"P",
    "gn:feature_code":"PPL",
    "gn:name":"Ad\u00e9n\u00e9ou",
    "gn:population":0,
    "gn:timezone":"Africa/Ndjamena",
    "iso:country":"TD",
    "name:und_x_variant":[
        "Addineou",
        "Ad\u00e9n\u00e9ou"
    ],
    "wof:name":"Adeneou",
    "wof:placetype":"locality"
},
  "geometry": {"coordinates":[15.47008,12.41909],"type":"Point"}
}