{
  "type": "Feature",
  "properties": {
    "gn:admin1_code":"12.0",
    "gn:asciiname":"Djaouame",
    "gn:country_code":"TD",
    "gn:dem":532,
    "gn:feature_class":"P",
    "gn:feature_code":"PPL",
    "gn:name":"Djaouam\u00e9",
    "gn:population":0,
    "gn:timezone":"Africa/Ndjamena",
    "iso:country":"TD",
    "name:fra_x_preferred":[
        "Djaouam\u00e9"
    ],
    "wof:name":"Djaouame",
    "wof:placetype":"locality"
},
  "geometry": {"coordinates":[20.83376,13.52606],"type":"Point"}
}