{
  "type": "Feature",
  "properties": {
    "gn:admin1_code":"12.0",
    "gn:asciiname":"Hadjernoga",
    "gn:country_code":"TD",
    "gn:dem":729,
    "gn:feature_class":"P",
    "gn:feature_code":"PPL",
    "gn:name":"Hadjernoga",
    "gn:population":0,
    "gn:timezone":"Africa/Ndjamena",
    "iso:country":"TD",
    "name:fra_x_preferred":[
        "Hadjernoga"
    ],
    "wof:name":"Hadjernoga",
    "wof:placetype":"locality"
},
  "geometry": {"coordinates":[21.09905,14.06704],"type":"Point"}
}