{
  "type": "Feature",
  "properties": {
    "gn:admin1_code":"9.0",
    "gn:asciiname":"Njagou",
    "gn:country_code":"TD",
    "gn:dem":446,
    "gn:feature_class":"P",
    "gn:feature_code":"PPL",
    "gn:name":"Njagou",
    "gn:population":0,
    "gn:timezone":"Africa/Ndjamena",
    "iso:country":"TD",
    "name:und_x_variant":[
        "Njagu",
        "Njagou"
    ],
    "wof:name":"Njagou",
    "wof:placetype":"locality"
},
  "geometry": {"coordinates":[15.5079,8.2663],"type":"Point"}
}