{
  "type": "Feature",
  "properties": {
    "gn:admin1_code":"12.0",
    "gn:asciiname":"Biren Beni Alba",
    "gn:country_code":"TD",
    "gn:dem":545,
    "gn:feature_class":"P",
    "gn:feature_code":"PPL",
    "gn:name":"Biren B\u00e9ni Alba",
    "gn:population":0,
    "gn:timezone":"Africa/Ndjamena",
    "iso:country":"TD",
    "name:fra_x_preferred":[
        "Biren B\u00e9ni Alba"
    ],
    "wof:name":"Biren Beni Alba",
    "wof:placetype":"locality"
},
  "geometry": {"coordinates":[20.87401,13.52409],"type":"Point"}
}