{
  "type": "Feature",
  "properties": {
    "gn:admin1_code":"14.0",
    "gn:asciiname":"Matiguil",
    "gn:country_code":"TD",
    "gn:dem":339,
    "gn:feature_class":"P",
    "gn:feature_code":"PPL",
    "gn:name":"Matiguil",
    "gn:population":0,
    "gn:timezone":"Africa/Ndjamena",
    "iso:country":"TD",
    "name:und_x_variant":[
        "Matigil",
        "Matiguil"
    ],
    "wof:name":"Matiguil",
    "wof:placetype":"locality"
},
  "geometry": {"coordinates":[16.3671,10.1805],"type":"Point"}
}