{
  "type": "Feature",
  "properties": {
    "gn:admin1_code":"15.0",
    "gn:asciiname":"Nabagaya",
    "gn:country_code":"TD",
    "gn:dem":297,
    "gn:feature_class":"P",
    "gn:feature_code":"PPL",
    "gn:name":"Nabagaya",
    "gn:population":0,
    "gn:timezone":"Africa/Ndjamena",
    "iso:country":"TD",
    "wof:name":"Nabagaya",
    "wof:placetype":"locality"
},
  "geometry": {"coordinates":[15.40295,12.22015],"type":"Point"}
}