{
  "type": "Feature",
  "properties": {
    "gn:admin1_code":"1.0",
    "gn:asciiname":"Hieda",
    "gn:country_code":"TD",
    "gn:dem":336,
    "gn:feature_class":"P",
    "gn:feature_code":"PPL",
    "gn:name":"Hi\u00e9da",
    "gn:population":0,
    "gn:timezone":"Africa/Ndjamena",
    "iso:country":"TD",
    "wof:name":"Hieda",
    "wof:placetype":"locality"
},
  "geometry": {"coordinates":[18.2549,13.2795],"type":"Point"}
}