{
  "type": "Feature",
  "properties": {
    "gn:admin1_code":"5.0",
    "gn:asciiname":"Gala",
    "gn:country_code":"TD",
    "gn:dem":450,
    "gn:feature_class":"P",
    "gn:feature_code":"PPL",
    "gn:name":"Gala",
    "gn:population":0,
    "gn:timezone":"Africa/Ndjamena",
    "iso:country":"TD",
    "name:bos_x_preferred":[
        "Gala"
    ],
    "name:bul_x_preferred":[
        "\u0413\u0430\u043b\u0430"
    ],
    "name:cat_x_preferred":[
        "Gala"
    ],
    "name:ceb_x_preferred":[
        "Gala"
    ],
    "name:ces_x_preferred":[
        "Gala"
    ],
    "name:deu_x_preferred":[
        "Gala"
    ],
    "name:epo_x_preferred":[
        "Gala"
    ],
    "name:fin_x_preferred":[
        "Gala"
    ],
    "name:fra_x_preferred":[
        "Gala"
    ],
    "name:glg_x_preferred":[
        "Gala"
    ],
    "name:heb_x_preferred":[
        "\u05d2\u05d0\u05dc\u05d4"
    ],
    "name:hun_x_preferred":[
        "Gala"
    ],
    "name:ita_x_preferred":[
        "Gala"
    ],
    "name:jpn_x_preferred":[
        "\u30ac\u30fc\u30e9"
    ],
    "name:nds_x_preferred":[
        "Gala"
    ],
    "name:nld_x_preferred":[
        "Gala"
    ],
    "name:pol_x_preferred":[
        "Gala"
    ],
    "name:por_x_preferred":[
        "Gala"
    ],
    "name:rus_x_preferred":[
        "Gala"
    ],
    "name:slk_x_preferred":[
        "Gala"
    ],
    "name:slv_x_preferred":[
        "Gala"
    ],
    "name:spa_x_preferred":[
        "Gala"
    ],
    "name:srp_x_preferred":[
        "\u0413\u0430\u043b\u0430"
    ],
    "name:swe_x_preferred":[
        "Gala"
    ],
    "name:tur_x_preferred":[
        "Gala"
    ],
    "wof:name":"Gala",
    "wof:placetype":"locality"
},
  "geometry": {"coordinates":[17.9736,11.7044],"type":"Point"}
}