{
  "type": "Feature",
  "properties": {
    "gn:admin1_code":"12.0",
    "gn:asciiname":"Andokone",
    "gn:country_code":"TD",
    "gn:dem":556,
    "gn:feature_class":"P",
    "gn:feature_code":"PPL",
    "gn:name":"Andokon\u00e9",
    "gn:population":0,
    "gn:timezone":"Africa/Ndjamena",
    "iso:country":"TD",
    "wof:name":"Andokone",
    "wof:placetype":"locality"
},
  "geometry": {"coordinates":[21.19241,13.20915],"type":"Point"}
}