{
  "type": "Feature",
  "properties": {
    "gn:admin1_code":"2.0",
    "gn:asciiname":"Kete",
    "gn:country_code":"TD",
    "gn:dem":961,
    "gn:feature_class":"P",
    "gn:feature_code":"PPL",
    "gn:name":"K\u00e9t\u00e9",
    "gn:population":0,
    "gn:timezone":"Africa/Ndjamena",
    "iso:country":"TD",
    "name:ceb_x_preferred":[
        "Kete"
    ],
    "name:fra_x_preferred":[
        "K\u00e9t\u00e9"
    ],
    "name:fra_x_variant":[
        "Kete"
    ],
    "name:nno_x_preferred":[
        "Kete"
    ],
    "name:swe_x_preferred":[
        "Kete"
    ],
    "wof:name":"Kete",
    "wof:placetype":"locality"
},
  "geometry": {"coordinates":[21.99543,14.53128],"type":"Point"}
}