{
  "type": "Feature",
  "properties": {
    "gn:admin1_code":"19.0",
    "gn:asciiname":"Bedjomo",
    "gn:country_code":"TD",
    "gn:dem":392,
    "gn:feature_class":"P",
    "gn:feature_code":"PPL",
    "gn:name":"Bedjomo",
    "gn:population":0,
    "gn:timezone":"Africa/Ndjamena",
    "iso:country":"TD",
    "wof:name":"Bedjomo",
    "wof:placetype":"locality"
},
  "geometry": {"coordinates":[17.18546,8.6354],"type":"Point"}
}