{
  "type": "Feature",
  "properties": {
    "gn:admin1_code":"12.0",
    "gn:asciiname":"Aouli",
    "gn:country_code":"TD",
    "gn:dem":800,
    "gn:feature_class":"P",
    "gn:feature_code":"PPL",
    "gn:name":"Aouli",
    "gn:population":0,
    "gn:timezone":"Africa/Ndjamena",
    "iso:country":"TD",
    "wof:name":"Aouli",
    "wof:placetype":"locality"
},
  "geometry": {"coordinates":[21.86198,13.33776],"type":"Point"}
}