{
  "type": "Feature",
  "properties": {
    "gn:admin1_code":"5.0",
    "gn:asciiname":"Farale",
    "gn:country_code":"TD",
    "gn:dem":514,
    "gn:feature_class":"P",
    "gn:feature_code":"PPL",
    "gn:name":"Farale",
    "gn:population":0,
    "gn:timezone":"Africa/Ndjamena",
    "iso:country":"TD",
    "wof:name":"Farale",
    "wof:placetype":"locality"
},
  "geometry": {"coordinates":[18.77163,12.00621],"type":"Point"}
}