{
  "type": "Feature",
  "properties": {
    "gn:admin1_code":"25.0",
    "gn:asciiname":"Hatab Djimeze",
    "gn:country_code":"TD",
    "gn:dem":678,
    "gn:feature_class":"P",
    "gn:feature_code":"PPL",
    "gn:name":"Hatab Djim\u00e8ze",
    "gn:population":0,
    "gn:timezone":"Africa/Ndjamena",
    "iso:country":"TD",
    "wof:name":"Hatab Djimeze",
    "wof:placetype":"locality"
},
  "geometry": {"coordinates":[22.75,11.45],"type":"Point"}
}