{
  "type": "Feature",
  "properties": {
    "gn:admin1_code":"13.0",
    "gn:asciiname":"Guelba",
    "gn:country_code":"TD",
    "gn:dem":473,
    "gn:feature_class":"P",
    "gn:feature_code":"PPL",
    "gn:name":"Guelba",
    "gn:population":0,
    "gn:timezone":"Africa/Ndjamena",
    "iso:country":"TD",
    "name:und_x_variant":[
        "A. Galba",
        "Galba",
        "Gelba",
        "Guelba"
    ],
    "wof:name":"Guelba",
    "wof:placetype":"locality"
},
  "geometry": {"coordinates":[19.0094,11.6308],"type":"Point"}
}