{
  "type": "Feature",
  "properties": {
    "gn:admin1_code":"12.0",
    "gn:asciiname":"Ali Manadji",
    "gn:country_code":"TD",
    "gn:dem":426,
    "gn:feature_class":"P",
    "gn:feature_code":"PPL",
    "gn:name":"Ali Manadji",
    "gn:population":0,
    "gn:timezone":"Africa/Ndjamena",
    "iso:country":"TD",
    "name:und_x_variant":[
        "Al Manadji",
        "Ali Manadji"
    ],
    "wof:name":"Ali Manadji",
    "wof:placetype":"locality"
},
  "geometry": {"coordinates":[20.23848,13.86012],"type":"Point"}
}