{
  "type": "Feature",
  "properties": {
    "gn:admin1_code":"12.0",
    "gn:asciiname":"Zanapte",
    "gn:country_code":"TD",
    "gn:dem":493,
    "gn:feature_class":"P",
    "gn:feature_code":"PPL",
    "gn:name":"Zanapt\u00e9",
    "gn:population":0,
    "gn:timezone":"Africa/Ndjamena",
    "iso:country":"TD",
    "name:fra_x_preferred":[
        "Zanapt\u00e9"
    ],
    "wof:name":"Zanapte",
    "wof:placetype":"locality"
},
  "geometry": {"coordinates":[20.62464,13.05114],"type":"Point"}
}