{
  "type": "Feature",
  "properties": {
    "gn:country":"TD",
    "gn:fcode":"PPL",
    "gn:population":17682,
    "iso:country":"TD",
    "name:fra_x_preferred":[
        "Dourbali"
    ],
    "name:ita_x_preferred":[
        "Dourbali"
    ],
    "name:pol_x_preferred":[
        "Dourbali"
    ],
    "name:ron_x_preferred":[
        "Dourbali"
    ],
    "name:rus_x_preferred":[
        "\u0414\u0443\u0440\u0431\u0430\u043b\u0438"
    ],
    "name:und_x_variant":[
        "Ndourbali"
    ],
    "qs:name":"Dourbali",
    "qs:photos_9r":0,
    "qs:photos_sr":0,
    "qs:pop_sr":"6",
    "wof:name":"Dourbali",
    "wof:placetype":"locality",
    "wof:population":17682
},
  "geometry": {"coordinates":[15.86323,11.80909],"type":"Point"}
}