{
  "type": "Feature",
  "properties": {
    "gn:admin1_code":"17.0",
    "gn:asciiname":"Dinakobo",
    "gn:country_code":"TD",
    "gn:dem":380,
    "gn:feature_class":"P",
    "gn:feature_code":"PPL",
    "gn:name":"Dinakobo",
    "gn:population":0,
    "gn:timezone":"Africa/Ndjamena",
    "iso:country":"TD",
    "name:und_x_variant":[
        "Ndenakobo",
        "Dinakobo"
    ],
    "wof:name":"Dinakobo",
    "wof:placetype":"locality"
},
  "geometry": {"coordinates":[18.45641,8.5756],"type":"Point"}
}