{
  "type": "Feature",
  "properties": {
    "gn:admin1_code":"12.0",
    "gn:asciiname":"Mokochache",
    "gn:country_code":"TD",
    "gn:dem":613,
    "gn:feature_class":"P",
    "gn:feature_code":"PPL",
    "gn:name":"Mokochach\u00e9",
    "gn:population":0,
    "gn:timezone":"Africa/Ndjamena",
    "iso:country":"TD",
    "name:und_x_variant":[
        "Nokochach\u00e9",
        "Mokochach\u00e9"
    ],
    "wof:name":"Mokochache",
    "wof:placetype":"locality"
},
  "geometry": {"coordinates":[21.48548,13.17361],"type":"Point"}
}