{
  "type": "Feature",
  "properties": {
    "gn:admin1_code":"2.0",
    "gn:asciiname":"Kourasiri",
    "gn:country_code":"TD",
    "gn:dem":890,
    "gn:feature_class":"P",
    "gn:feature_code":"PPL",
    "gn:name":"Kourasiri",
    "gn:population":0,
    "gn:timezone":"Africa/Ndjamena",
    "iso:country":"TD",
    "wof:name":"Kourasiri",
    "wof:placetype":"locality"
},
  "geometry": {"coordinates":[22.43333,15.06667],"type":"Point"}
}