{
  "type": "Feature",
  "properties": {
    "gn:admin1_code":"5.0",
    "gn:asciiname":"Aberei",
    "gn:country_code":"TD",
    "gn:dem":380,
    "gn:feature_class":"P",
    "gn:feature_code":"PPL",
    "gn:name":"Ab\u00e9re\u00ef",
    "gn:population":0,
    "gn:timezone":"Africa/Ndjamena",
    "iso:country":"TD",
    "name:und_x_variant":[
        "Abr\u00e9",
        "Ab\u00e9re\u00ef"
    ],
    "wof:name":"Aberei",
    "wof:placetype":"locality"
},
  "geometry": {"coordinates":[19.21161,12.61046],"type":"Point"}
}