{
  "type": "Feature",
  "properties": {
    "gn:admin1_code":"7.0",
    "gn:asciiname":"Kalimba",
    "gn:country_code":"TD",
    "gn:dem":294,
    "gn:feature_class":"P",
    "gn:feature_code":"PPL",
    "gn:name":"Kalimba",
    "gn:population":0,
    "gn:timezone":"Africa/Ndjamena",
    "iso:country":"TD",
    "name:und_x_variant":[
        "Kalimboa",
        "Kalimba"
    ],
    "wof:name":"Kalimba",
    "wof:placetype":"locality"
},
  "geometry": {"coordinates":[15.48636,13.34697],"type":"Point"}
}