{
  "type": "Feature",
  "properties": {
    "gn:admin1_code":"16.0",
    "gn:asciiname":"Golohana",
    "gn:country_code":"TD",
    "gn:dem":340,
    "gn:feature_class":"P",
    "gn:feature_code":"PPL",
    "gn:name":"Golohana",
    "gn:population":0,
    "gn:timezone":"Africa/Ndjamena",
    "iso:country":"TD",
    "wof:name":"Golohana",
    "wof:placetype":"locality"
},
  "geometry": {"coordinates":[15.84272,10.07495],"type":"Point"}
}