{
  "type": "Feature",
  "properties": {
    "gn:admin1_code":"16.0",
    "gn:asciiname":"Sorkaye",
    "gn:country_code":"TD",
    "gn:dem":322,
    "gn:feature_class":"P",
    "gn:feature_code":"PPL",
    "gn:name":"Sorkaye",
    "gn:population":0,
    "gn:timezone":"Africa/Ndjamena",
    "iso:country":"TD",
    "wof:name":"Sorkaye",
    "wof:placetype":"locality"
},
  "geometry": {"coordinates":[15.70232,10.51857],"type":"Point"}
}