{
  "type": "Feature",
  "properties": {
    "gn:admin1_code":"15.0",
    "gn:asciiname":"Mai Ache",
    "gn:country_code":"TD",
    "gn:dem":295,
    "gn:feature_class":"P",
    "gn:feature_code":"PPL",
    "gn:name":"Mai Ache",
    "gn:population":0,
    "gn:timezone":"Africa/Ndjamena",
    "iso:country":"TD",
    "name:und_x_variant":[
        "A\u00efch\u00e9",
        "Mai Aishe",
        "Mai Aiche",
        "Mia Acha",
        "Mai Ache"
    ],
    "wof:name":"Mai Ache",
    "wof:placetype":"locality"
},
  "geometry": {"coordinates":[15.73536,11.99455],"type":"Point"}
}