{
  "type": "Feature",
  "properties": {
    "gn:admin1_code":"17.0",
    "gn:asciiname":"Bourbe",
    "gn:country_code":"TD",
    "gn:dem":395,
    "gn:feature_class":"P",
    "gn:feature_code":"PPL",
    "gn:name":"Bourb\u00e9",
    "gn:population":0,
    "gn:timezone":"Africa/Ndjamena",
    "iso:country":"TD",
    "wof:name":"Bourbe",
    "wof:placetype":"locality"
},
  "geometry": {"coordinates":[18.9776,8.5651],"type":"Point"}
}