{
  "type": "Feature",
  "properties": {
    "gn:admin1_code":"8.0",
    "gn:asciiname":"Baila-Kali",
    "gn:country_code":"TD",
    "gn:dem":429,
    "gn:feature_class":"P",
    "gn:feature_code":"PPL",
    "gn:name":"Baila-Kali",
    "gn:population":0,
    "gn:timezone":"Africa/Ndjamena",
    "iso:country":"TD",
    "wof:name":"Baila-Kali",
    "wof:placetype":"locality"
},
  "geometry": {"coordinates":[15.53333,8.95],"type":"Point"}
}