{
  "type": "Feature",
  "properties": {
    "gn:admin1_code":"6.0",
    "gn:asciiname":"Oyoumbou",
    "gn:country_code":"TD",
    "gn:dem":328,
    "gn:feature_class":"P",
    "gn:feature_code":"PPL",
    "gn:name":"Oyoumbou",
    "gn:population":0,
    "gn:timezone":"Africa/Ndjamena",
    "iso:country":"TD",
    "wof:name":"Oyoumbou",
    "wof:placetype":"locality"
},
  "geometry": {"coordinates":[15.38747,14.13666],"type":"Point"}
}