{
  "type": "Feature",
  "properties": {
    "gn:admin1_code":"5.0",
    "gn:asciiname":"Ndaba",
    "gn:country_code":"TD",
    "gn:dem":351,
    "gn:feature_class":"P",
    "gn:feature_code":"PPL",
    "gn:name":"Ndaba",
    "gn:population":0,
    "gn:timezone":"Africa/Ndjamena",
    "iso:country":"TD",
    "wof:name":"Ndaba",
    "wof:placetype":"locality"
},
  "geometry": {"coordinates":[17.6564,10.5198],"type":"Point"}
}