{
  "type": "Feature",
  "properties": {
    "gn:admin1_code":"7.0",
    "gn:asciiname":"Tipsi",
    "gn:country_code":"TD",
    "gn:dem":287,
    "gn:feature_class":"P",
    "gn:feature_code":"PPL",
    "gn:name":"Tipsi",
    "gn:population":0,
    "gn:timezone":"Africa/Ndjamena",
    "iso:country":"TD",
    "wof:name":"Tipsi",
    "wof:placetype":"locality"
},
  "geometry": {"coordinates":[14.95,13.35],"type":"Point"}
}