{
  "type": "Feature",
  "properties": {
    "gn:admin1_code":"19.0",
    "gn:asciiname":"Soro",
    "gn:country_code":"TD",
    "gn:dem":353,
    "gn:feature_class":"P",
    "gn:feature_code":"PPL",
    "gn:name":"Soro",
    "gn:population":0,
    "gn:timezone":"Africa/Ndjamena",
    "iso:country":"TD",
    "wof:name":"Soro",
    "wof:placetype":"locality"
},
  "geometry": {"coordinates":[17.32153,9.45903],"type":"Point"}
}