{
  "type": "Feature",
  "properties": {
    "gn:admin1_code":"25.0",
    "gn:asciiname":"Moungalkasi",
    "gn:country_code":"TD",
    "gn:dem":642,
    "gn:feature_class":"P",
    "gn:feature_code":"PPL",
    "gn:name":"Moungalkasi",
    "gn:population":0,
    "gn:timezone":"Africa/Ndjamena",
    "iso:country":"TD",
    "wof:name":"Moungalkasi",
    "wof:placetype":"locality"
},
  "geometry": {"coordinates":[21.81667,12.58333],"type":"Point"}
}