{
  "type": "Feature",
  "properties": {
    "gn:admin1_code":"5.0",
    "gn:asciiname":"Nara Moura",
    "gn:country_code":"TD",
    "gn:dem":385,
    "gn:feature_class":"P",
    "gn:feature_code":"PPL",
    "gn:name":"Nara Moura",
    "gn:population":0,
    "gn:timezone":"Africa/Ndjamena",
    "iso:country":"TD",
    "wof:name":"Nara Moura",
    "wof:placetype":"locality"
},
  "geometry": {"coordinates":[18.7242,9.9878],"type":"Point"}
}