{
  "type": "Feature",
  "properties": {
    "gn:admin1_code":"19.0",
    "gn:asciiname":"Nado",
    "gn:country_code":"TD",
    "gn:dem":383,
    "gn:feature_class":"P",
    "gn:feature_code":"PPL",
    "gn:name":"Nado",
    "gn:population":0,
    "gn:timezone":"Africa/Ndjamena",
    "iso:country":"TD",
    "wof:name":"Nado",
    "wof:placetype":"locality"
},
  "geometry": {"coordinates":[17.54932,9.36673],"type":"Point"}
}