{
  "type": "Feature",
  "properties": {
    "gn:admin1_code":"2.0",
    "gn:asciiname":"Dourkoule",
    "gn:country_code":"TD",
    "gn:dem":1077,
    "gn:feature_class":"P",
    "gn:feature_code":"PPL",
    "gn:name":"Dourkoul\u00e9",
    "gn:population":0,
    "gn:timezone":"Africa/Ndjamena",
    "iso:country":"TD",
    "wof:name":"Dourkoule",
    "wof:placetype":"locality"
},
  "geometry": {"coordinates":[22.21667,14.45],"type":"Point"}
}