{
  "type": "Feature",
  "properties": {
    "gn:admin1_code":"17.0",
    "gn:asciiname":"Aka",
    "gn:country_code":"TD",
    "gn:dem":384,
    "gn:feature_class":"P",
    "gn:feature_code":"PPL",
    "gn:name":"Aka",
    "gn:population":0,
    "gn:timezone":"Africa/Ndjamena",
    "iso:country":"TD",
    "name:ceb_x_preferred":[
        "Aka"
    ],
    "name:ces_x_preferred":[
        "Aka"
    ],
    "name:deu_x_preferred":[
        "Aka"
    ],
    "name:fra_x_preferred":[
        "Aka"
    ],
    "name:lav_x_preferred":[
        "AKA"
    ],
    "name:nld_x_preferred":[
        "Aka"
    ],
    "name:pol_x_preferred":[
        "Aka"
    ],
    "name:rus_x_preferred":[
        "\u0410\u043a\u0430"
    ],
    "name:spa_x_preferred":[
        "Aka"
    ],
    "name:swe_x_preferred":[
        "Aka"
    ],
    "name:ukr_x_preferred":[
        "Aka"
    ],
    "wof:name":"Aka",
    "wof:placetype":"locality"
},
  "geometry": {"coordinates":[19.0197,9.48347],"type":"Point"}
}