{
  "type": "Feature",
  "properties": {
    "gn:admin1_code":"17.0",
    "gn:asciiname":"Djomal",
    "gn:country_code":"TD",
    "gn:dem":425,
    "gn:feature_class":"P",
    "gn:feature_code":"PPL",
    "gn:name":"Djomal",
    "gn:population":0,
    "gn:timezone":"Africa/Ndjamena",
    "iso:country":"TD",
    "wof:name":"Djomal",
    "wof:placetype":"locality"
},
  "geometry": {"coordinates":[17.8485,10.4935],"type":"Point"}
}