{
  "type": "Feature",
  "properties": {
    "gn:admin1_code":"26.0",
    "gn:asciiname":"Omou",
    "gn:country_code":"TD",
    "gn:dem":1078,
    "gn:feature_class":"P",
    "gn:feature_code":"PPL",
    "gn:name":"Omou",
    "gn:population":0,
    "gn:timezone":"Africa/Ndjamena",
    "iso:country":"TD",
    "wof:name":"Omou",
    "wof:placetype":"locality"
},
  "geometry": {"coordinates":[18.05,21.53333],"type":"Point"}
}