{
  "type": "Feature",
  "properties": {
    "gn:admin1_code":"19.0",
    "gn:asciiname":"Gondala",
    "gn:country_code":"TD",
    "gn:dem":375,
    "gn:feature_class":"P",
    "gn:feature_code":"PPL",
    "gn:name":"Gondala",
    "gn:population":0,
    "gn:timezone":"Africa/Ndjamena",
    "iso:country":"TD",
    "wof:name":"Gondala",
    "wof:placetype":"locality"
},
  "geometry": {"coordinates":[17.42406,9.17584],"type":"Point"}
}