{
  "type": "Feature",
  "properties": {
    "gn:admin1_code":"14.0",
    "gn:asciiname":"Djaoula",
    "gn:country_code":"TD",
    "gn:dem":392,
    "gn:feature_class":"P",
    "gn:feature_code":"PPL",
    "gn:name":"Djaoula",
    "gn:population":0,
    "gn:timezone":"Africa/Ndjamena",
    "iso:country":"TD",
    "name:und_x_variant":[
        "N\u2019Zaola",
        "Djaoula"
    ],
    "wof:name":"Djaoula",
    "wof:placetype":"locality"
},
  "geometry": {"coordinates":[16.15757,9.12673],"type":"Point"}
}