{
  "type": "Feature",
  "properties": {
    "gn:admin1_code":"18.0",
    "gn:asciiname":"Abdoulay Kaou",
    "gn:country_code":"TD",
    "gn:dem":292,
    "gn:feature_class":"P",
    "gn:feature_code":"PPL",
    "gn:name":"Abdoulay Kaou",
    "gn:population":0,
    "gn:timezone":"Africa/Ndjamena",
    "iso:country":"TD",
    "wof:name":"Abdoulay Kaou",
    "wof:placetype":"locality"
},
  "geometry": {"coordinates":[17.12994,12.5406],"type":"Point"}
}