{
  "type": "Feature",
  "properties": {
    "gn:admin1_code":"17.0",
    "gn:asciiname":"Toula",
    "gn:country_code":"TD",
    "gn:dem":355,
    "gn:feature_class":"P",
    "gn:feature_code":"PPL",
    "gn:name":"Toula",
    "gn:population":0,
    "gn:timezone":"Africa/Ndjamena",
    "iso:country":"TD",
    "name:ceb_x_preferred":[
        "Toula"
    ],
    "name:fra_x_preferred":[
        "Toula"
    ],
    "name:swe_x_preferred":[
        "Toula"
    ],
    "wof:name":"Toula",
    "wof:placetype":"locality"
},
  "geometry": {"coordinates":[17.7316,10.2669],"type":"Point"}
}