{
  "type": "Feature",
  "properties": {
    "gn:admin1_code":"2.0",
    "gn:asciiname":"Zanbane",
    "gn:country_code":"TD",
    "gn:dem":552,
    "gn:feature_class":"P",
    "gn:feature_code":"PPL",
    "gn:name":"Zanbane",
    "gn:population":0,
    "gn:timezone":"Africa/Ndjamena",
    "iso:country":"TD",
    "name:fra_x_preferred":[
        "Zanbane"
    ],
    "wof:name":"Zanbane",
    "wof:placetype":"locality"
},
  "geometry": {"coordinates":[21.14661,14.66068],"type":"Point"}
}