{
  "type": "Feature",
  "properties": {
    "gn:admin1_code":"19.0",
    "gn:asciiname":"Golt",
    "gn:country_code":"TD",
    "gn:dem":378,
    "gn:feature_class":"P",
    "gn:feature_code":"PPL",
    "gn:name":"Golt",
    "gn:population":0,
    "gn:timezone":"Africa/Ndjamena",
    "iso:country":"TD",
    "wof:name":"Golt",
    "wof:placetype":"locality"
},
  "geometry": {"coordinates":[17.41803,9.23514],"type":"Point"}
}