{
  "type": "Feature",
  "properties": {
    "gn:admin1_code":"16.0",
    "gn:asciiname":"Matchaka",
    "gn:country_code":"TD",
    "gn:dem":328,
    "gn:feature_class":"P",
    "gn:feature_code":"PPL",
    "gn:name":"Matchaka",
    "gn:population":0,
    "gn:timezone":"Africa/Ndjamena",
    "iso:country":"TD",
    "wof:name":"Matchaka",
    "wof:placetype":"locality"
},
  "geometry": {"coordinates":[15.60525,10.2175],"type":"Point"}
}