{
  "type": "Feature",
  "properties": {
    "gn:admin1_code":"18.0",
    "gn:asciiname":"Djimez",
    "gn:country_code":"TD",
    "gn:dem":316,
    "gn:feature_class":"P",
    "gn:feature_code":"PPL",
    "gn:name":"Djimez",
    "gn:population":0,
    "gn:timezone":"Africa/Ndjamena",
    "iso:country":"TD",
    "name:und_x_variant":[
        "Djim\u00e8ze",
        "Djimez"
    ],
    "wof:name":"Djimez",
    "wof:placetype":"locality"
},
  "geometry": {"coordinates":[17.1688,11.8522],"type":"Point"}
}