{
  "type": "Feature",
  "properties": {
    "gn:admin1_code":"18.0",
    "gn:asciiname":"Arboutchatak",
    "gn:country_code":"TD",
    "gn:dem":332,
    "gn:feature_class":"P",
    "gn:feature_code":"PPL",
    "gn:name":"Arboutchatak",
    "gn:population":0,
    "gn:timezone":"Africa/Ndjamena",
    "iso:country":"TD",
    "name:und_x_variant":[
        "Arboulchatap",
        "Arbotchak",
        "Arbouchatak",
        "Arboutchatak"
    ],
    "wof:name":"Arboutchatak",
    "wof:placetype":"locality"
},
  "geometry": {"coordinates":[17.55405,12.12937],"type":"Point"}
}