{
  "type": "Feature",
  "properties": {
    "gn:admin1_code":"25.0",
    "gn:asciiname":"Dirango",
    "gn:country_code":"TD",
    "gn:dem":603,
    "gn:feature_class":"P",
    "gn:feature_code":"PPL",
    "gn:name":"Dirango",
    "gn:population":0,
    "gn:timezone":"Africa/Ndjamena",
    "iso:country":"TD",
    "wof:name":"Dirango",
    "wof:placetype":"locality"
},
  "geometry": {"coordinates":[22.38333,12.23333],"type":"Point"}
}