{
  "type": "Feature",
  "properties": {
    "gn:admin1_code":"14.0",
    "gn:asciiname":"Bidakaride",
    "gn:country_code":"TD",
    "gn:dem":363,
    "gn:feature_class":"P",
    "gn:feature_code":"PPL",
    "gn:name":"Bidakarid\u00e9",
    "gn:population":0,
    "gn:timezone":"Africa/Ndjamena",
    "iso:country":"TD",
    "name:und_x_variant":[
        "B\u00e9dakarad\u00e9",
        "Bidakarid\u00e9"
    ],
    "wof:name":"Bidakaride",
    "wof:placetype":"locality"
},
  "geometry": {"coordinates":[16.62902,9.28027],"type":"Point"}
}