{
  "type": "Feature",
  "properties": {
    "gn:admin1_code":"19.0",
    "gn:asciiname":"Do",
    "gn:country_code":"TD",
    "gn:dem":381,
    "gn:feature_class":"P",
    "gn:feature_code":"PPL",
    "gn:name":"Do",
    "gn:population":0,
    "gn:timezone":"Africa/Ndjamena",
    "iso:country":"TD",
    "name:und_x_variant":[
        "D\u00f4o",
        "Do"
    ],
    "wof:name":"Do",
    "wof:placetype":"locality"
},
  "geometry": {"coordinates":[17.8461,8.3792],"type":"Point"}
}