{
  "type": "Feature",
  "properties": {
    "gn:admin1_code":"18.0",
    "gn:asciiname":"Am Chiguek",
    "gn:country_code":"TD",
    "gn:dem":296,
    "gn:feature_class":"P",
    "gn:feature_code":"PPL",
    "gn:name":"Am Chiguek",
    "gn:population":0,
    "gn:timezone":"Africa/Ndjamena",
    "iso:country":"TD",
    "name:und_x_variant":[
        "Achigek",
        "Am Chiguek"
    ],
    "wof:name":"Am Chiguek",
    "wof:placetype":"locality"
},
  "geometry": {"coordinates":[15.28344,12.30258],"type":"Point"}
}