{
  "type": "Feature",
  "properties": {
    "gn:admin1_code":"18.0",
    "gn:asciiname":"Abourda Ndouta",
    "gn:country_code":"TD",
    "gn:dem":296,
    "gn:feature_class":"P",
    "gn:feature_code":"PPL",
    "gn:name":"Abourda Ndouta",
    "gn:population":0,
    "gn:timezone":"Africa/Ndjamena",
    "iso:country":"TD",
    "name:und_x_variant":[
        "Bourda",
        "Abourda",
        "Abourda Ndouta"
    ],
    "wof:name":"Abourda Ndouta",
    "wof:placetype":"locality"
},
  "geometry": {"coordinates":[17.20731,12.52144],"type":"Point"}
}