{
  "type": "Feature",
  "properties": {
    "gn:admin1_code":"13.0",
    "gn:asciiname":"Alouvar",
    "gn:country_code":"TD",
    "gn:dem":478,
    "gn:feature_class":"P",
    "gn:feature_code":"PPL",
    "gn:name":"Alouvar",
    "gn:population":0,
    "gn:timezone":"Africa/Ndjamena",
    "iso:country":"TD",
    "wof:name":"Alouvar",
    "wof:placetype":"locality"
},
  "geometry": {"coordinates":[19.0441,11.6072],"type":"Point"}
}