{
  "type": "Feature",
  "properties": {
    "gn:admin1_code":"7.0",
    "gn:asciiname":"Arzat",
    "gn:country_code":"TD",
    "gn:dem":304,
    "gn:feature_class":"P",
    "gn:feature_code":"PPL",
    "gn:name":"Arzat",
    "gn:population":0,
    "gn:timezone":"Africa/Ndjamena",
    "iso:country":"TD",
    "name:nno_x_preferred":[
        "Arzat"
    ],
    "wof:name":"Arzat",
    "wof:placetype":"locality"
},
  "geometry": {"coordinates":[15.56546,13.51687],"type":"Point"}
}