{
  "type": "Feature",
  "properties": {
    "gn:admin1_code":"15.0",
    "gn:asciiname":"Guidgada",
    "gn:country_code":"TD",
    "gn:dem":330,
    "gn:feature_class":"P",
    "gn:feature_code":"PPL",
    "gn:name":"Guidgada",
    "gn:population":0,
    "gn:timezone":"Africa/Ndjamena",
    "iso:country":"TD",
    "name:und_x_variant":[
        "Gidgada",
        "Guidgada"
    ],
    "wof:name":"Guidgada",
    "wof:placetype":"locality"
},
  "geometry": {"coordinates":[16.1818,11.6474],"type":"Point"}
}