{
  "type": "Feature",
  "properties": {
    "gn:admin1_code":"9.0",
    "gn:asciiname":"Bebemkandji",
    "gn:country_code":"TD",
    "gn:dem":470,
    "gn:feature_class":"P",
    "gn:feature_code":"PPL",
    "gn:name":"B\u00e9b\u00e8mkandji",
    "gn:population":0,
    "gn:timezone":"Africa/Ndjamena",
    "iso:country":"TD",
    "wof:name":"Bebemkandji",
    "wof:placetype":"locality"
},
  "geometry": {"coordinates":[16.25726,8.01602],"type":"Point"}
}