{
  "type": "Feature",
  "properties": {
    "gn:admin1_code":"17.0",
    "gn:asciiname":"Mandekaga",
    "gn:country_code":"TD",
    "gn:dem":364,
    "gn:feature_class":"P",
    "gn:feature_code":"PPL",
    "gn:name":"Mand\u00e9kaga",
    "gn:population":0,
    "gn:timezone":"Africa/Ndjamena",
    "iso:country":"TD",
    "wof:name":"Mandekaga",
    "wof:placetype":"locality"
},
  "geometry": {"coordinates":[18.2744,9.2048],"type":"Point"}
}