{
  "type": "Feature",
  "properties": {
    "gn:admin1_code":"26.0",
    "gn:asciiname":"Tommi",
    "gn:country_code":"TD",
    "gn:dem":1151,
    "gn:feature_class":"P",
    "gn:feature_code":"PPL",
    "gn:name":"Tommi",
    "gn:population":0,
    "gn:timezone":"Africa/Ndjamena",
    "iso:country":"TD",
    "wof:name":"Tommi",
    "wof:placetype":"locality"
},
  "geometry": {"coordinates":[17.55,21.56667],"type":"Point"}
}