{
  "type": "Feature",
  "properties": {
    "gn:admin1_code":"2.0",
    "gn:asciiname":"Tourmoundi",
    "gn:country_code":"TD",
    "gn:dem":806,
    "gn:feature_class":"P",
    "gn:feature_code":"PPL",
    "gn:name":"Tourmoundi",
    "gn:population":0,
    "gn:timezone":"Africa/Ndjamena",
    "iso:country":"TD",
    "name:fra_x_preferred":[
        "Tourmoundi"
    ],
    "wof:name":"Tourmoundi",
    "wof:placetype":"locality"
},
  "geometry": {"coordinates":[21.38203,14.17827],"type":"Point"}
}