{
  "type": "Feature",
  "properties": {
    "gn:admin1_code":"20.0",
    "gn:asciiname":"Edaka",
    "gn:country_code":"TD",
    "gn:dem":388,
    "gn:feature_class":"P",
    "gn:feature_code":"PPL",
    "gn:name":"Edaka",
    "gn:population":0,
    "gn:timezone":"Africa/Ndjamena",
    "iso:country":"TD",
    "wof:name":"Edaka",
    "wof:placetype":"locality"
},
  "geometry": {"coordinates":[14.7418,9.2261],"type":"Point"}
}