{
  "type": "Feature",
  "properties": {
    "gn:admin1_code":"15.0",
    "gn:asciiname":"Maguilka",
    "gn:country_code":"TD",
    "gn:dem":304,
    "gn:feature_class":"P",
    "gn:feature_code":"PPL",
    "gn:name":"Maguilka",
    "gn:population":0,
    "gn:timezone":"Africa/Ndjamena",
    "iso:country":"TD",
    "name:und_x_variant":[
        "Magilka",
        "Maguilka"
    ],
    "wof:name":"Maguilka",
    "wof:placetype":"locality"
},
  "geometry": {"coordinates":[15.48907,11.79997],"type":"Point"}
}