{
  "type": "Feature",
  "properties": {
    "gn:admin1_code":"5.0",
    "gn:asciiname":"Ndjione",
    "gn:country_code":"TD",
    "gn:dem":510,
    "gn:feature_class":"P",
    "gn:feature_code":"PPL",
    "gn:name":"Ndjione",
    "gn:population":0,
    "gn:timezone":"Africa/Ndjamena",
    "iso:country":"TD",
    "name:und_x_variant":[
        "Ndjion",
        "Ndjione"
    ],
    "wof:name":"Ndjione",
    "wof:placetype":"locality"
},
  "geometry": {"coordinates":[18.36351,11.71505],"type":"Point"}
}