{
  "type": "Feature",
  "properties": {
    "gn:admin1_code":"15.0",
    "gn:asciiname":"Massafi",
    "gn:country_code":"TD",
    "gn:dem":299,
    "gn:feature_class":"P",
    "gn:feature_code":"PPL",
    "gn:name":"Massafi",
    "gn:population":0,
    "gn:timezone":"Africa/Ndjamena",
    "iso:country":"TD",
    "name:und_x_variant":[
        "Masafi",
        "Massafi"
    ],
    "wof:name":"Massafi",
    "wof:placetype":"locality"
},
  "geometry": {"coordinates":[15.89172,12.286],"type":"Point"}
}