{
  "type": "Feature",
  "properties": {
    "gn:admin1_code":"19.0",
    "gn:asciiname":"Kenguele",
    "gn:country_code":"TD",
    "gn:dem":409,
    "gn:feature_class":"P",
    "gn:feature_code":"PPL",
    "gn:name":"Kengu\u00e9l\u00e9",
    "gn:population":0,
    "gn:timezone":"Africa/Ndjamena",
    "iso:country":"TD",
    "wof:name":"Kenguele",
    "wof:placetype":"locality"
},
  "geometry": {"coordinates":[17.5722,8.9117],"type":"Point"}
}