{
  "type": "Feature",
  "properties": {
    "gn:admin1_code":"9.0",
    "gn:asciiname":"Bemotinnti",
    "gn:country_code":"TD",
    "gn:dem":385,
    "gn:feature_class":"P",
    "gn:feature_code":"PPL",
    "gn:name":"B\u00e9motinnti",
    "gn:population":0,
    "gn:timezone":"Africa/Ndjamena",
    "iso:country":"TD",
    "wof:name":"Bemotinnti",
    "wof:placetype":"locality"
},
  "geometry": {"coordinates":[16.94497,8.87304],"type":"Point"}
}