{
  "type": "Feature",
  "properties": {
    "gn:admin1_code":"7.0",
    "gn:asciiname":"Tao",
    "gn:cc2":"TD",
    "gn:country_code":"TD",
    "gn:dem":286,
    "gn:feature_class":"P",
    "gn:feature_code":"PPL",
    "gn:name":"Tao",
    "gn:population":0,
    "gn:timezone":"Africa/Ndjamena",
    "iso:country":"TD",
    "name:und_x_variant":[
        "Tao I",
        "Tao"
    ],
    "wof:name":"Tao",
    "wof:placetype":"locality"
},
  "geometry": {"coordinates":[14.88333,13.48333],"type":"Point"}
}