{
  "type": "Feature",
  "properties": {
    "gn:admin1_code":"16.0",
    "gn:asciiname":"Dom",
    "gn:country_code":"TD",
    "gn:dem":335,
    "gn:feature_class":"P",
    "gn:feature_code":"PPL",
    "gn:name":"Dom",
    "gn:population":0,
    "gn:timezone":"Africa/Ndjamena",
    "iso:country":"TD",
    "name:als_x_preferred":[
        "Dom"
    ],
    "name:cat_x_preferred":[
        "Dom"
    ],
    "name:ceb_x_preferred":[
        "Dom"
    ],
    "name:ces_x_preferred":[
        "Dom"
    ],
    "name:che_x_preferred":[
        "\u0426\u04c0\u0430"
    ],
    "name:dan_x_preferred":[
        "Dom"
    ],
    "name:deu_x_preferred":[
        "Dom"
    ],
    "name:ell_x_preferred":[
        "\u039d\u03c4\u03bf\u03bc"
    ],
    "name:fas_x_preferred":[
        "Dom"
    ],
    "name:fin_x_preferred":[
        "Dom"
    ],
    "name:nld_x_preferred":[
        "Dom"
    ],
    "name:nno_x_preferred":[
        "Dom"
    ],
    "name:pol_x_preferred":[
        "Dom"
    ],
    "name:por_x_preferred":[
        "Dom"
    ],
    "name:ron_x_preferred":[
        "Dom"
    ],
    "name:rus_x_preferred":[
        "\u0414\u043e\u043c"
    ],
    "name:slk_x_preferred":[
        "Dom"
    ],
    "name:spa_x_preferred":[
        "Dom"
    ],
    "name:swe_x_preferred":[
        "Dom"
    ],
    "name:tha_x_preferred":[
        "\u0e14\u0e2d\u0e21"
    ],
    "name:uzb_x_preferred":[
        "Dom"
    ],
    "wof:name":"Dom",
    "wof:placetype":"locality"
},
  "geometry": {"coordinates":[15.50604,9.90371],"type":"Point"}
}