{
  "type": "Feature",
  "properties": {
    "gn:admin1_code":"14.0",
    "gn:asciiname":"Pam",
    "gn:country_code":"TD",
    "gn:dem":354,
    "gn:feature_class":"P",
    "gn:feature_code":"PPL",
    "gn:name":"Pam",
    "gn:population":0,
    "gn:timezone":"Africa/Ndjamena",
    "iso:country":"TD",
    "wof:name":"Pam",
    "wof:placetype":"locality"
},
  "geometry": {"coordinates":[16.4035,9.5485],"type":"Point"}
}