{
  "type": "Feature",
  "properties": {
    "gn:admin1_code":"1.0",
    "gn:asciiname":"Wagna",
    "gn:country_code":"TD",
    "gn:dem":289,
    "gn:feature_class":"P",
    "gn:feature_code":"PPL",
    "gn:name":"Wagna",
    "gn:population":0,
    "gn:timezone":"Africa/Ndjamena",
    "iso:country":"TD",
    "name:ceb_x_preferred":[
        "Wagna"
    ],
    "name:deu_x_preferred":[
        "Wagna"
    ],
    "name:epo_x_preferred":[
        "Wagna"
    ],
    "name:fas_x_preferred":[
        "\u0648\u0627\u06af\u0646\u0627"
    ],
    "name:fra_x_preferred":[
        "Wagna"
    ],
    "name:hun_x_preferred":[
        "Wagna"
    ],
    "name:ita_x_preferred":[
        "Wagna"
    ],
    "name:kaz_x_preferred":[
        "\u0412\u0430\u0433\u043d\u0430"
    ],
    "name:nld_x_preferred":[
        "Wagna"
    ],
    "name:nno_x_preferred":[
        "Wagna"
    ],
    "name:pol_x_preferred":[
        "Wagna"
    ],
    "name:rus_x_preferred":[
        "\u0412\u0430\u0433\u043d\u0430"
    ],
    "name:slk_x_preferred":[
        "Wagna"
    ],
    "name:spa_x_preferred":[
        "Wagna"
    ],
    "name:swe_x_preferred":[
        "Wagna"
    ],
    "name:uzb_x_preferred":[
        "Wagna"
    ],
    "name:vie_x_preferred":[
        "Wagna"
    ],
    "name:vol_x_preferred":[
        "Wagna"
    ],
    "name:war_x_preferred":[
        "Wagna"
    ],
    "name:zho_x_preferred":[
        "\u74e6\u683c\u7eb3"
    ],
    "wof:name":"Wagna",
    "wof:placetype":"locality"
},
  "geometry": {"coordinates":[17.31468,12.90959],"type":"Point"}
}