{
  "type": "Feature",
  "properties": {
    "gn:admin1_code":"19.0",
    "gn:asciiname":"Gotekedi",
    "gn:country_code":"TD",
    "gn:dem":391,
    "gn:feature_class":"P",
    "gn:feature_code":"PPL",
    "gn:name":"Gotekedi",
    "gn:population":0,
    "gn:timezone":"Africa/Ndjamena",
    "iso:country":"TD",
    "wof:name":"Gotekedi",
    "wof:placetype":"locality"
},
  "geometry": {"coordinates":[17.2573,8.3734],"type":"Point"}
}