{
  "type": "Feature",
  "properties": {
    "gn:admin1_code":"18.0",
    "gn:asciiname":"Al Himede",
    "gn:country_code":"TD",
    "gn:dem":319,
    "gn:feature_class":"P",
    "gn:feature_code":"PPL",
    "gn:name":"Al Him\u00e9d\u00e9",
    "gn:population":0,
    "gn:timezone":"Africa/Ndjamena",
    "iso:country":"TD",
    "wof:name":"Al Himede",
    "wof:placetype":"locality"
},
  "geometry": {"coordinates":[17.13698,12.03478],"type":"Point"}
}