{
  "type": "Feature",
  "properties": {
    "gn:admin1_code":"18.0",
    "gn:asciiname":"Sarafa",
    "gn:country_code":"TD",
    "gn:dem":297,
    "gn:feature_class":"P",
    "gn:feature_code":"PPL",
    "gn:name":"Sarafa",
    "gn:population":0,
    "gn:timezone":"Africa/Ndjamena",
    "iso:country":"TD",
    "wof:name":"Sarafa",
    "wof:placetype":"locality"
},
  "geometry": {"coordinates":[15.59026,12.39785],"type":"Point"}
}