{
  "type": "Feature",
  "properties": {
    "gn:admin1_code":"18.0",
    "gn:asciiname":"Bir Kerala",
    "gn:country_code":"TD",
    "gn:dem":290,
    "gn:feature_class":"P",
    "gn:feature_code":"PPL",
    "gn:name":"Bir K\u00e9rala",
    "gn:population":0,
    "gn:timezone":"Africa/Ndjamena",
    "iso:country":"TD",
    "wof:name":"Bir Kerala",
    "wof:placetype":"locality"
},
  "geometry": {"coordinates":[15.4032,12.84271],"type":"Point"}
}