{
  "type": "Feature",
  "properties": {
    "gn:admin1_code":"9.0",
    "gn:asciiname":"Kaira",
    "gn:country_code":"TD",
    "gn:dem":415,
    "gn:feature_class":"P",
    "gn:feature_code":"PPL",
    "gn:name":"Ka\u00efra",
    "gn:population":0,
    "gn:timezone":"Africa/Ndjamena",
    "iso:country":"TD",
    "name:ceb_x_preferred":[
        "Kaira"
    ],
    "name:fin_x_preferred":[
        "Kaira"
    ],
    "name:ita_x_preferred":[
        "Kaira"
    ],
    "name:swe_x_preferred":[
        "Kaira"
    ],
    "wof:name":"Kaira",
    "wof:placetype":"locality"
},
  "geometry": {"coordinates":[16.26863,8.61262],"type":"Point"}
}