{
  "type": "Feature",
  "properties": {
    "gn:admin1_code":"17.0",
    "gn:asciiname":"Gour",
    "gn:country_code":"TD",
    "gn:dem":358,
    "gn:feature_class":"P",
    "gn:feature_code":"PPL",
    "gn:name":"Gour",
    "gn:population":0,
    "gn:timezone":"Africa/Ndjamena",
    "iso:country":"TD",
    "name:ceb_x_preferred":[
        "Gour"
    ],
    "name:swe_x_preferred":[
        "Gour"
    ],
    "wof:name":"Gour",
    "wof:placetype":"locality"
},
  "geometry": {"coordinates":[17.8518,10.078],"type":"Point"}
}