{
  "type": "Feature",
  "properties": {
    "gn:admin1_code":"19.0",
    "gn:asciiname":"Koudoti",
    "gn:country_code":"TD",
    "gn:dem":389,
    "gn:feature_class":"P",
    "gn:feature_code":"PPL",
    "gn:name":"Koudoti",
    "gn:population":0,
    "gn:timezone":"Africa/Ndjamena",
    "iso:country":"TD",
    "name:und_x_variant":[
        "Koudou",
        "Koudoti"
    ],
    "wof:name":"Koudoti",
    "wof:placetype":"locality"
},
  "geometry": {"coordinates":[17.5461,8.2162],"type":"Point"}
}