{
  "type": "Feature",
  "properties": {
    "gn:admin1_code":"9.0",
    "gn:asciiname":"Mini",
    "gn:country_code":"TD",
    "gn:dem":559,
    "gn:feature_class":"P",
    "gn:feature_code":"PPL",
    "gn:name":"Mini",
    "gn:population":0,
    "gn:timezone":"Africa/Ndjamena",
    "iso:country":"TD",
    "wof:name":"Mini",
    "wof:placetype":"locality"
},
  "geometry": {"coordinates":[15.54397,7.52701],"type":"Point"}
}