{
  "type": "Feature",
  "properties": {
    "gn:admin1_code":"9.0",
    "gn:asciiname":"Mini",
    "gn:country_code":"TD",
    "gn:dem":559,
    "gn:feature_class":"P",
    "gn:feature_code":"PPL",
    "gn:name":"Mini",
    "gn:population":0,
    "gn:timezone":"Africa/Ndjamena",
    "iso:country":"TD",
    "name:ara_x_preferred":[
        "\u0645\u064a\u0646\u064a \u0643\u0648\u0628\u0631"
    ],
    "name:azb_x_preferred":[
        "\u0645\u06cc\u0646\u06cc"
    ],
    "name:bul_x_preferred":[
        "\u041c\u0438\u043d\u0438"
    ],
    "name:cat_x_preferred":[
        "Mini"
    ],
    "name:ces_x_preferred":[
        "Mini"
    ],
    "name:ckb_x_preferred":[
        "\u0645\u06cc\u0646\u06cc \u06a9\u06c6\u067e\u06d5\u0631"
    ],
    "name:dan_x_preferred":[
        "Morris Mini"
    ],
    "name:deu_x_preferred":[
        "Mini"
    ],
    "name:epo_x_preferred":[
        "Mini"
    ],
    "name:eus_x_preferred":[
        "Mini"
    ],
    "name:fas_x_preferred":[
        "\u0645\u06cc\u0646\u06cc"
    ],
    "name:fin_x_preferred":[
        "Mini"
    ],
    "name:ind_x_preferred":[
        "Mini Cooper"
    ],
    "name:isl_x_preferred":[
        "Mini"
    ],
    "name:msa_x_preferred":[
        "Mini"
    ],
    "name:nld_x_preferred":[
        "Mini"
    ],
    "name:nor_x_preferred":[
        "Mini"
    ],
    "name:pol_x_preferred":[
        "Mini"
    ],
    "name:rus_x_preferred":[
        "Mini"
    ],
    "name:sco_x_preferred":[
        "Mini"
    ],
    "name:slk_x_preferred":[
        "Mini"
    ],
    "name:slv_x_preferred":[
        "Mini"
    ],
    "name:spa_x_preferred":[
        "Mini"
    ],
    "name:srp_x_preferred":[
        "\u041c\u0438\u043d\u0438"
    ],
    "name:swe_x_preferred":[
        "Mini"
    ],
    "name:tha_x_preferred":[
        "\u0e21\u0e34\u0e19\u0e34"
    ],
    "name:tur_x_preferred":[
        "Mini"
    ],
    "name:ukr_x_preferred":[
        "Mini"
    ],
    "name:vie_x_preferred":[
        "Mini"
    ],
    "wof:name":"Mini",
    "wof:placetype":"locality"
},
  "geometry": {"coordinates":[15.54397,7.52701],"type":"Point"}
}