{
  "type": "Feature",
  "properties": {
    "gn:admin1_code":"17.0",
    "gn:asciiname":"Missi",
    "gn:country_code":"TD",
    "gn:dem":377,
    "gn:feature_class":"P",
    "gn:feature_code":"PPL",
    "gn:name":"Missi",
    "gn:population":0,
    "gn:timezone":"Africa/Ndjamena",
    "iso:country":"TD",
    "wof:name":"Missi",
    "wof:placetype":"locality"
},
  "geometry": {"coordinates":[18.0751,9.285],"type":"Point"}
}