{
  "type": "Feature",
  "properties": {
    "gn:admin1_code":"25.0",
    "gn:asciiname":"Kochokor",
    "gn:country_code":"TD",
    "gn:dem":491,
    "gn:feature_class":"P",
    "gn:feature_code":"PPL",
    "gn:name":"Kochokor",
    "gn:population":0,
    "gn:timezone":"Africa/Ndjamena",
    "iso:country":"TD",
    "wof:name":"Kochokor",
    "wof:placetype":"locality"
},
  "geometry": {"coordinates":[21.298,11.7437],"type":"Point"}
}