{
  "type": "Feature",
  "properties": {
    "gn:admin1_code":"14.0",
    "gn:asciiname":"Moyou",
    "gn:country_code":"TD",
    "gn:dem":356,
    "gn:feature_class":"P",
    "gn:feature_code":"PPL",
    "gn:name":"Moyou",
    "gn:population":0,
    "gn:timezone":"Africa/Ndjamena",
    "iso:country":"TD",
    "wof:name":"Moyou",
    "wof:placetype":"locality"
},
  "geometry": {"coordinates":[16.4845,9.4681],"type":"Point"}
}