{
  "type": "Feature",
  "properties": {
    "gn:admin1_code":"19.0",
    "gn:asciiname":"Waidouaye",
    "gn:country_code":"TD",
    "gn:dem":367,
    "gn:feature_class":"P",
    "gn:feature_code":"PPL",
    "gn:name":"Wa\u00efdouaye",
    "gn:population":0,
    "gn:timezone":"Africa/Ndjamena",
    "iso:country":"TD",
    "wof:name":"Waidouaye",
    "wof:placetype":"locality"
},
  "geometry": {"coordinates":[17.33602,9.40413],"type":"Point"}
}