{
  "type": "Feature",
  "properties": {
    "gn:admin1_code":"2.0",
    "gn:asciiname":"Monada",
    "gn:country_code":"TD",
    "gn:dem":764,
    "gn:feature_class":"P",
    "gn:feature_code":"PPL",
    "gn:name":"Monada",
    "gn:population":0,
    "gn:timezone":"Africa/Ndjamena",
    "iso:country":"TD",
    "name:und_x_variant":[
        "Monoda",
        "Monada"
    ],
    "wof:name":"Monada",
    "wof:placetype":"locality"
},
  "geometry": {"coordinates":[21.18136,14.33532],"type":"Point"}
}