{
  "type": "Feature",
  "properties": {
    "gn:admin1_code":"13.0",
    "gn:asciiname":"Kodjo",
    "gn:country_code":"TD",
    "gn:dem":416,
    "gn:feature_class":"P",
    "gn:feature_code":"PPL",
    "gn:name":"Kodjo",
    "gn:population":0,
    "gn:timezone":"Africa/Ndjamena",
    "iso:country":"TD",
    "name:und_x_variant":[
        "Kodio",
        "Kodia",
        "Kodjo"
    ],
    "wof:name":"Kodjo",
    "wof:placetype":"locality"
},
  "geometry": {"coordinates":[19.8465,10.6334],"type":"Point"}
}