{
  "type": "Feature",
  "properties": {
    "gn:admin1_code":"8.0",
    "gn:asciiname":"Besi Bourou",
    "gn:country_code":"TD",
    "gn:dem":387,
    "gn:feature_class":"P",
    "gn:feature_code":"PPL",
    "gn:name":"Besi Bourou",
    "gn:population":0,
    "gn:timezone":"Africa/Ndjamena",
    "iso:country":"TD",
    "wof:name":"Besi Bourou",
    "wof:placetype":"locality"
},
  "geometry": {"coordinates":[15.71758,9.01877],"type":"Point"}
}