{
  "type": "Feature",
  "properties": {
    "gn:admin1_code":"16.0",
    "gn:asciiname":"Langaye",
    "gn:country_code":"TD",
    "gn:dem":337,
    "gn:feature_class":"P",
    "gn:feature_code":"PPL",
    "gn:name":"Langaye",
    "gn:population":0,
    "gn:timezone":"Africa/Ndjamena",
    "iso:country":"TD",
    "wof:name":"Langaye",
    "wof:placetype":"locality"
},
  "geometry": {"coordinates":[15.88387,10.09097],"type":"Point"}
}