{
  "type": "Feature",
  "properties": {
    "gn:admin1_code":"5.0",
    "gn:asciiname":"Am Khoumi",
    "gn:country_code":"TD",
    "gn:dem":406,
    "gn:feature_class":"P",
    "gn:feature_code":"PPL",
    "gn:name":"Am Khoumi",
    "gn:population":0,
    "gn:timezone":"Africa/Ndjamena",
    "iso:country":"TD",
    "wof:name":"Am Khoumi",
    "wof:placetype":"locality"
},
  "geometry": {"coordinates":[19.7133,12.8301],"type":"Point"}
}