{
  "type": "Feature",
  "properties": {
    "gn:admin1_code":"7.0",
    "gn:asciiname":"Ndiali",
    "gn:country_code":"TD",
    "gn:dem":309,
    "gn:feature_class":"P",
    "gn:feature_code":"PPL",
    "gn:name":"Ndiali",
    "gn:population":0,
    "gn:timezone":"Africa/Ndjamena",
    "iso:country":"TD",
    "wof:name":"Ndiali",
    "wof:placetype":"locality"
},
  "geometry": {"coordinates":[15.44737,13.72675],"type":"Point"}
}