{
  "type": "Feature",
  "properties": {
    "gn:admin1_code":"14.0",
    "gn:asciiname":"Tchere Ayba",
    "gn:country_code":"TD",
    "gn:dem":354,
    "gn:feature_class":"P",
    "gn:feature_code":"PPL",
    "gn:name":"Tch\u00e9r\u00e9 Ayba",
    "gn:population":0,
    "gn:timezone":"Africa/Ndjamena",
    "iso:country":"TD",
    "name:und_x_variant":[
        "Tch\u00e9r\u00e9",
        "Tch\u00e9r\u00e9 Ayba"
    ],
    "wof:name":"Tchere Ayba",
    "wof:placetype":"locality"
},
  "geometry": {"coordinates":[16.7283,9.414],"type":"Point"}
}