{
  "type": "Feature",
  "properties": {
    "gn:admin1_code":"15.0",
    "gn:asciiname":"Bilamtou",
    "gn:country_code":"TD",
    "gn:dem":335,
    "gn:feature_class":"P",
    "gn:feature_code":"PPL",
    "gn:name":"Bilamtou",
    "gn:population":0,
    "gn:timezone":"Africa/Ndjamena",
    "iso:country":"TD",
    "wof:name":"Bilamtou",
    "wof:placetype":"locality"
},
  "geometry": {"coordinates":[16.5254,10.61827],"type":"Point"}
}