{
  "type": "Feature",
  "properties": {
    "gn:admin1_code":"16.0",
    "gn:asciiname":"Diao Margass",
    "gn:country_code":"TD",
    "gn:dem":313,
    "gn:feature_class":"P",
    "gn:feature_code":"PPL",
    "gn:name":"Diao Margass",
    "gn:population":0,
    "gn:timezone":"Africa/Ndjamena",
    "iso:country":"TD",
    "wof:name":"Diao Margass",
    "wof:placetype":"locality"
},
  "geometry": {"coordinates":[15.33456,10.90425],"type":"Point"}
}