{
  "type": "Feature",
  "properties": {
    "gn:admin1_code":"8.0",
    "gn:asciiname":"Nama",
    "gn:country_code":"TD",
    "gn:dem":373,
    "gn:feature_class":"P",
    "gn:feature_code":"PPL",
    "gn:name":"Nama",
    "gn:population":0,
    "gn:timezone":"Africa/Ndjamena",
    "iso:country":"TD",
    "name:fra_x_preferred":[
        "Nama"
    ],
    "wof:name":"Nama",
    "wof:placetype":"locality"
},
  "geometry": {"coordinates":[16.55383,8.94728],"type":"Point"}
}