{
  "type": "Feature",
  "properties": {
    "gn:admin1_code":"12.0",
    "gn:asciiname":"Koudiomera",
    "gn:country_code":"TD",
    "gn:dem":600,
    "gn:feature_class":"P",
    "gn:feature_code":"PPL",
    "gn:name":"Koudiom\u00e9ra",
    "gn:population":0,
    "gn:timezone":"Africa/Ndjamena",
    "iso:country":"TD",
    "name:und_x_variant":[
        "Kadjimira",
        "Kadjmira",
        "Koudiom\u00e9ra"
    ],
    "wof:name":"Koudiomera",
    "wof:placetype":"locality"
},
  "geometry": {"coordinates":[21.05633,13.55892],"type":"Point"}
}