{
  "type": "Feature",
  "properties": {
    "gn:admin1_code":"2.0",
    "gn:asciiname":"Touil",
    "gn:country_code":"TD",
    "gn:dem":444,
    "gn:feature_class":"P",
    "gn:feature_code":"PPL",
    "gn:name":"Touil",
    "gn:population":0,
    "gn:timezone":"Africa/Ndjamena",
    "iso:country":"TD",
    "name:fra_x_preferred":[
        "Touil"
    ],
    "name:ita_x_preferred":[
        "Touil"
    ],
    "name:msa_x_preferred":[
        "Touil"
    ],
    "name:ron_x_preferred":[
        "Touil"
    ],
    "name:spa_x_preferred":[
        "Touil"
    ],
    "wof:name":"Touil",
    "wof:placetype":"locality"
},
  "geometry": {"coordinates":[20.47289,14.49793],"type":"Point"}
}