{
  "type": "Feature",
  "properties": {
    "gn:admin1_code":"5.0",
    "gn:asciiname":"Defafin",
    "gn:country_code":"TD",
    "gn:dem":340,
    "gn:feature_class":"P",
    "gn:feature_code":"PPL",
    "gn:name":"Defafin",
    "gn:population":0,
    "gn:timezone":"Africa/Ndjamena",
    "iso:country":"TD",
    "name:und_x_variant":[
        "Delafine",
        "Defafin"
    ],
    "wof:name":"Defafin",
    "wof:placetype":"locality"
},
  "geometry": {"coordinates":[17.6059,12.04627],"type":"Point"}
}