{
  "type": "Feature",
  "properties": {
    "gn:admin1_code":"7.0",
    "gn:asciiname":"Kayo",
    "gn:country_code":"TD",
    "gn:dem":292,
    "gn:feature_class":"P",
    "gn:feature_code":"PPL",
    "gn:name":"Kayo",
    "gn:population":0,
    "gn:timezone":"Africa/Ndjamena",
    "iso:country":"TD",
    "name:ceb_x_preferred":[
        "Kayo"
    ],
    "wof:name":"Kayo",
    "wof:placetype":"locality"
},
  "geometry": {"coordinates":[15.21667,13.41667],"type":"Point"}
}