{
  "type": "Feature",
  "properties": {
    "gn:admin1_code":"17.0",
    "gn:asciiname":"Gonjita",
    "gn:country_code":"TD",
    "gn:dem":374,
    "gn:feature_class":"P",
    "gn:feature_code":"PPL",
    "gn:name":"Gonjita",
    "gn:population":0,
    "gn:timezone":"Africa/Ndjamena",
    "iso:country":"TD",
    "wof:name":"Gonjita",
    "wof:placetype":"locality"
},
  "geometry": {"coordinates":[18.27632,8.69019],"type":"Point"}
}