{
  "type": "Feature",
  "properties": {
    "gn:admin1_code":"16.0",
    "gn:asciiname":"Gounou Hobo",
    "gn:country_code":"TD",
    "gn:dem":340,
    "gn:feature_class":"P",
    "gn:feature_code":"PPL",
    "gn:name":"Gounou Hobo",
    "gn:population":0,
    "gn:timezone":"Africa/Ndjamena",
    "iso:country":"TD",
    "wof:name":"Gounou Hobo",
    "wof:placetype":"locality"
},
  "geometry": {"coordinates":[15.35525,9.69849],"type":"Point"}
}