{
  "type": "Feature",
  "properties": {
    "gn:admin1_code":"18.0",
    "gn:asciiname":"Am Chechia",
    "gn:country_code":"TD",
    "gn:dem":289,
    "gn:feature_class":"P",
    "gn:feature_code":"PPL",
    "gn:name":"Am Ch\u00e9chia",
    "gn:population":0,
    "gn:timezone":"Africa/Ndjamena",
    "iso:country":"TD",
    "name:und_x_variant":[
        "Am Ch\u00e9chat",
        "Am Chechiat",
        "Am Ch\u00e9chia"
    ],
    "wof:name":"Am Chechia",
    "wof:placetype":"locality"
},
  "geometry": {"coordinates":[15.5291,12.83745],"type":"Point"}
}