{
  "type": "Feature",
  "properties": {
    "gn:admin1_code":"2.0",
    "gn:asciiname":"Kadour",
    "gn:country_code":"TD",
    "gn:dem":633,
    "gn:feature_class":"P",
    "gn:feature_code":"PPL",
    "gn:name":"Kadour",
    "gn:population":0,
    "gn:timezone":"Africa/Ndjamena",
    "iso:country":"TD",
    "name:fra_x_preferred":[
        "Kadour"
    ],
    "wof:name":"Kadour",
    "wof:placetype":"locality"
},
  "geometry": {"coordinates":[21.1766,14.53593],"type":"Point"}
}