{
  "type": "Feature",
  "properties": {
    "gn:admin1_code":"19.0",
    "gn:asciiname":"Bedoua",
    "gn:country_code":"TD",
    "gn:dem":383,
    "gn:feature_class":"P",
    "gn:feature_code":"PPL",
    "gn:name":"B\u00e9doua",
    "gn:population":0,
    "gn:timezone":"Africa/Ndjamena",
    "iso:country":"TD",
    "wof:name":"Bedoua",
    "wof:placetype":"locality"
},
  "geometry": {"coordinates":[17.1643,8.7025],"type":"Point"}
}