{
  "type": "Feature",
  "properties": {
    "gn:admin1_code":"15.0",
    "gn:asciiname":"Amoudater",
    "gn:country_code":"TD",
    "gn:dem":330,
    "gn:feature_class":"P",
    "gn:feature_code":"PPL",
    "gn:name":"Amoudater",
    "gn:population":0,
    "gn:timezone":"Africa/Ndjamena",
    "iso:country":"TD",
    "wof:name":"Amoudater",
    "wof:placetype":"locality"
},
  "geometry": {"coordinates":[15.86223,11.16044],"type":"Point"}
}