{
  "type": "Feature",
  "properties": {
    "gn:admin1_code":"18.0",
    "gn:asciiname":"Lassada",
    "gn:country_code":"TD",
    "gn:dem":294,
    "gn:feature_class":"P",
    "gn:feature_code":"PPL",
    "gn:name":"Lassada",
    "gn:population":0,
    "gn:timezone":"Africa/Ndjamena",
    "iso:country":"TD",
    "name:und_x_variant":[
        "Lasada"
    ],
    "wof:name":"Lassada",
    "wof:placetype":"locality"
},
  "geometry": {"coordinates":[15.11802,12.3077],"type":"Point"}
}