{
  "type": "Feature",
  "properties": {
    "gn:admin1_code":"16.0",
    "gn:asciiname":"Mogaye",
    "gn:country_code":"TD",
    "gn:dem":321,
    "gn:feature_class":"P",
    "gn:feature_code":"PPL",
    "gn:name":"Mogaye",
    "gn:population":0,
    "gn:timezone":"Africa/Ndjamena",
    "iso:country":"TD",
    "name:und_x_variant":[
        "Boudougour",
        "Moukaye",
        "Boudougau",
        "Mogaye"
    ],
    "wof:name":"Mogaye",
    "wof:placetype":"locality"
},
  "geometry": {"coordinates":[15.51934,10.636],"type":"Point"}
}