{
  "type": "Feature",
  "properties": {
    "gn:admin1_code":"18.0",
    "gn:asciiname":"Massalassef",
    "gn:country_code":"TD",
    "gn:dem":291,
    "gn:feature_class":"P",
    "gn:feature_code":"PPL",
    "gn:name":"Massalassef",
    "gn:population":0,
    "gn:timezone":"Africa/Ndjamena",
    "iso:country":"TD",
    "name:und_x_variant":[
        "Masalasef"
    ],
    "wof:name":"Massalassef",
    "wof:placetype":"locality"
},
  "geometry": {"coordinates":[14.96274,12.56288],"type":"Point"}
}