{
  "type": "Feature",
  "properties": {
    "gn:admin1_code":"12.0",
    "gn:asciiname":"Mataze",
    "gn:country_code":"TD",
    "gn:dem":546,
    "gn:feature_class":"P",
    "gn:feature_code":"PPL",
    "gn:name":"Mataz\u00e9",
    "gn:population":0,
    "gn:timezone":"Africa/Ndjamena",
    "iso:country":"TD",
    "wof:name":"Mataze",
    "wof:placetype":"locality"
},
  "geometry": {"coordinates":[21.28093,13.1447],"type":"Point"}
}