{
  "type": "Feature",
  "properties": {
    "gn:admin1_code":"17.0",
    "gn:asciiname":"Balekoutou",
    "gn:country_code":"TD",
    "gn:dem":376,
    "gn:feature_class":"P",
    "gn:feature_code":"PPL",
    "gn:name":"Bal\u00e9koutou",
    "gn:population":0,
    "gn:timezone":"Africa/Ndjamena",
    "iso:country":"TD",
    "name:und_x_variant":[
        "Balkoutou",
        "Bal\u00e9koutou"
    ],
    "wof:name":"Balekoutou",
    "wof:placetype":"locality"
},
  "geometry": {"coordinates":[18.50002000000001,9.70927],"type":"Point"}
}