{
  "type": "Feature",
  "properties": {
    "gn:admin1_code":"5.0",
    "gn:asciiname":"Biere",
    "gn:country_code":"TD",
    "gn:dem":360,
    "gn:feature_class":"P",
    "gn:feature_code":"PPL",
    "gn:name":"Bi\u00e9re",
    "gn:population":0,
    "gn:timezone":"Africa/Ndjamena",
    "iso:country":"TD",
    "wof:name":"Biere",
    "wof:placetype":"locality"
},
  "geometry": {"coordinates":[18.21533,12.42711],"type":"Point"}
}