{
  "type": "Feature",
  "properties": {
    "gn:admin1_code":"8.0",
    "gn:asciiname":"Kol",
    "gn:country_code":"TD",
    "gn:dem":456,
    "gn:feature_class":"P",
    "gn:feature_code":"PPL",
    "gn:name":"Kol",
    "gn:population":0,
    "gn:timezone":"Africa/Ndjamena",
    "iso:country":"TD",
    "wof:name":"Kol",
    "wof:placetype":"locality"
},
  "geometry": {"coordinates":[15.8299,8.5268],"type":"Point"}
}