{
  "type": "Feature",
  "properties": {
    "gn:admin1_code":"9.0",
    "gn:asciiname":"Mbibangan",
    "gn:country_code":"TD",
    "gn:dem":430,
    "gn:feature_class":"P",
    "gn:feature_code":"PPL",
    "gn:name":"Mbibangan",
    "gn:population":0,
    "gn:timezone":"Africa/Ndjamena",
    "iso:country":"TD",
    "wof:name":"Mbibangan",
    "wof:placetype":"locality"
},
  "geometry": {"coordinates":[15.8524,7.9751],"type":"Point"}
}