{
  "type": "Feature",
  "properties": {
    "gn:admin1_code":"19.0",
    "gn:asciiname":"Doba",
    "gn:country_code":"TD",
    "gn:dem":365,
    "gn:feature_class":"P",
    "gn:feature_code":"PPL",
    "gn:name":"Doba",
    "gn:population":0,
    "gn:timezone":"Africa/Ndjamena",
    "iso:country":"TD",
    "name:ceb_x_preferred":[
        "Doba"
    ],
    "name:ces_x_preferred":[
        "Doba"
    ],
    "name:deu_x_preferred":[
        "Doba"
    ],
    "name:epo_x_preferred":[
        "Doba"
    ],
    "name:fra_x_preferred":[
        "Doba"
    ],
    "name:hun_x_preferred":[
        "Doba"
    ],
    "name:ita_x_preferred":[
        "Doba"
    ],
    "name:nld_x_preferred":[
        "Doba"
    ],
    "name:pol_x_preferred":[
        "Doba"
    ],
    "name:por_x_preferred":[
        "Doba"
    ],
    "name:ron_x_preferred":[
        "Doba"
    ],
    "name:rue_x_preferred":[
        "\u0414\u043e\u0431\u0430"
    ],
    "name:rus_x_preferred":[
        "\u0414\u043e\u0431\u0430"
    ],
    "name:slk_x_preferred":[
        "Doba"
    ],
    "name:srp_x_preferred":[
        "\u0414\u043e\u0431\u0430"
    ],
    "name:swe_x_preferred":[
        "Doba"
    ],
    "name:ukr_x_preferred":[
        "\u0414\u043e\u0431\u0430"
    ],
    "wof:name":"Doba",
    "wof:placetype":"locality"
},
  "geometry": {"coordinates":[18.1289,9.0939],"type":"Point"}
}