{
  "type": "Feature",
  "properties": {
    "gn:admin1_code":"9.0",
    "gn:asciiname":"Soo",
    "gn:country_code":"TD",
    "gn:dem":476,
    "gn:feature_class":"P",
    "gn:feature_code":"PPL",
    "gn:name":"Soo",
    "gn:population":0,
    "gn:timezone":"Africa/Ndjamena",
    "iso:country":"TD",
    "name:ceb_x_preferred":[
        "Soo"
    ],
    "name:deu_x_preferred":[
        "Soo"
    ],
    "name:est_x_preferred":[
        "Soo"
    ],
    "name:fra_x_preferred":[
        "Soo"
    ],
    "name:nld_x_preferred":[
        "Soo"
    ],
    "name:pol_x_preferred":[
        "Soo"
    ],
    "name:swe_x_preferred":[
        "Soo"
    ],
    "wof:name":"Soo",
    "wof:placetype":"locality"
},
  "geometry": {"coordinates":[16.31969,8.44367],"type":"Point"}
}