{
  "type": "Feature",
  "properties": {
    "gn:admin1_code":"7.0",
    "gn:asciiname":"Feromasankale",
    "gn:country_code":"TD",
    "gn:dem":306,
    "gn:feature_class":"P",
    "gn:feature_code":"PPL",
    "gn:name":"F\u00e9romasankal\u00e9",
    "gn:population":0,
    "gn:timezone":"Africa/Ndjamena",
    "iso:country":"TD",
    "wof:name":"Feromasankale",
    "wof:placetype":"locality"
},
  "geometry": {"coordinates":[15.41707,13.6707],"type":"Point"}
}