{
  "type": "Feature",
  "properties": {
    "gn:admin1_code":"2.0",
    "gn:asciiname":"Adayt",
    "gn:country_code":"TD",
    "gn:dem":962,
    "gn:feature_class":"P",
    "gn:feature_code":"PPL",
    "gn:name":"Adayt",
    "gn:population":0,
    "gn:timezone":"Africa/Ndjamena",
    "iso:country":"TD",
    "name:fra_x_preferred":[
        "Adayt"
    ],
    "name:fra_x_variant":[
        "Adait"
    ],
    "wof:name":"Adayt",
    "wof:placetype":"locality"
},
  "geometry": {"coordinates":[21.98645,14.50644],"type":"Point"}
}