{
  "type": "Feature",
  "properties": {
    "gn:admin1_code":"9.0",
    "gn:asciiname":"Kame Dati",
    "gn:country_code":"TD",
    "gn:dem":437,
    "gn:feature_class":"P",
    "gn:feature_code":"PPL",
    "gn:name":"Kame Dati",
    "gn:population":0,
    "gn:timezone":"Africa/Ndjamena",
    "iso:country":"TD",
    "wof:name":"Kame Dati",
    "wof:placetype":"locality"
},
  "geometry": {"coordinates":[16.5586,9.1051],"type":"Point"}
}