{
  "type": "Feature",
  "properties": {
    "gn:admin1_code":"15.0",
    "gn:asciiname":"An Goudoum",
    "gn:country_code":"TD",
    "gn:dem":323,
    "gn:feature_class":"P",
    "gn:feature_code":"PPL",
    "gn:name":"An Goudoum",
    "gn:population":0,
    "gn:timezone":"Africa/Ndjamena",
    "iso:country":"TD",
    "wof:name":"An Goudoum",
    "wof:placetype":"locality"
},
  "geometry": {"coordinates":[15.90985,11.84124],"type":"Point"}
}