{
  "type": "Feature",
  "properties": {
    "gn:admin1_code":"20.0",
    "gn:asciiname":"Mankana",
    "gn:country_code":"TD",
    "gn:dem":482,
    "gn:feature_class":"P",
    "gn:feature_code":"PPL",
    "gn:name":"Mankana",
    "gn:population":0,
    "gn:timezone":"Africa/Ndjamena",
    "iso:country":"TD",
    "wof:name":"Mankana",
    "wof:placetype":"locality"
},
  "geometry": {"coordinates":[15.1966,8.8147],"type":"Point"}
}