{
  "type": "Feature",
  "properties": {
    "gn:admin1_code":"5.0",
    "gn:asciiname":"Koubourtou",
    "gn:country_code":"TD",
    "gn:dem":428,
    "gn:feature_class":"P",
    "gn:feature_code":"PPL",
    "gn:name":"Koubourtou",
    "gn:population":0,
    "gn:timezone":"Africa/Ndjamena",
    "iso:country":"TD",
    "wof:name":"Koubourtou",
    "wof:placetype":"locality"
},
  "geometry": {"coordinates":[18.6415,10.7929],"type":"Point"}
}