{
  "type": "Feature",
  "properties": {
    "gn:admin1_code":"14.0",
    "gn:asciiname":"Semeguin",
    "gn:country_code":"TD",
    "gn:dem":340,
    "gn:feature_class":"P",
    "gn:feature_code":"PPL",
    "gn:name":"S\u00e9m\u00e9guin",
    "gn:population":0,
    "gn:timezone":"Africa/Ndjamena",
    "iso:country":"TD",
    "name:und_x_variant":[
        "S\u00e9m\u00e9gin",
        "Semeguine",
        "S\u00e9m\u00e9guin"
    ],
    "wof:name":"Semeguin",
    "wof:placetype":"locality"
},
  "geometry": {"coordinates":[16.3367,10.0093],"type":"Point"}
}