{
  "type": "Feature",
  "properties": {
    "gn:admin1_code":"20.0",
    "gn:asciiname":"Dambri",
    "gn:country_code":"TD",
    "gn:dem":401,
    "gn:feature_class":"P",
    "gn:feature_code":"PPL",
    "gn:name":"Dambri",
    "gn:population":0,
    "gn:timezone":"Africa/Ndjamena",
    "iso:country":"TD",
    "wof:name":"Dambri",
    "wof:placetype":"locality"
},
  "geometry": {"coordinates":[14.6349,9.0979],"type":"Point"}
}