{
  "type": "Feature",
  "properties": {
    "gn:admin1_code":"19.0",
    "gn:asciiname":"Bedodan",
    "gn:country_code":"TD",
    "gn:dem":393,
    "gn:feature_class":"P",
    "gn:feature_code":"PPL",
    "gn:name":"B\u00e9dodan",
    "gn:population":0,
    "gn:timezone":"Africa/Ndjamena",
    "iso:country":"TD",
    "wof:name":"Bedodan",
    "wof:placetype":"locality"
},
  "geometry": {"coordinates":[17.2037,8.58476],"type":"Point"}
}