{
  "type": "Feature",
  "properties": {
    "gn:admin1_code":"16.0",
    "gn:asciiname":"Saiman",
    "gn:country_code":"TD",
    "gn:dem":317,
    "gn:feature_class":"P",
    "gn:feature_code":"PPL",
    "gn:name":"Sa\u00efman",
    "gn:population":0,
    "gn:timezone":"Africa/Ndjamena",
    "iso:country":"TD",
    "wof:name":"Saiman",
    "wof:placetype":"locality"
},
  "geometry": {"coordinates":[15.53333,10.95],"type":"Point"}
}