{
  "type": "Feature",
  "properties": {
    "gn:admin1_code":"15.0",
    "gn:asciiname":"Abou Idjelidje",
    "gn:country_code":"TD",
    "gn:dem":301,
    "gn:feature_class":"P",
    "gn:feature_code":"PPL",
    "gn:name":"Abou Idjelidje",
    "gn:population":0,
    "gn:timezone":"Africa/Ndjamena",
    "iso:country":"TD",
    "wof:name":"Abou Idjelidje",
    "wof:placetype":"locality"
},
  "geometry": {"coordinates":[15.6113,11.93718],"type":"Point"}
}