{
  "type": "Feature",
  "properties": {
    "gn:admin1_code":"1.0",
    "gn:asciiname":"Knach Knach",
    "gn:cc2":"TD",
    "gn:country_code":"TD",
    "gn:dem":330,
    "gn:feature_class":"P",
    "gn:feature_code":"PPL",
    "gn:name":"Knach Knach",
    "gn:population":0,
    "gn:timezone":"Africa/Ndjamena",
    "iso:country":"TD",
    "name:und_x_variant":[
        "Kachkach",
        "Knach Knach"
    ],
    "wof:name":"Knach Knach",
    "wof:placetype":"locality"
},
  "geometry": {"coordinates":[18.13333,13.15],"type":"Point"}
}