{
  "type": "Feature",
  "properties": {
    "gn:admin1_code":"12.0",
    "gn:asciiname":"Guese",
    "gn:country_code":"TD",
    "gn:dem":508,
    "gn:feature_class":"P",
    "gn:feature_code":"PPL",
    "gn:name":"Gu\u00e9s\u00e9",
    "gn:population":0,
    "gn:timezone":"Africa/Ndjamena",
    "iso:country":"TD",
    "name:fra_x_preferred":[
        "Gu\u00e9s\u00e9"
    ],
    "name:fra_x_variant":[
        "G\u00e9s\u00e9"
    ],
    "wof:name":"Guese",
    "wof:placetype":"locality"
},
  "geometry": {"coordinates":[20.76607000000001,13.05409],"type":"Point"}
}