{
  "type": "Feature",
  "properties": {
    "gn:admin1_code":"12.0",
    "gn:asciiname":"Am Karouba",
    "gn:country_code":"TD",
    "gn:dem":762,
    "gn:feature_class":"P",
    "gn:feature_code":"PPL",
    "gn:name":"Am Karouba",
    "gn:population":0,
    "gn:timezone":"Africa/Ndjamena",
    "iso:country":"TD",
    "wof:name":"Am Karouba",
    "wof:placetype":"locality"
},
  "geometry": {"coordinates":[21.71307,13.8564],"type":"Point"}
}