{
  "type": "Feature",
  "properties": {
    "gn:admin1_code":"17.0",
    "gn:asciiname":"Dakono",
    "gn:country_code":"TD",
    "gn:dem":395,
    "gn:feature_class":"P",
    "gn:feature_code":"PPL",
    "gn:name":"Dakono",
    "gn:population":0,
    "gn:timezone":"Africa/Ndjamena",
    "iso:country":"TD",
    "wof:name":"Dakono",
    "wof:placetype":"locality"
},
  "geometry": {"coordinates":[18.6034,8.5666],"type":"Point"}
}