{
  "type": "Feature",
  "properties": {
    "gn:admin1_code":"9.0",
    "gn:asciiname":"Bendo",
    "gn:cc2":"TD",
    "gn:country_code":"TD",
    "gn:dem":440,
    "gn:feature_class":"P",
    "gn:feature_code":"PPL",
    "gn:name":"Bendo",
    "gn:population":0,
    "gn:timezone":"Africa/Ndjamena",
    "iso:country":"TD",
    "name:und_x_variant":[
        "Bindo",
        "Bendo"
    ],
    "wof:name":"Bendo",
    "wof:placetype":"locality"
},
  "geometry": {"coordinates":[16.43333,8.43333],"type":"Point"}
}