{
  "type": "Feature",
  "properties": {
    "gn:admin1_code":"15.0",
    "gn:asciiname":"Miltou",
    "gn:country_code":"TD",
    "gn:dem":347,
    "gn:feature_class":"P",
    "gn:feature_code":"PPL",
    "gn:name":"Miltou",
    "gn:population":0,
    "gn:timezone":"Africa/Ndjamena",
    "iso:country":"TD",
    "name:und_x_variant":[
        "Miltu",
        "Mittou",
        "Miltou"
    ],
    "wof:name":"Miltou",
    "wof:placetype":"locality"
},
  "geometry": {"coordinates":[17.44057999999999,10.23087],"type":"Point"}
}