{
  "type": "Feature",
  "properties": {
    "gn:admin1_code":"16.0",
    "gn:asciiname":"Gaya Toungane",
    "gn:country_code":"TD",
    "gn:dem":354,
    "gn:feature_class":"P",
    "gn:feature_code":"PPL",
    "gn:name":"Gaya Toungan\u00e9",
    "gn:population":0,
    "gn:timezone":"Africa/Ndjamena",
    "iso:country":"TD",
    "wof:name":"Gaya Toungane",
    "wof:placetype":"locality"
},
  "geometry": {"coordinates":[15.46651,9.60677],"type":"Point"}
}