{
  "type": "Feature",
  "properties": {
    "gn:admin1_code":"9.0",
    "gn:asciiname":"Ninmbo",
    "gn:country_code":"TD",
    "gn:dem":382,
    "gn:feature_class":"P",
    "gn:feature_code":"PPL",
    "gn:name":"Ninmbo",
    "gn:population":0,
    "gn:timezone":"Africa/Ndjamena",
    "iso:country":"TD",
    "wof:name":"Ninmbo",
    "wof:placetype":"locality"
},
  "geometry": {"coordinates":[16.76009,8.688],"type":"Point"}
}