{
  "type": "Feature",
  "properties": {
    "gn:admin1_code":"15.0",
    "gn:asciiname":"Erere",
    "gn:country_code":"TD",
    "gn:dem":321,
    "gn:feature_class":"P",
    "gn:feature_code":"PPL",
    "gn:name":"Erere",
    "gn:population":0,
    "gn:timezone":"Africa/Ndjamena",
    "iso:country":"TD",
    "wof:name":"Erere",
    "wof:placetype":"locality"
},
  "geometry": {"coordinates":[15.55621,11.07956],"type":"Point"}
}