{
  "type": "Feature",
  "properties": {
    "gn:admin1_code":"5.0",
    "gn:asciiname":"Barama",
    "gn:country_code":"TD",
    "gn:dem":658,
    "gn:feature_class":"P",
    "gn:feature_code":"PPL",
    "gn:name":"Barama",
    "gn:population":0,
    "gn:timezone":"Africa/Ndjamena",
    "iso:country":"TD",
    "name:ceb_x_preferred":[
        "Barama"
    ],
    "name:swe_x_preferred":[
        "Barama"
    ],
    "wof:name":"Barama",
    "wof:placetype":"locality"
},
  "geometry": {"coordinates":[18.11053,12.07241],"type":"Point"}
}