{
  "type": "Feature",
  "properties": {
    "gn:admin1_code":"6.0",
    "gn:asciiname":"Gini",
    "gn:country_code":"TD",
    "gn:dem":316,
    "gn:feature_class":"P",
    "gn:feature_code":"PPL",
    "gn:name":"Gini",
    "gn:population":0,
    "gn:timezone":"Africa/Ndjamena",
    "iso:country":"TD",
    "wof:name":"Gini",
    "wof:placetype":"locality"
},
  "geometry": {"coordinates":[15.04465,14.08232],"type":"Point"}
}