{
  "type": "Feature",
  "properties": {
    "gn:admin1_code":"18.0",
    "gn:asciiname":"Lokhai",
    "gn:country_code":"TD",
    "gn:dem":291,
    "gn:feature_class":"P",
    "gn:feature_code":"PPL",
    "gn:name":"Lokha\u00ef",
    "gn:population":0,
    "gn:timezone":"Africa/Ndjamena",
    "iso:country":"TD",
    "name:und_x_variant":[
        "Loka\u00ef",
        "Lokha\u00ef"
    ],
    "wof:name":"Lokhai",
    "wof:placetype":"locality"
},
  "geometry": {"coordinates":[15.48559,12.80634],"type":"Point"}
}