{
  "type": "Feature",
  "properties": {
    "gn:admin1_code":"1.0",
    "gn:asciiname":"Am Djan",
    "gn:country_code":"TD",
    "gn:dem":428,
    "gn:feature_class":"P",
    "gn:feature_code":"PPL",
    "gn:name":"Am Djan",
    "gn:population":0,
    "gn:timezone":"Africa/Ndjamena",
    "iso:country":"TD",
    "name:fra_x_preferred":[
        "Am Djan"
    ],
    "wof:name":"Am Djan",
    "wof:placetype":"locality"
},
  "geometry": {"coordinates":[20.21906,13.58009],"type":"Point"}
}