{
  "type": "Feature",
  "properties": {
    "gn:admin1_code":"5.0",
    "gn:asciiname":"Tokore",
    "gn:country_code":"TD",
    "gn:dem":543,
    "gn:feature_class":"P",
    "gn:feature_code":"PPL",
    "gn:name":"Tokor\u00e9",
    "gn:population":0,
    "gn:timezone":"Africa/Ndjamena",
    "iso:country":"TD",
    "wof:name":"Tokore",
    "wof:placetype":"locality"
},
  "geometry": {"coordinates":[19.0067,12.0427],"type":"Point"}
}