{
  "type": "Feature",
  "properties": {
    "gn:admin1_code":"14.0",
    "gn:asciiname":"Moul",
    "gn:country_code":"TD",
    "gn:dem":357,
    "gn:feature_class":"P",
    "gn:feature_code":"PPL",
    "gn:name":"Moul",
    "gn:population":0,
    "gn:timezone":"Africa/Ndjamena",
    "iso:country":"TD",
    "wof:name":"Moul",
    "wof:placetype":"locality"
},
  "geometry": {"coordinates":[17.46835,9.67102],"type":"Point"}
}