{
  "type": "Feature",
  "properties": {
    "gn:admin1_code":"5.0",
    "gn:asciiname":"Marbo",
    "gn:country_code":"TD",
    "gn:dem":342,
    "gn:feature_class":"P",
    "gn:feature_code":"PPL",
    "gn:name":"Marbo",
    "gn:population":0,
    "gn:timezone":"Africa/Ndjamena",
    "iso:country":"TD",
    "wof:name":"Marbo",
    "wof:placetype":"locality"
},
  "geometry": {"coordinates":[17.63834,12.14517],"type":"Point"}
}