{
  "type": "Feature",
  "properties": {
    "gn:admin1_code":"14.0",
    "gn:asciiname":"Koulabanga",
    "gn:country_code":"TD",
    "gn:dem":398,
    "gn:feature_class":"P",
    "gn:feature_code":"PPL",
    "gn:name":"Koulabanga",
    "gn:population":0,
    "gn:timezone":"Africa/Ndjamena",
    "iso:country":"TD",
    "wof:name":"Koulabanga",
    "wof:placetype":"locality"
},
  "geometry": {"coordinates":[16.7371,9.1817],"type":"Point"}
}