{
  "type": "Feature",
  "properties": {
    "gn:admin1_code":"6.0",
    "gn:asciiname":"Tosou",
    "gn:country_code":"TD",
    "gn:dem":320,
    "gn:feature_class":"P",
    "gn:feature_code":"PPL",
    "gn:name":"Tosou",
    "gn:population":0,
    "gn:timezone":"Africa/Ndjamena",
    "iso:country":"TD",
    "wof:name":"Tosou",
    "wof:placetype":"locality"
},
  "geometry": {"coordinates":[15.53535,14.02202],"type":"Point"}
}