{
  "type": "Feature",
  "properties": {
    "gn:admin1_code":"19.0",
    "gn:asciiname":"Morissop",
    "gn:country_code":"TD",
    "gn:dem":356,
    "gn:feature_class":"P",
    "gn:feature_code":"PPL",
    "gn:name":"Morissop",
    "gn:population":0,
    "gn:timezone":"Africa/Ndjamena",
    "iso:country":"TD",
    "wof:name":"Morissop",
    "wof:placetype":"locality"
},
  "geometry": {"coordinates":[17.33563,9.41304],"type":"Point"}
}