{
  "type": "Feature",
  "properties": {
    "gn:admin1_code":"19.0",
    "gn:asciiname":"Magnia",
    "gn:country_code":"TD",
    "gn:dem":367,
    "gn:feature_class":"P",
    "gn:feature_code":"PPL",
    "gn:name":"Magnia",
    "gn:population":0,
    "gn:timezone":"Africa/Ndjamena",
    "iso:country":"TD",
    "wof:name":"Magnia",
    "wof:placetype":"locality"
},
  "geometry": {"coordinates":[17.32176,9.20585],"type":"Point"}
}