{
  "type": "Feature",
  "properties": {
    "gn:admin1_code":"15.0",
    "gn:asciiname":"Djoke",
    "gn:country_code":"TD",
    "gn:dem":323,
    "gn:feature_class":"P",
    "gn:feature_code":"PPL",
    "gn:name":"Djoke",
    "gn:population":0,
    "gn:timezone":"Africa/Ndjamena",
    "iso:country":"TD",
    "wof:name":"Djoke",
    "wof:placetype":"locality"
},
  "geometry": {"coordinates":[15.83812,11.07394],"type":"Point"}
}