{
  "type": "Feature",
  "properties": {
    "gn:admin1_code":"17.0",
    "gn:asciiname":"Mouray",
    "gn:country_code":"TD",
    "gn:dem":378,
    "gn:feature_class":"P",
    "gn:feature_code":"PPL",
    "gn:name":"Mouray",
    "gn:population":0,
    "gn:timezone":"Africa/Ndjamena",
    "iso:country":"TD",
    "name:fra_x_preferred":[
        "Mouray"
    ],
    "name:fra_x_variant":[
        "Mora\u00ef"
    ],
    "wof:name":"Mouray",
    "wof:placetype":"locality"
},
  "geometry": {"coordinates":[19.0802,9.0217],"type":"Point"}
}