{
  "type": "Feature",
  "properties": {
    "gn:admin1_code":"8.0",
    "gn:asciiname":"Maba",
    "gn:country_code":"TD",
    "gn:dem":375,
    "gn:feature_class":"P",
    "gn:feature_code":"PPL",
    "gn:name":"Maba",
    "gn:population":0,
    "gn:timezone":"Africa/Ndjamena",
    "iso:country":"TD",
    "name:ceb_x_preferred":[
        "Maba"
    ],
    "name:deu_x_preferred":[
        "Maba"
    ],
    "name:fra_x_preferred":[
        "Maba"
    ],
    "name:mlg_x_preferred":[
        "Maba"
    ],
    "name:rus_x_preferred":[
        "\u041c\u0430\u0431\u0430"
    ],
    "name:swe_x_preferred":[
        "Maba"
    ],
    "wof:name":"Maba",
    "wof:placetype":"locality"
},
  "geometry": {"coordinates":[16.2911,9.1504],"type":"Point"}
}