{
  "type": "Feature",
  "properties": {
    "gn:admin1_code":"16.0",
    "gn:asciiname":"Gamba",
    "gn:country_code":"TD",
    "gn:dem":381,
    "gn:feature_class":"P",
    "gn:feature_code":"PPL",
    "gn:name":"Gamba",
    "gn:population":0,
    "gn:timezone":"Africa/Ndjamena",
    "iso:country":"TD",
    "wof:name":"Gamba",
    "wof:placetype":"locality"
},
  "geometry": {"coordinates":[14.8587,9.6922],"type":"Point"}
}