{
  "type": "Feature",
  "properties": {
    "gn:admin1_code":"6.0",
    "gn:asciiname":"Kamila",
    "gn:country_code":"TD",
    "gn:dem":304,
    "gn:feature_class":"P",
    "gn:feature_code":"PPL",
    "gn:name":"Kamila",
    "gn:population":0,
    "gn:timezone":"Africa/Ndjamena",
    "iso:country":"TD",
    "wof:name":"Kamila",
    "wof:placetype":"locality"
},
  "geometry": {"coordinates":[14.42922,14.02657],"type":"Point"}
}