{
  "type": "Feature",
  "properties": {
    "gn:admin1_code":"8.0",
    "gn:asciiname":"Karkoubo",
    "gn:country_code":"TD",
    "gn:dem":467,
    "gn:feature_class":"P",
    "gn:feature_code":"PPL",
    "gn:name":"Karkoubo",
    "gn:population":0,
    "gn:timezone":"Africa/Ndjamena",
    "iso:country":"TD",
    "wof:name":"Karkoubo",
    "wof:placetype":"locality"
},
  "geometry": {"coordinates":[15.5858,8.3984],"type":"Point"}
}