{
  "type": "Feature",
  "properties": {
    "gn:admin1_code":"12.0",
    "gn:asciiname":"Mastaride",
    "gn:country_code":"TD",
    "gn:dem":521,
    "gn:feature_class":"P",
    "gn:feature_code":"PPL",
    "gn:name":"Mastarid\u00e9",
    "gn:population":0,
    "gn:timezone":"Africa/Ndjamena",
    "iso:country":"TD",
    "wof:name":"Mastaride",
    "wof:placetype":"locality"
},
  "geometry": {"coordinates":[21.21667,12.98333],"type":"Point"}
}