{
  "type": "Feature",
  "properties": {
    "gn:admin1_code":"13.0",
    "gn:asciiname":"Am Senena",
    "gn:country_code":"TD",
    "gn:dem":443,
    "gn:feature_class":"P",
    "gn:feature_code":"PPL",
    "gn:name":"Am S\u00e9n\u00e9na",
    "gn:population":0,
    "gn:timezone":"Africa/Ndjamena",
    "iso:country":"TD",
    "wof:name":"Am Senena",
    "wof:placetype":"locality"
},
  "geometry": {"coordinates":[20.4228,11.1329],"type":"Point"}
}