{
  "type": "Feature",
  "properties": {
    "gn:admin1_code":"12.0",
    "gn:asciiname":"Arbane",
    "gn:country_code":"TD",
    "gn:dem":694,
    "gn:feature_class":"P",
    "gn:feature_code":"PPL",
    "gn:name":"Arban\u00e9",
    "gn:population":0,
    "gn:timezone":"Africa/Ndjamena",
    "iso:country":"TD",
    "wof:name":"Arbane",
    "wof:placetype":"locality"
},
  "geometry": {"coordinates":[21.62745,13.41237],"type":"Point"}
}