{
  "type": "Feature",
  "properties": {
    "gn:admin1_code":"15.0",
    "gn:asciiname":"Arail",
    "gn:country_code":"TD",
    "gn:dem":304,
    "gn:feature_class":"P",
    "gn:feature_code":"PPL",
    "gn:name":"Ara\u00efl",
    "gn:population":0,
    "gn:timezone":"Africa/Ndjamena",
    "iso:country":"TD",
    "wof:name":"Arail",
    "wof:placetype":"locality"
},
  "geometry": {"coordinates":[16.00485,12.06314],"type":"Point"}
}