{
  "type": "Feature",
  "properties": {
    "gn:admin1_code":"5.0",
    "gn:asciiname":"Bandesongoye",
    "gn:country_code":"TD",
    "gn:dem":491,
    "gn:feature_class":"P",
    "gn:feature_code":"PPL",
    "gn:name":"Band\u00e9songoye",
    "gn:population":0,
    "gn:timezone":"Africa/Ndjamena",
    "iso:country":"TD",
    "wof:name":"Bandesongoye",
    "wof:placetype":"locality"
},
  "geometry": {"coordinates":[18.39901,11.96877],"type":"Point"}
}