{
  "type": "Feature",
  "properties": {
    "gn:admin1_code":"6.0",
    "gn:asciiname":"Momeni",
    "gn:country_code":"TD",
    "gn:dem":307,
    "gn:feature_class":"P",
    "gn:feature_code":"PPL",
    "gn:name":"Mom\u00e9ni",
    "gn:population":0,
    "gn:timezone":"Africa/Ndjamena",
    "iso:country":"TD",
    "wof:name":"Momeni",
    "wof:placetype":"locality"
},
  "geometry": {"coordinates":[15.27849,14.1004],"type":"Point"}
}