{
  "type": "Feature",
  "properties": {
    "gn:admin1_code":"17.0",
    "gn:asciiname":"Koulima",
    "gn:country_code":"TD",
    "gn:dem":398,
    "gn:feature_class":"P",
    "gn:feature_code":"PPL",
    "gn:name":"Koulima",
    "gn:population":0,
    "gn:timezone":"Africa/Ndjamena",
    "iso:country":"TD",
    "wof:name":"Koulima",
    "wof:placetype":"locality"
},
  "geometry": {"coordinates":[19.1595,9.6258],"type":"Point"}
}