{
  "type": "Feature",
  "properties": {
    "gn:admin1_code":"13.0",
    "gn:asciiname":"Darelech",
    "gn:country_code":"TD",
    "gn:dem":432,
    "gn:feature_class":"P",
    "gn:feature_code":"PPL",
    "gn:name":"Dar\u00e9lech",
    "gn:population":0,
    "gn:timezone":"Africa/Ndjamena",
    "iso:country":"TD",
    "name:und_x_variant":[
        "Dar el Esch",
        "Dar el Esh",
        "Dar\u00e9lech"
    ],
    "wof:name":"Darelech",
    "wof:placetype":"locality"
},
  "geometry": {"coordinates":[19.8029,11.7104],"type":"Point"}
}