{
  "type": "Feature",
  "properties": {
    "gn:admin1_code":"14.0",
    "gn:asciiname":"Tiadam",
    "gn:country_code":"TD",
    "gn:dem":359,
    "gn:feature_class":"P",
    "gn:feature_code":"PPL",
    "gn:name":"Tiadam",
    "gn:population":0,
    "gn:timezone":"Africa/Ndjamena",
    "iso:country":"TD",
    "wof:name":"Tiadam",
    "wof:placetype":"locality"
},
  "geometry": {"coordinates":[16.2823,9.3119],"type":"Point"}
}