{
  "type": "Feature",
  "properties": {
    "gn:admin1_code":"20.0",
    "gn:asciiname":"Bodoro",
    "gn:country_code":"TD",
    "gn:dem":332,
    "gn:feature_class":"P",
    "gn:feature_code":"PPL",
    "gn:name":"Bodoro",
    "gn:population":0,
    "gn:timezone":"Africa/Ndjamena",
    "iso:country":"TD",
    "name:und_x_variant":[
        "Bold\u00e9ro",
        "Bodoro"
    ],
    "wof:name":"Bodoro",
    "wof:placetype":"locality"
},
  "geometry": {"coordinates":[14.1351,9.8282],"type":"Point"}
}