{
  "type": "Feature",
  "properties": {
    "gn:admin1_code":"17.0",
    "gn:asciiname":"Bologadjia",
    "gn:country_code":"TD",
    "gn:dem":369,
    "gn:feature_class":"P",
    "gn:feature_code":"PPL",
    "gn:name":"Bologadjia",
    "gn:population":0,
    "gn:timezone":"Africa/Ndjamena",
    "iso:country":"TD",
    "wof:name":"Bologadjia",
    "wof:placetype":"locality"
},
  "geometry": {"coordinates":[18.25,9.51667],"type":"Point"}
}