{
  "type": "Feature",
  "properties": {
    "gn:admin1_code":"13.0",
    "gn:asciiname":"Kokodjo",
    "gn:country_code":"TD",
    "gn:dem":491,
    "gn:feature_class":"P",
    "gn:feature_code":"PPL",
    "gn:name":"Kokodjo",
    "gn:population":0,
    "gn:timezone":"Africa/Ndjamena",
    "iso:country":"TD",
    "name:und_x_variant":[
        "Kokodsong",
        "Kokodjo"
    ],
    "wof:name":"Kokodjo",
    "wof:placetype":"locality"
},
  "geometry": {"coordinates":[20.5594,11.7201],"type":"Point"}
}