{
  "type": "Feature",
  "properties": {
    "gn:admin1_code":"7.0",
    "gn:asciiname":"Ilili",
    "gn:country_code":"TD",
    "gn:dem":304,
    "gn:feature_class":"P",
    "gn:feature_code":"PPL",
    "gn:name":"Ilili",
    "gn:population":0,
    "gn:timezone":"Africa/Ndjamena",
    "iso:country":"TD",
    "name:und_x_variant":[
        "Illili",
        "Ilili"
    ],
    "wof:name":"Ilili",
    "wof:placetype":"locality"
},
  "geometry": {"coordinates":[15.73636,13.72524],"type":"Point"}
}