{
  "type": "Feature",
  "properties": {
    "gn:admin1_code":"19.0",
    "gn:asciiname":"Berigui",
    "gn:country_code":"TD",
    "gn:dem":379,
    "gn:feature_class":"P",
    "gn:feature_code":"PPL",
    "gn:name":"Berigui",
    "gn:population":0,
    "gn:timezone":"Africa/Ndjamena",
    "iso:country":"TD",
    "wof:name":"Berigui",
    "wof:placetype":"locality"
},
  "geometry": {"coordinates":[17.31004,8.4241],"type":"Point"}
}