{
  "type": "Feature",
  "properties": {
    "gn:admin1_code":"19.0",
    "gn:asciiname":"Koko",
    "gn:country_code":"TD",
    "gn:dem":378,
    "gn:feature_class":"P",
    "gn:feature_code":"PPL",
    "gn:name":"Koko",
    "gn:population":0,
    "gn:timezone":"Africa/Ndjamena",
    "iso:country":"TD",
    "wof:name":"Koko",
    "wof:placetype":"locality"
},
  "geometry": {"coordinates":[17.3954,8.866],"type":"Point"}
}