{
  "type": "Feature",
  "properties": {
    "gn:admin1_code":"13.0",
    "gn:asciiname":"Apguerean",
    "gn:country_code":"TD",
    "gn:dem":439,
    "gn:feature_class":"P",
    "gn:feature_code":"PPL",
    "gn:name":"Apgu\u00e9r\u00e9an",
    "gn:population":0,
    "gn:timezone":"Africa/Ndjamena",
    "iso:country":"TD",
    "name:und_x_variant":[
        "Apg\u00e9rean",
        "Apg\u00e9r\u00e9an",
        "Apgu\u00e9r\u00e9an"
    ],
    "wof:name":"Apguerean",
    "wof:placetype":"locality"
},
  "geometry": {"coordinates":[20.2613,11.1506],"type":"Point"}
}