{
  "type": "Feature",
  "properties": {
    "gn:admin1_code":"12.0",
    "gn:asciiname":"Guernye",
    "gn:country_code":"TD",
    "gn:dem":897,
    "gn:feature_class":"P",
    "gn:feature_code":"PPL",
    "gn:name":"Guerny\u00e9",
    "gn:population":0,
    "gn:timezone":"Africa/Ndjamena",
    "iso:country":"TD",
    "name:und_x_variant":[
        "Guerny\u00e9",
        "Gerny\u00e9"
    ],
    "wof:name":"Guernye",
    "wof:placetype":"locality"
},
  "geometry": {"coordinates":[22.05039,13.40471],"type":"Point"}
}