{
  "type": "Feature",
  "properties": {
    "gn:admin1_code":"17.0",
    "gn:asciiname":"Madimba",
    "gn:country_code":"TD",
    "gn:dem":370,
    "gn:feature_class":"P",
    "gn:feature_code":"PPL",
    "gn:name":"Madimba",
    "gn:population":0,
    "gn:timezone":"Africa/Ndjamena",
    "iso:country":"TD",
    "wof:name":"Madimba",
    "wof:placetype":"locality"
},
  "geometry": {"coordinates":[18.48666,8.83016],"type":"Point"}
}