{
  "type": "Feature",
  "properties": {
    "gn:admin1_code":"14.0",
    "gn:asciiname":"Tolo",
    "gn:country_code":"TD",
    "gn:dem":386,
    "gn:feature_class":"P",
    "gn:feature_code":"PPL",
    "gn:name":"Tolo",
    "gn:population":0,
    "gn:timezone":"Africa/Ndjamena",
    "iso:country":"TD",
    "wof:name":"Tolo",
    "wof:placetype":"locality"
},
  "geometry": {"coordinates":[16.1246,9.124],"type":"Point"}
}