{
  "type": "Feature",
  "properties": {
    "gn:admin1_code":"9.0",
    "gn:asciiname":"Dokabi",
    "gn:country_code":"TD",
    "gn:dem":436,
    "gn:feature_class":"P",
    "gn:feature_code":"PPL",
    "gn:name":"Dokabi",
    "gn:population":0,
    "gn:timezone":"Africa/Ndjamena",
    "iso:country":"TD",
    "wof:name":"Dokabi",
    "wof:placetype":"locality"
},
  "geometry": {"coordinates":[16.98007,7.68001],"type":"Point"}
}