{
  "type": "Feature",
  "properties": {
    "gn:admin1_code":"2.0",
    "gn:asciiname":"Ouaya-Ouaya",
    "gn:country_code":"TD",
    "gn:dem":740,
    "gn:feature_class":"P",
    "gn:feature_code":"PPL",
    "gn:name":"Ouaya-Ouaya",
    "gn:population":0,
    "gn:timezone":"Africa/Ndjamena",
    "iso:country":"TD",
    "name:fra_x_preferred":[
        "Ouaya-Ouaya"
    ],
    "name:und_x_variant":[
        "Ouaya",
        "Waya Waya"
    ],
    "wof:name":"Ouaya-Ouaya",
    "wof:placetype":"locality"
},
  "geometry": {"coordinates":[21.66022,14.91065],"type":"Point"}
}