{
  "type": "Feature",
  "properties": {
    "gn:admin1_code":"22.0",
    "gn:asciiname":"Molokh Goutioulouma",
    "gn:country_code":"TD",
    "gn:dem":307,
    "gn:feature_class":"P",
    "gn:feature_code":"PPL",
    "gn:name":"Molokh Goutioulouma",
    "gn:population":0,
    "gn:timezone":"Africa/Ndjamena",
    "iso:country":"TD",
    "wof:name":"Molokh Goutioulouma",
    "wof:placetype":"locality"
},
  "geometry": {"coordinates":[16.3851,13.258],"type":"Point"}
}