{
  "type": "Feature",
  "properties": {
    "gn:admin1_code":"9.0",
    "gn:asciiname":"Bekao II",
    "gn:country_code":"TD",
    "gn:dem":525,
    "gn:feature_class":"P",
    "gn:feature_code":"PPL",
    "gn:name":"Bekao II",
    "gn:population":0,
    "gn:timezone":"Africa/Ndjamena",
    "iso:country":"TD",
    "wof:name":"Bekao II",
    "wof:placetype":"locality"
},
  "geometry": {"coordinates":[16.0881,7.892],"type":"Point"}
}