{
  "type": "Feature",
  "properties": {
    "gn:admin1_code":"7.0",
    "gn:asciiname":"Ngalasoa Bodou",
    "gn:country_code":"TD",
    "gn:dem":286,
    "gn:feature_class":"P",
    "gn:feature_code":"PPL",
    "gn:name":"Ngalasoa Bodou",
    "gn:population":0,
    "gn:timezone":"Africa/Ndjamena",
    "iso:country":"TD",
    "wof:name":"Ngalasoa Bodou",
    "wof:placetype":"locality"
},
  "geometry": {"coordinates":[14.55,13.41667],"type":"Point"}
}