{
  "type": "Feature",
  "properties": {
    "gn:admin1_code":"13.0",
    "gn:asciiname":"Mored Kade",
    "gn:country_code":"TD",
    "gn:dem":483,
    "gn:feature_class":"P",
    "gn:feature_code":"PPL",
    "gn:name":"Mored Kad\u00e9",
    "gn:population":0,
    "gn:timezone":"Africa/Ndjamena",
    "iso:country":"TD",
    "wof:name":"Mored Kade",
    "wof:placetype":"locality"
},
  "geometry": {"coordinates":[21.05083,11.65034],"type":"Point"}
}