{
  "type": "Feature",
  "properties": {
    "gn:admin1_code":"19.0",
    "gn:asciiname":"Kabra",
    "gn:country_code":"TD",
    "gn:dem":380,
    "gn:feature_class":"P",
    "gn:feature_code":"PPL",
    "gn:name":"Kabra",
    "gn:population":0,
    "gn:timezone":"Africa/Ndjamena",
    "iso:country":"TD",
    "wof:name":"Kabra",
    "wof:placetype":"locality"
},
  "geometry": {"coordinates":[17.33202,9.00976],"type":"Point"}
}