{
  "type": "Feature",
  "properties": {
    "gn:admin1_code":"16.0",
    "gn:asciiname":"Belem",
    "gn:country_code":"TD",
    "gn:dem":318,
    "gn:feature_class":"P",
    "gn:feature_code":"PPL",
    "gn:name":"Belem",
    "gn:population":0,
    "gn:timezone":"Africa/Ndjamena",
    "iso:country":"TD",
    "wof:name":"Belem",
    "wof:placetype":"locality"
},
  "geometry": {"coordinates":[15.43157,10.9372],"type":"Point"}
}