{
  "type": "Feature",
  "properties": {
    "gn:admin1_code":"9.0",
    "gn:asciiname":"Ngara I",
    "gn:country_code":"TD",
    "gn:dem":430,
    "gn:feature_class":"P",
    "gn:feature_code":"PPL",
    "gn:name":"Ngara I",
    "gn:population":0,
    "gn:timezone":"Africa/Ndjamena",
    "iso:country":"TD",
    "wof:name":"Ngara I",
    "wof:placetype":"locality"
},
  "geometry": {"coordinates":[16.86607,8.22372],"type":"Point"}
}