{
  "type": "Feature",
  "properties": {
    "gn:admin1_code":"19.0",
    "gn:asciiname":"Bormane",
    "gn:country_code":"TD",
    "gn:dem":368,
    "gn:feature_class":"P",
    "gn:feature_code":"PPL",
    "gn:name":"Bormane",
    "gn:population":0,
    "gn:timezone":"Africa/Ndjamena",
    "iso:country":"TD",
    "wof:name":"Bormane",
    "wof:placetype":"locality"
},
  "geometry": {"coordinates":[17.15853,9.29323],"type":"Point"}
}