{
  "type": "Feature",
  "properties": {
    "gn:admin1_code":"5.0",
    "gn:asciiname":"Badago",
    "gn:country_code":"TD",
    "gn:dem":574,
    "gn:feature_class":"P",
    "gn:feature_code":"PPL",
    "gn:name":"Badago",
    "gn:population":0,
    "gn:timezone":"Africa/Ndjamena",
    "iso:country":"TD",
    "wof:name":"Badago",
    "wof:placetype":"locality"
},
  "geometry": {"coordinates":[18.8868,11.9888],"type":"Point"}
}