{
  "type": "Feature",
  "properties": {
    "gn:admin1_code":"14.0",
    "gn:asciiname":"Lobo",
    "gn:country_code":"TD",
    "gn:dem":365,
    "gn:feature_class":"P",
    "gn:feature_code":"PPL",
    "gn:name":"Lobo",
    "gn:population":0,
    "gn:timezone":"Africa/Ndjamena",
    "iso:country":"TD",
    "name:ceb_x_preferred":[
        "Lobo"
    ],
    "name:deu_x_preferred":[
        "Lobo"
    ],
    "name:epo_x_preferred":[
        "Lobo"
    ],
    "name:fin_x_preferred":[
        "Lobo"
    ],
    "name:fra_x_preferred":[
        "Lobo"
    ],
    "name:glg_x_preferred":[
        "Lobo"
    ],
    "name:ido_x_preferred":[
        "Lobo"
    ],
    "name:ita_x_preferred":[
        "Lobo"
    ],
    "name:nld_x_preferred":[
        "Lobo"
    ],
    "name:pol_x_preferred":[
        "Lobo"
    ],
    "name:por_x_preferred":[
        "Lobo"
    ],
    "name:rus_x_preferred":[
        "\u041b\u043e\u0431\u043e"
    ],
    "name:spa_x_preferred":[
        "Lobo"
    ],
    "name:swe_x_preferred":[
        "Lobo"
    ],
    "name:tgl_x_preferred":[
        "Lobo"
    ],
    "name:tha_x_preferred":[
        "\u0e42\u0e25\u0e42\u0e1a"
    ],
    "wof:name":"Lobo",
    "wof:placetype":"locality"
},
  "geometry": {"coordinates":[16.4306,9.2211],"type":"Point"}
}