{
  "type": "Feature",
  "properties": {
    "gn:admin1_code":"13.0",
    "gn:asciiname":"Djiodat",
    "gn:country_code":"TD",
    "gn:dem":468,
    "gn:feature_class":"P",
    "gn:feature_code":"PPL",
    "gn:name":"Djiodat",
    "gn:population":0,
    "gn:timezone":"Africa/Ndjamena",
    "iso:country":"TD",
    "wof:name":"Djiodat",
    "wof:placetype":"locality"
},
  "geometry": {"coordinates":[19.723,12.04899],"type":"Point"}
}