{
  "type": "Feature",
  "properties": {
    "gn:admin1_code":"14.0",
    "gn:asciiname":"Ouroungou",
    "gn:country_code":"TD",
    "gn:dem":350,
    "gn:feature_class":"P",
    "gn:feature_code":"PPL",
    "gn:name":"Ouroungou",
    "gn:population":0,
    "gn:timezone":"Africa/Ndjamena",
    "iso:country":"TD",
    "name:und_x_variant":[
        "Oroungou",
        "Ouroungou"
    ],
    "wof:name":"Ouroungou",
    "wof:placetype":"locality"
},
  "geometry": {"coordinates":[16.6292,9.6027],"type":"Point"}
}