{
  "type": "Feature",
  "properties": {
    "gn:admin1_code":"5.0",
    "gn:asciiname":"Oueleg",
    "gn:country_code":"TD",
    "gn:dem":557,
    "gn:feature_class":"P",
    "gn:feature_code":"PPL",
    "gn:name":"Ou\u00e9leg",
    "gn:population":0,
    "gn:timezone":"Africa/Ndjamena",
    "iso:country":"TD",
    "wof:name":"Oueleg",
    "wof:placetype":"locality"
},
  "geometry": {"coordinates":[18.6063,11.7676],"type":"Point"}
}