{
  "type": "Feature",
  "properties": {
    "gn:admin1_code":"25.0",
    "gn:asciiname":"Alfouro",
    "gn:country_code":"TD",
    "gn:dem":434,
    "gn:feature_class":"P",
    "gn:feature_code":"PPL",
    "gn:name":"Alfouro",
    "gn:population":0,
    "gn:timezone":"Africa/Ndjamena",
    "iso:country":"TD",
    "wof:name":"Alfouro",
    "wof:placetype":"locality"
},
  "geometry": {"coordinates":[20.23333,12.83333],"type":"Point"}
}