{
  "type": "Feature",
  "properties": {
    "gn:admin1_code":"20.0",
    "gn:asciiname":"Djalingo",
    "gn:country_code":"TD",
    "gn:dem":262,
    "gn:feature_class":"P",
    "gn:feature_code":"PPL",
    "gn:name":"Djalingo",
    "gn:population":0,
    "gn:timezone":"Africa/Ndjamena",
    "iso:country":"TD",
    "wof:name":"Djalingo",
    "wof:placetype":"locality"
},
  "geometry": {"coordinates":[14.0088,9.691],"type":"Point"}
}