{
  "type": "Feature",
  "properties": {
    "gn:admin1_code":"14.0",
    "gn:asciiname":"Maingone",
    "gn:country_code":"TD",
    "gn:dem":376,
    "gn:feature_class":"P",
    "gn:feature_code":"PPL",
    "gn:name":"Ma\u00efngone",
    "gn:population":0,
    "gn:timezone":"Africa/Ndjamena",
    "iso:country":"TD",
    "wof:name":"Maingone",
    "wof:placetype":"locality"
},
  "geometry": {"coordinates":[16.6859,9.2312],"type":"Point"}
}