{
  "type": "Feature",
  "properties": {
    "gn:admin1_code":"14.0",
    "gn:asciiname":"Bero Ndigou",
    "gn:country_code":"TD",
    "gn:dem":420,
    "gn:feature_class":"P",
    "gn:feature_code":"PPL",
    "gn:name":"B\u00e9ro Ndigou",
    "gn:population":0,
    "gn:timezone":"Africa/Ndjamena",
    "iso:country":"TD",
    "wof:name":"Bero Ndigou",
    "wof:placetype":"locality"
},
  "geometry": {"coordinates":[15.60879,9.24507],"type":"Point"}
}