{
  "type": "Feature",
  "properties": {
    "gn:admin1_code":"14.0",
    "gn:asciiname":"Diali",
    "gn:country_code":"TD",
    "gn:dem":347,
    "gn:feature_class":"P",
    "gn:feature_code":"PPL",
    "gn:name":"Diali",
    "gn:population":0,
    "gn:timezone":"Africa/Ndjamena",
    "iso:country":"TD",
    "wof:name":"Diali",
    "wof:placetype":"locality"
},
  "geometry": {"coordinates":[16.7238,9.5961],"type":"Point"}
}