{
  "type": "Feature",
  "properties": {
    "gn:admin1_code":"14.0",
    "gn:asciiname":"Meguene Ngolo",
    "gn:country_code":"TD",
    "gn:dem":364,
    "gn:feature_class":"P",
    "gn:feature_code":"PPL",
    "gn:name":"M\u00e9gu\u00e9n\u00e9 Ngolo",
    "gn:population":0,
    "gn:timezone":"Africa/Ndjamena",
    "iso:country":"TD",
    "name:und_x_variant":[
        "M\u00e9g\u00e9n\u00e9 Ngolo",
        "M\u00e9gu\u00e9n\u00e9",
        "M\u00e9gu\u00e9n\u00e9 Ngolo"
    ],
    "wof:name":"Meguene Ngolo",
    "wof:placetype":"locality"
},
  "geometry": {"coordinates":[15.76903,9.38058],"type":"Point"}
}