{
  "type": "Feature",
  "properties": {
    "gn:admin1_code":"17.0",
    "gn:asciiname":"Pare Sara II",
    "gn:country_code":"TD",
    "gn:dem":387,
    "gn:feature_class":"P",
    "gn:feature_code":"PPL",
    "gn:name":"Par\u00e9 Sara II",
    "gn:population":0,
    "gn:timezone":"Africa/Ndjamena",
    "iso:country":"TD",
    "wof:name":"Pare Sara II",
    "wof:placetype":"locality"
},
  "geometry": {"coordinates":[18.58158,8.69793],"type":"Point"}
}