{
  "type": "Feature",
  "properties": {
    "gn:admin1_code":"1.0",
    "gn:asciiname":"Am Rhirebi",
    "gn:country_code":"TD",
    "gn:dem":430,
    "gn:feature_class":"P",
    "gn:feature_code":"PPL",
    "gn:name":"Am Rhir\u00e9bi",
    "gn:population":0,
    "gn:timezone":"Africa/Ndjamena",
    "iso:country":"TD",
    "name:fra_x_preferred":[
        "Am Rhir\u00e9bi"
    ],
    "wof:name":"Am Rhirebi",
    "wof:placetype":"locality"
},
  "geometry": {"coordinates":[20.24717,13.2298],"type":"Point"}
}