{
  "type": "Feature",
  "properties": {
    "gn:admin1_code":"14.0",
    "gn:asciiname":"Sissi",
    "gn:country_code":"TD",
    "gn:dem":352,
    "gn:feature_class":"P",
    "gn:feature_code":"PPL",
    "gn:name":"Sissi",
    "gn:population":0,
    "gn:timezone":"Africa/Ndjamena",
    "iso:country":"TD",
    "name:ara_x_preferred":[
        "\u0627\u0644\u0633\u064a\u0633\u064a"
    ],
    "name:bre_x_preferred":[
        "Sissi"
    ],
    "name:ceb_x_preferred":[
        "Sissi"
    ],
    "name:ces_x_preferred":[
        "Sissi"
    ],
    "name:deu_x_preferred":[
        "Sissi"
    ],
    "name:fin_x_preferred":[
        "Sissi"
    ],
    "name:fra_x_preferred":[
        "Sissi"
    ],
    "name:heb_x_preferred":[
        "\u05e1\u05d9\u05e1\u05d9"
    ],
    "name:ita_x_preferred":[
        "Sissi"
    ],
    "name:nld_x_preferred":[
        "Sissi"
    ],
    "name:pol_x_preferred":[
        "Sissi"
    ],
    "name:por_x_preferred":[
        "Sissi"
    ],
    "name:rus_x_preferred":[
        "\u0421\u0438\u0441\u0441\u0438"
    ],
    "name:swe_x_preferred":[
        "Sissi"
    ],
    "name:vie_x_preferred":[
        "Sissi"
    ],
    "wof:name":"Sissi",
    "wof:placetype":"locality"
},
  "geometry": {"coordinates":[16.3086,9.6452],"type":"Point"}
}