{
  "type": "Feature",
  "properties": {
    "gn:admin1_code":"14.0",
    "gn:asciiname":"Hamgar",
    "gn:country_code":"TD",
    "gn:dem":363,
    "gn:feature_class":"P",
    "gn:feature_code":"PPL",
    "gn:name":"Hamgar",
    "gn:population":0,
    "gn:timezone":"Africa/Ndjamena",
    "iso:country":"TD",
    "name:und_x_variant":[
        "Amgar",
        "Hamgar"
    ],
    "wof:name":"Hamgar",
    "wof:placetype":"locality"
},
  "geometry": {"coordinates":[16.3386,9.3045],"type":"Point"}
}