{
  "type": "Feature",
  "properties": {
    "gn:admin1_code":"18.0",
    "gn:asciiname":"Al Adar",
    "gn:country_code":"TD",
    "gn:dem":287,
    "gn:feature_class":"P",
    "gn:feature_code":"PPL",
    "gn:name":"Al Adar",
    "gn:population":0,
    "gn:timezone":"Africa/Ndjamena",
    "iso:country":"TD",
    "wof:name":"Al Adar",
    "wof:placetype":"locality"
},
  "geometry": {"coordinates":[15.75257,12.9162],"type":"Point"}
}