{
  "type": "Feature",
  "properties": {
    "gn:admin1_code":"2.0",
    "gn:asciiname":"Mourou",
    "gn:country_code":"TD",
    "gn:dem":811,
    "gn:feature_class":"P",
    "gn:feature_code":"PPL",
    "gn:name":"Mourou",
    "gn:population":0,
    "gn:timezone":"Africa/Ndjamena",
    "iso:country":"TD",
    "name:deu_x_preferred":[
        "Mourou"
    ],
    "name:fra_x_preferred":[
        "Mourou"
    ],
    "name:nds_x_preferred":[
        "Mourou"
    ],
    "wof:name":"Mourou",
    "wof:placetype":"locality"
},
  "geometry": {"coordinates":[21.56967,14.14478],"type":"Point"}
}