{
  "type": "Feature",
  "properties": {
    "gn:admin1_code":"15.0",
    "gn:asciiname":"Koundoul",
    "gn:country_code":"TD",
    "gn:dem":298,
    "gn:feature_class":"P",
    "gn:feature_code":"PPL",
    "gn:name":"Koundoul",
    "gn:population":0,
    "gn:timezone":"Africa/Ndjamena",
    "iso:country":"TD",
    "name:ita_x_preferred":[
        "Koundoul"
    ],
    "name:rus_x_preferred":[
        "\u041a\u0443\u043d\u0434\u0443\u043b\u044c"
    ],
    "name:und_x_variant":[
        "Koundouli",
        "Kondoul"
    ],
    "wof:name":"Koundoul",
    "wof:placetype":"locality"
},
  "geometry": {"coordinates":[15.15087,11.97016],"type":"Point"}
}