{
  "type": "Feature",
  "properties": {
    "gn:admin1_code":"12.0",
    "gn:asciiname":"Tamam",
    "gn:country_code":"TD",
    "gn:dem":713,
    "gn:feature_class":"P",
    "gn:feature_code":"PPL",
    "gn:name":"Tamam",
    "gn:population":0,
    "gn:timezone":"Africa/Ndjamena",
    "iso:country":"TD",
    "wof:name":"Tamam",
    "wof:placetype":"locality"
},
  "geometry": {"coordinates":[21.58141,13.65205],"type":"Point"}
}