{
  "type": "Feature",
  "properties": {
    "gn:admin1_code":"12.0",
    "gn:asciiname":"Rimele",
    "gn:country_code":"TD",
    "gn:dem":768,
    "gn:feature_class":"P",
    "gn:feature_code":"PPL",
    "gn:name":"Rim\u00e9l\u00e9",
    "gn:population":0,
    "gn:timezone":"Africa/Ndjamena",
    "iso:country":"TD",
    "name:fra_x_preferred":[
        "Rim\u00e9l\u00e9"
    ],
    "wof:name":"Rimele",
    "wof:placetype":"locality"
},
  "geometry": {"coordinates":[21.24795,14.05877],"type":"Point"}
}