{
  "type": "Feature",
  "properties": {
    "gn:admin1_code":"18.0",
    "gn:asciiname":"Abd Oumbour",
    "gn:country_code":"TD",
    "gn:dem":290,
    "gn:feature_class":"P",
    "gn:feature_code":"PPL",
    "gn:name":"Abd Oumbour",
    "gn:population":0,
    "gn:timezone":"Africa/Ndjamena",
    "iso:country":"TD",
    "wof:name":"Abd Oumbour",
    "wof:placetype":"locality"
},
  "geometry": {"coordinates":[16.50766,12.71637],"type":"Point"}
}