{
  "type": "Feature",
  "properties": {
    "gn:admin1_code":"16.0",
    "gn:asciiname":"Djarao Golo I",
    "gn:country_code":"TD",
    "gn:dem":343,
    "gn:feature_class":"P",
    "gn:feature_code":"PPL",
    "gn:name":"Djarao Golo I",
    "gn:population":0,
    "gn:timezone":"Africa/Ndjamena",
    "iso:country":"TD",
    "wof:name":"Djarao Golo I",
    "wof:placetype":"locality"
},
  "geometry": {"coordinates":[15.5054,9.6698],"type":"Point"}
}