{
  "type": "Feature",
  "properties": {
    "gn:admin1_code":"18.0",
    "gn:asciiname":"Badanga",
    "gn:country_code":"TD",
    "gn:dem":340,
    "gn:feature_class":"P",
    "gn:feature_code":"PPL",
    "gn:name":"Badanga",
    "gn:population":0,
    "gn:timezone":"Africa/Ndjamena",
    "iso:country":"TD",
    "name:und_x_variant":[
        "B\u00e9danga",
        "Badanga"
    ],
    "wof:name":"Badanga",
    "wof:placetype":"locality"
},
  "geometry": {"coordinates":[17.41583,11.59917],"type":"Point"}
}