{
  "type": "Feature",
  "properties": {
    "gn:admin1_code":"15.0",
    "gn:asciiname":"Delfin Bornou",
    "gn:country_code":"TD",
    "gn:dem":338,
    "gn:feature_class":"P",
    "gn:feature_code":"PPL",
    "gn:name":"Delfin Bornou",
    "gn:population":0,
    "gn:timezone":"Africa/Ndjamena",
    "iso:country":"TD",
    "name:und_x_variant":[
        "Deltine",
        "D\u00e9kin\u00e9",
        "Delfin",
        "Delfine",
        "Delfin Bornou"
    ],
    "wof:name":"Delfin Bornou",
    "wof:placetype":"locality"
},
  "geometry": {"coordinates":[16.77771,10.64583],"type":"Point"}
}