{
  "type": "Feature",
  "properties": {
    "gn:admin1_code":"9.0",
    "gn:asciiname":"Damala",
    "gn:country_code":"TD",
    "gn:dem":396,
    "gn:feature_class":"P",
    "gn:feature_code":"PPL",
    "gn:name":"Damala",
    "gn:population":0,
    "gn:timezone":"Africa/Ndjamena",
    "iso:country":"TD",
    "wof:name":"Damala",
    "wof:placetype":"locality"
},
  "geometry": {"coordinates":[16.93117,8.63672],"type":"Point"}
}