{
  "type": "Feature",
  "properties": {
    "gn:admin1_code":"8.0",
    "gn:asciiname":"Sar",
    "gn:country_code":"TD",
    "gn:dem":406,
    "gn:feature_class":"P",
    "gn:feature_code":"PPL",
    "gn:name":"Sar",
    "gn:population":0,
    "gn:timezone":"Africa/Ndjamena",
    "iso:country":"TD",
    "wof:name":"Sar",
    "wof:placetype":"locality"
},
  "geometry": {"coordinates":[16.2712,9.0942],"type":"Point"}
}