{
  "type": "Feature",
  "properties": {
    "gn:admin1_code":"2.0",
    "gn:asciiname":"Kouro",
    "gn:country_code":"TD",
    "gn:dem":648,
    "gn:feature_class":"P",
    "gn:feature_code":"PPL",
    "gn:name":"Kouro",
    "gn:population":0,
    "gn:timezone":"Africa/Ndjamena",
    "iso:country":"TD",
    "name:fra_x_preferred":[
        "Kouro"
    ],
    "wof:name":"Kouro",
    "wof:placetype":"locality"
},
  "geometry": {"coordinates":[21.07485,14.36745],"type":"Point"}
}