{
  "type": "Feature",
  "properties": {
    "gn:admin1_code":"9.0",
    "gn:asciiname":"Pakai",
    "gn:country_code":"TD",
    "gn:dem":556,
    "gn:feature_class":"P",
    "gn:feature_code":"PPL",
    "gn:name":"Paka\u00ef",
    "gn:population":0,
    "gn:timezone":"Africa/Ndjamena",
    "iso:country":"TD",
    "wof:name":"Pakai",
    "wof:placetype":"locality"
},
  "geometry": {"coordinates":[15.63333,7.61667],"type":"Point"}
}