{
  "type": "Feature",
  "properties": {
    "gn:admin1_code":"1.0",
    "gn:asciiname":"Nardiana",
    "gn:country_code":"TD",
    "gn:dem":305,
    "gn:feature_class":"P",
    "gn:feature_code":"PPL",
    "gn:name":"Nardiana",
    "gn:population":0,
    "gn:timezone":"Africa/Ndjamena",
    "iso:country":"TD",
    "wof:name":"Nardiana",
    "wof:placetype":"locality"
},
  "geometry": {"coordinates":[17.92476,13.02318],"type":"Point"}
}