{
  "type": "Feature",
  "properties": {
    "gn:admin1_code":"7.0",
    "gn:asciiname":"Koudouboul",
    "gn:country_code":"TD",
    "gn:dem":288,
    "gn:feature_class":"P",
    "gn:feature_code":"PPL",
    "gn:name":"Koudouboul",
    "gn:population":0,
    "gn:timezone":"Africa/Ndjamena",
    "iso:country":"TD",
    "wof:name":"Koudouboul",
    "wof:placetype":"locality"
},
  "geometry": {"coordinates":[14.93298,13.31334],"type":"Point"}
}