{
  "type": "Feature",
  "properties": {
    "gn:admin1_code":"9.0",
    "gn:asciiname":"Ebaygane",
    "gn:country_code":"TD",
    "gn:dem":462,
    "gn:feature_class":"P",
    "gn:feature_code":"PPL",
    "gn:name":"Ebaygane",
    "gn:population":0,
    "gn:timezone":"Africa/Ndjamena",
    "iso:country":"TD",
    "wof:name":"Ebaygane",
    "wof:placetype":"locality"
},
  "geometry": {"coordinates":[15.8977,7.9973],"type":"Point"}
}