{
  "type": "Feature",
  "properties": {
    "gn:admin1_code":"25.0",
    "gn:asciiname":"Am Djemena",
    "gn:country_code":"TD",
    "gn:dem":592,
    "gn:feature_class":"P",
    "gn:feature_code":"PPL",
    "gn:name":"Am Dj\u00e9m\u00e9na",
    "gn:population":0,
    "gn:timezone":"Africa/Ndjamena",
    "iso:country":"TD",
    "wof:name":"Am Djemena",
    "wof:placetype":"locality"
},
  "geometry": {"coordinates":[21.93333,12.28333],"type":"Point"}
}