{
  "type": "Feature",
  "properties": {
    "gn:admin1_code":"20.0",
    "gn:asciiname":"Mekabra",
    "gn:country_code":"TD",
    "gn:dem":476,
    "gn:feature_class":"P",
    "gn:feature_code":"PPL",
    "gn:name":"M\u00e9kabra",
    "gn:population":0,
    "gn:timezone":"Africa/Ndjamena",
    "iso:country":"TD",
    "name:und_x_variant":[
        "Mekabara",
        "M\u00e9kabra"
    ],
    "wof:name":"Mekabra",
    "wof:placetype":"locality"
},
  "geometry": {"coordinates":[15.2013,8.8929],"type":"Point"}
}