{
  "type": "Feature",
  "properties": {
    "gn:admin1_code":"14.0",
    "gn:asciiname":"Gore",
    "gn:country_code":"TD",
    "gn:dem":341,
    "gn:feature_class":"P",
    "gn:feature_code":"PPL",
    "gn:name":"Gor\u00e9",
    "gn:population":0,
    "gn:timezone":"Africa/Ndjamena",
    "iso:country":"TD",
    "wof:name":"Gore",
    "wof:placetype":"locality"
},
  "geometry": {"coordinates":[16.6789,9.9127],"type":"Point"}
}