{
  "type": "Feature",
  "properties": {
    "gn:admin1_code":"14.0",
    "gn:asciiname":"Djoro",
    "gn:country_code":"TD",
    "gn:dem":438,
    "gn:feature_class":"P",
    "gn:feature_code":"PPL",
    "gn:name":"Djoro",
    "gn:population":0,
    "gn:timezone":"Africa/Ndjamena",
    "iso:country":"TD",
    "wof:name":"Djoro",
    "wof:placetype":"locality"
},
  "geometry": {"coordinates":[16.6247,9.1502],"type":"Point"}
}