{
  "type": "Feature",
  "properties": {
    "gn:admin1_code":"1.0",
    "gn:asciiname":"Terkama",
    "gn:country_code":"TD",
    "gn:dem":338,
    "gn:feature_class":"P",
    "gn:feature_code":"PPL",
    "gn:name":"Terkama",
    "gn:population":0,
    "gn:timezone":"Africa/Ndjamena",
    "iso:country":"TD",
    "wof:name":"Terkama",
    "wof:placetype":"locality"
},
  "geometry": {"coordinates":[18.43333,13.16667],"type":"Point"}
}