{
  "type": "Feature",
  "properties": {
    "gn:admin1_code":"5.0",
    "gn:asciiname":"Baroual",
    "gn:country_code":"TD",
    "gn:dem":510,
    "gn:feature_class":"P",
    "gn:feature_code":"PPL",
    "gn:name":"Baroual",
    "gn:population":0,
    "gn:timezone":"Africa/Ndjamena",
    "iso:country":"TD",
    "wof:name":"Baroual",
    "wof:placetype":"locality"
},
  "geometry": {"coordinates":[18.3323,11.3407],"type":"Point"}
}