{
  "type": "Feature",
  "properties": {
    "gn:admin1_code":"5.0",
    "gn:asciiname":"Motgoro",
    "gn:country_code":"TD",
    "gn:dem":425,
    "gn:feature_class":"P",
    "gn:feature_code":"PPL",
    "gn:name":"Motgoro",
    "gn:population":0,
    "gn:timezone":"Africa/Ndjamena",
    "iso:country":"TD",
    "wof:name":"Motgoro",
    "wof:placetype":"locality"
},
  "geometry": {"coordinates":[18.1271,11.8172],"type":"Point"}
}