{
  "type": "Feature",
  "properties": {
    "gn:admin1_code":"21.0",
    "gn:asciiname":"Chankrous",
    "gn:country_code":"TD",
    "gn:dem":294,
    "gn:feature_class":"P",
    "gn:feature_code":"PPL",
    "gn:name":"Chankrous",
    "gn:population":0,
    "gn:timezone":"Africa/Ndjamena",
    "iso:country":"TD",
    "wof:name":"Chankrous",
    "wof:placetype":"locality"
},
  "geometry": {"coordinates":[15.0746,12.14099],"type":"Point"}
}