{
  "type": "Feature",
  "properties": {
    "gn:admin1_code":"18.0",
    "gn:asciiname":"Adaba",
    "gn:country_code":"TD",
    "gn:dem":290,
    "gn:feature_class":"P",
    "gn:feature_code":"PPL",
    "gn:name":"Adaba",
    "gn:population":0,
    "gn:timezone":"Africa/Ndjamena",
    "iso:country":"TD",
    "name:und_x_variant":[
        "Ams\u00e9d\u00e9r\u00e9",
        "Am S\u00e9d\u00e9r\u00e9"
    ],
    "wof:name":"Adaba",
    "wof:placetype":"locality"
},
  "geometry": {"coordinates":[14.90737,12.76167],"type":"Point"}
}