{
  "type": "Feature",
  "properties": {
    "gn:admin1_code":"18.0",
    "gn:asciiname":"Touka",
    "gn:country_code":"TD",
    "gn:dem":331,
    "gn:feature_class":"P",
    "gn:feature_code":"PPL",
    "gn:name":"Touka",
    "gn:population":0,
    "gn:timezone":"Africa/Ndjamena",
    "iso:country":"TD",
    "name:azb_x_preferred":[
        "\u062a\u0648\u06a9\u0627"
    ],
    "name:ceb_x_preferred":[
        "Touka"
    ],
    "name:fas_x_preferred":[
        "\u062a\u0648\u06a9\u0627"
    ],
    "name:fra_x_preferred":[
        "Touka"
    ],
    "name:swe_x_preferred":[
        "Touka"
    ],
    "wof:name":"Touka",
    "wof:placetype":"locality"
},
  "geometry": {"coordinates":[17.4388,12.09926],"type":"Point"}
}