{
  "type": "Feature",
  "properties": {
    "gn:admin1_code":"6.0",
    "gn:asciiname":"Bir Alali",
    "gn:country_code":"TD",
    "gn:dem":357,
    "gn:feature_class":"P",
    "gn:feature_code":"PPL",
    "gn:name":"Bir Alali",
    "gn:population":0,
    "gn:timezone":"Africa/Ndjamena",
    "iso:country":"TD",
    "name:und_x_variant":[
        "Fort Pradie",
        "Bir Alalioukiri",
        "Bir Alati",
        "Bir Alali"
    ],
    "wof:name":"Bir Alali",
    "wof:placetype":"locality"
},
  "geometry": {"coordinates":[15.34849,14.42768],"type":"Point"}
}