{
  "type": "Feature",
  "properties": {
    "gn:admin1_code":"5.0",
    "gn:asciiname":"Zamera",
    "gn:country_code":"TD",
    "gn:dem":448,
    "gn:feature_class":"P",
    "gn:feature_code":"PPL",
    "gn:name":"Zamera",
    "gn:population":0,
    "gn:timezone":"Africa/Ndjamena",
    "iso:country":"TD",
    "name:und_x_variant":[
        "Zamara",
        "Zamera"
    ],
    "wof:name":"Zamera",
    "wof:placetype":"locality"
},
  "geometry": {"coordinates":[18.95025,10.96038],"type":"Point"}
}