{
  "type": "Feature",
  "properties": {
    "gn:admin1_code":"9.0",
    "gn:asciiname":"Karoua",
    "gn:country_code":"TD",
    "gn:dem":499,
    "gn:feature_class":"P",
    "gn:feature_code":"PPL",
    "gn:name":"Karoua",
    "gn:population":0,
    "gn:timezone":"Africa/Ndjamena",
    "iso:country":"TD",
    "name:fra_x_preferred":[
        "Karoua"
    ],
    "wof:name":"Karoua",
    "wof:placetype":"locality"
},
  "geometry": {"coordinates":[16.32981,8.5021],"type":"Point"}
}