{
  "type": "Feature",
  "properties": {
    "gn:admin1_code":"1.0",
    "gn:asciiname":"Ab Garip",
    "gn:country_code":"TD",
    "gn:dem":367,
    "gn:feature_class":"P",
    "gn:feature_code":"PPL",
    "gn:name":"Ab Garip",
    "gn:population":0,
    "gn:timezone":"Africa/Ndjamena",
    "iso:country":"TD",
    "name:und_x_variant":[
        "Ab Garib",
        "Ab Garip"
    ],
    "wof:name":"Ab Garip",
    "wof:placetype":"locality"
},
  "geometry": {"coordinates":[19.2334,13.5216],"type":"Point"}
}