{
  "type": "Feature",
  "properties": {
    "gn:admin1_code":"16.0",
    "gn:asciiname":"Paikadi",
    "gn:country_code":"TD",
    "gn:dem":331,
    "gn:feature_class":"P",
    "gn:feature_code":"PPL",
    "gn:name":"Paikadi",
    "gn:population":0,
    "gn:timezone":"Africa/Ndjamena",
    "iso:country":"TD",
    "name:und_x_variant":[
        "Pahikadi",
        "Paikadi"
    ],
    "wof:name":"Paikadi",
    "wof:placetype":"locality"
},
  "geometry": {"coordinates":[16.1128,10.6845],"type":"Point"}
}