{
  "type": "Feature",
  "properties": {
    "gn:admin1_code":"8.0",
    "gn:asciiname":"Taoui",
    "gn:country_code":"TD",
    "gn:dem":397,
    "gn:feature_class":"P",
    "gn:feature_code":"PPL",
    "gn:name":"Taoui",
    "gn:population":0,
    "gn:timezone":"Africa/Ndjamena",
    "iso:country":"TD",
    "wof:name":"Taoui",
    "wof:placetype":"locality"
},
  "geometry": {"coordinates":[16.0383,8.5677],"type":"Point"}
}