{
  "type": "Feature",
  "properties": {
    "gn:admin1_code":"23.0",
    "gn:asciiname":"Mordangay",
    "gn:country_code":"TD",
    "gn:dem":222,
    "gn:feature_class":"P",
    "gn:feature_code":"PPL",
    "gn:name":"Mordangay",
    "gn:population":0,
    "gn:timezone":"Africa/Ndjamena",
    "iso:country":"TD",
    "name:fra_x_preferred":[
        "Mordangay"
    ],
    "wof:name":"Mordangay",
    "wof:placetype":"locality"
},
  "geometry": {"coordinates":[19.04825,17.89765],"type":"Point"}
}