{
  "type": "Feature",
  "properties": {
    "gn:admin1_code":"15.0",
    "gn:asciiname":"Baranga",
    "gn:country_code":"TD",
    "gn:dem":340,
    "gn:feature_class":"P",
    "gn:feature_code":"PPL",
    "gn:name":"Baranga",
    "gn:population":0,
    "gn:timezone":"Africa/Ndjamena",
    "iso:country":"TD",
    "name:ron_x_preferred":[
        "Baranga"
    ],
    "name:spa_x_preferred":[
        "Barangay"
    ],
    "wof:name":"Baranga",
    "wof:placetype":"locality"
},
  "geometry": {"coordinates":[17.0633,10.5396],"type":"Point"}
}