{
  "type": "Feature",
  "properties": {
    "gn:admin1_code":"12.0",
    "gn:asciiname":"Djarkene",
    "gn:country_code":"TD",
    "gn:dem":477,
    "gn:feature_class":"P",
    "gn:feature_code":"PPL",
    "gn:name":"Djark\u00e9n\u00e9",
    "gn:population":0,
    "gn:timezone":"Africa/Ndjamena",
    "iso:country":"TD",
    "name:und_x_variant":[
        "Djerk\u00e9n\u00e9",
        "Djark\u00e9n\u00e9"
    ],
    "wof:name":"Djarkene",
    "wof:placetype":"locality"
},
  "geometry": {"coordinates":[20.52027,14.10165],"type":"Point"}
}