{
  "type": "Feature",
  "properties": {
    "gn:admin1_code":"2.0",
    "gn:asciiname":"Soyo",
    "gn:country_code":"TD",
    "gn:dem":808,
    "gn:feature_class":"P",
    "gn:feature_code":"PPL",
    "gn:name":"Soyo",
    "gn:population":0,
    "gn:timezone":"Africa/Ndjamena",
    "iso:country":"TD",
    "name:fra_x_preferred":[
        "Soyo"
    ],
    "wof:name":"Soyo",
    "wof:placetype":"locality"
},
  "geometry": {"coordinates":[21.28937,14.18752],"type":"Point"}
}