{
  "type": "Feature",
  "properties": {
    "gn:admin1_code":"2.0",
    "gn:asciiname":"Mandoun",
    "gn:country_code":"TD",
    "gn:dem":716,
    "gn:feature_class":"P",
    "gn:feature_code":"PPL",
    "gn:name":"Mandoun",
    "gn:population":0,
    "gn:timezone":"Africa/Ndjamena",
    "iso:country":"TD",
    "name:fra_x_preferred":[
        "Mandoun"
    ],
    "wof:name":"Mandoun",
    "wof:placetype":"locality"
},
  "geometry": {"coordinates":[21.17966,14.14694],"type":"Point"}
}