{
  "type": "Feature",
  "properties": {
    "gn:admin1_code":"17.0",
    "gn:asciiname":"Tieng",
    "gn:country_code":"TD",
    "gn:dem":354,
    "gn:feature_class":"P",
    "gn:feature_code":"PPL",
    "gn:name":"Tieng",
    "gn:population":0,
    "gn:timezone":"Africa/Ndjamena",
    "iso:country":"TD",
    "name:und_x_variant":[
        "Tiong",
        "Tieng"
    ],
    "wof:name":"Tieng",
    "wof:placetype":"locality"
},
  "geometry": {"coordinates":[17.69813,9.80963],"type":"Point"}
}