{
  "type": "Feature",
  "properties": {
    "gn:admin1_code":"20.0",
    "gn:asciiname":"Djavou",
    "gn:country_code":"TD",
    "gn:dem":382,
    "gn:feature_class":"P",
    "gn:feature_code":"PPL",
    "gn:name":"Djavou",
    "gn:population":0,
    "gn:timezone":"Africa/Ndjamena",
    "iso:country":"TD",
    "wof:name":"Djavou",
    "wof:placetype":"locality"
},
  "geometry": {"coordinates":[14.3591,9.365],"type":"Point"}
}