{
  "type": "Feature",
  "properties": {
    "gn:admin1_code":"9.0",
    "gn:asciiname":"Bingamara",
    "gn:country_code":"TD",
    "gn:dem":399,
    "gn:feature_class":"P",
    "gn:feature_code":"PPL",
    "gn:name":"Bingamara",
    "gn:population":0,
    "gn:timezone":"Africa/Ndjamena",
    "iso:country":"TD",
    "wof:name":"Bingamara",
    "wof:placetype":"locality"
},
  "geometry": {"coordinates":[16.6411,8.67555],"type":"Point"}
}