{
  "type": "Feature",
  "properties": {
    "gn:admin1_code":"7.0",
    "gn:asciiname":"Bifou Kengela",
    "gn:country_code":"TD",
    "gn:dem":290,
    "gn:feature_class":"P",
    "gn:feature_code":"PPL",
    "gn:name":"Bifou Keng\u00e9la",
    "gn:population":0,
    "gn:timezone":"Africa/Ndjamena",
    "iso:country":"TD",
    "wof:name":"Bifou Kengela",
    "wof:placetype":"locality"
},
  "geometry": {"coordinates":[14.26667,13.81667],"type":"Point"}
}