{
  "type": "Feature",
  "properties": {
    "gn:admin1_code":"1.0",
    "gn:asciiname":"Am Kouchou",
    "gn:country_code":"TD",
    "gn:dem":416,
    "gn:feature_class":"P",
    "gn:feature_code":"PPL",
    "gn:name":"Am Kouchou",
    "gn:population":0,
    "gn:timezone":"Africa/Ndjamena",
    "iso:country":"TD",
    "name:fra_x_preferred":[
        "Am Kouchou"
    ],
    "wof:name":"Am Kouchou",
    "wof:placetype":"locality"
},
  "geometry": {"coordinates":[20.07711,13.53077],"type":"Point"}
}