{
  "type": "Feature",
  "properties": {
    "gn:admin1_code":"15.0",
    "gn:asciiname":"Maidougouri",
    "gn:country_code":"TD",
    "gn:dem":300,
    "gn:feature_class":"P",
    "gn:feature_code":"PPL",
    "gn:name":"Ma\u00efdougouri",
    "gn:population":0,
    "gn:timezone":"Africa/Ndjamena",
    "iso:country":"TD",
    "wof:name":"Maidougouri",
    "wof:placetype":"locality"
},
  "geometry": {"coordinates":[15.2377,11.76072],"type":"Point"}
}