{
  "type": "Feature",
  "properties": {
    "gn:admin1_code":"13.0",
    "gn:asciiname":"Al Goz",
    "gn:country_code":"TD",
    "gn:dem":434,
    "gn:feature_class":"P",
    "gn:feature_code":"PPL",
    "gn:name":"Al Goz",
    "gn:population":0,
    "gn:timezone":"Africa/Ndjamena",
    "iso:country":"TD",
    "name:und_x_variant":[
        "El Goz",
        "Al Goz"
    ],
    "wof:name":"Al Goz",
    "wof:placetype":"locality"
},
  "geometry": {"coordinates":[20.1268,11.4811],"type":"Point"}
}