{
  "type": "Feature",
  "properties": {
    "gn:admin1_code":"16.0",
    "gn:asciiname":"Kedoua",
    "gn:country_code":"TD",
    "gn:dem":327,
    "gn:feature_class":"P",
    "gn:feature_code":"PPL",
    "gn:name":"K\u00e9doua",
    "gn:population":0,
    "gn:timezone":"Africa/Ndjamena",
    "iso:country":"TD",
    "wof:name":"Kedoua",
    "wof:placetype":"locality"
},
  "geometry": {"coordinates":[15.12875,9.98931],"type":"Point"}
}