{
  "type": "Feature",
  "properties": {
    "gn:admin1_code":"18.0",
    "gn:asciiname":"Abou Gounde",
    "gn:country_code":"TD",
    "gn:dem":293,
    "gn:feature_class":"P",
    "gn:feature_code":"PPL",
    "gn:name":"Abou Gound\u00e9",
    "gn:population":0,
    "gn:timezone":"Africa/Ndjamena",
    "iso:country":"TD",
    "name:und_x_variant":[
        "Aboungod\u00e9",
        "Abou Gound\u00e9"
    ],
    "wof:name":"Abou Gounde",
    "wof:placetype":"locality"
},
  "geometry": {"coordinates":[16.83333,13.03333],"type":"Point"}
}