{
  "type": "Feature",
  "properties": {
    "gn:admin1_code":"13.0",
    "gn:asciiname":"Dangasti",
    "gn:country_code":"TD",
    "gn:dem":465,
    "gn:feature_class":"P",
    "gn:feature_code":"PPL",
    "gn:name":"Dangasti",
    "gn:population":0,
    "gn:timezone":"Africa/Ndjamena",
    "iso:country":"TD",
    "wof:name":"Dangasti",
    "wof:placetype":"locality"
},
  "geometry": {"coordinates":[20.8063,11.3302],"type":"Point"}
}