{
  "type": "Feature",
  "properties": {
    "gn:admin1_code":"5.0",
    "gn:asciiname":"Gormolo Am Ziefe",
    "gn:country_code":"TD",
    "gn:dem":455,
    "gn:feature_class":"P",
    "gn:feature_code":"PPL",
    "gn:name":"Gormolo Am Zi\u00e9f\u00e9",
    "gn:population":0,
    "gn:timezone":"Africa/Ndjamena",
    "iso:country":"TD",
    "wof:name":"Gormolo Am Ziefe",
    "wof:placetype":"locality"
},
  "geometry": {"coordinates":[19.5987,12.4579],"type":"Point"}
}