{
  "type": "Feature",
  "properties": {
    "gn:admin1_code":"7.0",
    "gn:asciiname":"Roudo Ndiara",
    "gn:country_code":"TD",
    "gn:dem":307,
    "gn:feature_class":"P",
    "gn:feature_code":"PPL",
    "gn:name":"Roudo Ndiara",
    "gn:population":0,
    "gn:timezone":"Africa/Ndjamena",
    "iso:country":"TD",
    "wof:name":"Roudo Ndiara",
    "wof:placetype":"locality"
},
  "geometry": {"coordinates":[15.3115,13.67847],"type":"Point"}
}