{
  "type": "Feature",
  "properties": {
    "gn:admin1_code":"17.0",
    "gn:asciiname":"Banda II",
    "gn:country_code":"TD",
    "gn:dem":373,
    "gn:feature_class":"P",
    "gn:feature_code":"PPL",
    "gn:name":"Banda II",
    "gn:population":0,
    "gn:timezone":"Africa/Ndjamena",
    "iso:country":"TD",
    "wof:name":"Banda II",
    "wof:placetype":"locality"
},
  "geometry": {"coordinates":[18.4208,8.8274],"type":"Point"}
}