{
  "type": "Feature",
  "properties": {
    "gn:admin1_code":"17.0",
    "gn:asciiname":"Hiam",
    "gn:country_code":"TD",
    "gn:dem":394,
    "gn:feature_class":"P",
    "gn:feature_code":"PPL",
    "gn:name":"Hiam",
    "gn:population":0,
    "gn:timezone":"Africa/Ndjamena",
    "iso:country":"TD",
    "wof:name":"Hiam",
    "wof:placetype":"locality"
},
  "geometry": {"coordinates":[18.147,10.2566],"type":"Point"}
}