{
  "type": "Feature",
  "properties": {
    "gn:admin1_code":"22.0",
    "gn:asciiname":"Boroiam",
    "gn:country_code":"TD",
    "gn:dem":310,
    "gn:feature_class":"P",
    "gn:feature_code":"PPL",
    "gn:name":"Boroiam",
    "gn:population":0,
    "gn:timezone":"Africa/Ndjamena",
    "iso:country":"TD",
    "wof:name":"Boroiam",
    "wof:placetype":"locality"
},
  "geometry": {"coordinates":[15.68646,13.91899],"type":"Point"}
}