{
  "type": "Feature",
  "properties": {
    "gn:admin1_code":"19.0",
    "gn:asciiname":"Dobo",
    "gn:country_code":"TD",
    "gn:dem":411,
    "gn:feature_class":"P",
    "gn:feature_code":"PPL",
    "gn:name":"Dobo",
    "gn:population":0,
    "gn:timezone":"Africa/Ndjamena",
    "iso:country":"TD",
    "name:ceb_x_preferred":[
        "Dobo"
    ],
    "name:deu_x_preferred":[
        "Dobo"
    ],
    "name:fra_x_preferred":[
        "Dobo"
    ],
    "name:swe_x_preferred":[
        "Dobo"
    ],
    "wof:name":"Dobo",
    "wof:placetype":"locality"
},
  "geometry": {"coordinates":[17.45342,8.06638],"type":"Point"}
}