{
  "type": "Feature",
  "properties": {
    "gn:admin1_code":"12.0",
    "gn:asciiname":"Dodorok",
    "gn:country_code":"TD",
    "gn:dem":908,
    "gn:feature_class":"P",
    "gn:feature_code":"PPL",
    "gn:name":"Dodorok",
    "gn:population":0,
    "gn:timezone":"Africa/Ndjamena",
    "iso:country":"TD",
    "wof:name":"Dodorok",
    "wof:placetype":"locality"
},
  "geometry": {"coordinates":[21.93062,13.43101],"type":"Point"}
}