{
  "type": "Feature",
  "properties": {
    "gn:admin1_code":"12.0",
    "gn:asciiname":"Djamal Haro",
    "gn:country_code":"TD",
    "gn:dem":808,
    "gn:feature_class":"P",
    "gn:feature_code":"PPL",
    "gn:name":"Djamal Haro",
    "gn:population":0,
    "gn:timezone":"Africa/Ndjamena",
    "iso:country":"TD",
    "wof:name":"Djamal Haro",
    "wof:placetype":"locality"
},
  "geometry": {"coordinates":[21.7873,13.57395],"type":"Point"}
}