{
  "type": "Feature",
  "properties": {
    "gn:admin1_code":"18.0",
    "gn:asciiname":"Moura",
    "gn:country_code":"TD",
    "gn:dem":291,
    "gn:feature_class":"P",
    "gn:feature_code":"PPL",
    "gn:name":"Moura",
    "gn:population":0,
    "gn:timezone":"Africa/Ndjamena",
    "iso:country":"TD",
    "name:ceb_x_preferred":[
        "Moura"
    ],
    "name:deu_x_preferred":[
        "Moura"
    ],
    "name:fra_x_preferred":[
        "Moura"
    ],
    "name:glg_x_preferred":[
        "Moura"
    ],
    "name:jpn_x_preferred":[
        "\u30e2\u30a6\u30e9"
    ],
    "name:por_x_preferred":[
        "Moura"
    ],
    "name:rus_x_preferred":[
        "\u041c\u043e\u0443\u0440\u0430"
    ],
    "wof:name":"Moura",
    "wof:placetype":"locality"
},
  "geometry": {"coordinates":[15.74536,13.01455],"type":"Point"}
}