{
  "type": "Feature",
  "properties": {
    "gn:admin1_code":"1.0",
    "gn:asciiname":"Bandjedid",
    "gn:country_code":"TD",
    "gn:dem":390,
    "gn:feature_class":"P",
    "gn:feature_code":"PPL",
    "gn:name":"Bandjedid",
    "gn:population":0,
    "gn:timezone":"Africa/Ndjamena",
    "iso:country":"TD",
    "wof:name":"Bandjedid",
    "wof:placetype":"locality"
},
  "geometry": {"coordinates":[19.71667,13.53333],"type":"Point"}
}