{
  "type": "Feature",
  "properties": {
    "gn:admin1_code":"2.0",
    "gn:asciiname":"Am Nabak",
    "gn:country_code":"TD",
    "gn:dem":973,
    "gn:feature_class":"P",
    "gn:feature_code":"PPL",
    "gn:name":"Am Nabak",
    "gn:population":0,
    "gn:timezone":"Africa/Ndjamena",
    "iso:country":"TD",
    "wof:name":"Am Nabak",
    "wof:placetype":"locality"
},
  "geometry": {"coordinates":[22.33333,14.78333],"type":"Point"}
}