{
  "type": "Feature",
  "properties": {
    "gn:admin1_code":"12.0",
    "gn:asciiname":"Abisa Madala",
    "gn:country_code":"TD",
    "gn:dem":477,
    "gn:feature_class":"P",
    "gn:feature_code":"PPL",
    "gn:name":"Abisa Madala",
    "gn:population":0,
    "gn:timezone":"Africa/Ndjamena",
    "iso:country":"TD",
    "wof:name":"Abisa Madala",
    "wof:placetype":"locality"
},
  "geometry": {"coordinates":[20.71204,14.32695],"type":"Point"}
}