{
  "type": "Feature",
  "properties": {
    "gn:admin1_code":"20.0",
    "gn:asciiname":"Bissi Keda",
    "gn:country_code":"TD",
    "gn:dem":334,
    "gn:feature_class":"P",
    "gn:feature_code":"PPL",
    "gn:name":"Bissi K\u00e9da",
    "gn:population":0,
    "gn:timezone":"Africa/Ndjamena",
    "iso:country":"TD",
    "name:und_x_variant":[
        "Bisi K\u00e9da",
        "Bissi K\u00e9da"
    ],
    "wof:name":"Bissi Keda",
    "wof:placetype":"locality"
},
  "geometry": {"coordinates":[14.5992,9.2648],"type":"Point"}
}