{
  "type": "Feature",
  "properties": {
    "gn:admin1_code":"15.0",
    "gn:asciiname":"Tchaouay",
    "gn:country_code":"TD",
    "gn:dem":328,
    "gn:feature_class":"P",
    "gn:feature_code":"PPL",
    "gn:name":"Tchaouay",
    "gn:population":0,
    "gn:timezone":"Africa/Ndjamena",
    "iso:country":"TD",
    "wof:name":"Tchaouay",
    "wof:placetype":"locality"
},
  "geometry": {"coordinates":[16.061,11.5955],"type":"Point"}
}