{
  "type": "Feature",
  "properties": {
    "gn:admin1_code":"17.0",
    "gn:asciiname":"Moudal",
    "gn:country_code":"TD",
    "gn:dem":372,
    "gn:feature_class":"P",
    "gn:feature_code":"PPL",
    "gn:name":"Moudal",
    "gn:population":0,
    "gn:timezone":"Africa/Ndjamena",
    "iso:country":"TD",
    "wof:name":"Moudal",
    "wof:placetype":"locality"
},
  "geometry": {"coordinates":[18.08387,8.66989],"type":"Point"}
}