{
  "type": "Feature",
  "properties": {
    "gn:country":"TD",
    "gn:fcode":"PPL",
    "gn:pop":1000,
    "iso:country":"TD",
    "name:ara_x_preferred":[
        "\u0642\u0648\u0632 \u0628\u064a\u062f\u0627"
    ],
    "name:ceb_x_preferred":[
        "Goz Be\u00efda"
    ],
    "name:deu_x_preferred":[
        "Goz Be\u00efda"
    ],
    "name:eng_x_preferred":[
        "Goz Beida"
    ],
    "name:eng_x_variant":[
        "Goz Be\u00efda"
    ],
    "name:fra_x_preferred":[
        "Goz Be\u00efda"
    ],
    "name:ita_x_preferred":[
        "Goz Be\u00efda"
    ],
    "name:jpn_x_preferred":[
        "\u30b4\u30be\u30fb\u30d9\u30a4\u30c0"
    ],
    "name:mrj_x_preferred":[
        "\u0413\u043e\u0437-\u0411\u0435\u0439\u0434\u0430"
    ],
    "name:nld_x_preferred":[
        "Goz Be\u00efda"
    ],
    "name:pol_x_preferred":[
        "Goz Be\u00efda"
    ],
    "name:ron_x_preferred":[
        "Goz Be\u00efda"
    ],
    "name:rus_x_preferred":[
        "\u0413\u043e\u0437-\u0411\u0435\u0439\u0434\u0430"
    ],
    "name:urd_x_preferred":[
        "\u0642\u0648\u0632 \u0628\u06cc\u0636\u0627"
    ],
    "name:zho_x_preferred":[
        "\u6208\u8332\u8c9d\u9054"
    ],
    "qs:name":"Goz Be\u00efda",
    "qs:photos_9r":0,
    "qs:photos_sr":0,
    "qs:pop_sr":"2",
    "wd:wordcount":292,
    "wof:name":"Goz Be\u00efda",
    "wof:placetype":"locality",
    "wof:population":1000
},
  "geometry": {"coordinates":[21.41667,12.21667],"type":"Point"}
}