{
  "type": "Feature",
  "properties": {
    "gn:admin1_code":"8.0",
    "gn:asciiname":"Barbina",
    "gn:country_code":"TD",
    "gn:dem":398,
    "gn:feature_class":"P",
    "gn:feature_code":"PPL",
    "gn:name":"Barbina",
    "gn:population":0,
    "gn:timezone":"Africa/Ndjamena",
    "iso:country":"TD",
    "name:und_x_variant":[
        "Babina",
        "Barbina"
    ],
    "wof:name":"Barbina",
    "wof:placetype":"locality"
},
  "geometry": {"coordinates":[15.73192,8.82234],"type":"Point"}
}