{
  "type": "Feature",
  "properties": {
    "gn:admin1_code":"16.0",
    "gn:asciiname":"Ossin",
    "gn:country_code":"TD",
    "gn:dem":350,
    "gn:feature_class":"P",
    "gn:feature_code":"PPL",
    "gn:name":"Ossin",
    "gn:population":0,
    "gn:timezone":"Africa/Ndjamena",
    "iso:country":"TD",
    "wof:name":"Ossin",
    "wof:placetype":"locality"
},
  "geometry": {"coordinates":[14.8744,9.9463],"type":"Point"}
}