{
  "type": "Feature",
  "properties": {
    "gn:admin1_code":"16.0",
    "gn:asciiname":"Grand Tougoude",
    "gn:country_code":"TD",
    "gn:dem":332,
    "gn:feature_class":"P",
    "gn:feature_code":"PPL",
    "gn:name":"Grand Tougoud\u00e9",
    "gn:population":0,
    "gn:timezone":"Africa/Ndjamena",
    "iso:country":"TD",
    "name:und_x_variant":[
        "Tougoud\u00e9",
        "Grand Tougoud\u00e9"
    ],
    "wof:name":"Grand Tougoude",
    "wof:placetype":"locality"
},
  "geometry": {"coordinates":[15.4984,10.15121],"type":"Point"}
}