{
  "type": "Feature",
  "properties": {
    "gn:admin1_code":"5.0",
    "gn:asciiname":"Kilgnata",
    "gn:country_code":"TD",
    "gn:dem":443,
    "gn:feature_class":"P",
    "gn:feature_code":"PPL",
    "gn:name":"Kilgnata",
    "gn:population":0,
    "gn:timezone":"Africa/Ndjamena",
    "iso:country":"TD",
    "wof:name":"Kilgnata",
    "wof:placetype":"locality"
},
  "geometry": {"coordinates":[18.83669,12.34225],"type":"Point"}
}