{
  "type": "Feature",
  "properties": {
    "gn:admin1_code":"1.0",
    "gn:asciiname":"Seita Dankoutch",
    "gn:country_code":"TD",
    "gn:dem":304,
    "gn:feature_class":"P",
    "gn:feature_code":"PPL",
    "gn:name":"Seita Dankoutch",
    "gn:population":0,
    "gn:timezone":"Africa/Ndjamena",
    "iso:country":"TD",
    "wof:name":"Seita Dankoutch",
    "wof:placetype":"locality"
},
  "geometry": {"coordinates":[17.89409,12.98091],"type":"Point"}
}