{
  "type": "Feature",
  "properties": {
    "gn:admin1_code":"14.0",
    "gn:asciiname":"Doumbadgue",
    "gn:country_code":"TD",
    "gn:dem":421,
    "gn:feature_class":"P",
    "gn:feature_code":"PPL",
    "gn:name":"Doumbadgu\u00e9",
    "gn:population":0,
    "gn:timezone":"Africa/Ndjamena",
    "iso:country":"TD",
    "name:und_x_variant":[
        "Doumbadg\u00e9",
        "Doumbadj\u00e9",
        "Doumbadgu\u00e9"
    ],
    "wof:name":"Doumbadgue",
    "wof:placetype":"locality"
},
  "geometry": {"coordinates":[15.61023,9.04597],"type":"Point"}
}