{
  "type": "Feature",
  "properties": {
    "gn:admin1_code":"15.0",
    "gn:asciiname":"Katche",
    "gn:country_code":"TD",
    "gn:dem":299,
    "gn:feature_class":"P",
    "gn:feature_code":"PPL",
    "gn:name":"Katch\u00e9",
    "gn:population":0,
    "gn:timezone":"Africa/Ndjamena",
    "iso:country":"TD",
    "wof:name":"Katche",
    "wof:placetype":"locality"
},
  "geometry": {"coordinates":[15.87014,12.21469],"type":"Point"}
}