{
  "type": "Feature",
  "properties": {
    "gn:admin1_code":"16.0",
    "gn:asciiname":"Djouboul",
    "gn:country_code":"TD",
    "gn:dem":345,
    "gn:feature_class":"P",
    "gn:feature_code":"PPL",
    "gn:name":"Djouboul",
    "gn:population":0,
    "gn:timezone":"Africa/Ndjamena",
    "iso:country":"TD",
    "wof:name":"Djouboul",
    "wof:placetype":"locality"
},
  "geometry": {"coordinates":[15.9425,9.6621],"type":"Point"}
}