{
  "type": "Feature",
  "properties": {
    "gn:admin1_code":"9.0",
    "gn:asciiname":"Koumabila",
    "gn:country_code":"TD",
    "gn:dem":503,
    "gn:feature_class":"P",
    "gn:feature_code":"PPL",
    "gn:name":"Koumabila",
    "gn:population":0,
    "gn:timezone":"Africa/Ndjamena",
    "iso:country":"TD",
    "name:und_x_variant":[
        "Koumabita",
        "Koumabeda",
        "Koumabila"
    ],
    "wof:name":"Koumabila",
    "wof:placetype":"locality"
},
  "geometry": {"coordinates":[15.7539,8.2226],"type":"Point"}
}