{
  "type": "Feature",
  "properties": {
    "gn:admin1_code":"19.0",
    "gn:asciiname":"Daibo",
    "gn:country_code":"TD",
    "gn:dem":386,
    "gn:feature_class":"P",
    "gn:feature_code":"PPL",
    "gn:name":"Da\u00efbo",
    "gn:population":0,
    "gn:timezone":"Africa/Ndjamena",
    "iso:country":"TD",
    "wof:name":"Daibo",
    "wof:placetype":"locality"
},
  "geometry": {"coordinates":[17.26467,8.38083],"type":"Point"}
}