{
  "type": "Feature",
  "properties": {
    "gn:admin1_code":"20.0",
    "gn:asciiname":"Latta",
    "gn:country_code":"TD",
    "gn:dem":279,
    "gn:feature_class":"P",
    "gn:feature_code":"PPL",
    "gn:name":"Latta",
    "gn:population":0,
    "gn:timezone":"Africa/Ndjamena",
    "iso:country":"TD",
    "name:ceb_x_preferred":[
        "Latta"
    ],
    "name:deu_x_preferred":[
        "Latta"
    ],
    "name:fin_x_preferred":[
        "Latta"
    ],
    "name:fra_x_preferred":[
        "Latta"
    ],
    "name:pol_x_preferred":[
        "Latta"
    ],
    "name:rus_x_preferred":[
        "\u041b\u0430\u0442\u0442\u0430"
    ],
    "name:swe_x_preferred":[
        "Latta"
    ],
    "name:ukr_x_preferred":[
        "\u041b\u0430\u0442\u0442\u0430"
    ],
    "wof:name":"Latta",
    "wof:placetype":"locality"
},
  "geometry": {"coordinates":[14.5514,9.5658],"type":"Point"}
}