{
  "type": "Feature",
  "properties": {
    "gn:admin1_code":"2.0",
    "gn:asciiname":"Deker",
    "gn:country_code":"TD",
    "gn:dem":592,
    "gn:feature_class":"P",
    "gn:feature_code":"PPL",
    "gn:name":"D\u00e9k\u00e9r",
    "gn:population":0,
    "gn:timezone":"Africa/Ndjamena",
    "iso:country":"TD",
    "name:fra_x_preferred":[
        "D\u00e9k\u00e9r"
    ],
    "name:und_x_variant":[
        "Doker"
    ],
    "wof:name":"Deker",
    "wof:placetype":"locality"
},
  "geometry": {"coordinates":[21.07191,14.45595],"type":"Point"}
}