{
  "type": "Feature",
  "properties": {
    "gn:admin1_code":"1.0",
    "gn:asciiname":"Djounia",
    "gn:country_code":"TD",
    "gn:dem":288,
    "gn:feature_class":"P",
    "gn:feature_code":"PPL",
    "gn:name":"Djounia",
    "gn:population":0,
    "gn:timezone":"Africa/Ndjamena",
    "iso:country":"TD",
    "wof:name":"Djounia",
    "wof:placetype":"locality"
},
  "geometry": {"coordinates":[17.70678999999999,12.85819],"type":"Point"}
}