{
  "type": "Feature",
  "properties": {
    "gn:admin1_code":"18.0",
    "gn:asciiname":"Kameron Guini",
    "gn:country_code":"TD",
    "gn:dem":290,
    "gn:feature_class":"P",
    "gn:feature_code":"PPL",
    "gn:name":"Kameron Guini",
    "gn:population":0,
    "gn:timezone":"Africa/Ndjamena",
    "iso:country":"TD",
    "name:und_x_variant":[
        "Kameron Gini",
        "Kameron Guini"
    ],
    "wof:name":"Kameron Guini",
    "wof:placetype":"locality"
},
  "geometry": {"coordinates":[15.50431,12.98317],"type":"Point"}
}