{
  "type": "Feature",
  "properties": {
    "gn:admin1_code":"18.0",
    "gn:asciiname":"Rahat el Bagar",
    "gn:country_code":"TD",
    "gn:dem":310,
    "gn:feature_class":"P",
    "gn:feature_code":"PPL",
    "gn:name":"Rahat el Bagar",
    "gn:population":0,
    "gn:timezone":"Africa/Ndjamena",
    "iso:country":"TD",
    "wof:name":"Rahat el Bagar",
    "wof:placetype":"locality"
},
  "geometry": {"coordinates":[17.09401,12.1662],"type":"Point"}
}