{
  "type": "Feature",
  "properties": {
    "gn:admin1_code":"12.0",
    "gn:asciiname":"Kengala",
    "gn:country_code":"TD",
    "gn:dem":764,
    "gn:feature_class":"P",
    "gn:feature_code":"PPL",
    "gn:name":"Kengala",
    "gn:population":0,
    "gn:timezone":"Africa/Ndjamena",
    "iso:country":"TD",
    "name:fra_x_preferred":[
        "Kengala"
    ],
    "wof:name":"Kengala",
    "wof:placetype":"locality"
},
  "geometry": {"coordinates":[21.3007,14.0748],"type":"Point"}
}