{
  "type": "Feature",
  "properties": {
    "gn:admin1_code":"15.0",
    "gn:asciiname":"Modiomou",
    "gn:country_code":"TD",
    "gn:dem":329,
    "gn:feature_class":"P",
    "gn:feature_code":"PPL",
    "gn:name":"Modiomou",
    "gn:population":0,
    "gn:timezone":"Africa/Ndjamena",
    "iso:country":"TD",
    "wof:name":"Modiomou",
    "wof:placetype":"locality"
},
  "geometry": {"coordinates":[16.05,11.03333],"type":"Point"}
}