{
  "type": "Feature",
  "properties": {
    "gn:admin1_code":"7.0",
    "gn:asciiname":"Graerom",
    "gn:country_code":"TD",
    "gn:dem":284,
    "gn:feature_class":"P",
    "gn:feature_code":"PPL",
    "gn:name":"Gra\u00e9rom",
    "gn:population":0,
    "gn:timezone":"Africa/Ndjamena",
    "iso:country":"TD",
    "wof:name":"Graerom",
    "wof:placetype":"locality"
},
  "geometry": {"coordinates":[14.47089,13.33106],"type":"Point"}
}