{
  "type": "Feature",
  "properties": {
    "gn:admin1_code":"15.0",
    "gn:asciiname":"Araz",
    "gn:country_code":"TD",
    "gn:dem":319,
    "gn:feature_class":"P",
    "gn:feature_code":"PPL",
    "gn:name":"Araz",
    "gn:population":0,
    "gn:timezone":"Africa/Ndjamena",
    "iso:country":"TD",
    "wof:name":"Araz",
    "wof:placetype":"locality"
},
  "geometry": {"coordinates":[15.89176,11.91821],"type":"Point"}
}