{
  "type": "Feature",
  "properties": {
    "gn:admin1_code":"19.0",
    "gn:asciiname":"Bouna",
    "gn:country_code":"TD",
    "gn:dem":379,
    "gn:feature_class":"P",
    "gn:feature_code":"PPL",
    "gn:name":"Bouna",
    "gn:population":0,
    "gn:timezone":"Africa/Ndjamena",
    "iso:country":"TD",
    "name:ceb_x_preferred":[
        "Bouna"
    ],
    "name:fra_x_preferred":[
        "Bouna"
    ],
    "name:ita_x_preferred":[
        "Bouna"
    ],
    "name:swa_x_preferred":[
        "Bouna"
    ],
    "name:swe_x_preferred":[
        "Bouna"
    ],
    "name:und_x_variant":[
        "Bebouna"
    ],
    "wof:name":"Bouna",
    "wof:placetype":"locality"
},
  "geometry": {"coordinates":[17.4274,8.49325],"type":"Point"}
}