{
  "type": "Feature",
  "properties": {
    "gn:admin1_code":"16.0",
    "gn:asciiname":"Djouno",
    "gn:country_code":"TD",
    "gn:dem":338,
    "gn:feature_class":"P",
    "gn:feature_code":"PPL",
    "gn:name":"Djouno",
    "gn:population":0,
    "gn:timezone":"Africa/Ndjamena",
    "iso:country":"TD",
    "wof:name":"Djouno",
    "wof:placetype":"locality"
},
  "geometry": {"coordinates":[16.1249,10.167],"type":"Point"}
}