{
  "type": "Feature",
  "properties": {
    "gn:admin1_code":"12.0",
    "gn:asciiname":"Touroko",
    "gn:country_code":"TD",
    "gn:dem":882,
    "gn:feature_class":"P",
    "gn:feature_code":"PPL",
    "gn:name":"Touroko",
    "gn:population":0,
    "gn:timezone":"Africa/Ndjamena",
    "iso:country":"TD",
    "name:fra_x_preferred":[
        "Touroko"
    ],
    "wof:name":"Touroko",
    "wof:placetype":"locality"
},
  "geometry": {"coordinates":[21.7543,14.03061],"type":"Point"}
}