{
  "type": "Feature",
  "properties": {
    "gn:admin1_code":"9.0",
    "gn:asciiname":"Sara Karer",
    "gn:country_code":"TD",
    "gn:dem":441,
    "gn:feature_class":"P",
    "gn:feature_code":"PPL",
    "gn:name":"Sara Kar\u00e8r",
    "gn:population":0,
    "gn:timezone":"Africa/Ndjamena",
    "iso:country":"TD",
    "name:und_x_variant":[
        "Sarakar\u00e8re",
        "Sara Kar\u00e8r"
    ],
    "wof:name":"Sara Karer",
    "wof:placetype":"locality"
},
  "geometry": {"coordinates":[15.5427,8.1745],"type":"Point"}
}