{
  "type": "Feature",
  "properties": {
    "gn:admin1_code":"13.0",
    "gn:asciiname":"Bilibili",
    "gn:country_code":"TD",
    "gn:dem":403,
    "gn:feature_class":"P",
    "gn:feature_code":"PPL",
    "gn:name":"Bilibili",
    "gn:population":0,
    "gn:timezone":"Africa/Ndjamena",
    "iso:country":"TD",
    "wof:name":"Bilibili",
    "wof:placetype":"locality"
},
  "geometry": {"coordinates":[19.7214,10.2685],"type":"Point"}
}