{
  "type": "Feature",
  "properties": {
    "gn:admin1_code":"13.0",
    "gn:asciiname":"Bilibili",
    "gn:country_code":"TD",
    "gn:dem":403,
    "gn:feature_class":"P",
    "gn:feature_code":"PPL",
    "gn:name":"Bilibili",
    "gn:population":0,
    "gn:timezone":"Africa/Ndjamena",
    "iso:country":"TD",
    "name:ara_x_preferred":[
        "\u0628\u064a\u0644\u064a\u0628\u064a\u0644\u064a"
    ],
    "name:cdo_x_preferred":[
        "Bilibili"
    ],
    "name:deu_x_preferred":[
        "Bilibili"
    ],
    "name:epo_x_preferred":[
        "Bilibili"
    ],
    "name:fra_x_preferred":[
        "Bilibili"
    ],
    "name:ind_x_preferred":[
        "Bilibili"
    ],
    "name:jpn_x_preferred":[
        "Bilibili"
    ],
    "name:kor_x_preferred":[
        "\ube44\ub9ac\ube44\ub9ac"
    ],
    "name:nep_x_preferred":[
        "\u092c\u093f\u0932\u093f\u092c\u093f\u0932\u0940"
    ],
    "name:spa_x_preferred":[
        "Bilibili"
    ],
    "name:tur_x_preferred":[
        "Bilibili"
    ],
    "name:wuu_x_preferred":[
        "Bilibili"
    ],
    "name:zho_x_preferred":[
        "Bilibili"
    ],
    "wof:name":"Bilibili",
    "wof:placetype":"locality"
},
  "geometry": {"coordinates":[19.7214,10.2685],"type":"Point"}
}