{
  "type": "Feature",
  "properties": {
    "gn:admin1_code":"12.0",
    "gn:asciiname":"Asal",
    "gn:country_code":"TD",
    "gn:dem":490,
    "gn:feature_class":"P",
    "gn:feature_code":"PPL",
    "gn:name":"Asal",
    "gn:population":0,
    "gn:timezone":"Africa/Ndjamena",
    "iso:country":"TD",
    "name:fra_x_preferred":[
        "Asal"
    ],
    "wof:name":"Asal",
    "wof:placetype":"locality"
},
  "geometry": {"coordinates":[20.6754,13.20174],"type":"Point"}
}