{
  "type": "Feature",
  "properties": {
    "gn:admin1_code":"19.0",
    "gn:asciiname":"Koussaki",
    "gn:country_code":"TD",
    "gn:dem":373,
    "gn:feature_class":"P",
    "gn:feature_code":"PPL",
    "gn:name":"Koussaki",
    "gn:population":0,
    "gn:timezone":"Africa/Ndjamena",
    "iso:country":"TD",
    "wof:name":"Koussaki",
    "wof:placetype":"locality"
},
  "geometry": {"coordinates":[17.25313,9.29413],"type":"Point"}
}