{
  "type": "Feature",
  "properties": {
    "gn:admin1_code":"2.0",
    "gn:asciiname":"Djierna",
    "gn:country_code":"TD",
    "gn:dem":996,
    "gn:feature_class":"P",
    "gn:feature_code":"PPL",
    "gn:name":"Dji\u00e9rna",
    "gn:population":0,
    "gn:timezone":"Africa/Ndjamena",
    "iso:country":"TD",
    "wof:name":"Djierna",
    "wof:placetype":"locality"
},
  "geometry": {"coordinates":[22.25,14.63333],"type":"Point"}
}