{
  "type": "Feature",
  "properties": {
    "gn:admin1_code":"19.0",
    "gn:asciiname":"Birboti",
    "gn:country_code":"TD",
    "gn:dem":374,
    "gn:feature_class":"P",
    "gn:feature_code":"PPL",
    "gn:name":"Birboti",
    "gn:population":0,
    "gn:timezone":"Africa/Ndjamena",
    "iso:country":"TD",
    "wof:name":"Birboti",
    "wof:placetype":"locality"
},
  "geometry": {"coordinates":[17.10246,9.26922],"type":"Point"}
}