{
  "type": "Feature",
  "properties": {
    "gn:admin1_code":"19.0",
    "gn:asciiname":"Moussoro",
    "gn:country_code":"TD",
    "gn:dem":375,
    "gn:feature_class":"P",
    "gn:feature_code":"PPL",
    "gn:name":"Moussoro",
    "gn:population":0,
    "gn:timezone":"Africa/Ndjamena",
    "iso:country":"TD",
    "name:bul_x_preferred":[
        "\u041c\u0443\u0441\u043e\u0440\u043e"
    ],
    "name:ceb_x_preferred":[
        "Moussoro"
    ],
    "name:fra_x_preferred":[
        "Moussoro"
    ],
    "name:frr_x_preferred":[
        "Moussoro"
    ],
    "name:hrv_x_preferred":[
        "Moussoro"
    ],
    "name:ita_x_preferred":[
        "Moussoro"
    ],
    "name:kor_x_preferred":[
        "\ubb34\uc18c\ub85c"
    ],
    "name:lit_x_preferred":[
        "Musoras"
    ],
    "name:mrj_x_preferred":[
        "\u041c\u0443\u0441\u0441\u043e\u0440\u043e"
    ],
    "name:pol_x_preferred":[
        "Moussoro"
    ],
    "name:por_x_preferred":[
        "Moussoro"
    ],
    "name:ron_x_preferred":[
        "Moussoro"
    ],
    "name:rus_x_preferred":[
        "\u041c\u0443\u0441\u0441\u043e\u0440\u043e"
    ],
    "name:ukr_x_preferred":[
        "\u041c\u0443\u0441\u043e\u0440\u043e"
    ],
    "name:urd_x_preferred":[
        "\u0645\u0648\u0633\u0648\u0631\u0648"
    ],
    "name:zho_x_preferred":[
        "\u7a46\u7d22\u7f85"
    ],
    "wof:name":"Moussoro",
    "wof:placetype":"locality"
},
  "geometry": {"coordinates":[17.66056,8.6191],"type":"Point"}
}