{
  "type": "Feature",
  "properties": {
    "gn:admin1_code":"15.0",
    "gn:asciiname":"Maigana",
    "gn:country_code":"TD",
    "gn:dem":300,
    "gn:feature_class":"P",
    "gn:feature_code":"PPL",
    "gn:name":"Ma\u00efgana",
    "gn:population":0,
    "gn:timezone":"Africa/Ndjamena",
    "iso:country":"TD",
    "wof:name":"Maigana",
    "wof:placetype":"locality"
},
  "geometry": {"coordinates":[16.45502,12.18192],"type":"Point"}
}