{
  "type": "Feature",
  "properties": {
    "gn:admin1_code":"9.0",
    "gn:asciiname":"Babao",
    "gn:country_code":"TD",
    "gn:dem":506,
    "gn:feature_class":"P",
    "gn:feature_code":"PPL",
    "gn:name":"Babao",
    "gn:population":0,
    "gn:timezone":"Africa/Ndjamena",
    "iso:country":"TD",
    "name:deu_x_preferred":[
        "Babao"
    ],
    "wof:name":"Babao",
    "wof:placetype":"locality"
},
  "geometry": {"coordinates":[15.6562,7.8433],"type":"Point"}
}