{
  "type": "Feature",
  "properties": {
    "gn:admin1_code":"20.0",
    "gn:asciiname":"Dombao",
    "gn:country_code":"TD",
    "gn:dem":446,
    "gn:feature_class":"P",
    "gn:feature_code":"PPL",
    "gn:name":"Dombao",
    "gn:population":0,
    "gn:timezone":"Africa/Ndjamena",
    "iso:country":"TD",
    "name:und_x_variant":[
        "Dombao Manda",
        "Dombao"
    ],
    "wof:name":"Dombao",
    "wof:placetype":"locality"
},
  "geometry": {"coordinates":[15.23333,8.93333],"type":"Point"}
}