{
  "type": "Feature",
  "properties": {
    "gn:admin1_code":"1.0",
    "gn:asciiname":"Kornoe",
    "gn:country_code":"TD",
    "gn:dem":418,
    "gn:feature_class":"P",
    "gn:feature_code":"PPL",
    "gn:name":"Kornoe",
    "gn:population":0,
    "gn:timezone":"Africa/Ndjamena",
    "iso:country":"TD",
    "name:fra_x_preferred":[
        "Kornoe"
    ],
    "wof:name":"Kornoe",
    "wof:placetype":"locality"
},
  "geometry": {"coordinates":[20.05501,13.65148],"type":"Point"}
}