{
  "type": "Feature",
  "properties": {
    "gn:admin1_code":"12.0",
    "gn:asciiname":"Idjerleben",
    "gn:country_code":"TD",
    "gn:dem":652,
    "gn:feature_class":"P",
    "gn:feature_code":"PPL",
    "gn:name":"Idjerl\u00e9ben",
    "gn:population":0,
    "gn:timezone":"Africa/Ndjamena",
    "iso:country":"TD",
    "wof:name":"Idjerleben",
    "wof:placetype":"locality"
},
  "geometry": {"coordinates":[21.18231,13.42736],"type":"Point"}
}