{
  "type": "Feature",
  "properties": {
    "gn:admin1_code":"14.0",
    "gn:asciiname":"Guilam",
    "gn:country_code":"TD",
    "gn:dem":355,
    "gn:feature_class":"P",
    "gn:feature_code":"PPL",
    "gn:name":"Guilam",
    "gn:population":0,
    "gn:timezone":"Africa/Ndjamena",
    "iso:country":"TD",
    "wof:name":"Guilam",
    "wof:placetype":"locality"
},
  "geometry": {"coordinates":[16.44001,9.50268],"type":"Point"}
}