{
  "type": "Feature",
  "properties": {
    "gn:admin1_code":"25.0",
    "gn:asciiname":"Andoro",
    "gn:country_code":"TD",
    "gn:dem":503,
    "gn:feature_class":"P",
    "gn:feature_code":"PPL",
    "gn:name":"Andoro",
    "gn:population":0,
    "gn:timezone":"Africa/Ndjamena",
    "iso:country":"TD",
    "wof:name":"Andoro",
    "wof:placetype":"locality"
},
  "geometry": {"coordinates":[21.4512,11.9263],"type":"Point"}
}