{
  "type": "Feature",
  "properties": {
    "gn:admin1_code":"14.0",
    "gn:asciiname":"Tchaboudou",
    "gn:country_code":"TD",
    "gn:dem":358,
    "gn:feature_class":"P",
    "gn:feature_code":"PPL",
    "gn:name":"Tchaboudou",
    "gn:population":0,
    "gn:timezone":"Africa/Ndjamena",
    "iso:country":"TD",
    "wof:name":"Tchaboudou",
    "wof:placetype":"locality"
},
  "geometry": {"coordinates":[16.7198,9.3861],"type":"Point"}
}