{
  "type": "Feature",
  "properties": {
    "gn:admin1_code":"8.0",
    "gn:asciiname":"Kay Kiro",
    "gn:country_code":"TD",
    "gn:dem":417,
    "gn:feature_class":"P",
    "gn:feature_code":"PPL",
    "gn:name":"Kay Kiro",
    "gn:population":0,
    "gn:timezone":"Africa/Ndjamena",
    "iso:country":"TD",
    "wof:name":"Kay Kiro",
    "wof:placetype":"locality"
},
  "geometry": {"coordinates":[15.8692,8.9787],"type":"Point"}
}