{
  "type": "Feature",
  "properties": {
    "gn:admin1_code":"15.0",
    "gn:asciiname":"Bougal",
    "gn:country_code":"TD",
    "gn:dem":334,
    "gn:feature_class":"P",
    "gn:feature_code":"PPL",
    "gn:name":"Bougal",
    "gn:population":0,
    "gn:timezone":"Africa/Ndjamena",
    "iso:country":"TD",
    "wof:name":"Bougal",
    "wof:placetype":"locality"
},
  "geometry": {"coordinates":[15.92592,11.43734],"type":"Point"}
}