{
  "type": "Feature",
  "properties": {
    "gn:admin1_code":"18.0",
    "gn:asciiname":"Assouala",
    "gn:country_code":"TD",
    "gn:dem":293,
    "gn:feature_class":"P",
    "gn:feature_code":"PPL",
    "gn:name":"Assouala",
    "gn:population":0,
    "gn:timezone":"Africa/Ndjamena",
    "iso:country":"TD",
    "wof:name":"Assouala",
    "wof:placetype":"locality"
},
  "geometry": {"coordinates":[15.80978,12.4759],"type":"Point"}
}