{
  "type": "Feature",
  "properties": {
    "gn:admin1_code":"1.0",
    "gn:asciiname":"Koseat",
    "gn:country_code":"TD",
    "gn:dem":399,
    "gn:feature_class":"P",
    "gn:feature_code":"PPL",
    "gn:name":"Kos\u00e9at",
    "gn:population":0,
    "gn:timezone":"Africa/Ndjamena",
    "iso:country":"TD",
    "wof:name":"Koseat",
    "wof:placetype":"locality"
},
  "geometry": {"coordinates":[19.6675,12.9762],"type":"Point"}
}