{
  "type": "Feature",
  "properties": {
    "gn:admin1_code":"12.0",
    "gn:asciiname":"Langue",
    "gn:country_code":"TD",
    "gn:dem":668,
    "gn:feature_class":"P",
    "gn:feature_code":"PPL",
    "gn:name":"Langu\u00e9",
    "gn:population":0,
    "gn:timezone":"Africa/Ndjamena",
    "iso:country":"TD",
    "name:ceb_x_preferred":[
        "Langue"
    ],
    "name:fra_x_preferred":[
        "Langue"
    ],
    "name:ita_x_preferred":[
        "Langue"
    ],
    "name:nld_x_preferred":[
        "Langue"
    ],
    "name:por_x_preferred":[
        "Langue"
    ],
    "name:spa_x_preferred":[
        "Langue"
    ],
    "name:swe_x_preferred":[
        "Langue"
    ],
    "name:und_x_variant":[
        "Langu\u00e9",
        "Lang\u00e9"
    ],
    "name:urd_x_preferred":[
        "\u0644\u0627\u0646\u06af\u0648\u06cc"
    ],
    "wof:name":"Langue",
    "wof:placetype":"locality"
},
  "geometry": {"coordinates":[21.55925,13.41503],"type":"Point"}
}