{
  "type": "Feature",
  "properties": {
    "gn:admin1_code":"14.0",
    "gn:asciiname":"Enga",
    "gn:country_code":"TD",
    "gn:dem":363,
    "gn:feature_class":"P",
    "gn:feature_code":"PPL",
    "gn:name":"Enga",
    "gn:population":0,
    "gn:timezone":"Africa/Ndjamena",
    "iso:country":"TD",
    "name:ceb_x_preferred":[
        "Enga"
    ],
    "name:fin_x_preferred":[
        "Enga"
    ],
    "name:heb_x_preferred":[
        "\u05d0\u05e0\u05d2\u05d4"
    ],
    "name:hun_x_preferred":[
        "Enga"
    ],
    "name:swe_x_preferred":[
        "Enga"
    ],
    "name:und_x_variant":[
        "Inga"
    ],
    "wof:name":"Enga",
    "wof:placetype":"locality"
},
  "geometry": {"coordinates":[15.70879,9.42419],"type":"Point"}
}