{
  "type": "Feature",
  "properties": {
    "gn:admin1_code":"14.0",
    "gn:asciiname":"Enga",
    "gn:country_code":"TD",
    "gn:dem":363,
    "gn:feature_class":"P",
    "gn:feature_code":"PPL",
    "gn:name":"Enga",
    "gn:population":0,
    "gn:timezone":"Africa/Ndjamena",
    "iso:country":"TD",
    "name:und_x_variant":[
        "Inga",
        "Enga"
    ],
    "wof:name":"Enga",
    "wof:placetype":"locality"
},
  "geometry": {"coordinates":[15.70879,9.42419],"type":"Point"}
}