{
  "type": "Feature",
  "properties": {
    "gn:admin1_code":"12.0",
    "gn:asciiname":"Gendaker",
    "gn:country_code":"TD",
    "gn:dem":429,
    "gn:feature_class":"P",
    "gn:feature_code":"PPL",
    "gn:name":"Gendaker",
    "gn:population":0,
    "gn:timezone":"Africa/Ndjamena",
    "iso:country":"TD",
    "wof:name":"Gendaker",
    "wof:placetype":"locality"
},
  "geometry": {"coordinates":[20.37334,14.24662],"type":"Point"}
}