{
  "type": "Feature",
  "properties": {
    "gn:admin1_code":"12.0",
    "gn:asciiname":"Diour",
    "gn:country_code":"TD",
    "gn:dem":532,
    "gn:feature_class":"P",
    "gn:feature_code":"PPL",
    "gn:name":"Diour",
    "gn:population":0,
    "gn:timezone":"Africa/Ndjamena",
    "iso:country":"TD",
    "name:fra_x_preferred":[
        "Diour"
    ],
    "wof:name":"Diour",
    "wof:placetype":"locality"
},
  "geometry": {"coordinates":[20.80107000000001,13.56898],"type":"Point"}
}