{
  "type": "Feature",
  "properties": {
    "gn:admin1_code":"15.0",
    "gn:asciiname":"Mafaling",
    "gn:country_code":"TD",
    "gn:dem":335,
    "gn:feature_class":"P",
    "gn:feature_code":"PPL",
    "gn:name":"Mafaling",
    "gn:population":0,
    "gn:timezone":"Africa/Ndjamena",
    "iso:country":"TD",
    "name:und_x_variant":[
        "Maffaling",
        "Maffeling",
        "Maraling",
        "Mafaling"
    ],
    "wof:name":"Mafaling",
    "wof:placetype":"locality"
},
  "geometry": {"coordinates":[16.45709,10.55304],"type":"Point"}
}