{
  "type": "Feature",
  "properties": {
    "gn:admin1_code":"12.0",
    "gn:asciiname":"Mourdiguin",
    "gn:country_code":"TD",
    "gn:dem":497,
    "gn:feature_class":"P",
    "gn:feature_code":"PPL",
    "gn:name":"Mourdiguin",
    "gn:population":0,
    "gn:timezone":"Africa/Ndjamena",
    "iso:country":"TD",
    "name:fra_x_preferred":[
        "Mourdiguin"
    ],
    "name:und_x_variant":[
        "Mourdiguine",
        "Mourdigin"
    ],
    "wof:name":"Mourdiguin",
    "wof:placetype":"locality"
},
  "geometry": {"coordinates":[20.65513,13.23183],"type":"Point"}
}