{
  "type": "Feature",
  "properties": {
    "gn:admin1_code":"19.0",
    "gn:asciiname":"Boukenaoua I",
    "gn:country_code":"TD",
    "gn:dem":396,
    "gn:feature_class":"P",
    "gn:feature_code":"PPL",
    "gn:name":"Boukenaoua I",
    "gn:population":0,
    "gn:timezone":"Africa/Ndjamena",
    "iso:country":"TD",
    "wof:name":"Boukenaoua I",
    "wof:placetype":"locality"
},
  "geometry": {"coordinates":[17.80862,8.0663],"type":"Point"}
}