{
  "type": "Feature",
  "properties": {
    "gn:admin1_code":"19.0",
    "gn:asciiname":"Nara",
    "gn:country_code":"TD",
    "gn:dem":381,
    "gn:feature_class":"P",
    "gn:feature_code":"PPL",
    "gn:name":"Nara",
    "gn:population":0,
    "gn:timezone":"Africa/Ndjamena",
    "iso:country":"TD",
    "name:ast_x_preferred":[
        "Nara"
    ],
    "name:aze_x_preferred":[
        "Nara"
    ],
    "name:cat_x_preferred":[
        "Nara"
    ],
    "name:ceb_x_preferred":[
        "Nara"
    ],
    "name:deu_x_preferred":[
        "Nara"
    ],
    "name:epo_x_preferred":[
        "Nara"
    ],
    "name:fas_x_preferred":[
        "\u0646\u0627\u0631\u0627"
    ],
    "name:fin_x_preferred":[
        "Nara"
    ],
    "name:fra_x_preferred":[
        "Nara"
    ],
    "name:heb_x_preferred":[
        "\u05e0\u05d0\u05e8\u05d4"
    ],
    "name:hrv_x_preferred":[
        "Nara"
    ],
    "name:hun_x_preferred":[
        "Nara"
    ],
    "name:ind_x_preferred":[
        "Nara"
    ],
    "name:ita_x_preferred":[
        "Nara"
    ],
    "name:jpn_x_preferred":[
        "\u5948\u826f"
    ],
    "name:kor_x_preferred":[
        "\ub098\ub77c"
    ],
    "name:lit_x_preferred":[
        "Nara"
    ],
    "name:nah_x_preferred":[
        "Nara"
    ],
    "name:nld_x_preferred":[
        "Nara"
    ],
    "name:nor_x_preferred":[
        "Nara"
    ],
    "name:pnb_x_preferred":[
        "\u0646\u0627\u0631\u0627"
    ],
    "name:pol_x_preferred":[
        "Nara"
    ],
    "name:por_x_preferred":[
        "Nara"
    ],
    "name:ron_x_preferred":[
        "Nara"
    ],
    "name:slk_x_preferred":[
        "Nara"
    ],
    "name:slv_x_preferred":[
        "Nara"
    ],
    "name:spa_x_preferred":[
        "Nara"
    ],
    "name:srp_x_preferred":[
        "Nara"
    ],
    "name:swa_x_preferred":[
        "Nara"
    ],
    "name:swe_x_preferred":[
        "Nara"
    ],
    "name:tgl_x_preferred":[
        "Nara"
    ],
    "name:tha_x_preferred":[
        "\u0e19\u0e30\u0e23\u0e30"
    ],
    "name:tur_x_preferred":[
        "Nara"
    ],
    "wof:name":"Nara",
    "wof:placetype":"locality"
},
  "geometry": {"coordinates":[17.2981,8.811],"type":"Point"}
}