{
  "type": "Feature",
  "properties": {
    "gn:admin1_code":"9.0",
    "gn:asciiname":"Kaouey",
    "gn:country_code":"TD",
    "gn:dem":449,
    "gn:feature_class":"P",
    "gn:feature_code":"PPL",
    "gn:name":"Kaouey",
    "gn:population":0,
    "gn:timezone":"Africa/Ndjamena",
    "iso:country":"TD",
    "wof:name":"Kaouey",
    "wof:placetype":"locality"
},
  "geometry": {"coordinates":[16.30467,8.24658],"type":"Point"}
}