{
  "type": "Feature",
  "properties": {
    "gn:admin1_code":"18.0",
    "gn:asciiname":"Am Basatna",
    "gn:country_code":"TD",
    "gn:dem":300,
    "gn:feature_class":"P",
    "gn:feature_code":"PPL",
    "gn:name":"Am Basatna",
    "gn:population":0,
    "gn:timezone":"Africa/Ndjamena",
    "iso:country":"TD",
    "wof:name":"Am Basatna",
    "wof:placetype":"locality"
},
  "geometry": {"coordinates":[16.51289,12.40833],"type":"Point"}
}