{
  "type": "Feature",
  "properties": {
    "gn:admin1_code":"1.0",
    "gn:asciiname":"Bororik",
    "gn:country_code":"TD",
    "gn:dem":429,
    "gn:feature_class":"P",
    "gn:feature_code":"PPL",
    "gn:name":"Bororik",
    "gn:population":0,
    "gn:timezone":"Africa/Ndjamena",
    "iso:country":"TD",
    "name:und_x_variant":[
        "Bororit",
        "Bororik"
    ],
    "wof:name":"Bororik",
    "wof:placetype":"locality"
},
  "geometry": {"coordinates":[20.1773,13.45116],"type":"Point"}
}