{
  "type": "Feature",
  "properties": {
    "gn:admin1_code":"19.0",
    "gn:asciiname":"Bebo Pen",
    "gn:country_code":"TD",
    "gn:dem":395,
    "gn:feature_class":"P",
    "gn:feature_code":"PPL",
    "gn:name":"Bebo Pen",
    "gn:population":0,
    "gn:timezone":"Africa/Ndjamena",
    "iso:country":"TD",
    "wof:name":"Bebo Pen",
    "wof:placetype":"locality"
},
  "geometry": {"coordinates":[17.2494,8.3753],"type":"Point"}
}