{
  "type": "Feature",
  "properties": {
    "gn:admin1_code":"19.0",
    "gn:asciiname":"Maikoutou",
    "gn:country_code":"TD",
    "gn:dem":394,
    "gn:feature_class":"P",
    "gn:feature_code":"PPL",
    "gn:name":"Ma\u00efkoutou",
    "gn:population":0,
    "gn:timezone":"Africa/Ndjamena",
    "iso:country":"TD",
    "name:und_x_variant":[
        "Ma\u00efkotou",
        "Ma\u00efkoutou"
    ],
    "wof:name":"Maikoutou",
    "wof:placetype":"locality"
},
  "geometry": {"coordinates":[17.89629,7.97945],"type":"Point"}
}