{
  "type": "Feature",
  "properties": {
    "gn:admin1_code":"9.0",
    "gn:asciiname":"Bedjamnia",
    "gn:country_code":"TD",
    "gn:dem":460,
    "gn:feature_class":"P",
    "gn:feature_code":"PPL",
    "gn:name":"Bedjamnia",
    "gn:population":0,
    "gn:timezone":"Africa/Ndjamena",
    "iso:country":"TD",
    "wof:name":"Bedjamnia",
    "wof:placetype":"locality"
},
  "geometry": {"coordinates":[15.76667,8.06667],"type":"Point"}
}