{
  "type": "Feature",
  "properties": {
    "gn:admin1_code":"15.0",
    "gn:asciiname":"Gangi",
    "gn:country_code":"TD",
    "gn:dem":296,
    "gn:feature_class":"P",
    "gn:feature_code":"PPL",
    "gn:name":"Gangi",
    "gn:population":0,
    "gn:timezone":"Africa/Ndjamena",
    "iso:country":"TD",
    "name:ceb_x_preferred":[
        "Gangi"
    ],
    "name:ita_x_preferred":[
        "Gangi"
    ],
    "name:scn_x_preferred":[
        "Gangi"
    ],
    "name:sco_x_preferred":[
        "Gangi"
    ],
    "name:swe_x_preferred":[
        "Gangi"
    ],
    "wof:name":"Gangi",
    "wof:placetype":"locality"
},
  "geometry": {"coordinates":[15.20873,11.86106],"type":"Point"}
}