{
  "type": "Feature",
  "properties": {
    "gn:admin1_code":"13.0",
    "gn:asciiname":"Samata II",
    "gn:country_code":"TD",
    "gn:dem":410,
    "gn:feature_class":"P",
    "gn:feature_code":"PPL",
    "gn:name":"Samata II",
    "gn:population":0,
    "gn:timezone":"Africa/Ndjamena",
    "iso:country":"TD",
    "name:fra_x_preferred":[
        "Samata II"
    ],
    "wof:name":"Samata II",
    "wof:placetype":"locality"
},
  "geometry": {"coordinates":[20.7865,9.79878],"type":"Point"}
}