{
  "type": "Feature",
  "properties": {
    "gn:admin1_code":"15.0",
    "gn:asciiname":"Goguena",
    "gn:country_code":"TD",
    "gn:dem":327,
    "gn:feature_class":"P",
    "gn:feature_code":"PPL",
    "gn:name":"Gogu\u00e9na",
    "gn:population":0,
    "gn:timezone":"Africa/Ndjamena",
    "iso:country":"TD",
    "name:und_x_variant":[
        "Gog\u00e9na",
        "Gogu\u00e9na"
    ],
    "wof:name":"Goguena",
    "wof:placetype":"locality"
},
  "geometry": {"coordinates":[17.11466,11.5491],"type":"Point"}
}