{
  "type": "Feature",
  "properties": {
    "gn:admin1_code":"18.0",
    "gn:asciiname":"Abou Choukouri",
    "gn:country_code":"TD",
    "gn:dem":289,
    "gn:feature_class":"P",
    "gn:feature_code":"PPL",
    "gn:name":"Abou Choukouri",
    "gn:population":0,
    "gn:timezone":"Africa/Ndjamena",
    "iso:country":"TD",
    "wof:name":"Abou Choukouri",
    "wof:placetype":"locality"
},
  "geometry": {"coordinates":[15.62829,13.00081],"type":"Point"}
}