{
  "type": "Feature",
  "properties": {
    "gn:admin1_code":"7.0",
    "gn:asciiname":"Bouloul",
    "gn:country_code":"TD",
    "gn:dem":291,
    "gn:feature_class":"P",
    "gn:feature_code":"PPL",
    "gn:name":"Bouloul",
    "gn:population":0,
    "gn:timezone":"Africa/Ndjamena",
    "iso:country":"TD",
    "wof:name":"Bouloul",
    "wof:placetype":"locality"
},
  "geometry": {"coordinates":[15.69221,13.26453],"type":"Point"}
}