{
  "type": "Feature",
  "properties": {
    "gn:admin1_code":"13.0",
    "gn:asciiname":"Outchero",
    "gn:country_code":"TD",
    "gn:dem":474,
    "gn:feature_class":"P",
    "gn:feature_code":"PPL",
    "gn:name":"Outch\u00e9ro",
    "gn:population":0,
    "gn:timezone":"Africa/Ndjamena",
    "iso:country":"TD",
    "wof:name":"Outchero",
    "wof:placetype":"locality"
},
  "geometry": {"coordinates":[19.525,11.9632],"type":"Point"}
}