{
  "type": "Feature",
  "properties": {
    "gn:admin1_code":"12.0",
    "gn:asciiname":"Kororok",
    "gn:country_code":"TD",
    "gn:dem":754,
    "gn:feature_class":"P",
    "gn:feature_code":"PPL",
    "gn:name":"Kororok",
    "gn:population":0,
    "gn:timezone":"Africa/Ndjamena",
    "iso:country":"TD",
    "name:fra_x_preferred":[
        "Kororok"
    ],
    "wof:name":"Kororok",
    "wof:placetype":"locality"
},
  "geometry": {"coordinates":[21.21755,14.03633],"type":"Point"}
}