{
  "type": "Feature",
  "properties": {
    "gn:admin1_code":"9.0",
    "gn:asciiname":"Bemia",
    "gn:country_code":"TD",
    "gn:dem":400,
    "gn:feature_class":"P",
    "gn:feature_code":"PPL",
    "gn:name":"B\u00e9mia",
    "gn:population":0,
    "gn:timezone":"Africa/Ndjamena",
    "iso:country":"TD",
    "name:fra_x_preferred":[
        "B\u00e9mia"
    ],
    "wof:name":"Bemia",
    "wof:placetype":"locality"
},
  "geometry": {"coordinates":[16.87793,8.96722],"type":"Point"}
}