{
  "type": "Feature",
  "properties": {
    "gn:admin1_code":"7.0",
    "gn:asciiname":"Melierom",
    "gn:country_code":"TD",
    "gn:dem":287,
    "gn:feature_class":"P",
    "gn:feature_code":"PPL",
    "gn:name":"M\u00e9li\u00e9rom",
    "gn:population":0,
    "gn:timezone":"Africa/Ndjamena",
    "iso:country":"TD",
    "wof:name":"Melierom",
    "wof:placetype":"locality"
},
  "geometry": {"coordinates":[14.93859,13.27703],"type":"Point"}
}