{
  "type": "Feature",
  "properties": {
    "gn:admin1_code":"19.0",
    "gn:asciiname":"Kaguibe",
    "gn:country_code":"TD",
    "gn:dem":379,
    "gn:feature_class":"P",
    "gn:feature_code":"PPL",
    "gn:name":"Kaguib\u00e9",
    "gn:population":0,
    "gn:timezone":"Africa/Ndjamena",
    "iso:country":"TD",
    "name:und_x_variant":[
        "Kaguid\u00e9",
        "Kaguib\u00e9"
    ],
    "wof:name":"Kaguibe",
    "wof:placetype":"locality"
},
  "geometry": {"coordinates":[17.7517,8.6103],"type":"Point"}
}