{
  "type": "Feature",
  "properties": {
    "gn:admin1_code":"2.0",
    "gn:asciiname":"Kirzim",
    "gn:country_code":"TD",
    "gn:dem":491,
    "gn:feature_class":"P",
    "gn:feature_code":"PPL",
    "gn:name":"Kirzim",
    "gn:population":0,
    "gn:timezone":"Africa/Ndjamena",
    "iso:country":"TD",
    "wof:name":"Kirzim",
    "wof:placetype":"locality"
},
  "geometry": {"coordinates":[20.87671,14.81565],"type":"Point"}
}