{
  "type": "Feature",
  "properties": {
    "gn:admin1_code":"5.0",
    "gn:asciiname":"Fil",
    "gn:country_code":"TD",
    "gn:dem":450,
    "gn:feature_class":"P",
    "gn:feature_code":"PPL",
    "gn:name":"Fil",
    "gn:population":0,
    "gn:timezone":"Africa/Ndjamena",
    "iso:country":"TD",
    "name:cat_x_preferred":[
        "Fil"
    ],
    "name:ceb_x_preferred":[
        "Fil"
    ],
    "name:dan_x_preferred":[
        "Fil"
    ],
    "name:fra_x_preferred":[
        "Fil"
    ],
    "name:nno_x_preferred":[
        "Fil"
    ],
    "name:oci_x_preferred":[
        "Fil"
    ],
    "name:swe_x_preferred":[
        "Fil"
    ],
    "name:tur_x_preferred":[
        "Fil"
    ],
    "name:uzb_x_preferred":[
        "Fil"
    ],
    "wof:name":"Fil",
    "wof:placetype":"locality"
},
  "geometry": {"coordinates":[19.0423,11.2195],"type":"Point"}
}