{
  "type": "Feature",
  "properties": {
    "gn:admin1_code":"1.0",
    "gn:asciiname":"Hidjelidj",
    "gn:country_code":"TD",
    "gn:dem":334,
    "gn:feature_class":"P",
    "gn:feature_code":"PPL",
    "gn:name":"Hidj\u00e9lidj",
    "gn:population":0,
    "gn:timezone":"Africa/Ndjamena",
    "iso:country":"TD",
    "name:und_x_variant":[
        "Idjelidj",
        "Hidj\u00e9lidj"
    ],
    "wof:name":"Hidjelidj",
    "wof:placetype":"locality"
},
  "geometry": {"coordinates":[18.2415,13.1276],"type":"Point"}
}