{
  "type": "Feature",
  "properties": {
    "gn:admin1_code":"2.0",
    "gn:asciiname":"Kondobor",
    "gn:country_code":"TD",
    "gn:dem":480,
    "gn:feature_class":"P",
    "gn:feature_code":"PPL",
    "gn:name":"Kondobor",
    "gn:population":0,
    "gn:timezone":"Africa/Ndjamena",
    "iso:country":"TD",
    "wof:name":"Kondobor",
    "wof:placetype":"locality"
},
  "geometry": {"coordinates":[20.74628,14.47404],"type":"Point"}
}