{
  "type": "Feature",
  "properties": {
    "gn:admin1_code":"8.0",
    "gn:asciiname":"Bidamay",
    "gn:country_code":"TD",
    "gn:dem":449,
    "gn:feature_class":"P",
    "gn:feature_code":"PPL",
    "gn:name":"Bidamay",
    "gn:population":0,
    "gn:timezone":"Africa/Ndjamena",
    "iso:country":"TD",
    "wof:name":"Bidamay",
    "wof:placetype":"locality"
},
  "geometry": {"coordinates":[15.6677,8.5083],"type":"Point"}
}