{
  "type": "Feature",
  "properties": {
    "gn:admin1_code":"20.0",
    "gn:asciiname":"Toufoultrene",
    "gn:country_code":"TD",
    "gn:dem":246,
    "gn:feature_class":"P",
    "gn:feature_code":"PPL",
    "gn:name":"Toufoultr\u00e9n\u00e9",
    "gn:population":0,
    "gn:timezone":"Africa/Ndjamena",
    "iso:country":"TD",
    "wof:name":"Toufoultrene",
    "wof:placetype":"locality"
},
  "geometry": {"coordinates":[14.2638,9.6382],"type":"Point"}
}