{
  "type": "Feature",
  "properties": {
    "gn:admin1_code":"12.0",
    "gn:asciiname":"Andadja Djebel",
    "gn:country_code":"TD",
    "gn:dem":712,
    "gn:feature_class":"P",
    "gn:feature_code":"PPL",
    "gn:name":"Andadja Djebel",
    "gn:population":0,
    "gn:timezone":"Africa/Ndjamena",
    "iso:country":"TD",
    "wof:name":"Andadja Djebel",
    "wof:placetype":"locality"
},
  "geometry": {"coordinates":[22.02891,13.14344],"type":"Point"}
}