{
  "type": "Feature",
  "properties": {
    "gn:admin1_code":"19.0",
    "gn:asciiname":"Nganguiele",
    "gn:country_code":"TD",
    "gn:dem":389,
    "gn:feature_class":"P",
    "gn:feature_code":"PPL",
    "gn:name":"Ngangui\u00e9l\u00e9",
    "gn:population":0,
    "gn:timezone":"Africa/Ndjamena",
    "iso:country":"TD",
    "wof:name":"Nganguiele",
    "wof:placetype":"locality"
},
  "geometry": {"coordinates":[17.34745,8.64133],"type":"Point"}
}