{
  "type": "Feature",
  "properties": {
    "gn:admin1_code":"9.0",
    "gn:asciiname":"Betolo",
    "gn:country_code":"TD",
    "gn:dem":454,
    "gn:feature_class":"P",
    "gn:feature_code":"PPL",
    "gn:name":"B\u00e9tolo",
    "gn:population":0,
    "gn:timezone":"Africa/Ndjamena",
    "iso:country":"TD",
    "wof:name":"Betolo",
    "wof:placetype":"locality"
},
  "geometry": {"coordinates":[16.51221,7.97345],"type":"Point"}
}