{
  "type": "Feature",
  "properties": {
    "gn:admin1_code":"9.0",
    "gn:asciiname":"Sara Kay",
    "gn:country_code":"TD",
    "gn:dem":451,
    "gn:feature_class":"P",
    "gn:feature_code":"PPL",
    "gn:name":"Sara Kay",
    "gn:population":0,
    "gn:timezone":"Africa/Ndjamena",
    "iso:country":"TD",
    "wof:name":"Sara Kay",
    "wof:placetype":"locality"
},
  "geometry": {"coordinates":[15.5599,8.1706],"type":"Point"}
}