{
  "type": "Feature",
  "properties": {
    "gn:admin1_code":"7.0",
    "gn:asciiname":"Yeri",
    "gn:country_code":"TD",
    "gn:dem":305,
    "gn:feature_class":"P",
    "gn:feature_code":"PPL",
    "gn:name":"Yeri",
    "gn:population":0,
    "gn:timezone":"Africa/Ndjamena",
    "iso:country":"TD",
    "name:ceb_x_preferred":[
        "Yeri"
    ],
    "name:swe_x_preferred":[
        "Yeri"
    ],
    "wof:name":"Yeri",
    "wof:placetype":"locality"
},
  "geometry": {"coordinates":[15.27979,13.65969],"type":"Point"}
}