{
  "type": "Feature",
  "properties": {
    "gn:admin1_code":"5.0",
    "gn:asciiname":"Saraf",
    "gn:country_code":"TD",
    "gn:dem":455,
    "gn:feature_class":"P",
    "gn:feature_code":"PPL",
    "gn:name":"Saraf",
    "gn:population":0,
    "gn:timezone":"Africa/Ndjamena",
    "iso:country":"TD",
    "name:und_x_variant":[
        "Sarouf",
        "Saraf"
    ],
    "wof:name":"Saraf",
    "wof:placetype":"locality"
},
  "geometry": {"coordinates":[19.6944,12.5449],"type":"Point"}
}