{
  "type": "Feature",
  "properties": {
    "gn:admin1_code":"12.0",
    "gn:asciiname":"Niame",
    "gn:country_code":"TD",
    "gn:dem":496,
    "gn:feature_class":"P",
    "gn:feature_code":"PPL",
    "gn:name":"Niam\u00e9",
    "gn:population":0,
    "gn:timezone":"Africa/Ndjamena",
    "iso:country":"TD",
    "name:fra_x_preferred":[
        "Niam\u00e9"
    ],
    "wof:name":"Niame",
    "wof:placetype":"locality"
},
  "geometry": {"coordinates":[20.72853,13.63141],"type":"Point"}
}