{
  "type": "Feature",
  "properties": {
    "gn:admin1_code":"1.0",
    "gn:asciiname":"Kokandi",
    "gn:country_code":"TD",
    "gn:dem":405,
    "gn:feature_class":"P",
    "gn:feature_code":"PPL",
    "gn:name":"Kokandi",
    "gn:population":0,
    "gn:timezone":"Africa/Ndjamena",
    "iso:country":"TD",
    "wof:name":"Kokandi",
    "wof:placetype":"locality"
},
  "geometry": {"coordinates":[19.9782,13.305],"type":"Point"}
}