{
  "type": "Feature",
  "properties": {
    "gn:admin1_code":"17.0",
    "gn:asciiname":"Bogdjo",
    "gn:country_code":"TD",
    "gn:dem":369,
    "gn:feature_class":"P",
    "gn:feature_code":"PPL",
    "gn:name":"Bogdjo",
    "gn:population":0,
    "gn:timezone":"Africa/Ndjamena",
    "iso:country":"TD",
    "wof:name":"Bogdjo",
    "wof:placetype":"locality"
},
  "geometry": {"coordinates":[18.2837,9.0238],"type":"Point"}
}