{
  "type": "Feature",
  "properties": {
    "gn:admin1_code":"1.0",
    "gn:asciiname":"Lemka Naasan",
    "gn:country_code":"TD",
    "gn:dem":332,
    "gn:feature_class":"P",
    "gn:feature_code":"PPL",
    "gn:name":"Lemka Naasan",
    "gn:population":0,
    "gn:timezone":"Africa/Ndjamena",
    "iso:country":"TD",
    "wof:name":"Lemka Naasan",
    "wof:placetype":"locality"
},
  "geometry": {"coordinates":[18.064,13.2306],"type":"Point"}
}