{
  "type": "Feature",
  "properties": {
    "gn:admin1_code":"20.0",
    "gn:asciiname":"Lao Nangara",
    "gn:country_code":"TD",
    "gn:dem":388,
    "gn:feature_class":"P",
    "gn:feature_code":"PPL",
    "gn:name":"Lao Nangara",
    "gn:population":0,
    "gn:timezone":"Africa/Ndjamena",
    "iso:country":"TD",
    "name:und_x_variant":[
        "Lao Nongara",
        "Lao Nangara"
    ],
    "wof:name":"Lao Nangara",
    "wof:placetype":"locality"
},
  "geometry": {"coordinates":[15.25741,9.16396],"type":"Point"}
}