{
  "type": "Feature",
  "properties": {
    "gn:admin1_code":"8.0",
    "gn:asciiname":"Doholo",
    "gn:country_code":"TD",
    "gn:dem":392,
    "gn:feature_class":"P",
    "gn:feature_code":"PPL",
    "gn:name":"Doholo",
    "gn:population":0,
    "gn:timezone":"Africa/Ndjamena",
    "iso:country":"TD",
    "wof:name":"Doholo",
    "wof:placetype":"locality"
},
  "geometry": {"coordinates":[16.24642,9.12337],"type":"Point"}
}