{
  "type": "Feature",
  "properties": {
    "gn:admin1_code":"9.0",
    "gn:asciiname":"Sao",
    "gn:country_code":"TD",
    "gn:dem":499,
    "gn:feature_class":"P",
    "gn:feature_code":"PPL",
    "gn:name":"Sao",
    "gn:population":0,
    "gn:timezone":"Africa/Ndjamena",
    "iso:country":"TD",
    "wof:name":"Sao",
    "wof:placetype":"locality"
},
  "geometry": {"coordinates":[16.0192,7.8996],"type":"Point"}
}