{
  "type": "Feature",
  "properties": {
    "gn:admin1_code":"25.0",
    "gn:asciiname":"Tafe",
    "gn:country_code":"TD",
    "gn:dem":543,
    "gn:feature_class":"P",
    "gn:feature_code":"PPL",
    "gn:name":"Taf\u00e9",
    "gn:population":0,
    "gn:timezone":"Africa/Ndjamena",
    "iso:country":"TD",
    "wof:name":"Tafe",
    "wof:placetype":"locality"
},
  "geometry": {"coordinates":[20.9802,11.9046],"type":"Point"}
}