{
  "type": "Feature",
  "properties": {
    "gn:admin1_code":"9.0",
    "gn:asciiname":"Kadounga",
    "gn:country_code":"TD",
    "gn:dem":454,
    "gn:feature_class":"P",
    "gn:feature_code":"PPL",
    "gn:name":"Kadounga",
    "gn:population":0,
    "gn:timezone":"Africa/Ndjamena",
    "iso:country":"TD",
    "wof:name":"Kadounga",
    "wof:placetype":"locality"
},
  "geometry": {"coordinates":[15.8401,7.9649],"type":"Point"}
}