{
  "type": "Feature",
  "properties": {
    "gn:admin1_code":"1.0",
    "gn:asciiname":"Zoumbat",
    "gn:country_code":"TD",
    "gn:dem":410,
    "gn:feature_class":"P",
    "gn:feature_code":"PPL",
    "gn:name":"Zoumbat",
    "gn:population":0,
    "gn:timezone":"Africa/Ndjamena",
    "iso:country":"TD",
    "name:fra_x_preferred":[
        "Zoumbat"
    ],
    "wof:name":"Zoumbat",
    "wof:placetype":"locality"
},
  "geometry": {"coordinates":[20.00648,13.59494],"type":"Point"}
}