{
  "type": "Feature",
  "properties": {
    "gn:admin1_code":"19.0",
    "gn:asciiname":"Gaboulo",
    "gn:country_code":"TD",
    "gn:dem":416,
    "gn:feature_class":"P",
    "gn:feature_code":"PPL",
    "gn:name":"Gaboulo",
    "gn:population":0,
    "gn:timezone":"Africa/Ndjamena",
    "iso:country":"TD",
    "name:und_x_variant":[
        "Gabou",
        "Gaboulo"
    ],
    "wof:name":"Gaboulo",
    "wof:placetype":"locality"
},
  "geometry": {"coordinates":[17.45547,8.98993],"type":"Point"}
}