{
  "type": "Feature",
  "properties": {
    "gn:admin1_code":"5.0",
    "gn:asciiname":"Korbo",
    "gn:country_code":"TD",
    "gn:dem":524,
    "gn:feature_class":"P",
    "gn:feature_code":"PPL",
    "gn:name":"Korbo",
    "gn:population":0,
    "gn:timezone":"Africa/Ndjamena",
    "iso:country":"TD",
    "wof:name":"Korbo",
    "wof:placetype":"locality"
},
  "geometry": {"coordinates":[18.24843,12.08121],"type":"Point"}
}