{
  "type": "Feature",
  "properties": {
    "gn:admin1_code":"15.0",
    "gn:asciiname":"Griouali",
    "gn:cc2":"TD",
    "gn:country_code":"TD",
    "gn:dem":333,
    "gn:feature_class":"P",
    "gn:feature_code":"PPL",
    "gn:name":"Griouali",
    "gn:population":0,
    "gn:timezone":"Africa/Ndjamena",
    "iso:country":"TD",
    "name:und_x_variant":[
        "Grou\u00e9li",
        "Griou\u00e9li",
        "Griouali"
    ],
    "wof:name":"Griouali",
    "wof:placetype":"locality"
},
  "geometry": {"coordinates":[16.15,11.26667],"type":"Point"}
}