{
  "type": "Feature",
  "properties": {
    "gn:admin1_code":"1.0",
    "gn:asciiname":"Ab Mahamat Sawa",
    "gn:country_code":"TD",
    "gn:dem":298,
    "gn:feature_class":"P",
    "gn:feature_code":"PPL",
    "gn:name":"Ab Mahamat Sawa",
    "gn:population":0,
    "gn:timezone":"Africa/Ndjamena",
    "iso:country":"TD",
    "wof:name":"Ab Mahamat Sawa",
    "wof:placetype":"locality"
},
  "geometry": {"coordinates":[17.7246,13.1001],"type":"Point"}
}