{
  "type": "Feature",
  "properties": {
    "gn:admin1_code":"8.0",
    "gn:asciiname":"Konkoundja",
    "gn:country_code":"TD",
    "gn:dem":527,
    "gn:feature_class":"P",
    "gn:feature_code":"PPL",
    "gn:name":"Konkoundja",
    "gn:population":0,
    "gn:timezone":"Africa/Ndjamena",
    "iso:country":"TD",
    "name:und_x_variant":[
        "Konkoudja",
        "Konkoundja"
    ],
    "wof:name":"Konkoundja",
    "wof:placetype":"locality"
},
  "geometry": {"coordinates":[15.35821,8.46132],"type":"Point"}
}