{
  "type": "Feature",
  "properties": {
    "gn:admin1_code":"16.0",
    "gn:asciiname":"Ayedena",
    "gn:country_code":"TD",
    "gn:dem":319,
    "gn:feature_class":"P",
    "gn:feature_code":"PPL",
    "gn:name":"Ay\u00e9d\u00e9na",
    "gn:population":0,
    "gn:timezone":"Africa/Ndjamena",
    "iso:country":"TD",
    "wof:name":"Ayedena",
    "wof:placetype":"locality"
},
  "geometry": {"coordinates":[15.33471,10.5698],"type":"Point"}
}