{
  "type": "Feature",
  "properties": {
    "gn:admin1_code":"7.0",
    "gn:asciiname":"Kafia",
    "gn:country_code":"TD",
    "gn:dem":284,
    "gn:feature_class":"P",
    "gn:feature_code":"PPL",
    "gn:name":"Kafia",
    "gn:population":0,
    "gn:timezone":"Africa/Ndjamena",
    "iso:country":"TD",
    "wof:name":"Kafia",
    "wof:placetype":"locality"
},
  "geometry": {"coordinates":[14.35,13.53333],"type":"Point"}
}