{
  "type": "Feature",
  "properties": {
    "gn:admin1_code":"17.0",
    "gn:asciiname":"Kouaba",
    "gn:country_code":"TD",
    "gn:dem":372,
    "gn:feature_class":"P",
    "gn:feature_code":"PPL",
    "gn:name":"Kouaba",
    "gn:population":0,
    "gn:timezone":"Africa/Ndjamena",
    "iso:country":"TD",
    "wof:name":"Kouaba",
    "wof:placetype":"locality"
},
  "geometry": {"coordinates":[18.56669,9.92617],"type":"Point"}
}