{
  "type": "Feature",
  "properties": {
    "gn:admin1_code":"8.0",
    "gn:asciiname":"Dodjigui",
    "gn:country_code":"TD",
    "gn:dem":460,
    "gn:feature_class":"P",
    "gn:feature_code":"PPL",
    "gn:name":"Dodjigui",
    "gn:population":0,
    "gn:timezone":"Africa/Ndjamena",
    "iso:country":"TD",
    "wof:name":"Dodjigui",
    "wof:placetype":"locality"
},
  "geometry": {"coordinates":[15.74323,8.58849],"type":"Point"}
}