{
  "type": "Feature",
  "properties": {
    "gn:admin1_code":"12.0",
    "gn:asciiname":"Mourdaba",
    "gn:country_code":"TD",
    "gn:dem":473,
    "gn:feature_class":"P",
    "gn:feature_code":"PPL",
    "gn:name":"Mourdaba",
    "gn:population":0,
    "gn:timezone":"Africa/Ndjamena",
    "iso:country":"TD",
    "wof:name":"Mourdaba",
    "wof:placetype":"locality"
},
  "geometry": {"coordinates":[20.59697,14.12988],"type":"Point"}
}