{
  "type": "Feature",
  "properties": {
    "gn:admin1_code":"18.0",
    "gn:asciiname":"Bendioui",
    "gn:country_code":"TD",
    "gn:dem":291,
    "gn:feature_class":"P",
    "gn:feature_code":"PPL",
    "gn:name":"Bendioui",
    "gn:population":0,
    "gn:timezone":"Africa/Ndjamena",
    "iso:country":"TD",
    "name:und_x_variant":[
        "Bendiwi",
        "Bendioui"
    ],
    "wof:name":"Bendioui",
    "wof:placetype":"locality"
},
  "geometry": {"coordinates":[15.25463,12.4648],"type":"Point"}
}