{
  "type": "Feature",
  "properties": {
    "gn:admin1_code":"14.0",
    "gn:asciiname":"Mbaiwel",
    "gn:country_code":"TD",
    "gn:dem":399,
    "gn:feature_class":"P",
    "gn:feature_code":"PPL",
    "gn:name":"Mba\u00efwel",
    "gn:population":0,
    "gn:timezone":"Africa/Ndjamena",
    "iso:country":"TD",
    "wof:name":"Mbaiwel",
    "wof:placetype":"locality"
},
  "geometry": {"coordinates":[16.176,9.0957],"type":"Point"}
}