{
  "type": "Feature",
  "properties": {
    "gn:admin1_code":"9.0",
    "gn:asciiname":"Nassian",
    "gn:country_code":"TD",
    "gn:dem":384,
    "gn:feature_class":"P",
    "gn:feature_code":"PPL",
    "gn:name":"Nassian",
    "gn:population":0,
    "gn:timezone":"Africa/Ndjamena",
    "iso:country":"TD",
    "name:fra_x_preferred":[
        "Nassian"
    ],
    "name:fra_x_variant":[
        "Niassa",
        "Nazia",
        "Nasian",
        "Nasia"
    ],
    "name:ita_x_preferred":[
        "Nassian"
    ],
    "name:msa_x_preferred":[
        "Nassian"
    ],
    "name:spa_x_preferred":[
        "Nassian"
    ],
    "name:und_x_variant":[
        "Nazia",
        "Nasia",
        "Nasian",
        "Niassa"
    ],
    "wof:name":"Nassian",
    "wof:placetype":"locality"
},
  "geometry": {"coordinates":[16.77582,8.83842],"type":"Point"}
}