{
  "type": "Feature",
  "properties": {
    "gn:admin1_code":"7.0",
    "gn:asciiname":"Ouadifil",
    "gn:country_code":"TD",
    "gn:dem":302,
    "gn:feature_class":"P",
    "gn:feature_code":"PPL",
    "gn:name":"Ouadifil",
    "gn:population":0,
    "gn:timezone":"Africa/Ndjamena",
    "iso:country":"TD",
    "wof:name":"Ouadifil",
    "wof:placetype":"locality"
},
  "geometry": {"coordinates":[15.48221,13.73696],"type":"Point"}
}