{
  "type": "Feature",
  "properties": {
    "gn:admin1_code":"20.0",
    "gn:asciiname":"Gonogono",
    "gn:country_code":"TD",
    "gn:dem":342,
    "gn:feature_class":"P",
    "gn:feature_code":"PPL",
    "gn:name":"Gonogono",
    "gn:population":0,
    "gn:timezone":"Africa/Ndjamena",
    "iso:country":"TD",
    "wof:name":"Gonogono",
    "wof:placetype":"locality"
},
  "geometry": {"coordinates":[16.1417,9.9118],"type":"Point"}
}