{
  "type": "Feature",
  "properties": {
    "gn:admin1_code":"16.0",
    "gn:asciiname":"Bogoye",
    "gn:country_code":"TD",
    "gn:dem":316,
    "gn:feature_class":"P",
    "gn:feature_code":"PPL",
    "gn:name":"Bogoye",
    "gn:population":0,
    "gn:timezone":"Africa/Ndjamena",
    "iso:country":"TD",
    "wof:name":"Bogoye",
    "wof:placetype":"locality"
},
  "geometry": {"coordinates":[15.42867,11.04116],"type":"Point"}
}