{
  "type": "Feature",
  "properties": {
    "gn:admin1_code":"15.0",
    "gn:asciiname":"Djogue",
    "gn:country_code":"TD",
    "gn:dem":326,
    "gn:feature_class":"P",
    "gn:feature_code":"PPL",
    "gn:name":"Djogu\u00e9",
    "gn:population":0,
    "gn:timezone":"Africa/Ndjamena",
    "iso:country":"TD",
    "wof:name":"Djogue",
    "wof:placetype":"locality"
},
  "geometry": {"coordinates":[15.78333,10.96667],"type":"Point"}
}