{
  "type": "Feature",
  "properties": {
    "gn:admin1_code":"9.0",
    "gn:asciiname":"Ngara II",
    "gn:country_code":"TD",
    "gn:dem":421,
    "gn:feature_class":"P",
    "gn:feature_code":"PPL",
    "gn:name":"Ngara II",
    "gn:population":0,
    "gn:timezone":"Africa/Ndjamena",
    "iso:country":"TD",
    "wof:name":"Ngara II",
    "wof:placetype":"locality"
},
  "geometry": {"coordinates":[16.84486,8.21742],"type":"Point"}
}