{
  "type": "Feature",
  "properties": {
    "gn:admin1_code":"1.0",
    "gn:asciiname":"Am Sayala Haddad",
    "gn:country_code":"TD",
    "gn:dem":299,
    "gn:feature_class":"P",
    "gn:feature_code":"PPL",
    "gn:name":"Am Sayala Haddad",
    "gn:population":0,
    "gn:timezone":"Africa/Ndjamena",
    "iso:country":"TD",
    "wof:name":"Am Sayala Haddad",
    "wof:placetype":"locality"
},
  "geometry": {"coordinates":[17.78773,13.02961],"type":"Point"}
}