{
  "type": "Feature",
  "properties": {
    "gn:admin1_code":"22.0",
    "gn:asciiname":"Yelanga",
    "gn:country_code":"TD",
    "gn:dem":299,
    "gn:feature_class":"P",
    "gn:feature_code":"PPL",
    "gn:name":"Y\u00e9langa",
    "gn:population":0,
    "gn:timezone":"Africa/Ndjamena",
    "iso:country":"TD",
    "wof:name":"Yelanga",
    "wof:placetype":"locality"
},
  "geometry": {"coordinates":[16.338,13.29],"type":"Point"}
}