{
  "type": "Feature",
  "properties": {
    "gn:admin1_code":"28.0",
    "gn:asciiname":"Ounianga Kebir",
    "gn:country_code":"TD",
    "gn:dem":386,
    "gn:feature_class":"P",
    "gn:feature_code":"PPL",
    "gn:name":"Ounianga K\u00e9bir",
    "gn:population":0,
    "gn:timezone":"Africa/Ndjamena",
    "iso:country":"TD",
    "name:fra_x_preferred":[
        "Ounianga K\u00e9bir"
    ],
    "wof:name":"Ounianga Kebir",
    "wof:placetype":"locality"
},
  "geometry": {"coordinates":[20.48887,19.05263],"type":"Point"}
}