{
  "type": "Feature",
  "properties": {
    "gn:admin1_code":"28.0",
    "gn:asciiname":"Ounianga Kebir",
    "gn:country_code":"TD",
    "gn:dem":386,
    "gn:feature_class":"P",
    "gn:feature_code":"PPL",
    "gn:name":"Ounianga K\u00e9bir",
    "gn:population":0,
    "gn:timezone":"Africa/Ndjamena",
    "iso:country":"TD",
    "name:fra_x_preferred":[
        "Ounianga K\u00e9bir"
    ],
    "name:nld_x_preferred":[
        "Ounianga K\u00e9bir"
    ],
    "name:rus_x_preferred":[
        "\u0423\u043d\u0438\u0430\u043d\u0433\u0430-\u041a\u0435\u0431\u0438\u0440"
    ],
    "name:urd_x_preferred":[
        "\u0627\u0648\u0646\u06cc\u0627\u0646\u06af\u0627 \u06a9\u0628\u06cc\u0631"
    ],
    "wof:name":"Ounianga Kebir",
    "wof:placetype":"locality"
},
  "geometry": {"coordinates":[20.48887,19.05263],"type":"Point"}
}