{
  "type": "Feature",
  "properties": {
    "gn:admin1_code":"8.0",
    "gn:asciiname":"Laokassi",
    "gn:country_code":"TD",
    "gn:dem":420,
    "gn:feature_class":"P",
    "gn:feature_code":"PPL",
    "gn:name":"Laokassi",
    "gn:population":0,
    "gn:timezone":"Africa/Ndjamena",
    "iso:country":"TD",
    "name:und_x_variant":[
        "Laokasi",
        "Lakassi",
        "Lokassi",
        "Laokas",
        "Laokassi"
    ],
    "wof:name":"Laokassi",
    "wof:placetype":"locality"
},
  "geometry": {"coordinates":[15.69369,8.85036],"type":"Point"}
}