{
  "type": "Feature",
  "properties": {
    "gn:admin1_code":"2.0",
    "gn:asciiname":"Alabidi",
    "gn:country_code":"TD",
    "gn:dem":930,
    "gn:feature_class":"P",
    "gn:feature_code":"PPL",
    "gn:name":"Alabidi",
    "gn:population":0,
    "gn:timezone":"Africa/Ndjamena",
    "iso:country":"TD",
    "wof:name":"Alabidi",
    "wof:placetype":"locality"
},
  "geometry": {"coordinates":[22.38333,15.16667],"type":"Point"}
}