{
  "type": "Feature",
  "properties": {
    "gn:admin1_code":"14.0",
    "gn:asciiname":"Koubno",
    "gn:country_code":"TD",
    "gn:dem":352,
    "gn:feature_class":"P",
    "gn:feature_code":"PPL",
    "gn:name":"Koubno",
    "gn:population":0,
    "gn:timezone":"Africa/Ndjamena",
    "iso:country":"TD",
    "wof:name":"Koubno",
    "wof:placetype":"locality"
},
  "geometry": {"coordinates":[16.8228,9.4012],"type":"Point"}
}