{
  "type": "Feature",
  "properties": {
    "gn:admin1_code":"9.0",
    "gn:asciiname":"Koutou",
    "gn:country_code":"TD",
    "gn:dem":389,
    "gn:feature_class":"P",
    "gn:feature_code":"PPL",
    "gn:name":"Koutou",
    "gn:population":0,
    "gn:timezone":"Africa/Ndjamena",
    "iso:country":"TD",
    "wof:name":"Koutou",
    "wof:placetype":"locality"
},
  "geometry": {"coordinates":[16.93145,8.87445],"type":"Point"}
}