{
  "type": "Feature",
  "properties": {
    "gn:admin1_code":"13.0",
    "gn:asciiname":"Barda",
    "gn:country_code":"TD",
    "gn:dem":482,
    "gn:feature_class":"P",
    "gn:feature_code":"PPL",
    "gn:name":"Barda",
    "gn:population":0,
    "gn:timezone":"Africa/Ndjamena",
    "iso:country":"TD",
    "wof:name":"Barda",
    "wof:placetype":"locality"
},
  "geometry": {"coordinates":[20.9961,11.6125],"type":"Point"}
}