{
  "type": "Feature",
  "properties": {
    "gn:admin1_code":"20.0",
    "gn:asciiname":"Madallao",
    "gn:country_code":"TD",
    "gn:dem":347,
    "gn:feature_class":"P",
    "gn:feature_code":"PPL",
    "gn:name":"Madallao",
    "gn:population":0,
    "gn:timezone":"Africa/Ndjamena",
    "iso:country":"TD",
    "wof:name":"Madallao",
    "wof:placetype":"locality"
},
  "geometry": {"coordinates":[14.4844,9.9863],"type":"Point"}
}