{
  "type": "Feature",
  "properties": {
    "gn:admin1_code":"2.0",
    "gn:asciiname":"Fitourkan",
    "gn:country_code":"TD",
    "gn:dem":874,
    "gn:feature_class":"P",
    "gn:feature_code":"PPL",
    "gn:name":"Fitourkan",
    "gn:population":0,
    "gn:timezone":"Africa/Ndjamena",
    "iso:country":"TD",
    "name:fra_x_preferred":[
        "Fitourkan"
    ],
    "wof:name":"Fitourkan",
    "wof:placetype":"locality"
},
  "geometry": {"coordinates":[21.35672000000001,14.32074],"type":"Point"}
}