{
  "type": "Feature",
  "properties": {
    "gn:admin1_code":"2.0",
    "gn:asciiname":"Troa Toua",
    "gn:country_code":"TD",
    "gn:dem":983,
    "gn:feature_class":"P",
    "gn:feature_code":"PPL",
    "gn:name":"Troa Toua",
    "gn:population":0,
    "gn:timezone":"Africa/Ndjamena",
    "iso:country":"TD",
    "name:fra_x_preferred":[
        "Troa Toua"
    ],
    "name:fra_x_variant":[
        "Troatoua"
    ],
    "wof:name":"Troa Toua",
    "wof:placetype":"locality"
},
  "geometry": {"coordinates":[21.98761,14.96636],"type":"Point"}
}