{
  "type": "Feature",
  "properties": {
    "gn:admin1_code":"9.0",
    "gn:asciiname":"Betissa",
    "gn:country_code":"TD",
    "gn:dem":497,
    "gn:feature_class":"P",
    "gn:feature_code":"PPL",
    "gn:name":"Betissa",
    "gn:population":0,
    "gn:timezone":"Africa/Ndjamena",
    "iso:country":"TD",
    "wof:name":"Betissa",
    "wof:placetype":"locality"
},
  "geometry": {"coordinates":[15.3338,8.401],"type":"Point"}
}