{
  "type": "Feature",
  "properties": {
    "gn:admin1_code":"15.0",
    "gn:asciiname":"Tirmi Bornou",
    "gn:country_code":"TD",
    "gn:dem":336,
    "gn:feature_class":"P",
    "gn:feature_code":"PPL",
    "gn:name":"Tirmi Bornou",
    "gn:population":0,
    "gn:timezone":"Africa/Ndjamena",
    "iso:country":"TD",
    "wof:name":"Tirmi Bornou",
    "wof:placetype":"locality"
},
  "geometry": {"coordinates":[16.7459,10.8447],"type":"Point"}
}