{
  "type": "Feature",
  "properties": {
    "gn:admin1_code":"20.0",
    "gn:asciiname":"Sodje Mbay",
    "gn:country_code":"TD",
    "gn:dem":445,
    "gn:feature_class":"P",
    "gn:feature_code":"PPL",
    "gn:name":"Sodj\u00e9 Mbay",
    "gn:population":0,
    "gn:timezone":"Africa/Ndjamena",
    "iso:country":"TD",
    "wof:name":"Sodje Mbay",
    "wof:placetype":"locality"
},
  "geometry": {"coordinates":[14.9332,9.4034],"type":"Point"}
}