{
  "type": "Feature",
  "properties": {
    "gn:admin1_code":"2.0",
    "gn:asciiname":"Teouel",
    "gn:country_code":"TD",
    "gn:dem":873,
    "gn:feature_class":"P",
    "gn:feature_code":"PPL",
    "gn:name":"Teouel",
    "gn:population":0,
    "gn:timezone":"Africa/Ndjamena",
    "iso:country":"TD",
    "name:fra_x_preferred":[
        "Teouel"
    ],
    "name:fra_x_variant":[
        "T\u00e9wel"
    ],
    "wof:name":"Teouel",
    "wof:placetype":"locality"
},
  "geometry": {"coordinates":[21.47274,14.48039],"type":"Point"}
}