{
  "type": "Feature",
  "properties": {
    "gn:admin1_code":"7.0",
    "gn:asciiname":"Kalari",
    "gn:country_code":"TD",
    "gn:dem":294,
    "gn:feature_class":"P",
    "gn:feature_code":"PPL",
    "gn:name":"Kalari",
    "gn:population":0,
    "gn:timezone":"Africa/Ndjamena",
    "iso:country":"TD",
    "name:mal_x_preferred":[
        "\u0d15\u0d33\u0d30\u0d3f"
    ],
    "wof:name":"Kalari",
    "wof:placetype":"locality"
},
  "geometry": {"coordinates":[15.55579,13.67977],"type":"Point"}
}