{
  "type": "Feature",
  "properties": {
    "gn:admin1_code":"9.0",
    "gn:asciiname":"Ganbagde",
    "gn:country_code":"TD",
    "gn:dem":387,
    "gn:feature_class":"P",
    "gn:feature_code":"PPL",
    "gn:name":"Ganbagde",
    "gn:population":0,
    "gn:timezone":"Africa/Ndjamena",
    "iso:country":"TD",
    "wof:name":"Ganbagde",
    "wof:placetype":"locality"
},
  "geometry": {"coordinates":[16.6182,9.0258],"type":"Point"}
}