{
  "type": "Feature",
  "properties": {
    "gn:admin1_code":"19.0",
    "gn:asciiname":"Gansila",
    "gn:country_code":"TD",
    "gn:dem":388,
    "gn:feature_class":"P",
    "gn:feature_code":"PPL",
    "gn:name":"Gansila",
    "gn:population":0,
    "gn:timezone":"Africa/Ndjamena",
    "iso:country":"TD",
    "wof:name":"Gansila",
    "wof:placetype":"locality"
},
  "geometry": {"coordinates":[17.5621,8.2545],"type":"Point"}
}