{
  "type": "Feature",
  "properties": {
    "gn:admin1_code":"9.0",
    "gn:asciiname":"Ramga",
    "gn:country_code":"TD",
    "gn:dem":490,
    "gn:feature_class":"P",
    "gn:feature_code":"PPL",
    "gn:name":"Ramga",
    "gn:population":0,
    "gn:timezone":"Africa/Ndjamena",
    "iso:country":"TD",
    "name:und_x_variant":[
        "Ranga",
        "Ramga"
    ],
    "wof:name":"Ramga",
    "wof:placetype":"locality"
},
  "geometry": {"coordinates":[16.78668,7.83365],"type":"Point"}
}