{
  "type": "Feature",
  "properties": {
    "gn:admin1_code":"18.0",
    "gn:asciiname":"Goz Na am",
    "gn:country_code":"TD",
    "gn:dem":307,
    "gn:feature_class":"P",
    "gn:feature_code":"PPL",
    "gn:name":"Goz Na am",
    "gn:population":0,
    "gn:timezone":"Africa/Ndjamena",
    "iso:country":"TD",
    "wof:name":"Goz Na am",
    "wof:placetype":"locality"
},
  "geometry": {"coordinates":[17.11752000000001,12.22732],"type":"Point"}
}