{
  "type": "Feature",
  "properties": {
    "gn:admin1_code":"9.0",
    "gn:asciiname":"Beguetibe",
    "gn:country_code":"TD",
    "gn:dem":500,
    "gn:feature_class":"P",
    "gn:feature_code":"PPL",
    "gn:name":"B\u00e9gu\u00e9tib\u00e9",
    "gn:population":0,
    "gn:timezone":"Africa/Ndjamena",
    "iso:country":"TD",
    "name:und_x_variant":[
        "Baguetibe",
        "B\u00e9gu\u00e9tib\u00e9"
    ],
    "wof:name":"Beguetibe",
    "wof:placetype":"locality"
},
  "geometry": {"coordinates":[16.07606,7.74485],"type":"Point"}
}