{
  "type": "Feature",
  "properties": {
    "gn:admin1_code":"8.0",
    "gn:asciiname":"Kaya",
    "gn:country_code":"TD",
    "gn:dem":423,
    "gn:feature_class":"P",
    "gn:feature_code":"PPL",
    "gn:name":"Kaya",
    "gn:population":0,
    "gn:timezone":"Africa/Ndjamena",
    "iso:country":"TD",
    "wof:name":"Kaya",
    "wof:placetype":"locality"
},
  "geometry": {"coordinates":[16.2337,9.01],"type":"Point"}
}