{
  "type": "Feature",
  "properties": {
    "gn:admin1_code":"17.0",
    "gn:asciiname":"Bemboro",
    "gn:country_code":"TD",
    "gn:dem":391,
    "gn:feature_class":"P",
    "gn:feature_code":"PPL",
    "gn:name":"Bemboro",
    "gn:population":0,
    "gn:timezone":"Africa/Ndjamena",
    "iso:country":"TD",
    "wof:name":"Bemboro",
    "wof:placetype":"locality"
},
  "geometry": {"coordinates":[17.97212,9.28143],"type":"Point"}
}