{
  "type": "Feature",
  "properties": {
    "gn:admin1_code":"14.0",
    "gn:asciiname":"Manda",
    "gn:country_code":"TD",
    "gn:dem":390,
    "gn:feature_class":"P",
    "gn:feature_code":"PPL",
    "gn:name":"Manda",
    "gn:population":0,
    "gn:timezone":"Africa/Ndjamena",
    "iso:country":"TD",
    "wof:name":"Manda",
    "wof:placetype":"locality"
},
  "geometry": {"coordinates":[16.1432,9.0859],"type":"Point"}
}