{
  "type": "Feature",
  "properties": {
    "gn:admin1_code":"17.0",
    "gn:asciiname":"Ndila II",
    "gn:country_code":"TD",
    "gn:dem":367,
    "gn:feature_class":"P",
    "gn:feature_code":"PPL",
    "gn:name":"Ndila II",
    "gn:population":0,
    "gn:timezone":"Africa/Ndjamena",
    "iso:country":"TD",
    "wof:name":"Ndila II",
    "wof:placetype":"locality"
},
  "geometry": {"coordinates":[18.39497,9.01303],"type":"Point"}
}