{
  "type": "Feature",
  "properties": {
    "gn:admin1_code":"19.0",
    "gn:asciiname":"Mayumtoro",
    "gn:country_code":"TD",
    "gn:dem":390,
    "gn:feature_class":"P",
    "gn:feature_code":"PPL",
    "gn:name":"Mayumtoro",
    "gn:population":0,
    "gn:timezone":"Africa/Ndjamena",
    "iso:country":"TD",
    "name:und_x_variant":[
        "Mayumt\u00e9ro",
        "Mayumtoro"
    ],
    "wof:name":"Mayumtoro",
    "wof:placetype":"locality"
},
  "geometry": {"coordinates":[17.69885,8.22015],"type":"Point"}
}