{
  "type": "Feature",
  "properties": {
    "gn:admin1_code":"8.0",
    "gn:asciiname":"Barnon",
    "gn:country_code":"TD",
    "gn:dem":384,
    "gn:feature_class":"P",
    "gn:feature_code":"PPL",
    "gn:name":"Barnon",
    "gn:population":0,
    "gn:timezone":"Africa/Ndjamena",
    "iso:country":"TD",
    "wof:name":"Barnon",
    "wof:placetype":"locality"
},
  "geometry": {"coordinates":[15.95938,9.04109],"type":"Point"}
}