{
  "type": "Feature",
  "properties": {
    "gn:admin1_code":"2.0",
    "gn:asciiname":"Bornodoukoume",
    "gn:country_code":"TD",
    "gn:dem":576,
    "gn:feature_class":"P",
    "gn:feature_code":"PPL",
    "gn:name":"Bornodoukoum\u00e9",
    "gn:population":0,
    "gn:timezone":"Africa/Ndjamena",
    "iso:country":"TD",
    "name:fra_x_preferred":[
        "Bornodoukoum\u00e9"
    ],
    "wof:name":"Bornodoukoume",
    "wof:placetype":"locality"
},
  "geometry": {"coordinates":[21.23225,14.84459],"type":"Point"}
}