{
  "type": "Feature",
  "properties": {
    "gn:admin1_code":"8.0",
    "gn:asciiname":"Poutoukouni",
    "gn:country_code":"TD",
    "gn:dem":410,
    "gn:feature_class":"P",
    "gn:feature_code":"PPL",
    "gn:name":"Poutoukouni",
    "gn:population":0,
    "gn:timezone":"Africa/Ndjamena",
    "iso:country":"TD",
    "wof:name":"Poutoukouni",
    "wof:placetype":"locality"
},
  "geometry": {"coordinates":[16.54548,8.81138],"type":"Point"}
}