{
  "type": "Feature",
  "properties": {
    "gn:admin1_code":"14.0",
    "gn:asciiname":"Domogou Kebiang",
    "gn:country_code":"TD",
    "gn:dem":351,
    "gn:feature_class":"P",
    "gn:feature_code":"PPL",
    "gn:name":"Domogou K\u00e9biang",
    "gn:population":0,
    "gn:timezone":"Africa/Ndjamena",
    "iso:country":"TD",
    "wof:name":"Domogou Kebiang",
    "wof:placetype":"locality"
},
  "geometry": {"coordinates":[16.5565,9.5818],"type":"Point"}
}