{
  "type": "Feature",
  "properties": {
    "gn:admin1_code":"23.0",
    "gn:asciiname":"Oun",
    "gn:country_code":"TD",
    "gn:dem":865,
    "gn:feature_class":"P",
    "gn:feature_code":"PPL",
    "gn:name":"Oun",
    "gn:population":0,
    "gn:timezone":"Africa/Ndjamena",
    "iso:country":"TD",
    "wof:name":"Oun",
    "wof:placetype":"locality"
},
  "geometry": {"coordinates":[19.16667,21.63333],"type":"Point"}
}