{
  "type": "Feature",
  "properties": {
    "gn:admin1_code":"18.0",
    "gn:asciiname":"Ladalam",
    "gn:country_code":"TD",
    "gn:dem":293,
    "gn:feature_class":"P",
    "gn:feature_code":"PPL",
    "gn:name":"Ladalam",
    "gn:population":0,
    "gn:timezone":"Africa/Ndjamena",
    "iso:country":"TD",
    "wof:name":"Ladalam",
    "wof:placetype":"locality"
},
  "geometry": {"coordinates":[15.55531,12.51212],"type":"Point"}
}