{
  "type": "Feature",
  "properties": {
    "gn:admin1_code":"25.0",
    "gn:asciiname":"Kounous",
    "gn:country_code":"TD",
    "gn:dem":521,
    "gn:feature_class":"P",
    "gn:feature_code":"PPL",
    "gn:name":"Kounous",
    "gn:population":0,
    "gn:timezone":"Africa/Ndjamena",
    "iso:country":"TD",
    "wof:name":"Kounous",
    "wof:placetype":"locality"
},
  "geometry": {"coordinates":[21.80805,11.97325],"type":"Point"}
}