{
  "type": "Feature",
  "properties": {
    "gn:admin1_code":"1.0",
    "gn:asciiname":"Korinjoe",
    "gn:country_code":"TD",
    "gn:dem":339,
    "gn:feature_class":"P",
    "gn:feature_code":"PPL",
    "gn:name":"Korinjo\u00e9",
    "gn:population":0,
    "gn:timezone":"Africa/Ndjamena",
    "iso:country":"TD",
    "wof:name":"Korinjoe",
    "wof:placetype":"locality"
},
  "geometry": {"coordinates":[18.4101,13.2372],"type":"Point"}
}