{
  "type": "Feature",
  "properties": {
    "gn:admin1_code":"14.0",
    "gn:asciiname":"Goubgou",
    "gn:country_code":"TD",
    "gn:dem":349,
    "gn:feature_class":"P",
    "gn:feature_code":"PPL",
    "gn:name":"Goubgou",
    "gn:population":0,
    "gn:timezone":"Africa/Ndjamena",
    "iso:country":"TD",
    "wof:name":"Goubgou",
    "wof:placetype":"locality"
},
  "geometry": {"coordinates":[16.648,9.6279],"type":"Point"}
}