{
  "type": "Feature",
  "properties": {
    "gn:admin1_code":"15.0",
    "gn:asciiname":"Ouenabdou",
    "gn:country_code":"TD",
    "gn:dem":325,
    "gn:feature_class":"P",
    "gn:feature_code":"PPL",
    "gn:name":"Ou\u00e9nabdou",
    "gn:population":0,
    "gn:timezone":"Africa/Ndjamena",
    "iso:country":"TD",
    "name:und_x_variant":[
        "Ou\u00e9nabdou",
        "Ouendou Abdou"
    ],
    "wof:name":"Ouenabdou",
    "wof:placetype":"locality"
},
  "geometry": {"coordinates":[15.93692,10.88471],"type":"Point"}
}