{
  "type": "Feature",
  "properties": {
    "gn:admin1_code":"19.0",
    "gn:asciiname":"Moyon",
    "gn:country_code":"TD",
    "gn:dem":388,
    "gn:feature_class":"P",
    "gn:feature_code":"PPL",
    "gn:name":"Moyon",
    "gn:population":0,
    "gn:timezone":"Africa/Ndjamena",
    "iso:country":"TD",
    "wof:name":"Moyon",
    "wof:placetype":"locality"
},
  "geometry": {"coordinates":[17.58485,8.33208],"type":"Point"}
}