{
  "type": "Feature",
  "properties": {
    "gn:admin1_code":"19.0",
    "gn:asciiname":"Moyon",
    "gn:country_code":"TD",
    "gn:dem":388,
    "gn:feature_class":"P",
    "gn:feature_code":"PPL",
    "gn:name":"Moyon",
    "gn:population":0,
    "gn:timezone":"Africa/Ndjamena",
    "iso:country":"TD",
    "name:bug_x_preferred":[
        "Moyon"
    ],
    "name:cat_x_preferred":[
        "Moyon"
    ],
    "name:ceb_x_preferred":[
        "Moyon"
    ],
    "name:deu_x_preferred":[
        "Moyon"
    ],
    "name:eus_x_preferred":[
        "Moyon"
    ],
    "name:fra_x_preferred":[
        "Moyon"
    ],
    "name:hun_x_preferred":[
        "Moyon"
    ],
    "name:ita_x_preferred":[
        "Moyon"
    ],
    "name:kaz_x_preferred":[
        "\u041c\u0443\u0430\u0439\u043e\u043d"
    ],
    "name:lat_x_preferred":[
        "Moyon"
    ],
    "name:msa_x_preferred":[
        "Moyon"
    ],
    "name:nld_x_preferred":[
        "Moyon"
    ],
    "name:oci_x_preferred":[
        "Moyon"
    ],
    "name:pms_x_preferred":[
        "Moyon"
    ],
    "name:pol_x_preferred":[
        "Moyon"
    ],
    "name:por_x_preferred":[
        "Moyon"
    ],
    "name:ron_x_preferred":[
        "Moyon"
    ],
    "name:slk_x_preferred":[
        "Moyon"
    ],
    "name:spa_x_preferred":[
        "Moyon"
    ],
    "name:swe_x_preferred":[
        "Moyon"
    ],
    "name:ukr_x_preferred":[
        "\u041c\u0443\u0430\u0439\u043e\u043d"
    ],
    "name:uzb_x_preferred":[
        "Moyon"
    ],
    "name:vie_x_preferred":[
        "Moyon"
    ],
    "name:vol_x_preferred":[
        "Moyon"
    ],
    "name:war_x_preferred":[
        "Moyon"
    ],
    "name:zho_x_preferred":[
        "\u7a46\u74e6\u7fc1"
    ],
    "wof:name":"Moyon",
    "wof:placetype":"locality"
},
  "geometry": {"coordinates":[17.58485,8.33208],"type":"Point"}
}