{
  "type": "Feature",
  "properties": {
    "gn:admin1_code":"18.0",
    "gn:asciiname":"Achim",
    "gn:country_code":"TD",
    "gn:dem":286,
    "gn:feature_class":"P",
    "gn:feature_code":"PPL",
    "gn:name":"Achim",
    "gn:population":0,
    "gn:timezone":"Africa/Ndjamena",
    "iso:country":"TD",
    "name:ara_x_preferred":[
        "\u0622\u062e\u064a\u0645"
    ],
    "name:azb_x_preferred":[
        "\u0622\u062e\u06cc\u0645"
    ],
    "name:ceb_x_preferred":[
        "Achim"
    ],
    "name:ces_x_preferred":[
        "Achim"
    ],
    "name:dan_x_preferred":[
        "Achim"
    ],
    "name:deu_x_preferred":[
        "Achim"
    ],
    "name:epo_x_preferred":[
        "Achim"
    ],
    "name:est_x_preferred":[
        "Achim"
    ],
    "name:eus_x_preferred":[
        "Achim"
    ],
    "name:fas_x_preferred":[
        "\u0622\u062e\u06cc\u0645"
    ],
    "name:fin_x_preferred":[
        "Achim"
    ],
    "name:fra_x_preferred":[
        "Achim"
    ],
    "name:hun_x_preferred":[
        "Achim"
    ],
    "name:ita_x_preferred":[
        "Achim"
    ],
    "name:jpn_x_preferred":[
        "\u30a2\u30d2\u30e0"
    ],
    "name:kaz_x_preferred":[
        "\u0410\u0445\u0438\u043c"
    ],
    "name:kir_x_preferred":[
        "\u0410\u0445\u0438\u043c"
    ],
    "name:msa_x_preferred":[
        "Achim"
    ],
    "name:nds_x_preferred":[
        "Gemeen Achem"
    ],
    "name:nld_x_preferred":[
        "Achim"
    ],
    "name:pol_x_preferred":[
        "Achim"
    ],
    "name:por_x_preferred":[
        "Achim"
    ],
    "name:ron_x_preferred":[
        "Achim"
    ],
    "name:rus_x_preferred":[
        "\u0410\u0445\u0438\u043c"
    ],
    "name:spa_x_preferred":[
        "Achim"
    ],
    "name:srp_x_preferred":[
        "\u0410\u0445\u0438\u043c"
    ],
    "name:swe_x_preferred":[
        "Achim"
    ],
    "name:tur_x_preferred":[
        "Achim"
    ],
    "name:ukr_x_preferred":[
        "\u0410\u0445\u0456\u043c"
    ],
    "name:uzb_x_preferred":[
        "Achim"
    ],
    "name:vie_x_preferred":[
        "Achim"
    ],
    "name:war_x_preferred":[
        "Achim"
    ],
    "name:zho_x_preferred":[
        "\u963f\u5e0c\u59c6"
    ],
    "wof:name":"Achim",
    "wof:placetype":"locality"
},
  "geometry": {"coordinates":[15.81213,13.0494],"type":"Point"}
}