{
  "type": "Feature",
  "properties": {
    "gn:admin1_code":"1.0",
    "gn:asciiname":"Tondobay",
    "gn:country_code":"TD",
    "gn:dem":374,
    "gn:feature_class":"P",
    "gn:feature_code":"PPL",
    "gn:name":"Tondobay",
    "gn:population":0,
    "gn:timezone":"Africa/Ndjamena",
    "iso:country":"TD",
    "wof:name":"Tondobay",
    "wof:placetype":"locality"
},
  "geometry": {"coordinates":[19.4839,13.9793],"type":"Point"}
}