{
  "type": "Feature",
  "properties": {
    "gn:admin1_code":"12.0",
    "gn:asciiname":"Donkouch",
    "gn:country_code":"TD",
    "gn:dem":731,
    "gn:feature_class":"P",
    "gn:feature_code":"PPL",
    "gn:name":"Donkouch",
    "gn:population":0,
    "gn:timezone":"Africa/Ndjamena",
    "iso:country":"TD",
    "wof:name":"Donkouch",
    "wof:placetype":"locality"
},
  "geometry": {"coordinates":[21.60791,13.36779],"type":"Point"}
}