{
  "type": "Feature",
  "properties": {
    "gn:admin1_code":"15.0",
    "gn:asciiname":"Deraia",
    "gn:country_code":"TD",
    "gn:dem":298,
    "gn:feature_class":"P",
    "gn:feature_code":"PPL",
    "gn:name":"Dera\u00efa",
    "gn:population":0,
    "gn:timezone":"Africa/Ndjamena",
    "iso:country":"TD",
    "wof:name":"Deraia",
    "wof:placetype":"locality"
},
  "geometry": {"coordinates":[15.48415,11.94481],"type":"Point"}
}