{
  "type": "Feature",
  "properties": {
    "gn:admin1_code":"9.0",
    "gn:asciiname":"Dolam",
    "gn:country_code":"TD",
    "gn:dem":454,
    "gn:feature_class":"P",
    "gn:feature_code":"PPL",
    "gn:name":"Dolam",
    "gn:population":0,
    "gn:timezone":"Africa/Ndjamena",
    "iso:country":"TD",
    "name:und_x_variant":[
        "Doloam",
        "Dolam"
    ],
    "wof:name":"Dolam",
    "wof:placetype":"locality"
},
  "geometry": {"coordinates":[16.37954,7.96078],"type":"Point"}
}