{
  "type": "Feature",
  "properties": {
    "gn:admin1_code":"7.0",
    "gn:asciiname":"Ango",
    "gn:country_code":"TD",
    "gn:dem":280,
    "gn:feature_class":"P",
    "gn:feature_code":"PPL",
    "gn:name":"Ango",
    "gn:population":0,
    "gn:timezone":"Africa/Ndjamena",
    "iso:country":"TD",
    "name:bul_x_preferred":[
        "\u0410\u043d\u0433\u043e"
    ],
    "name:fra_x_preferred":[
        "Ango"
    ],
    "name:pol_x_preferred":[
        "Ango"
    ],
    "name:ron_x_preferred":[
        "Ango"
    ],
    "wof:name":"Ango",
    "wof:placetype":"locality"
},
  "geometry": {"coordinates":[14.83333,13.48333],"type":"Point"}
}