{
  "type": "Feature",
  "properties": {
    "gn:admin1_code":"18.0",
    "gn:asciiname":"Kasara",
    "gn:country_code":"TD",
    "gn:dem":292,
    "gn:feature_class":"P",
    "gn:feature_code":"PPL",
    "gn:name":"Kasara",
    "gn:population":0,
    "gn:timezone":"Africa/Ndjamena",
    "iso:country":"TD",
    "name:eng_x_preferred":[
        "Kasara"
    ],
    "wof:name":"Kasara",
    "wof:placetype":"locality"
},
  "geometry": {"coordinates":[14.58333,12.81667],"type":"Point"}
}