{
  "type": "Feature",
  "properties": {
    "gn:admin1_code":"6.0",
    "gn:asciiname":"Inchiboula",
    "gn:country_code":"TD",
    "gn:dem":310,
    "gn:feature_class":"P",
    "gn:feature_code":"PPL",
    "gn:name":"Inchiboula",
    "gn:population":0,
    "gn:timezone":"Africa/Ndjamena",
    "iso:country":"TD",
    "wof:name":"Inchiboula",
    "wof:placetype":"locality"
},
  "geometry": {"coordinates":[15.20577,14.00575],"type":"Point"}
}