{
  "type": "Feature",
  "properties": {
    "gn:admin1_code":"15.0",
    "gn:asciiname":"Malamouri",
    "gn:country_code":"TD",
    "gn:dem":335,
    "gn:feature_class":"P",
    "gn:feature_code":"PPL",
    "gn:name":"Malamouri",
    "gn:population":0,
    "gn:timezone":"Africa/Ndjamena",
    "iso:country":"TD",
    "wof:name":"Malamouri",
    "wof:placetype":"locality"
},
  "geometry": {"coordinates":[16.728,10.8691],"type":"Point"}
}