{
  "type": "Feature",
  "properties": {
    "gn:admin1_code":"22.0",
    "gn:asciiname":"Kouri Filonga",
    "gn:country_code":"TD",
    "gn:dem":302,
    "gn:feature_class":"P",
    "gn:feature_code":"PPL",
    "gn:name":"Kouri Filonga",
    "gn:population":0,
    "gn:timezone":"Africa/Ndjamena",
    "iso:country":"TD",
    "wof:name":"Kouri Filonga",
    "wof:placetype":"locality"
},
  "geometry": {"coordinates":[16.1356,13.2115],"type":"Point"}
}