{
  "type": "Feature",
  "properties": {
    "gn:admin1_code":"12.0",
    "gn:asciiname":"Lelkinbe",
    "gn:country_code":"TD",
    "gn:dem":639,
    "gn:feature_class":"P",
    "gn:feature_code":"PPL",
    "gn:name":"L\u00e8lkinb\u00e9",
    "gn:population":0,
    "gn:timezone":"Africa/Ndjamena",
    "iso:country":"TD",
    "wof:name":"Lelkinbe",
    "wof:placetype":"locality"
},
  "geometry": {"coordinates":[21.28723,13.61002],"type":"Point"}
}