{
  "type": "Feature",
  "properties": {
    "gn:admin1_code":"17.0",
    "gn:asciiname":"Boyama",
    "gn:country_code":"TD",
    "gn:dem":381,
    "gn:feature_class":"P",
    "gn:feature_code":"PPL",
    "gn:name":"Boyama",
    "gn:population":0,
    "gn:timezone":"Africa/Ndjamena",
    "iso:country":"TD",
    "name:und_x_variant":[
        "Bryama",
        "Boyama"
    ],
    "wof:name":"Boyama",
    "wof:placetype":"locality"
},
  "geometry": {"coordinates":[19.3159,9.3125],"type":"Point"}
}