{
  "type": "Feature",
  "properties": {
    "gn:admin1_code":"12.0",
    "gn:asciiname":"Bourtay Zaoue",
    "gn:country_code":"TD",
    "gn:dem":483,
    "gn:feature_class":"P",
    "gn:feature_code":"PPL",
    "gn:name":"Bourtay Zaou\u00e9",
    "gn:population":0,
    "gn:timezone":"Africa/Ndjamena",
    "iso:country":"TD",
    "wof:name":"Bourtay Zaoue",
    "wof:placetype":"locality"
},
  "geometry": {"coordinates":[20.63083,14.08807],"type":"Point"}
}