{
  "type": "Feature",
  "properties": {
    "gn:admin1_code":"15.0",
    "gn:asciiname":"Koutbouli",
    "gn:country_code":"TD",
    "gn:dem":331,
    "gn:feature_class":"P",
    "gn:feature_code":"PPL",
    "gn:name":"Koutbouli",
    "gn:population":0,
    "gn:timezone":"Africa/Ndjamena",
    "iso:country":"TD",
    "wof:name":"Koutbouli",
    "wof:placetype":"locality"
},
  "geometry": {"coordinates":[16.3674,11.3957],"type":"Point"}
}