{
  "type": "Feature",
  "properties": {
    "gn:admin1_code":"15.0",
    "gn:asciiname":"Mavrio",
    "gn:country_code":"TD",
    "gn:dem":300,
    "gn:feature_class":"P",
    "gn:feature_code":"PPL",
    "gn:name":"Mavrio",
    "gn:population":0,
    "gn:timezone":"Africa/Ndjamena",
    "iso:country":"TD",
    "name:und_x_variant":[
        "Mabrio",
        "Mavrio"
    ],
    "wof:name":"Mavrio",
    "wof:placetype":"locality"
},
  "geometry": {"coordinates":[15.25,12.02747],"type":"Point"}
}