{
  "type": "Feature",
  "properties": {
    "gn:admin1_code":"8.0",
    "gn:asciiname":"Menani",
    "gn:country_code":"TD",
    "gn:dem":452,
    "gn:feature_class":"P",
    "gn:feature_code":"PPL",
    "gn:name":"M\u00e9nani",
    "gn:population":0,
    "gn:timezone":"Africa/Ndjamena",
    "iso:country":"TD",
    "name:und_x_variant":[
        "Mainani",
        "M\u00e9nani"
    ],
    "wof:name":"Menani",
    "wof:placetype":"locality"
},
  "geometry": {"coordinates":[15.9196,8.6685],"type":"Point"}
}