{
  "type": "Feature",
  "properties": {
    "gn:admin1_code":"12.0",
    "gn:asciiname":"Miele Karbani",
    "gn:country_code":"TD",
    "gn:dem":710,
    "gn:feature_class":"P",
    "gn:feature_code":"PPL",
    "gn:name":"Mi\u00e9l\u00e9 Karbani",
    "gn:population":0,
    "gn:timezone":"Africa/Ndjamena",
    "iso:country":"TD",
    "wof:name":"Miele Karbani",
    "wof:placetype":"locality"
},
  "geometry": {"coordinates":[21.60637,13.66724],"type":"Point"}
}