{
  "type": "Feature",
  "properties": {
    "gn:admin1_code":"7.0",
    "gn:asciiname":"Matakayap Kangama",
    "gn:country_code":"TD",
    "gn:dem":293,
    "gn:feature_class":"P",
    "gn:feature_code":"PPL",
    "gn:name":"Matakayap Kangama",
    "gn:population":0,
    "gn:timezone":"Africa/Ndjamena",
    "iso:country":"TD",
    "name:und_x_variant":[
        "Kangama",
        "Matakayap",
        "Matakayap Kangama"
    ],
    "wof:name":"Matakayap Kangama",
    "wof:placetype":"locality"
},
  "geometry": {"coordinates":[15.68434,13.68333],"type":"Point"}
}