{
  "type": "Feature",
  "properties": {
    "gn:admin1_code":"12.0",
    "gn:asciiname":"Gabina",
    "gn:country_code":"TD",
    "gn:dem":815,
    "gn:feature_class":"P",
    "gn:feature_code":"PPL",
    "gn:name":"Gabina",
    "gn:population":0,
    "gn:timezone":"Africa/Ndjamena",
    "iso:country":"TD",
    "wof:name":"Gabina",
    "wof:placetype":"locality"
},
  "geometry": {"coordinates":[22.01502,13.2612],"type":"Point"}
}