{
  "type": "Feature",
  "properties": {
    "gn:admin1_code":"19.0",
    "gn:asciiname":"Mormoto",
    "gn:country_code":"TD",
    "gn:dem":382,
    "gn:feature_class":"P",
    "gn:feature_code":"PPL",
    "gn:name":"Mormoto",
    "gn:population":0,
    "gn:timezone":"Africa/Ndjamena",
    "iso:country":"TD",
    "wof:name":"Mormoto",
    "wof:placetype":"locality"
},
  "geometry": {"coordinates":[17.96599999999999,8.5331],"type":"Point"}
}