{
  "type": "Feature",
  "properties": {
    "gn:admin1_code":"14.0",
    "gn:asciiname":"Tasmana",
    "gn:country_code":"TD",
    "gn:dem":358,
    "gn:feature_class":"P",
    "gn:feature_code":"PPL",
    "gn:name":"Tasmana",
    "gn:population":0,
    "gn:timezone":"Africa/Ndjamena",
    "iso:country":"TD",
    "wof:name":"Tasmana",
    "wof:placetype":"locality"
},
  "geometry": {"coordinates":[16.3923,9.3218],"type":"Point"}
}