{
  "type": "Feature",
  "properties": {
    "gn:admin1_code":"5.0",
    "gn:asciiname":"Fielme",
    "gn:country_code":"TD",
    "gn:dem":431,
    "gn:feature_class":"P",
    "gn:feature_code":"PPL",
    "gn:name":"Fielm\u00e9",
    "gn:population":0,
    "gn:timezone":"Africa/Ndjamena",
    "iso:country":"TD",
    "wof:name":"Fielme",
    "wof:placetype":"locality"
},
  "geometry": {"coordinates":[18.1319,11.9801],"type":"Point"}
}