{
  "type": "Feature",
  "properties": {
    "gn:admin1_code":"12.0",
    "gn:asciiname":"Hidjelidje",
    "gn:country_code":"TD",
    "gn:dem":486,
    "gn:feature_class":"P",
    "gn:feature_code":"PPL",
    "gn:name":"Hidj\u00e9lidj\u00e9",
    "gn:population":0,
    "gn:timezone":"Africa/Ndjamena",
    "iso:country":"TD",
    "name:fra_x_preferred":[
        "Hidj\u00e9lidj\u00e9"
    ],
    "wof:name":"Hidjelidje",
    "wof:placetype":"locality"
},
  "geometry": {"coordinates":[20.63528,13.54321],"type":"Point"}
}