{
  "type": "Feature",
  "properties": {
    "gn:admin1_code":"9.0",
    "gn:asciiname":"Beklbi",
    "gn:country_code":"TD",
    "gn:dem":535,
    "gn:feature_class":"P",
    "gn:feature_code":"PPL",
    "gn:name":"B\u00e9klbi",
    "gn:population":0,
    "gn:timezone":"Africa/Ndjamena",
    "iso:country":"TD",
    "name:und_x_variant":[
        "Bekibi",
        "Bikibi",
        "B\u00e9klbi"
    ],
    "wof:name":"Beklbi",
    "wof:placetype":"locality"
},
  "geometry": {"coordinates":[16.02964,7.79325],"type":"Point"}
}