{
  "type": "Feature",
  "properties": {
    "gn:admin1_code":"2.0",
    "gn:asciiname":"Sirinie",
    "gn:country_code":"TD",
    "gn:dem":1020,
    "gn:feature_class":"P",
    "gn:feature_code":"PPL",
    "gn:name":"Sirini\u00e9",
    "gn:population":0,
    "gn:timezone":"Africa/Ndjamena",
    "iso:country":"TD",
    "name:fra_x_preferred":[
        "Sirini\u00e9"
    ],
    "wof:name":"Sirinie",
    "wof:placetype":"locality"
},
  "geometry": {"coordinates":[21.97868,14.88399],"type":"Point"}
}