{
  "type": "Feature",
  "properties": {
    "gn:admin1_code":"15.0",
    "gn:asciiname":"Tchior",
    "gn:country_code":"TD",
    "gn:dem":329,
    "gn:feature_class":"P",
    "gn:feature_code":"PPL",
    "gn:name":"Tchior",
    "gn:population":0,
    "gn:timezone":"Africa/Ndjamena",
    "iso:country":"TD",
    "wof:name":"Tchior",
    "wof:placetype":"locality"
},
  "geometry": {"coordinates":[16.1684,10.5227],"type":"Point"}
}