{
  "type": "Feature",
  "properties": {
    "gn:admin1_code":"5.0",
    "gn:asciiname":"Araka",
    "gn:country_code":"TD",
    "gn:dem":443,
    "gn:feature_class":"P",
    "gn:feature_code":"PPL",
    "gn:name":"Araka",
    "gn:population":0,
    "gn:timezone":"Africa/Ndjamena",
    "iso:country":"TD",
    "wof:name":"Araka",
    "wof:placetype":"locality"
},
  "geometry": {"coordinates":[19.43415,12.36711],"type":"Point"}
}