{
  "type": "Feature",
  "properties": {
    "gn:admin1_code":"19.0",
    "gn:asciiname":"Goumga",
    "gn:country_code":"TD",
    "gn:dem":349,
    "gn:feature_class":"P",
    "gn:feature_code":"PPL",
    "gn:name":"Goumga",
    "gn:population":0,
    "gn:timezone":"Africa/Ndjamena",
    "iso:country":"TD",
    "wof:name":"Goumga",
    "wof:placetype":"locality"
},
  "geometry": {"coordinates":[17.24381,9.53438],"type":"Point"}
}