{
  "type": "Feature",
  "properties": {
    "gn:admin1_code":"12.0",
    "gn:asciiname":"Ogourbo",
    "gn:country_code":"TD",
    "gn:dem":638,
    "gn:feature_class":"P",
    "gn:feature_code":"PPL",
    "gn:name":"Ogourbo",
    "gn:population":0,
    "gn:timezone":"Africa/Ndjamena",
    "iso:country":"TD",
    "wof:name":"Ogourbo",
    "wof:placetype":"locality"
},
  "geometry": {"coordinates":[21.03317,13.8707],"type":"Point"}
}