{
  "type": "Feature",
  "properties": {
    "gn:admin1_code":"17.0",
    "gn:asciiname":"Guinguini",
    "gn:country_code":"TD",
    "gn:dem":460,
    "gn:feature_class":"P",
    "gn:feature_code":"PPL",
    "gn:name":"Guinguini",
    "gn:population":0,
    "gn:timezone":"Africa/Ndjamena",
    "iso:country":"TD",
    "wof:name":"Guinguini",
    "wof:placetype":"locality"
},
  "geometry": {"coordinates":[18.89334,9.64243],"type":"Point"}
}