{
  "type": "Feature",
  "properties": {
    "gn:admin1_code":"1.0",
    "gn:asciiname":"Mondouri",
    "gn:country_code":"TD",
    "gn:dem":437,
    "gn:feature_class":"P",
    "gn:feature_code":"PPL",
    "gn:name":"Mondouri",
    "gn:population":0,
    "gn:timezone":"Africa/Ndjamena",
    "iso:country":"TD",
    "name:fra_x_preferred":[
        "Mondouri"
    ],
    "wof:name":"Mondouri",
    "wof:placetype":"locality"
},
  "geometry": {"coordinates":[20.22667,13.77637],"type":"Point"}
}