{
  "type": "Feature",
  "properties": {
    "gn:admin1_code":"25.0",
    "gn:asciiname":"Sisi",
    "gn:country_code":"TD",
    "gn:dem":668,
    "gn:feature_class":"P",
    "gn:feature_code":"PPL",
    "gn:name":"Sisi",
    "gn:population":0,
    "gn:timezone":"Africa/Ndjamena",
    "iso:country":"TD",
    "wof:name":"Sisi",
    "wof:placetype":"locality"
},
  "geometry": {"coordinates":[21.83333,12.71667],"type":"Point"}
}