{
  "type": "Feature",
  "properties": {
    "gn:admin1_code":"12.0",
    "gn:asciiname":"Abogoroum Ramadan",
    "gn:country_code":"TD",
    "gn:dem":431,
    "gn:feature_class":"P",
    "gn:feature_code":"PPL",
    "gn:name":"Abogoroum Ramadan",
    "gn:population":0,
    "gn:timezone":"Africa/Ndjamena",
    "iso:country":"TD",
    "name:und_x_variant":[
        "Abgoroum Ramadan",
        "Abogoroum Ramadan"
    ],
    "wof:name":"Abogoroum Ramadan",
    "wof:placetype":"locality"
},
  "geometry": {"coordinates":[20.23407000000001,14.07937],"type":"Point"}
}