{
  "type": "Feature",
  "properties": {
    "gn:admin1_code":"1.0",
    "gn:asciiname":"At Tawil",
    "gn:country_code":"TD",
    "gn:dem":327,
    "gn:feature_class":"P",
    "gn:feature_code":"PPL",
    "gn:name":"At Tawil",
    "gn:population":0,
    "gn:timezone":"Africa/Ndjamena",
    "iso:country":"TD",
    "wof:name":"At Tawil",
    "wof:placetype":"locality"
},
  "geometry": {"coordinates":[18.1078,13.1348],"type":"Point"}
}