{
  "type": "Feature",
  "properties": {
    "gn:admin1_code":"9.0",
    "gn:asciiname":"Koutre",
    "gn:country_code":"TD",
    "gn:dem":552,
    "gn:feature_class":"P",
    "gn:feature_code":"PPL",
    "gn:name":"Koutr\u00e9",
    "gn:population":0,
    "gn:timezone":"Africa/Ndjamena",
    "iso:country":"TD",
    "wof:name":"Koutre",
    "wof:placetype":"locality"
},
  "geometry": {"coordinates":[15.5849,7.8706],"type":"Point"}
}