{
  "type": "Feature",
  "properties": {
    "gn:admin1_code":"14.0",
    "gn:asciiname":"Yaogou",
    "gn:country_code":"TD",
    "gn:dem":352,
    "gn:feature_class":"P",
    "gn:feature_code":"PPL",
    "gn:name":"Yaogou",
    "gn:population":0,
    "gn:timezone":"Africa/Ndjamena",
    "iso:country":"TD",
    "name:und_x_variant":[
        "Yogou",
        "Yaogou"
    ],
    "wof:name":"Yaogou",
    "wof:placetype":"locality"
},
  "geometry": {"coordinates":[16.99,9.4429],"type":"Point"}
}