{
  "type": "Feature",
  "properties": {
    "gn:admin1_code":"1.0",
    "gn:asciiname":"Noumi",
    "gn:country_code":"TD",
    "gn:dem":429,
    "gn:feature_class":"P",
    "gn:feature_code":"PPL",
    "gn:name":"Noumi",
    "gn:population":0,
    "gn:timezone":"Africa/Ndjamena",
    "iso:country":"TD",
    "name:fra_x_preferred":[
        "Noumi"
    ],
    "wof:name":"Noumi",
    "wof:placetype":"locality"
},
  "geometry": {"coordinates":[20.15532,13.66461],"type":"Point"}
}