{
  "type": "Feature",
  "properties": {
    "gn:admin1_code":"20.0",
    "gn:asciiname":"Mbio",
    "gn:country_code":"TD",
    "gn:dem":402,
    "gn:feature_class":"P",
    "gn:feature_code":"PPL",
    "gn:name":"Mbio",
    "gn:population":0,
    "gn:timezone":"Africa/Ndjamena",
    "iso:country":"TD",
    "wof:name":"Mbio",
    "wof:placetype":"locality"
},
  "geometry": {"coordinates":[15.2579,9.2179],"type":"Point"}
}