{
  "type": "Feature",
  "properties": {
    "gn:admin1_code":"16.0",
    "gn:asciiname":"Djidi Bagaye",
    "gn:cc2":"TD",
    "gn:country_code":"TD",
    "gn:dem":333,
    "gn:feature_class":"P",
    "gn:feature_code":"PPL",
    "gn:name":"Djidi Bagaye",
    "gn:population":0,
    "gn:timezone":"Africa/Ndjamena",
    "iso:country":"TD",
    "name:und_x_variant":[
        "Djida Barga\u00ef",
        "Djidi Bagaye"
    ],
    "wof:name":"Djidi Bagaye",
    "wof:placetype":"locality"
},
  "geometry": {"coordinates":[15.56667,9.78333],"type":"Point"}
}