{
  "type": "Feature",
  "properties": {
    "gn:admin1_code":"15.0",
    "gn:asciiname":"Boutadoulba",
    "gn:country_code":"TD",
    "gn:dem":323,
    "gn:feature_class":"P",
    "gn:feature_code":"PPL",
    "gn:name":"Boutadoulba",
    "gn:population":0,
    "gn:timezone":"Africa/Ndjamena",
    "iso:country":"TD",
    "wof:name":"Boutadoulba",
    "wof:placetype":"locality"
},
  "geometry": {"coordinates":[15.66984,11.11241],"type":"Point"}
}