{
  "type": "Feature",
  "properties": {
    "gn:admin1_code":"19.0",
    "gn:asciiname":"Gonebe",
    "gn:country_code":"TD",
    "gn:dem":380,
    "gn:feature_class":"P",
    "gn:feature_code":"PPL",
    "gn:name":"Gon\u00e9b\u00e9",
    "gn:population":0,
    "gn:timezone":"Africa/Ndjamena",
    "iso:country":"TD",
    "wof:name":"Gonebe",
    "wof:placetype":"locality"
},
  "geometry": {"coordinates":[17.51667,8.46667],"type":"Point"}
}