{
  "type": "Feature",
  "properties": {
    "gn:admin1_code":"5.0",
    "gn:asciiname":"Oua",
    "gn:country_code":"TD",
    "gn:dem":403,
    "gn:feature_class":"P",
    "gn:feature_code":"PPL",
    "gn:name":"Oua",
    "gn:population":0,
    "gn:timezone":"Africa/Ndjamena",
    "iso:country":"TD",
    "wof:name":"Oua",
    "wof:placetype":"locality"
},
  "geometry": {"coordinates":[17.9304,11.0192],"type":"Point"}
}