{
  "type": "Feature",
  "properties": {
    "gn:admin1_code":"9.0",
    "gn:asciiname":"Robe Gore",
    "gn:country_code":"TD",
    "gn:dem":451,
    "gn:feature_class":"P",
    "gn:feature_code":"PPL",
    "gn:name":"Rob\u00e9 Gor\u00e9",
    "gn:population":0,
    "gn:timezone":"Africa/Ndjamena",
    "iso:country":"TD",
    "wof:name":"Robe Gore",
    "wof:placetype":"locality"
},
  "geometry": {"coordinates":[16.70717999999999,7.93941],"type":"Point"}
}