{
  "type": "Feature",
  "properties": {
    "gn:admin1_code":"15.0",
    "gn:asciiname":"Nianie",
    "gn:country_code":"TD",
    "gn:dem":335,
    "gn:feature_class":"P",
    "gn:feature_code":"PPL",
    "gn:name":"Niani\u00e9",
    "gn:population":0,
    "gn:timezone":"Africa/Ndjamena",
    "iso:country":"TD",
    "wof:name":"Nianie",
    "wof:placetype":"locality"
},
  "geometry": {"coordinates":[16.7035,10.9762],"type":"Point"}
}