{
  "type": "Feature",
  "properties": {
    "gn:admin1_code":"2.0",
    "gn:asciiname":"Am Gafal",
    "gn:country_code":"TD",
    "gn:dem":485,
    "gn:feature_class":"P",
    "gn:feature_code":"PPL",
    "gn:name":"Am Gafal",
    "gn:population":0,
    "gn:timezone":"Africa/Ndjamena",
    "iso:country":"TD",
    "wof:name":"Am Gafal",
    "wof:placetype":"locality"
},
  "geometry": {"coordinates":[20.78921,14.76656],"type":"Point"}
}