{
  "type": "Feature",
  "properties": {
    "gn:admin1_code":"17.0",
    "gn:asciiname":"Koumakeniako",
    "gn:country_code":"TD",
    "gn:dem":411,
    "gn:feature_class":"P",
    "gn:feature_code":"PPL",
    "gn:name":"Koumak\u00e9niako",
    "gn:population":0,
    "gn:timezone":"Africa/Ndjamena",
    "iso:country":"TD",
    "wof:name":"Koumakeniako",
    "wof:placetype":"locality"
},
  "geometry": {"coordinates":[19.00663,9.64749],"type":"Point"}
}