{
  "type": "Feature",
  "properties": {
    "gn:admin1_code":"13.0",
    "gn:asciiname":"Mangueigne",
    "gn:country_code":"TD",
    "gn:dem":443,
    "gn:feature_class":"P",
    "gn:feature_code":"PPL",
    "gn:name":"Mangueigne",
    "gn:population":0,
    "gn:timezone":"Africa/Ndjamena",
    "iso:country":"TD",
    "name:ita_x_preferred":[
        "Mangueigne"
    ],
    "name:und_x_variant":[
        "Manguei\u00f3ne",
        "Mangeine",
        "Mangeigne"
    ],
    "wof:name":"Mangueigne",
    "wof:placetype":"locality"
},
  "geometry": {"coordinates":[21.3132,10.5151],"type":"Point"}
}