{
  "type": "Feature",
  "properties": {
    "gn:admin1_code":"18.0",
    "gn:asciiname":"Am Djenene",
    "gn:country_code":"TD",
    "gn:dem":310,
    "gn:feature_class":"P",
    "gn:feature_code":"PPL",
    "gn:name":"Am Dj\u00e9n\u00e9ne",
    "gn:population":0,
    "gn:timezone":"Africa/Ndjamena",
    "iso:country":"TD",
    "wof:name":"Am Djenene",
    "wof:placetype":"locality"
},
  "geometry": {"coordinates":[16.90068,12.12863],"type":"Point"}
}