{
  "type": "Feature",
  "properties": {
    "gn:admin1_code":"16.0",
    "gn:asciiname":"Gouyou",
    "gn:country_code":"TD",
    "gn:dem":351,
    "gn:feature_class":"P",
    "gn:feature_code":"PPL",
    "gn:name":"Gouyou",
    "gn:population":0,
    "gn:timezone":"Africa/Ndjamena",
    "iso:country":"TD",
    "name:und_x_variant":[
        "Goujou",
        "G\u016dj\u016d",
        "Gouyou"
    ],
    "wof:name":"Gouyou",
    "wof:placetype":"locality"
},
  "geometry": {"coordinates":[14.9427,9.9482],"type":"Point"}
}