{
  "type": "Feature",
  "properties": {
    "gn:admin1_code":"1.0",
    "gn:asciiname":"Kouka",
    "gn:country_code":"TD",
    "gn:dem":371,
    "gn:feature_class":"P",
    "gn:feature_code":"PPL",
    "gn:name":"Kouka",
    "gn:population":0,
    "gn:timezone":"Africa/Ndjamena",
    "iso:country":"TD",
    "wof:name":"Kouka",
    "wof:placetype":"locality"
},
  "geometry": {"coordinates":[19.28333,13.16667],"type":"Point"}
}