{
  "type": "Feature",
  "properties": {
    "gn:admin1_code":"16.0",
    "gn:asciiname":"Loude",
    "gn:country_code":"TD",
    "gn:dem":324,
    "gn:feature_class":"P",
    "gn:feature_code":"PPL",
    "gn:name":"Loud\u00e9",
    "gn:population":0,
    "gn:timezone":"Africa/Ndjamena",
    "iso:country":"TD",
    "wof:name":"Loude",
    "wof:placetype":"locality"
},
  "geometry": {"coordinates":[15.07039,9.917],"type":"Point"}
}