{
  "type": "Feature",
  "properties": {
    "gn:admin1_code":"15.0",
    "gn:asciiname":"Djindere",
    "gn:country_code":"TD",
    "gn:dem":293,
    "gn:feature_class":"P",
    "gn:feature_code":"PPL",
    "gn:name":"Djind\u00e9r\u00e9",
    "gn:population":0,
    "gn:timezone":"Africa/Ndjamena",
    "iso:country":"TD",
    "name:und_x_variant":[
        "Dindere",
        "Djind\u00e9r\u00e9"
    ],
    "wof:name":"Djindere",
    "wof:placetype":"locality"
},
  "geometry": {"coordinates":[15.41188,12.15798],"type":"Point"}
}