{
  "type": "Feature",
  "properties": {
    "gn:admin1_code":"14.0",
    "gn:asciiname":"Kambaya",
    "gn:country_code":"TD",
    "gn:dem":408,
    "gn:feature_class":"P",
    "gn:feature_code":"PPL",
    "gn:name":"Kambaya",
    "gn:population":0,
    "gn:timezone":"Africa/Ndjamena",
    "iso:country":"TD",
    "wof:name":"Kambaya",
    "wof:placetype":"locality"
},
  "geometry": {"coordinates":[16.7817,9.1467],"type":"Point"}
}