{
  "type": "Feature",
  "properties": {
    "gn:admin1_code":"2.0",
    "gn:asciiname":"Kineda",
    "gn:country_code":"TD",
    "gn:dem":681,
    "gn:feature_class":"P",
    "gn:feature_code":"PPL",
    "gn:name":"Kin\u00e9da",
    "gn:population":0,
    "gn:timezone":"Africa/Ndjamena",
    "iso:country":"TD",
    "name:und_x_variant":[
        "Kir\u00e9da",
        "Kin\u00e9da"
    ],
    "wof:name":"Kineda",
    "wof:placetype":"locality"
},
  "geometry": {"coordinates":[21.1758,14.44339],"type":"Point"}
}