{
  "type": "Feature",
  "properties": {
    "gn:admin1_code":"25.0",
    "gn:asciiname":"Arday",
    "gn:country_code":"TD",
    "gn:dem":563,
    "gn:feature_class":"P",
    "gn:feature_code":"PPL",
    "gn:name":"Arday",
    "gn:population":0,
    "gn:timezone":"Africa/Ndjamena",
    "iso:country":"TD",
    "name:und_x_variant":[
        "Ardey",
        "Arde\u00ef",
        "Arday"
    ],
    "wof:name":"Arday",
    "wof:placetype":"locality"
},
  "geometry": {"coordinates":[22.38333,12.05],"type":"Point"}
}