{
  "type": "Feature",
  "properties": {
    "gn:admin1_code":"12.0",
    "gn:asciiname":"Marchout",
    "gn:country_code":"TD",
    "gn:dem":535,
    "gn:feature_class":"P",
    "gn:feature_code":"PPL",
    "gn:name":"Marchout",
    "gn:population":0,
    "gn:timezone":"Africa/Ndjamena",
    "iso:country":"TD",
    "name:und_x_variant":[
        "Marchoud",
        "Marchout"
    ],
    "wof:name":"Marchout",
    "wof:placetype":"locality"
},
  "geometry": {"coordinates":[20.84069,13.56156],"type":"Point"}
}