{
  "type": "Feature",
  "properties": {
    "gn:admin1_code":"12.0",
    "gn:asciiname":"Manzolo",
    "gn:country_code":"TD",
    "gn:dem":521,
    "gn:feature_class":"P",
    "gn:feature_code":"PPL",
    "gn:name":"Manzolo",
    "gn:population":0,
    "gn:timezone":"Africa/Ndjamena",
    "iso:country":"TD",
    "name:fra_x_preferred":[
        "Manzolo"
    ],
    "wof:name":"Manzolo",
    "wof:placetype":"locality"
},
  "geometry": {"coordinates":[20.72156,13.46297],"type":"Point"}
}