{
  "type": "Feature",
  "properties": {
    "gn:admin1_code":"1.0",
    "gn:asciiname":"Guies Zatalborno",
    "gn:country_code":"TD",
    "gn:dem":384,
    "gn:feature_class":"P",
    "gn:feature_code":"PPL",
    "gn:name":"Guies Zatalborno",
    "gn:population":0,
    "gn:timezone":"Africa/Ndjamena",
    "iso:country":"TD",
    "name:und_x_variant":[
        "Gies Zatalborno",
        "Guies Zatalborno"
    ],
    "wof:name":"Guies Zatalborno",
    "wof:placetype":"locality"
},
  "geometry": {"coordinates":[19.6509,13.2531],"type":"Point"}
}