{
  "type": "Feature",
  "properties": {
    "gn:admin1_code":"19.0",
    "gn:asciiname":"Ngalo",
    "gn:country_code":"TD",
    "gn:dem":375,
    "gn:feature_class":"P",
    "gn:feature_code":"PPL",
    "gn:name":"Ngalo",
    "gn:population":0,
    "gn:timezone":"Africa/Ndjamena",
    "iso:country":"TD",
    "name:und_x_variant":[
        "Galo",
        "Ngalo"
    ],
    "wof:name":"Ngalo",
    "wof:placetype":"locality"
},
  "geometry": {"coordinates":[17.80807,8.72772],"type":"Point"}
}