{
  "type": "Feature",
  "properties": {
    "gn:admin1_code":"20.0",
    "gn:asciiname":"Mapapale",
    "gn:country_code":"TD",
    "gn:dem":328,
    "gn:feature_class":"P",
    "gn:feature_code":"PPL",
    "gn:name":"Mapapal\u00e9",
    "gn:population":0,
    "gn:timezone":"Africa/Ndjamena",
    "iso:country":"TD",
    "wof:name":"Mapapale",
    "wof:placetype":"locality"
},
  "geometry": {"coordinates":[14.4044,9.5972],"type":"Point"}
}