{
  "type": "Feature",
  "properties": {
    "gn:admin1_code":"17.0",
    "gn:asciiname":"Djember",
    "gn:country_code":"TD",
    "gn:dem":356,
    "gn:feature_class":"P",
    "gn:feature_code":"PPL",
    "gn:name":"Djember",
    "gn:population":0,
    "gn:timezone":"Africa/Ndjamena",
    "iso:country":"TD",
    "name:und_x_variant":[
        "Jember",
        "Djamber",
        "Djember"
    ],
    "wof:name":"Djember",
    "wof:placetype":"locality"
},
  "geometry": {"coordinates":[17.8297,10.4134],"type":"Point"}
}