{
  "type": "Feature",
  "properties": {
    "gn:admin1_code":"1.0",
    "gn:asciiname":"Chafok",
    "gn:country_code":"TD",
    "gn:dem":400,
    "gn:feature_class":"P",
    "gn:feature_code":"PPL",
    "gn:name":"Chafok",
    "gn:population":0,
    "gn:timezone":"Africa/Ndjamena",
    "iso:country":"TD",
    "wof:name":"Chafok",
    "wof:placetype":"locality"
},
  "geometry": {"coordinates":[19.82925,13.30853],"type":"Point"}
}