{
  "type": "Feature",
  "properties": {
    "gn:admin1_code":"26.0",
    "gn:asciiname":"Bouro",
    "gn:country_code":"TD",
    "gn:dem":1459,
    "gn:feature_class":"P",
    "gn:feature_code":"PPL",
    "gn:name":"Bouro",
    "gn:population":0,
    "gn:timezone":"Africa/Ndjamena",
    "iso:country":"TD",
    "wof:name":"Bouro",
    "wof:placetype":"locality"
},
  "geometry": {"coordinates":[17.41667,21.11667000000001],"type":"Point"}
}