{
  "type": "Feature",
  "properties": {
    "gn:admin1_code":"12.0",
    "gn:asciiname":"Balangosi",
    "gn:country_code":"TD",
    "gn:dem":587,
    "gn:feature_class":"P",
    "gn:feature_code":"PPL",
    "gn:name":"Balangosi",
    "gn:population":0,
    "gn:timezone":"Africa/Ndjamena",
    "iso:country":"TD",
    "wof:name":"Balangosi",
    "wof:placetype":"locality"
},
  "geometry": {"coordinates":[21.56667,12.88333],"type":"Point"}
}